Workbook

Sheet Leeme
B2: Reto Actinver 2026: las 145 acciones de la plataforma, con datos y calculadora de portafolio
B3: Precios actualizados con Yahoo Finance: 8 de octubre de 2026, ~11:10 h CDMX. Precio de compra/venta y volumen del monitor: foto del 2026-10-08. Datos descriptivos del pasado: NO son una recomendación de inversión y no predicen lo que va a pasar.
B5: Qué hay en cada hoja
B6: • Acciones: las 145 de tu monitor (Reto Actinver > Monitores > Acciones), con el precio de compra y de venta que vio la plataforma, la diferencia entre ambos, el volumen disponible y los datos históricos en pesos.
B7: • Mi portafolio: eliges emisoras y porcentajes (celdas amarillas). Revisa las reglas del reto, los costos reales (comisión + diferencia compra-venta) y cuánto se ha movido un portafolio así.
B8: • Correlaciones / Covarianza: qué tanto se mueven juntas (apoyo de la calculadora).
B10: Lo que más cambia el resultado: la diferencia entre precio de compra y de venta
B11: • Si compras al precio de venta y vendes al precio de compra, pierdes esa diferencia cada vez que haces el viaje completo. En las mexicanas es de centésimas de punto porcentual; en muchas del exterior (SIC) es de 2% a 5%.
B12: • 'Sin contraparte' = hoy no hay quien compre o quien venda (precio $0.00): esa orden no se asigna. Son datos de un instante; cambian durante el día.
B13: • Estos precios son una foto del monitor al momento de copiarlo. Vuelve a revisarlo en la plataforma antes de operar.
B15: Cómo leer las columnas históricas
B16: • Todo está en pesos. En las acciones del exterior se usó el precio en dólares por el tipo de cambio del día (aproximación del precio SIC en pesos).
... B35: • Mi portafolio viene llenado con el ganador (Ganar (máx. prob. top 3) · 5 emisoras). No es una recomendación de inversión.

Sheet Pronóstico
A1: Pronóstico, portafolios de 5 a 12 emisoras y ganador
A2: Datos al 8 de octubre de 2026, ~11:10 h CDMX. El pronóstico usa señales reales (precio objetivo de analistas y momento), pero su capacidad de predicción es baja: el resultado lo decide sobre todo el mercado. No es una recomendación de inversión.
A4: Supuestos (celdas amarillas editables)
A5: IC: capacidad de pronóstico de las señales | B5: 0.05 | C5: 0.05 = una buena señal; 0 = sin pronóstico propio por acción
A6: Rendimiento anual esperado de la canasta | B6: 0.08 | C6: Prima de mercado
A7: Sesiones que faltan | B7: ='Mi portafolio'!$H$4 -> 25 | C7: De la hoja Mi portafolio
A8: Rendimiento esperado de la canasta en el lapso | B8: =B6*B7/252 -> 0.0079365079
A9: Mov. típico (±1σ) de la canasta en el lapso | B9: =SQRT(SUM(Covarianza!$B$6:$EO$149)/144^2*B7/252) -> 0.049266704 | C9: Canasta de las 144, mismo peso
A10: Umbral para el top 3 | B10: 0.2 | C10: En una edición pasada los 3 primeros superaron +20%
A12: Escenario | B12: Probabilidad | C12: Rend. de la canasta
A13: Bajista | B13: 0.25 | C13: =B8-B9 -> -0.041330196
A14: Base | B14: 0.5 | C14: =B8 -> 0.0079365079
A15: Alcista | B15: 0.25 | C15: =B8+B9 -> 0.057203212
A18: ¿Cuántas emisoras? Mejor portafolio para cada número (simulación de 60,000 trayectorias)*
A19: Objetivo | B19: Emisoras | C19: Prob. de superar +20% (top 3) | D19: Prob. de superar +30% | E19: Ganancia esperada ($) | F19: Prob. de terminar en positivo | G19: Prob. de perder más de $100k | H19: Peor 5% ($) | I19: Mejor 5% ($) | J19: Composición
A20: Ganar (máx. prob. top 3) | B20: 5 | C20: 0.1556 | D20: 0.0693 | E20: 31585.189 | F20: 0.5829 | G20: 0.2055 | H20: -274081.06 | I20: 340792.77 | J20: PINFRA * 3%, BOLSA A 3%, GFNORTE O 3%, INTC * 41%, MU * 50%
A21: Ganar (máx. prob. top 3) | B21: 6 | C21: 0.1513 | D21: 0.0659 | E21: 31343.091 | F21: 0.5842 | G21: 0.2012 | H21: -268336.3 | I21: 333952.34 | J21: AVGO * 3%, PINFRA * 3%, BOLSA A 3%, GFNORTE O 3%, INTC * 38%, MU * 50%
A22: Ganar (máx. prob. top 3) | B22: 7 | C22: 0.1446 | D22: 0.0619 | E22: 30911.388 | F22: 0.5853 | G22: 0.1957 | H22: -260766.82 | I22: 324738.32 | J22: GOOGL * 3%, AVGO * 3%, PINFRA * 3%, BOLSA A 3%, GFNORTE O 3%, INTC * 35%, MU * 50%
A23: Ganar (máx. prob. top 3) | B23: 8 | C23: 0.1382 | D23: 0.0572 | E23: 30549.94 | F23: 0.5865 | G23: 0.19 | H23: -252650.73 | I23: 315689.88 | J23: LAB B 3%, GOOGL * 3%, AVGO * 3%, PINFRA * 3%, BOLSA A 3%, GFNORTE O 3%, INTC * 32%, MU * 50%
A24: Ganar (máx. prob. top 3) | B24: 9 | C24: 0.1311 | D24: 0.0532 | E24: 30032.257 | F24: 0.5877 | G24: 0.1839 | H24: -245039.44 | I24: 306683.04 | J24: R A 3%, LAB B 3%, GOOGL * 3%, AVGO * 3%, PINFRA * 3%, BOLSA A 3%, GFNORTE O 3%, INTC * 29%, MU * 50%
A25: Ganar (máx. prob. top 3) | B25: 10 | C25: 0.1248 | D25: 0.049 | E25: 29681.039 | F25: 0.5892 | G25: 0.1783 | H25: -237304.31 | I25: 298303.16 | J25: GCC * 3%, R A 3%, LAB B 3%, GOOGL * 3%, AVGO * 3%, PINFRA * 3%, BOLSA A 3%, GFNORTE O 3%, INTC * 26%, MU * 50%
A26: Ganar (máx. prob. top 3) | B26: 11 | C26: 0.1177 | D26: 0.0453 | E26: 29194.975 | F26: 0.59 | G26: 0.1715 | H26: -229623.05 | I26: 289627.57 | J26: BBAJIO O 3%, GCC * 3%, R A 3%, LAB B 3%, GOOGL * 3%, AVGO * 3%, PINFRA * 3%, BOLSA A 3%, GFNORTE O 3%, INTC * 23%, MU * 50%
A27: Ganar (máx. prob. top 3) | B27: 12 | C27: 0.1107 | D27: 0.0415 | E27: 28681.843 | F27: 0.5911 | G27: 0.1658 | H27: -221584.98 | I27: 280803.97 | J27: ORBIA * 3%, BBAJIO O 3%, GCC * 3%, R A 3%, LAB B 3%, GOOGL * 3%, AVGO * 3%, PINFRA * 3%, BOLSA A 3%, GFNORTE O 3%, INTC * 20%, MU * 50%
A28: Balanceado (ganancia/riesgo) | B28: 5 | C28: 0.0291 | D28: 0.0075 | E28: 20109.769 | F28: 0.608 | G28: 0.0756 | H28: -124544.36 | I28: 165154.49 | J28: BABA N 9%, GCC * 17%, CEMEX CPO 23%, LAB B 24%, MU * 28%
A29: Balanceado (ganancia/riesgo) | B29: 6 | C29: 0.0271 | D29: 0.0068 | E29: 19717.541 | F29: 0.6077 | G29: 0.0727 | H29: -121803.07 | I29: 161832.37 | J29: GENTERA * 6%, BABA N 8%, GCC * 15%, CEMEX CPO 21%, LAB B 22%, MU * 28%
A30: Balanceado (ganancia/riesgo) | B30: 7 | C30: 0.0258 | D30: 0.0065 | E30: 19431.341 | F30: 0.6073 | G30: 0.0709 | H30: -120155.04 | I30: 159563.77 | J30: GOOGL * 3%, GENTERA * 5%, BABA N 7%, GCC * 15%, CEMEX CPO 21%, LAB B 21%, MU * 27%
A31: Balanceado (ganancia/riesgo) | B31: 8 | C31: 0.0239 | D31: 0.006 | E31: 18927.635 | F31: 0.6072 | G31: 0.0683 | H31: -117612.89 | I31: 155752.97 | J31: SIGMAF A 3%, GOOGL * 3%, GENTERA * 5%, BABA N 7%, GCC * 14%, CEMEX CPO 20%, LAB B 21%, MU * 27%
... A36: Referencia | B36: 5 | C36: 0.0077 | D36: 0.0017 | E36: 5324.7583 | F36: 0.5405 | G36: 0.0457 | H36: -95996.047 | I36: 105529.47 | J36: NVDA * 30%, GFNORTE O 20%, GMEXICO B 20%, MSFT * 15%, GOOGL * 15%
A38: Ganador
A39: Portafolio ganador (máxima probabilidad de top 3) | B39: Ganar (máx. prob. top 3) · 5 emisoras
A40: Composición | B40: PINFRA * 3%, BOLSA A 3%, GFNORTE O 3%, INTC * 41%, MU * 50%
A41: Ganancia esperada con pronóstico ($) | B41: =Portafolios!F28 -> 31585.189
A42: Si el mercado baja ($) | B42: =Portafolios!F25 -> -68690.52
A43: Escenario base ($) | B43: =Portafolios!F26 -> 31585.189
A44: Si el mercado sube ($) | B44: =Portafolios!F27 -> 131860.9
A45: Ganancia esperada sin pronóstico propio, IC = 0 ($)* | B45: 5173
A46: Prob. de superar +20% sin pronóstico propio* | B46: 0.1263
A48: Cómo se pronostica cada acción: beta × rendimiento esperado de la canasta + alfa − costo. Alfa = IC × mov. típico × puntaje; el puntaje promedia el potencial al precio objetivo de analistas (5 o más analistas) y el momento de 12 meses sin el último mes, estandarizados entre las 144.
A49: Por qué gana un portafolio concentrado: el premio es para los 3 primeros, así que importa la probabilidad de un resultado muy alto, no el promedio. Más emisoras bajan el riesgo, pero también la probabilidad de llegar a +20%. El ganador mete el máximo permitido (50%) en la acción con mejor pronóstico y casi todo lo demás en la segunda; las otras 3 cumplen el mínimo de 5 emisoras.
A50: Universo: operables, diferencia compra-venta de 1.5% o menos y con liquidez (mexicanas: al menos $20 millones operados al día; SIC: al menos $40,000 en el mejor nivel del monitor). Para el objetivo de ganar solo entran emisoras con pronóstico positivo.
A51: * Valores grises (cursiva): simulación en Python con la covarianza del último año y colas gruesas (t de Student, 4 g.l.). No se recalculan si cambias los supuestos; las fórmulas sí.
A52: Riesgo: el ganador pierde más de $100,000 en cerca de 1 de cada 5 simulaciones. Es dinero virtual; los premios por avance (quizzes y Tracks) no dependen de esto.

Sheet Órdenes
A1: Órdenes para el portafolio ganador
A2: Actualiza el precio (celda amarilla) con el precio de venta que veas en la plataforma justo antes de mandar la orden; los títulos se recalculan. Horario: 7:30 a 14:00 (desde el 3 de noviembre, 8:30 a 15:00). Las órdenes asignadas no se cancelan.
A4: Emisora | B4: Tipo | C4: Peso | D4: Precio de venta ($) | E4: Títulos a comprar | F4: Importe ($) | G4: Comisión + IVA ($) | H4: Total ($) | I4: Próximo reporte
A5: MU * | B5: =INDEX(Acciones!$B$5:$B$148,MATCH($A5,Acciones!$A$5:$A$148,0)) -> Exterior (SIC) | C5: 0.5 | D5: 19524.99 | E5: =INT(C5*'Mi portafolio'!$C$4*0.997/D5) -> 25 | F5: =E5*D5 -> 488124.75 | G5: =F5*'Mi portafolio'!$C$5 -> 566.22471 | H5: =F5+G5 -> 488690.97 | I5: =INDEX(Acciones!$Y$5:$Y$148,MATCH($A5,Acciones!$A$5:$A$148,0)) -> 2026-12-23
A6: INTC * | B6: =INDEX(Acciones!$B$5:$B$148,MATCH($A6,Acciones!$A$5:$A$148,0)) -> Exterior (SIC) | C6: 0.41 | D6: 1999.99 | E6: =INT(C6*'Mi portafolio'!$C$4*0.997/D6) -> 204 | F6: =E6*D6 -> 407997.96 | G6: =F6*'Mi portafolio'!$C$5 -> 473.27763 | H6: =F6+G6 -> 408471.24 | I6: =INDEX(Acciones!$Y$5:$Y$148,MATCH($A6,Acciones!$A$5:$A$148,0)) -> 2026-10-29
A7: PINFRA * | B7: =INDEX(Acciones!$B$5:$B$148,MATCH($A7,Acciones!$A$5:$A$148,0)) -> Mexicana | C7: 0.03 | D7: 274.13 | E7: =INT(C7*'Mi portafolio'!$C$4*0.997/D7) -> 109 | F7: =E7*D7 -> 29880.17 | G7: =F7*'Mi portafolio'!$C$5 -> 34.660997 | H7: =F7+G7 -> 29914.831 | I7: =INDEX(Acciones!$Y$5:$Y$148,MATCH($A7,Acciones!$A$5:$A$148,0)) -> 2026-10-22
A8: GFNORTE O | B8: =INDEX(Acciones!$B$5:$B$148,MATCH($A8,Acciones!$A$5:$A$148,0)) -> Mexicana | C8: 0.03 | D8: 189.55 | E8: =INT(C8*'Mi portafolio'!$C$4*0.997/D8) -> 157 | F8: =E8*D8 -> 29759.35 | G8: =F8*'Mi portafolio'!$C$5 -> 34.520846 | H8: =F8+G8 -> 29793.871 | I8: =INDEX(Acciones!$Y$5:$Y$148,MATCH($A8,Acciones!$A$5:$A$148,0)) -> 2026-11-03
A9: BOLSA A | B9: =INDEX(Acciones!$B$5:$B$148,MATCH($A9,Acciones!$A$5:$A$148,0)) -> Mexicana | C9: 0.03 | D9: 35.25 | E9: =INT(C9*'Mi portafolio'!$C$4*0.997/D9) -> 848 | F9: =E9*D9 -> 29892 | G9: =F9*'Mi portafolio'!$C$5 -> 34.67472 | H9: =F9+G9 -> 29926.675 | I9: =INDEX(Acciones!$Y$5:$Y$148,MATCH($A9,Acciones!$A$5:$A$148,0)) -> 2026-10-20
A10: Total | C10: =SUM(C5:C9) -> 1 | F10: =SUM(F5:F9) -> 985654.23 | G10: =SUM(G5:G9) -> 1143.3589 | H10: =SUM(H5:H9) -> 986797.59
A11: Efectivo que queda | H11: ='Mi portafolio'!$C$4-H10 -> 13202.411
A13: Cómo operar:
A14: 1. Revisa que el poder de compra sea $1,000,000 y que las 5 emisoras estén operables.
A15: 2. Primero las dos posiciones grandes, con orden limitada al precio de venta que ves, para no pagar de más.
A16: 3. Luego las tres chicas: cumplen el mínimo de 5 emisoras.
A17: 4. Debe quedar un poco de efectivo para comisiones. No hace falta mover nada después: cada compra y venta cuesta.
A18: 5. Si una orden no se asigna, vuelve a revisar el precio de venta: el monitor cambia durante el día.

Sheet Mi portafolio
A1: Mi portafolio del Reto Actinver 2026
A2: Elige emisoras en las celdas amarillas (lista desplegable) y su porcentaje. Todo lo demás se calcula solo.
A4: Capital del reto ($) | C4: 1000000 | E4: Sesiones que faltan (aprox.) | H4: 25
A5: Comisión por operación (0.10% + 16% IVA) | C5: =0.001*1.16 -> 0.00116
A7: Emisora | B7: Peso (%) | C7: Tipo | D7: Perfil por volatilidad | E7: Volatilidad anual | F7: Mov. típico ±1σ (25 ses.) | G7: Peor caída 1 año | H7: Diferencia compra-venta | I7: ¿Operable hoy? | J7: Importe a comprar ($) | K7: Costo estimado ida y vuelta ($) | L7: Peor ventana 25 ses. (3a) en $ | M7: Mejor ventana 25 ses. (3a) en $ | N7: Beta | O7: Peso × beta
A8: MU * | B8: 0.5 | C8: =IF($A8="","",INDEX(Acciones!$B$5:$B$148,MATCH($A8,Acciones!$A$5:$A$148,0))) -> Exterior (SIC) | D8: =IF($A8="","",INDEX(Acciones!$U$5:$U$148,MATCH($A8,Acciones!$A$5:$A$148,0))) -> Mayor movimiento | E8: =IF($A8="","",INDEX(Acciones!$O$5:$O$148,MATCH($A8,Acciones!$A$5:$A$148,0))) -> 0.80749836 | F8: =IF($A8="","",E8*SQRT($H$4/252)) -> 0.25433808 | G8: =IF($A8="","",INDEX(Acciones!$Q$5:$Q$148,MATCH($A8,Acciones!$A$5:$A$148,0))) -> -0.39731057 | H8: =IF($A8="","",IF(INDEX(Acciones!$G$5:$G$148,MATCH($A8,Acciones!$A$5:$A$148,0))="","n/d",INDEX(Acciones!$G$5:$G$148,MATCH($A8,Acciones!$A$5:$A$148,0)))) -> 0.0090021865 | I8: =IF($A8="","",INDEX(Acciones!$J$5:$J$148,MATCH($A8,Acciones!$A$5:$A$148,0))) -> Sí | J8: =IF(OR($A8="",$B8=""),"",$B8*$C$4) -> 500000 | K8: =IF(J8="","",J8*(IF(ISNUMBER(H8),H8,0)+2*$C$5)) -> 5661.0932 | L8: =IF(J8="","",J8*INDEX(Acciones!$T$5:$T$148,MATCH($A8,Acciones!$A$5:$A$148,0))) -> -171250.29 | M8: =IF(J8="","",J8*INDEX(Acciones!$S$5:$S$148,MATCH($A8,Acciones!$A$5:$A$148,0))) -> 553587.28 | N8: =IF($A8="","",INDEX(Acciones!$R$5:$R$148,MATCH($A8,Acciones!$A$5:$A$148,0))) -> 1.3721711 | O8: =IF(OR($A8="",$B8=""),0,$B8*N8) -> 0.68608554
A9: INTC * | B9: 0.41 | C9: =IF($A9="","",INDEX(Acciones!$B$5:$B$148,MATCH($A9,Acciones!$A$5:$A$148,0))) -> Exterior (SIC) | D9: =IF($A9="","",INDEX(Acciones!$U$5:$U$148,MATCH($A9,Acciones!$A$5:$A$148,0))) -> Mayor movimiento | E9: =IF($A9="","",INDEX(Acciones!$O$5:$O$148,MATCH($A9,Acciones!$A$5:$A$148,0))) -> 0.77688602 | F9: =IF($A9="","",E9*SQRT($H$4/252)) -> 0.2446961 | G9: =IF($A9="","",INDEX(Acciones!$Q$5:$Q$148,MATCH($A9,Acciones!$A$5:$A$148,0))) -> -0.41604291 | H9: =IF($A9="","",IF(INDEX(Acciones!$G$5:$G$148,MATCH($A9,Acciones!$A$5:$A$148,0))="","n/d",INDEX(Acciones!$G$5:$G$148,MATCH($A9,Acciones!$A$5:$A$148,0)))) -> 0.010040201 | I9: =IF($A9="","",INDEX(Acciones!$J$5:$J$148,MATCH($A9,Acciones!$A$5:$A$148,0))) -> Sí | J9: =IF(OR($A9="",$B9=""),"",$B9*$C$4) -> 410000 | K9: =IF(J9="","",J9*(IF(ISNUMBER(H9),H9,0)+2*$C$5)) -> 5067.6824 | L9: =IF(J9="","",J9*INDEX(Acciones!$T$5:$T$148,MATCH($A9,Acciones!$A$5:$A$148,0))) -> -165455.89 | M9: =IF(J9="","",J9*INDEX(Acciones!$S$5:$S$148,MATCH($A9,Acciones!$A$5:$A$148,0))) -> 596188.59 | N9: =IF($A9="","",INDEX(Acciones!$R$5:$R$148,MATCH($A9,Acciones!$A$5:$A$148,0))) -> 1.440998 | O9: =IF(OR($A9="",$B9=""),0,$B9*N9) -> 0.59080917
A10: PINFRA * | B10: 0.03 | C10: =IF($A10="","",INDEX(Acciones!$B$5:$B$148,MATCH($A10,Acciones!$A$5:$A$148,0))) -> Mexicana | D10: =IF($A10="","",INDEX(Acciones!$U$5:$U$148,MATCH($A10,Acciones!$A$5:$A$148,0))) -> Menor movimiento | E10: =IF($A10="","",INDEX(Acciones!$O$5:$O$148,MATCH($A10,Acciones!$A$5:$A$148,0))) -> 0.24898937 | F10: =IF($A10="","",E10*SQRT($H$4/252)) -> 0.07842428 | G10: =IF($A10="","",INDEX(Acciones!$Q$5:$Q$148,MATCH($A10,Acciones!$A$5:$A$148,0))) -> -0.16145538 | H10: =IF($A10="","",IF(INDEX(Acciones!$G$5:$G$148,MATCH($A10,Acciones!$A$5:$A$148,0))="","n/d",INDEX(Acciones!$G$5:$G$148,MATCH($A10,Acciones!$A$5:$A$148,0)))) -> 0.0002553859 | I10: =IF($A10="","",INDEX(Acciones!$J$5:$J$148,MATCH($A10,Acciones!$A$5:$A$148,0))) -> Sí | J10: =IF(OR($A10="",$B10=""),"",$B10*$C$4) -> 30000 | K10: =IF(J10="","",J10*(IF(ISNUMBER(H10),H10,0)+2*$C$5)) -> 77.261577 | L10: =IF(J10="","",J10*INDEX(Acciones!$T$5:$T$148,MATCH($A10,Acciones!$A$5:$A$148,0))) -> -4021.2204 | M10: =IF(J10="","",J10*INDEX(Acciones!$S$5:$S$148,MATCH($A10,Acciones!$A$5:$A$148,0))) -> 5986.5525 | N10: =IF($A10="","",INDEX(Acciones!$R$5:$R$148,MATCH($A10,Acciones!$A$5:$A$148,0))) -> 1.023781 | O10: =IF(OR($A10="",$B10=""),0,$B10*N10) -> 0.03071343
A11: GFNORTE O | B11: 0.03 | C11: =IF($A11="","",INDEX(Acciones!$B$5:$B$148,MATCH($A11,Acciones!$A$5:$A$148,0))) -> Mexicana | D11: =IF($A11="","",INDEX(Acciones!$U$5:$U$148,MATCH($A11,Acciones!$A$5:$A$148,0))) -> Menor movimiento | E11: =IF($A11="","",INDEX(Acciones!$O$5:$O$148,MATCH($A11,Acciones!$A$5:$A$148,0))) -> 0.25786944 | F11: =IF($A11="","",E11*SQRT($H$4/252)) -> 0.081221238 | G11: =IF($A11="","",INDEX(Acciones!$Q$5:$Q$148,MATCH($A11,Acciones!$A$5:$A$148,0))) -> -0.11808635 | H11: =IF($A11="","",IF(INDEX(Acciones!$G$5:$G$148,MATCH($A11,Acciones!$A$5:$A$148,0))="","n/d",INDEX(Acciones!$G$5:$G$148,MATCH($A11,Acciones!$A$5:$A$148,0)))) -> 0.0003165893 | I11: =IF($A11="","",INDEX(Acciones!$J$5:$J$148,MATCH($A11,Acciones!$A$5:$A$148,0))) -> Sí | J11: =IF(OR($A11="",$B11=""),"",$B11*$C$4) -> 30000 | K11: =IF(J11="","",J11*(IF(ISNUMBER(H11),H11,0)+2*$C$5)) -> 79.097679 | L11: =IF(J11="","",J11*INDEX(Acciones!$T$5:$T$148,MATCH($A11,Acciones!$A$5:$A$148,0))) -> -7351.8883 | M11: =IF(J11="","",J11*INDEX(Acciones!$S$5:$S$148,MATCH($A11,Acciones!$A$5:$A$148,0))) -> 9839.1127 | N11: =IF($A11="","",INDEX(Acciones!$R$5:$R$148,MATCH($A11,Acciones!$A$5:$A$148,0))) -> 1.100209 | O11: =IF(OR($A11="",$B11=""),0,$B11*N11) -> 0.033006271
A12: BOLSA A | B12: 0.03 | C12: =IF($A12="","",INDEX(Acciones!$B$5:$B$148,MATCH($A12,Acciones!$A$5:$A$148,0))) -> Mexicana | D12: =IF($A12="","",INDEX(Acciones!$U$5:$U$148,MATCH($A12,Acciones!$A$5:$A$148,0))) -> Menor movimiento | E12: =IF($A12="","",INDEX(Acciones!$O$5:$O$148,MATCH($A12,Acciones!$A$5:$A$148,0))) -> 0.26448767 | F12: =IF($A12="","",E12*SQRT($H$4/252)) -> 0.083305786 | G12: =IF($A12="","",INDEX(Acciones!$Q$5:$Q$148,MATCH($A12,Acciones!$A$5:$A$148,0))) -> -0.11782474 | H12: =IF($A12="","",IF(INDEX(Acciones!$G$5:$G$148,MATCH($A12,Acciones!$A$5:$A$148,0))="","n/d",INDEX(Acciones!$G$5:$G$148,MATCH($A12,Acciones!$A$5:$A$148,0)))) -> 0.0008514261 | I12: =IF($A12="","",INDEX(Acciones!$J$5:$J$148,MATCH($A12,Acciones!$A$5:$A$148,0))) -> Sí | J12: =IF(OR($A12="",$B12=""),"",$B12*$C$4) -> 30000 | K12: =IF(J12="","",J12*(IF(ISNUMBER(H12),H12,0)+2*$C$5)) -> 95.142783 | L12: =IF(J12="","",J12*INDEX(Acciones!$T$5:$T$148,MATCH($A12,Acciones!$A$5:$A$148,0))) -> -4092.0106 | M12: =IF(J12="","",J12*INDEX(Acciones!$S$5:$S$148,MATCH($A12,Acciones!$A$5:$A$148,0))) -> 9026.3945 | N12: =IF($A12="","",INDEX(Acciones!$R$5:$R$148,MATCH($A12,Acciones!$A$5:$A$148,0))) -> 0.57477112 | O12: =IF(OR($A12="",$B12=""),0,$B12*N12) -> 0.017243134
C13: =IF($A13="","",INDEX(Acciones!$B$5:$B$148,MATCH($A13,Acciones!$A$5:$A$148,0))) | D13: =IF($A13="","",INDEX(Acciones!$U$5:$U$148,MATCH($A13,Acciones!$A$5:$A$148,0))) | E13: =IF($A13="","",INDEX(Acciones!$O$5:$O$148,MATCH($A13,Acciones!$A$5:$A$148,0))) | F13: =IF($A13="","",E13*SQRT($H$4/252)) | G13: =IF($A13="","",INDEX(Acciones!$Q$5:$Q$148,MATCH($A13,Acciones!$A$5:$A$148,0))) | H13: =IF($A13="","",IF(INDEX(Acciones!$G$5:$G$148,MATCH($A13,Acciones!$A$5:$A$148,0))="","n/d",INDEX(Acciones!$G$5:$G$148,MATCH($A13,Acciones!$A$5:$A$148,0)))) | I13: =IF($A13="","",INDEX(Acciones!$J$5:$J$148,MATCH($A13,Acciones!$A$5:$A$148,0))) | J13: =IF(OR($A13="",$B13=""),"",$B13*$C$4) | K13: =IF(J13="","",J13*(IF(ISNUMBER(H13),H13,0)+2*$C$5)) | L13: =IF(J13="","",J13*INDEX(Acciones!$T$5:$T$148,MATCH($A13,Acciones!$A$5:$A$148,0))) | M13: =IF(J13="","",J13*INDEX(Acciones!$S$5:$S$148,MATCH($A13,Acciones!$A$5:$A$148,0))) | N13: =IF($A13="","",INDEX(Acciones!$R$5:$R$148,MATCH($A13,Acciones!$A$5:$A$148,0))) | O13: =IF(OR($A13="",$B13=""),0,$B13*N13) -> 0
C14: =IF($A14="","",INDEX(Acciones!$B$5:$B$148,MATCH($A14,Acciones!$A$5:$A$148,0))) | D14: =IF($A14="","",INDEX(Acciones!$U$5:$U$148,MATCH($A14,Acciones!$A$5:$A$148,0))) | E14: =IF($A14="","",INDEX(Acciones!$O$5:$O$148,MATCH($A14,Acciones!$A$5:$A$148,0))) | F14: =IF($A14="","",E14*SQRT($H$4/252)) | G14: =IF($A14="","",INDEX(Acciones!$Q$5:$Q$148,MATCH($A14,Acciones!$A$5:$A$148,0))) | H14: =IF($A14="","",IF(INDEX(Acciones!$G$5:$G$148,MATCH($A14,Acciones!$A$5:$A$148,0))="","n/d",INDEX(Acciones!$G$5:$G$148,MATCH($A14,Acciones!$A$5:$A$148,0)))) | I14: =IF($A14="","",INDEX(Acciones!$J$5:$J$148,MATCH($A14,Acciones!$A$5:$A$148,0))) | J14: =IF(OR($A14="",$B14=""),"",$B14*$C$4) | K14: =IF(J14="","",J14*(IF(ISNUMBER(H14),H14,0)+2*$C$5)) | L14: =IF(J14="","",J14*INDEX(Acciones!$T$5:$T$148,MATCH($A14,Acciones!$A$5:$A$148,0))) | M14: =IF(J14="","",J14*INDEX(Acciones!$S$5:$S$148,MATCH($A14,Acciones!$A$5:$A$148,0))) | N14: =IF($A14="","",INDEX(Acciones!$R$5:$R$148,MATCH($A14,Acciones!$A$5:$A$148,0))) | O14: =IF(OR($A14="",$B14=""),0,$B14*N14) -> 0
C15: =IF($A15="","",INDEX(Acciones!$B$5:$B$148,MATCH($A15,Acciones!$A$5:$A$148,0))) | D15: =IF($A15="","",INDEX(Acciones!$U$5:$U$148,MATCH($A15,Acciones!$A$5:$A$148,0))) | E15: =IF($A15="","",INDEX(Acciones!$O$5:$O$148,MATCH($A15,Acciones!$A$5:$A$148,0))) | F15: =IF($A15="","",E15*SQRT($H$4/252)) | G15: =IF($A15="","",INDEX(Acciones!$Q$5:$Q$148,MATCH($A15,Acciones!$A$5:$A$148,0))) | H15: =IF($A15="","",IF(INDEX(Acciones!$G$5:$G$148,MATCH($A15,Acciones!$A$5:$A$148,0))="","n/d",INDEX(Acciones!$G$5:$G$148,MATCH($A15,Acciones!$A$5:$A$148,0)))) | I15: =IF($A15="","",INDEX(Acciones!$J$5:$J$148,MATCH($A15,Acciones!$A$5:$A$148,0))) | J15: =IF(OR($A15="",$B15=""),"",$B15*$C$4) | K15: =IF(J15="","",J15*(IF(ISNUMBER(H15),H15,0)+2*$C$5)) | L15: =IF(J15="","",J15*INDEX(Acciones!$T$5:$T$148,MATCH($A15,Acciones!$A$5:$A$148,0))) | M15: =IF(J15="","",J15*INDEX(Acciones!$S$5:$S$148,MATCH($A15,Acciones!$A$5:$A$148,0))) | N15: =IF($A15="","",INDEX(Acciones!$R$5:$R$148,MATCH($A15,Acciones!$A$5:$A$148,0))) | O15: =IF(OR($A15="",$B15=""),0,$B15*N15) -> 0
C16: =IF($A16="","",INDEX(Acciones!$B$5:$B$148,MATCH($A16,Acciones!$A$5:$A$148,0))) | D16: =IF($A16="","",INDEX(Acciones!$U$5:$U$148,MATCH($A16,Acciones!$A$5:$A$148,0))) | E16: =IF($A16="","",INDEX(Acciones!$O$5:$O$148,MATCH($A16,Acciones!$A$5:$A$148,0))) | F16: =IF($A16="","",E16*SQRT($H$4/252)) | G16: =IF($A16="","",INDEX(Acciones!$Q$5:$Q$148,MATCH($A16,Acciones!$A$5:$A$148,0))) | H16: =IF($A16="","",IF(INDEX(Acciones!$G$5:$G$148,MATCH($A16,Acciones!$A$5:$A$148,0))="","n/d",INDEX(Acciones!$G$5:$G$148,MATCH($A16,Acciones!$A$5:$A$148,0)))) | I16: =IF($A16="","",INDEX(Acciones!$J$5:$J$148,MATCH($A16,Acciones!$A$5:$A$148,0))) | J16: =IF(OR($A16="",$B16=""),"",$B16*$C$4) | K16: =IF(J16="","",J16*(IF(ISNUMBER(H16),H16,0)+2*$C$5)) | L16: =IF(J16="","",J16*INDEX(Acciones!$T$5:$T$148,MATCH($A16,Acciones!$A$5:$A$148,0))) | M16: =IF(J16="","",J16*INDEX(Acciones!$S$5:$S$148,MATCH($A16,Acciones!$A$5:$A$148,0))) | N16: =IF($A16="","",INDEX(Acciones!$R$5:$R$148,MATCH($A16,Acciones!$A$5:$A$148,0))) | O16: =IF(OR($A16="",$B16=""),0,$B16*N16) -> 0
C17: =IF($A17="","",INDEX(Acciones!$B$5:$B$148,MATCH($A17,Acciones!$A$5:$A$148,0))) | D17: =IF($A17="","",INDEX(Acciones!$U$5:$U$148,MATCH($A17,Acciones!$A$5:$A$148,0))) | E17: =IF($A17="","",INDEX(Acciones!$O$5:$O$148,MATCH($A17,Acciones!$A$5:$A$148,0))) | F17: =IF($A17="","",E17*SQRT($H$4/252)) | G17: =IF($A17="","",INDEX(Acciones!$Q$5:$Q$148,MATCH($A17,Acciones!$A$5:$A$148,0))) | H17: =IF($A17="","",IF(INDEX(Acciones!$G$5:$G$148,MATCH($A17,Acciones!$A$5:$A$148,0))="","n/d",INDEX(Acciones!$G$5:$G$148,MATCH($A17,Acciones!$A$5:$A$148,0)))) | I17: =IF($A17="","",INDEX(Acciones!$J$5:$J$148,MATCH($A17,Acciones!$A$5:$A$148,0))) | J17: =IF(OR($A17="",$B17=""),"",$B17*$C$4) | K17: =IF(J17="","",J17*(IF(ISNUMBER(H17),H17,0)+2*$C$5)) | L17: =IF(J17="","",J17*INDEX(Acciones!$T$5:$T$148,MATCH($A17,Acciones!$A$5:$A$148,0))) | M17: =IF(J17="","",J17*INDEX(Acciones!$S$5:$S$148,MATCH($A17,Acciones!$A$5:$A$148,0))) | N17: =IF($A17="","",INDEX(Acciones!$R$5:$R$148,MATCH($A17,Acciones!$A$5:$A$148,0))) | O17: =IF(OR($A17="",$B17=""),0,$B17*N17) -> 0
C18: =IF($A18="","",INDEX(Acciones!$B$5:$B$148,MATCH($A18,Acciones!$A$5:$A$148,0))) | D18: =IF($A18="","",INDEX(Acciones!$U$5:$U$148,MATCH($A18,Acciones!$A$5:$A$148,0))) | E18: =IF($A18="","",INDEX(Acciones!$O$5:$O$148,MATCH($A18,Acciones!$A$5:$A$148,0))) | F18: =IF($A18="","",E18*SQRT($H$4/252)) | G18: =IF($A18="","",INDEX(Acciones!$Q$5:$Q$148,MATCH($A18,Acciones!$A$5:$A$148,0))) | H18: =IF($A18="","",IF(INDEX(Acciones!$G$5:$G$148,MATCH($A18,Acciones!$A$5:$A$148,0))="","n/d",INDEX(Acciones!$G$5:$G$148,MATCH($A18,Acciones!$A$5:$A$148,0)))) | I18: =IF($A18="","",INDEX(Acciones!$J$5:$J$148,MATCH($A18,Acciones!$A$5:$A$148,0))) | J18: =IF(OR($A18="",$B18=""),"",$B18*$C$4) | K18: =IF(J18="","",J18*(IF(ISNUMBER(H18),H18,0)+2*$C$5)) | L18: =IF(J18="","",J18*INDEX(Acciones!$T$5:$T$148,MATCH($A18,Acciones!$A$5:$A$148,0))) | M18: =IF(J18="","",J18*INDEX(Acciones!$S$5:$S$148,MATCH($A18,Acciones!$A$5:$A$148,0))) | N18: =IF($A18="","",INDEX(Acciones!$R$5:$R$148,MATCH($A18,Acciones!$A$5:$A$148,0))) | O18: =IF(OR($A18="",$B18=""),0,$B18*N18) -> 0
C19: =IF($A19="","",INDEX(Acciones!$B$5:$B$148,MATCH($A19,Acciones!$A$5:$A$148,0))) | D19: =IF($A19="","",INDEX(Acciones!$U$5:$U$148,MATCH($A19,Acciones!$A$5:$A$148,0))) | E19: =IF($A19="","",INDEX(Acciones!$O$5:$O$148,MATCH($A19,Acciones!$A$5:$A$148,0))) | F19: =IF($A19="","",E19*SQRT($H$4/252)) | G19: =IF($A19="","",INDEX(Acciones!$Q$5:$Q$148,MATCH($A19,Acciones!$A$5:$A$148,0))) | H19: =IF($A19="","",IF(INDEX(Acciones!$G$5:$G$148,MATCH($A19,Acciones!$A$5:$A$148,0))="","n/d",INDEX(Acciones!$G$5:$G$148,MATCH($A19,Acciones!$A$5:$A$148,0)))) | I19: =IF($A19="","",INDEX(Acciones!$J$5:$J$148,MATCH($A19,Acciones!$A$5:$A$148,0))) | J19: =IF(OR($A19="",$B19=""),"",$B19*$C$4) | K19: =IF(J19="","",J19*(IF(ISNUMBER(H19),H19,0)+2*$C$5)) | L19: =IF(J19="","",J19*INDEX(Acciones!$T$5:$T$148,MATCH($A19,Acciones!$A$5:$A$148,0))) | M19: =IF(J19="","",J19*INDEX(Acciones!$S$5:$S$148,MATCH($A19,Acciones!$A$5:$A$148,0))) | N19: =IF($A19="","",INDEX(Acciones!$R$5:$R$148,MATCH($A19,Acciones!$A$5:$A$148,0))) | O19: =IF(OR($A19="",$B19=""),0,$B19*N19) -> 0
A21: Resumen y revisión de reglas
A22: Suma de pesos | B22: =SUM($B$8:$B$19) -> 1 | C22: =IF(ABS(B22-1)<0.0005,"OK: 100%",IF(B22<1,"Te falta "&TEXT(1-B22,"0.0%")&" por asignar (queda en efectivo, que no rinde)","Pasas de 100% por "&TEXT(B22-1,"0.0%"))) -> OK: 100%
A23: Emisoras distintas (mín. 5) | B23: =SUMPRODUCT(($A$8:$A$19<>"")*($B$8:$B$19>0)/COUNTIF($A$8:$A$19,$A$8:$A$19&"")) -> 5 | C23: =IF(B23>=5,"OK","REVISAR: necesitas al menos 5") -> OK
A24: Peso máximo en una emisora (máx. 50%) | B24: =MAX($B$8:$B$19) -> 0.5 | C24: =IF(B24<=0.5,"OK","REVISAR: ninguna puede pasar de 50%") -> OK
A25: Emisoras repetidas en la lista | B25: =SUMPRODUCT(($A$8:$A$19<>"")*(COUNTIF($A$8:$A$19,$A$8:$A$19)>1)) -> 0 | C25: =IF(B25=0,"OK","REVISAR: repetiste una emisora") -> OK
A26: Emisoras sin contraparte hoy | B26: =SUMPRODUCT(($A$8:$A$19<>"")*($I$8:$I$19<>"Sí")) -> 0 | C26: =IF(B26=0,"OK","REVISAR: hoy no hay quien compre o venda alguna de tus emisoras") -> OK
A27: Total a invertir ($) | B27: =SUM($J$8:$J$19) -> 1000000
A28: Comisión total de compra ($) | B28: =B27*$C$5 -> 1160
A29: Costo estimado ida y vuelta ($) | B29: =SUM($K$8:$K$19) -> 10980.278 | C29: ="Comisiones + diferencia compra-venta: "&TEXT(B29/$C$4,"0.00%")&" del capital" -> Comisiones + diferencia compra-venta: 1.10% del capital
A30: Volatilidad anual del portafolio | B30: =SQRT(Covarianza!$B$2) -> 0.64990176 | C30: Usa la correlación entre emisoras (hoja Covarianza).
A31: Mov. típico del portafolio (±1σ) en el lapso | B31: =B30*SQRT($H$4/252) -> 0.20469981 | C31: ~2 de cada 3 veces el resultado cae dentro de ± este porcentaje.
A32: Mov. típico en pesos (±1σ) | B32: =B31*SUM($J$8:$J$19) -> 204699.81 | C32: Solo la parte invertida; descuenta costos.
A33: Beta del portafolio vs IPC (aprox.) | B33: =SUM($O$8:$O$19) -> 1.3578575 | C33: 1 = se mueve como el IPC; >1 más; <1 menos.
A35: Los rangos son históricos y orientativos; el precio real puede salirse de ellos. No es una recomendación de inversión.

Sheet Portafolios
A1: Portafolios: ganador, alternativa balanceada y tu idea
A2: Pesos en celdas amarillas (se pueden cambiar). Pronóstico, alfa y costo salen de la hoja Acciones.
A4: Emisora | B4: Pronóstico 25 ses. | C4: Beta vs canasta | D4: Alfa | E4: Costo ida y vuelta | F4: Ganador: Ganar (máx. prob. top 3) · 5 emisoras | G4: Alternativa: Balanceado (ganancia/riesgo) · 5 emisoras | H4: Tu idea (NVDA + Banorte)
A5: PINFRA * | B5: =INDEX(Acciones!$AI$5:$AI$148,MATCH($A5,Acciones!$A$5:$A$148,0)) -> 0.00098557317 | C5: =INDEX(Acciones!$AF$5:$AF$148,MATCH($A5,Acciones!$A$5:$A$148,0)) -> 0.46574944 | D5: =INDEX(Acciones!$AG$5:$AG$148,MATCH($A5,Acciones!$A$5:$A$148,0)) -> -0.00013546506 | E5: =INDEX(Acciones!$AH$5:$AH$148,MATCH($A5,Acciones!$A$5:$A$148,0)) -> 0.0025753859 | F5: 0.03 | G5: 0 | H5: 0
A6: BOLSA A | B6: =INDEX(Acciones!$AI$5:$AI$148,MATCH($A6,Acciones!$A$5:$A$148,0)) -> 0.0019031141 | C6: =INDEX(Acciones!$AF$5:$AF$148,MATCH($A6,Acciones!$A$5:$A$148,0)) -> 0.57983186 | D6: =INDEX(Acciones!$AG$5:$AG$148,MATCH($A6,Acciones!$A$5:$A$148,0)) -> 0.0004727001 | E6: =INDEX(Acciones!$AH$5:$AH$148,MATCH($A6,Acciones!$A$5:$A$148,0)) -> 0.0031714261 | F6: 0.03 | G6: 0 | H6: 0
A7: GFNORTE O | B7: =INDEX(Acciones!$AI$5:$AI$148,MATCH($A7,Acciones!$A$5:$A$148,0)) -> 0.0030148751 | C7: =INDEX(Acciones!$AF$5:$AF$148,MATCH($A7,Acciones!$A$5:$A$148,0)) -> 0.55438802 | D7: =INDEX(Acciones!$AG$5:$AG$148,MATCH($A7,Acciones!$A$5:$A$148,0)) -> 0.0012515595 | E7: =INDEX(Acciones!$AH$5:$AH$148,MATCH($A7,Acciones!$A$5:$A$148,0)) -> 0.0026365893 | F7: 0.03 | G7: 0 | H7: 0.2
A8: INTC * | B8: =INDEX(Acciones!$AI$5:$AI$148,MATCH($A8,Acciones!$A$5:$A$148,0)) -> 0.020417025 | C8: =INDEX(Acciones!$AF$5:$AF$148,MATCH($A8,Acciones!$A$5:$A$148,0)) -> 2.2198287 | D8: =INDEX(Acciones!$AG$5:$AG$148,MATCH($A8,Acciones!$A$5:$A$148,0)) -> 0.015159538 | E8: =INDEX(Acciones!$AH$5:$AH$148,MATCH($A8,Acciones!$A$5:$A$148,0)) -> 0.012360201 | F8: 0.41 | G8: 0 | H8: 0
A9: MU * | B9: =INDEX(Acciones!$AI$5:$AI$148,MATCH($A9,Acciones!$A$5:$A$148,0)) -> 0.046074203 | C9: =INDEX(Acciones!$AF$5:$AF$148,MATCH($A9,Acciones!$A$5:$A$148,0)) -> 2.1544716 | D9: =INDEX(Acciones!$AG$5:$AG$148,MATCH($A9,Acciones!$A$5:$A$148,0)) -> 0.040297408 | E9: =INDEX(Acciones!$AH$5:$AH$148,MATCH($A9,Acciones!$A$5:$A$148,0)) -> 0.011322186 | F9: 0.5 | G9: 0.283 | H9: 0
A10: BABA N | B10: =INDEX(Acciones!$AI$5:$AI$148,MATCH($A10,Acciones!$A$5:$A$148,0)) -> 0.0089938062 | C10: =INDEX(Acciones!$AF$5:$AF$148,MATCH($A10,Acciones!$A$5:$A$148,0)) -> 0.94932214 | D10: =INDEX(Acciones!$AG$5:$AG$148,MATCH($A10,Acciones!$A$5:$A$148,0)) -> 0.0058475834 | E10: =INDEX(Acciones!$AH$5:$AH$148,MATCH($A10,Acciones!$A$5:$A$148,0)) -> 0.0043880799 | F10: 0 | G10: 0.086 | H10: 0
A11: GCC * | B11: =INDEX(Acciones!$AI$5:$AI$148,MATCH($A11,Acciones!$A$5:$A$148,0)) -> 0.0087097642 | C11: =INDEX(Acciones!$AF$5:$AF$148,MATCH($A11,Acciones!$A$5:$A$148,0)) -> 0.61055927 | D11: =INDEX(Acciones!$AG$5:$AG$148,MATCH($A11,Acciones!$A$5:$A$148,0)) -> 0.007554388 | E11: =INDEX(Acciones!$AH$5:$AH$148,MATCH($A11,Acciones!$A$5:$A$148,0)) -> 0.0036903323 | F11: 0 | G11: 0.167 | H11: 0
A12: CEMEX CPO | B12: =INDEX(Acciones!$AI$5:$AI$148,MATCH($A12,Acciones!$A$5:$A$148,0)) -> 0.01259636 | C12: =INDEX(Acciones!$AF$5:$AF$148,MATCH($A12,Acciones!$A$5:$A$148,0)) -> 0.95654766 | D12: =INDEX(Acciones!$AG$5:$AG$148,MATCH($A12,Acciones!$A$5:$A$148,0)) -> 0.0079012467 | E12: =INDEX(Acciones!$AH$5:$AH$148,MATCH($A12,Acciones!$A$5:$A$148,0)) -> 0.002896535 | F12: 0 | G12: 0.227 | H12: 0
A13: LAB B | B13: =INDEX(Acciones!$AI$5:$AI$148,MATCH($A13,Acciones!$A$5:$A$148,0)) -> 0.0083687665 | C13: =INDEX(Acciones!$AF$5:$AF$148,MATCH($A13,Acciones!$A$5:$A$148,0)) -> 0.62552022 | D13: =INDEX(Acciones!$AG$5:$AG$148,MATCH($A13,Acciones!$A$5:$A$148,0)) -> 0.0065089417 | E13: =INDEX(Acciones!$AH$5:$AH$148,MATCH($A13,Acciones!$A$5:$A$148,0)) -> 0.0031046214 | F13: 0 | G13: 0.237 | H13: 0
A14: NVDA * | B14: =INDEX(Acciones!$AI$5:$AI$148,MATCH($A14,Acciones!$A$5:$A$148,0)) -> 0.0078862285 | C14: =INDEX(Acciones!$AF$5:$AF$148,MATCH($A14,Acciones!$A$5:$A$148,0)) -> 1.0939895 | D14: =INDEX(Acciones!$AG$5:$AG$148,MATCH($A14,Acciones!$A$5:$A$148,0)) -> 0.0059578335 | E14: =INDEX(Acciones!$AH$5:$AH$148,MATCH($A14,Acciones!$A$5:$A$148,0)) -> 0.0067540614 | F14: 0 | G14: 0 | H14: 0.3
A15: GMEXICO B | B15: =INDEX(Acciones!$AI$5:$AI$148,MATCH($A15,Acciones!$A$5:$A$148,0)) -> 0.010287097 | C15: =INDEX(Acciones!$AF$5:$AF$148,MATCH($A15,Acciones!$A$5:$A$148,0)) -> 1.2348725 | D15: =INDEX(Acciones!$AG$5:$AG$148,MATCH($A15,Acciones!$A$5:$A$148,0)) -> 0.0028928806 | E15: =INDEX(Acciones!$AH$5:$AH$148,MATCH($A15,Acciones!$A$5:$A$148,0)) -> 0.0024063595 | F15: 0 | G15: 0 | H15: 0.2
A16: MSFT * | B16: =INDEX(Acciones!$AI$5:$AI$148,MATCH($A16,Acciones!$A$5:$A$148,0)) -> -0.0040369448 | C16: =INDEX(Acciones!$AF$5:$AF$148,MATCH($A16,Acciones!$A$5:$A$148,0)) -> 0.78798255 | D16: =INDEX(Acciones!$AG$5:$AG$148,MATCH($A16,Acciones!$A$5:$A$148,0)) -> -0.0061390696 | E16: =INDEX(Acciones!$AH$5:$AH$148,MATCH($A16,Acciones!$A$5:$A$148,0)) -> 0.0041517049 | F16: 0 | G16: 0 | H16: 0.15
A17: GOOGL * | B17: =INDEX(Acciones!$AI$5:$AI$148,MATCH($A17,Acciones!$A$5:$A$148,0)) -> 0.0060269147 | C17: =INDEX(Acciones!$AF$5:$AF$148,MATCH($A17,Acciones!$A$5:$A$148,0)) -> 1.0356739 | D17: =INDEX(Acciones!$AG$5:$AG$148,MATCH($A17,Acciones!$A$5:$A$148,0)) -> 0.0016992723 | E17: =INDEX(Acciones!$AH$5:$AH$148,MATCH($A17,Acciones!$A$5:$A$148,0)) -> 0.0038919918 | F17: 0 | G17: 0 | H17: 0.15
A19: Suma de pesos | F19: =SUM(F$5:F$17) -> 1 | G19: =SUM(G$5:G$17) -> 1 | H19: =SUM(H$5:H$17) -> 1
A20: Emisoras distintas (mín. 5) | F20: =COUNTIF(F$5:F$17,">0") -> 5 | G20: =COUNTIF(G$5:G$17,">0") -> 5 | H20: =COUNTIF(H$5:H$17,">0") -> 5
A21: Peso máximo (máx. 50%) | F21: =MAX(F$5:F$17) -> 0.5 | G21: =MAX(G$5:G$17) -> 0.283 | H21: =MAX(H$5:H$17) -> 0.3
A22: Revisión de reglas | F22: =IF(AND(ABS(F19-1)<0.0005,F20>=5,F21<=0.5),"OK","REVISAR") -> OK | G22: =IF(AND(ABS(G19-1)<0.0005,G20>=5,G21<=0.5),"OK","REVISAR") -> OK | H22: =IF(AND(ABS(H19-1)<0.0005,H20>=5,H21<=0.5),"OK","REVISAR") -> OK
A23: Beta vs canasta | F23: =SUMPRODUCT(F$5:F$17,$C$5:$C$17) -> 2.0353647 | G23: =SUMPRODUCT(G$5:G$17,$C$5:$C$17) -> 1.1587052 | H23: =SUMPRODUCT(H$5:H$17,$C$5:$C$17) -> 0.95959742
A24: Costo estimado ida y vuelta ($) | F24: =SUMPRODUCT(F$5:F$17,$E$5:$E$17)*'Mi portafolio'!$C$4 -> 10980.278 | G24: =SUMPRODUCT(G$5:G$17,$E$5:$E$17)*'Mi portafolio'!$C$4 -> 5591.1479 | H24: =SUMPRODUCT(H$5:H$17,$E$5:$E$17)*'Mi portafolio'!$C$4 -> 4241.3627
A25: Ganancia neta si el mercado baja ($) | F25: ='Mi portafolio'!$C$4*(SUMPRODUCT(F$5:F$17,$C$5:$C$17)*Pronóstico!$C$13+SUMPRODUCT(F$5:F$17,$D$5:$D$17))-F24 -> -68690.52 | G25: ='Mi portafolio'!$C$4*(SUMPRODUCT(G$5:G$17,$C$5:$C$17)*Pronóstico!$C$13+SUMPRODUCT(G$5:G$17,$D$5:$D$17))-G24 -> -36975.816 | H25: ='Mi portafolio'!$C$4*(SUMPRODUCT(H$5:H$17,$C$5:$C$17)*Pronóstico!$C$13+SUMPRODUCT(H$5:H$17,$D$5:$D$17))-H24 -> -41951.444
A26: Ganancia neta, escenario base ($) | F26: ='Mi portafolio'!$C$4*(SUMPRODUCT(F$5:F$17,$C$5:$C$17)*Pronóstico!$C$14+SUMPRODUCT(F$5:F$17,$D$5:$D$17))-F24 -> 31585.189 | G26: ='Mi portafolio'!$C$4*(SUMPRODUCT(G$5:G$17,$C$5:$C$17)*Pronóstico!$C$14+SUMPRODUCT(G$5:G$17,$D$5:$D$17))-G24 -> 20109.769 | H26: ='Mi portafolio'!$C$4*(SUMPRODUCT(H$5:H$17,$C$5:$C$17)*Pronóstico!$C$14+SUMPRODUCT(H$5:H$17,$D$5:$D$17))-H24 -> 5324.7583
A27: Ganancia neta si el mercado sube ($) | F27: ='Mi portafolio'!$C$4*(SUMPRODUCT(F$5:F$17,$C$5:$C$17)*Pronóstico!$C$15+SUMPRODUCT(F$5:F$17,$D$5:$D$17))-F24 -> 131860.9 | G27: ='Mi portafolio'!$C$4*(SUMPRODUCT(G$5:G$17,$C$5:$C$17)*Pronóstico!$C$15+SUMPRODUCT(G$5:G$17,$D$5:$D$17))-G24 -> 77195.354 | H27: ='Mi portafolio'!$C$4*(SUMPRODUCT(H$5:H$17,$C$5:$C$17)*Pronóstico!$C$15+SUMPRODUCT(H$5:H$17,$D$5:$D$17))-H24 -> 52600.961
A28: Ganancia esperada ($) | F28: =Pronóstico!$B$13*F25+Pronóstico!$B$14*F26+Pronóstico!$B$15*F27 -> 31585.189 | G28: =Pronóstico!$B$13*G25+Pronóstico!$B$14*G26+Pronóstico!$B$15*G27 -> 20109.769 | H28: =Pronóstico!$B$13*H25+Pronóstico!$B$14*H26+Pronóstico!$B$15*H27 -> 5324.7583

Sheet Acciones
A1: Las 145 acciones del Reto: mercado y datos históricos (precios actualizados: 8 de octubre de 2026, ~11:10 h CDMX)
A2: Último precio, rendimientos, volatilidad, beta y ventanas: Yahoo Finance al momento indicado (SIC = precio en dólares × tipo de cambio). Precio de compra/venta, diferencia y volumen: foto del monitor de la plataforma. No es una recomendación de inversión.
A4: Emisora | B4: Tipo | C4: Último precio ($) | D4: Var. del día | E4: Precio de compra ($) | F4: Precio de venta ($) | G4: Diferencia compra-venta | H4: Volumen compra | I4: Volumen venta | J4: ¿Operable hoy? | K4: Rend. 1 mes | L4: Rend. 3 meses | M4: Rend. 6 meses | N4: Rend. 12 meses | O4: Volatilidad anual (1 año) | P4: Mov. típico ±1σ en 25 sesiones | Q4: Peor caída (1 año) | R4: Beta vs IPC | S4: Mejor ventana 25 ses. (3 años) | T4: Peor ventana 25 ses. (3 años) | U4: Perfil por volatilidad | V4: Precio objetivo analistas ($) | W4: Potencial al objetivo | X4: Nº de analistas | Y4: Próximo reporte | Z4: ¿Reporta antes del 13-nov? | AA4: Importe operado diario ($, mexicanas) | AB4: Importe en mejor nivel del monitor ($) | AC4: ¿Líquida para el reto? | AD4: Momento 12-1 | AE4: Puntaje (z) | AF4: Beta vs canasta | AG4: Alfa (25 ses.) | AH4: Costo ida y vuelta | AI4: Pronóstico 25 ses. (neto)
A5: BRKB * | B5: Exterior (SIC) | C5: 9256.9408 | D5: 0.017592588 | E5: 9095.02 | F5: 9383.91 | G5: 0.031266962 | H5: 4540 | I5: 4437 | J5: Sí | K5: 0.080341301 | L5: 0.064611655 | M5: 0.13166246 | N5: 0.019998168 | O5: 0.1636282 | P5: 0.051538039 | Q5: -0.14409367 | R5: -0.018943812 | S5: 0.16964278 | T5: -0.10669456 | U5: Menor movimiento | V5: 9941.7935 | X5: 3 | Y5: 2026-11-07 | Z5: Sí | AA5: 4.1587311e+10 | AB5: 41024502 | AC5: Sí | AD5: -0.055855619 | AE5: -0.70161436 | AF5: 0.22234006 | AG5: =Pronóstico!$B$5*P5*AE5 -> -0.0018079914 | AH5: =IF(ISNUMBER(G5),G5,1)+2*'Mi portafolio'!$C$5 -> 0.033586962 | AI5: =AF5*Pronóstico!$B$8+AG5-AH5 -> -0.03363035
A6: SIGMAF A | B6: Mexicana | C6: 18.27 | D6: -0.0097614046 | E6: 18.24 | F6: 18.25 | G6: 0.0005480954 | H6: 915 | I6: 558 | J6: Sí | K6: -0.0041577083 | L6: 0.13925836 | M6: 0.16839548 | N6: 0.26047505 | O6: 0.17140322 | P6: 0.053986941 | Q6: -0.076276235 | R6: 0.27606045 | S6: 0.36138743 | T6: -0.29017615 | U6: Menor movimiento | V6: 21.96154 | W6: 0.20205473 | X6: 13 | Y6: 2026-10-27 | Z6: Sí | AA6: 1.9631986e+08 | AB6: 10177.92 | AC6: Sí | AD6: 0.26573762 | AE6: 0.38109012 | AF6: 0.080961132 | AG6: =Pronóstico!$B$5*P6*AE6 -> 0.0010286945 | AH6: =IF(ISNUMBER(G6),G6,1)+2*'Mi portafolio'!$C$5 -> 0.0028680954 | AI6: =AF6*Pronóstico!$B$8+AG6-AH6 -> -0.0011968522
A7: LIVEPOL C-1 | B7: Mexicana | C7: 102.63 | D7: -0.0027208123 | E7: 102.32 | F7: 102.53 | G7: 0.0020502807 | H7: 90 | I7: 322 | J7: Sí | K7: 0.036099249 | L7: 0.04129585 | M7: -0.028344037 | N7: 0.21008767 | O7: 0.1923828 | P7: 0.060594887 | Q7: -0.093163267 | R7: 0.19070879 | S7: 0.22779885 | T7: -0.16988791 | U7: Menor movimiento | V7: 121.85333 | W7: 0.18730712 | X7: 15 | Y7: 2026-10-26 | Z7: Sí | AA7: 26577589 | AB7: 9227.7 | AC7: Sí | AD7: 0.1679264 | AE7: 0.0099671564 | AF7: 0.13603299 | AG7: =Pronóstico!$B$5*P7*AE7 -> 3.0197936e-05 | AH7: =IF(ISNUMBER(G7),G7,1)+2*'Mi portafolio'!$C$5 -> 0.0043702807 | AI7: =AF7*Pronóstico!$B$8+AG7-AH7 -> -0.0032604558
A8: GRUMA B | B8: Mexicana | C8: 236.31 | D8: 0.0011862344 | E8: 236.41 | F8: 236.52 | G8: 0.0004651851 | H8: 28 | I8: 126 | J8: Sí | K8: 0.00093336623 | L8: -0.15384277 | M8: -0.21367341 | N8: -0.23815012 | O8: 0.19431637 | P8: 0.061203904 | Q8: -0.34068714 | R8: 0.44959422 | S8: 0.19377777 | T8: -0.12940001 | U8: Menor movimiento | V8: 336.53845 | W8: 0.42413969 | X8: 13 | Y8: 2026-10-21 | Z8: Sí | AA8: 1.2808089e+08 | AB8: 6626.2 | AC8: Sí | AD8: -0.23886054 | AE8: -0.046533891 | AF8: 0.32823286 | AG8: =Pronóstico!$B$5*P8*AE8 -> -0.00014240279 | AH8: =IF(ISNUMBER(G8),G8,1)+2*'Mi portafolio'!$C$5 -> 0.0027851851 | AI8: =AF8*Pronóstico!$B$8+AG8-AH8 -> -0.00032256515
A9: KO * | B9: Exterior (SIC) | C9: 1593.9405 | D9: 0.033297739 | E9: 1557.06 | F9: 1593.98 | G9: 0.023433533 | H9: 10809 | I9: 7200 | J9: Sí | K9: 0.082758688 | L9: 0.087189905 | M9: 0.24159178 | N9: 0.29686426 | O9: 0.20368899 | P9: 0.064156003 | Q9: -0.0891337 | R9: 0.014929544 | S9: 0.18931175 | T9: -0.088620351 | U9: Menor movimiento | V9: 1714.2745 | W9: 0.075494699 | X9: 23 | Y9: 2026-10-27 | Z9: Sí | AA9: 2.4643653e+10 | AB9: 11347200 | AC9: Sí | AD9: 0.1977408 | AE9: -0.45693769 | AF9: 0.17451437 | AG9: =Pronóstico!$B$5*P9*AE9 -> -0.0014657648 | AH9: =IF(ISNUMBER(G9),G9,1)+2*'Mi portafolio'!$C$5 -> 0.025753533 | AI9: =AF9*Pronóstico!$B$8+AG9-AH9 -> -0.025834263
A10: FIBRAMQ 12 | B10: Mexicana | C10: 44.7 | D10: -0.0024548227 | E10: 44.5 | F10: 44.64 | G10: 0.0031411263 | H10: 800 | I10: 704 | J10: Sí | K10: 0.050255958 | L10: -0.0025079808 | M10: 0.074129929 | N10: 0.61163255 | O10: 0.20399409 | P10: 0.064252099 | Q10: -0.097821091 | R10: 0.25057426 | S10: 0.23105558 | T10: -0.12913625 | U10: Menor movimiento | V10: 45.2 | W10: 0.011185682 | X10: 5 | Y10: 2026-10-22 | Z10: Sí | AA10: 19640045 | AB10: 31328 | AC10: No | AD10: 0.53451408 | AE10: 0.3343799 | AF10: 0.099824706 | AG10: =Pronóstico!$B$5*P10*AE10 -> 0.0010742305 | AH10: =IF(ISNUMBER(G10),G10,1)+2*'Mi portafolio'!$C$5 -> 0.0054611263 | AI10: =AF10*Pronóstico!$B$8+AG10-AH10 -> -0.0035946362
A11: VESTA * | B11: Mexicana | C11: 61.44 | D11: 0.011859681 | E11: 61.42 | F11: 61.43 | G11: 0.0001628002 | H11: 2852 | I11: 259 | J11: Sí | K11: 0.076020321 | L11: 0.028461291 | M11: -0.020362533 | N11: 0.26323597 | O11: 0.20555417 | P11: 0.064743477 | Q11: -0.10973071 | R11: 0.50655052 | S11: 0.24913269 | T11: -0.15201769 | U11: Menor movimiento | V11: 70.30285 | W11: 0.14425212 | X11: 13 | Y11: 2026-10-22 | Z11: Sí | AA11: 1.2720499e+08 | AB11: 15910.37 | AC11: Sí | AD11: 0.17398895 | AE11: -0.18630461 | AF11: 0.29134221 | AG11: =Pronóstico!$B$5*P11*AE11 -> -0.0006031004 | AH11: =IF(ISNUMBER(G11),G11,1)+2*'Mi portafolio'!$C$5 -> 0.0024828002 | AI11: =AF11*Pronóstico!$B$8+AG11-AH11 -> -0.00077366085
A12: MCD * | B12: Exterior (SIC) | C12: 4296.2705 | D12: 0.034819757 | E12: 4247.15 | F12: 4349.19 | G12: 0.023740336 | H12: 4000 | I12: 4100 | J12: Sí | K12: 0.0016071095 | L12: -0.093719102 | M12: -0.17622049 | N12: -0.22446979 | O12: 0.2083813 | P12: 0.06563394 | Q12: -0.29821461 | R12: 0.11188668 | S12: 0.23320535 | T12: -0.14651694 | U12: Menor movimiento | V12: 5332.5998 | W12: 0.24121604 | X12: 29 | Y12: 2026-11-04 | Z12: Sí | AA12: 2.7266259e+10 | AB12: 16904040 | AC12: Sí | AD12: -0.22571415 | AE12: -0.91878182 | AF12: 0.35088758 | AG12: =Pronóstico!$B$5*P12*AE12 -> -0.0030151635 | AH12: =IF(ISNUMBER(G12),G12,1)+2*'Mi portafolio'!$C$5 -> 0.026060336 | AI12: =AF12*Pronóstico!$B$8+AG12-AH12 -> -0.026290677
A13: JNJ * | B13: Exterior (SIC) | C13: 4646.6234 | D13: 0.00053527089 | E13: 4501.21 | F13: 4649.99 | G13: 0.032515954 | H13: 400 | I13: 400 | J13: Sí | K13: 0.028863284 | L13: 0.035120277 | M13: 0.14045199 | N13: 0.33423234 | O13: 0.20608619 | P13: 0.06491105 | Q13: -0.14032686 | R13: 0.076451413 | S13: 0.20093586 | T13: -0.11843229 | U13: Menor movimiento | V13: 5076.2386 | W13: 0.092457515 | X13: 22 | Y13: 2026-10-13 | Z13: Sí | AA13: 3.1676408e+10 | AB13: 1816800 | AC13: Sí | AD13: 0.29680237 | AE13: -0.070963462 | AF13: 0.17148039 | AG13: =Pronóstico!$B$5*P13*AE13 -> -0.00023031564 | AH13: =IF(ISNUMBER(G13),G13,1)+2*'Mi portafolio'!$C$5 -> 0.034835954 | AI13: =AF13*Pronóstico!$B$8+AG13-AH13 -> -0.033705314
A14: PG * | B14: Exterior (SIC) | C14: 2720.227 | D14: 0.024012943 | E14: 2696.01 | F14: 2749.99 | G14: 0.019823724 | H14: 1805 | I14: 1500 | J14: Sí | K14: 0.12768393 | L14: 0.055358738 | M14: 0.11603236 | N14: 0.0034504537 | O14: 0.20825066 | P14: 0.065592793 | Q14: -0.15054703 | R14: 0.14404813 | S14: 0.15501072 | T14: -0.11334235 | U14: Menor movimiento | V14: 2918.6867 | W14: 0.072957024 | X14: 23 | Y14: 2026-10-22 | Z14: Sí | AA14: 2.088026e+10 | AB14: 4065000 | AC14: Sí | AD14: -0.11016693 | AE14: -1.4063574 | AF14: 0.28100479 | AG14: =Pronóstico!$B$5*P14*AE14 -> -0.0046123454 | AH14: =IF(ISNUMBER(G14),G14,1)+2*'Mi portafolio'!$C$5 -> 0.022143724 | AI14: =AF14*Pronóstico!$B$8+AG14-AH14 -> -0.024525872
A15: WALMEX * | B15: Mexicana | C15: 46.72 | D15: 0.00021422438 | E15: 46.72 | F15: 46.74 | G15: 0.0004279906 | H15: 2268 | I15: 901 | J15: Sí | K15: 0.015659009 | L15: -0.059605298 | M15: -0.18527563 | N15: -0.22272242 | O15: 0.20278226 | P15: 0.063870409 | Q15: -0.27139285 | R15: 0.51770404 | S15: 0.18236067 | T15: -0.1722792 | U15: Menor movimiento | V15: 58.03889 | W15: 0.24227076 | X15: 18 | Y15: 2026-10-27 | Z15: Sí | AA15: 7.9408248e+08 | AB15: 42103.73 | AC15: Sí | AD15: -0.23470616 | AE15: -0.94087878 | AF15: 0.34880215 | AG15: =Pronóstico!$B$5*P15*AE15 -> -0.0030047156 | AH15: =IF(ISNUMBER(G15),G15,1)+2*'Mi portafolio'!$C$5 -> 0.0027479906 | AI15: =AF15*Pronóstico!$B$8+AG15-AH15 -> -0.0029844352
A16: AGNC * | B16: Exterior (SIC) | C16: 154.57279 | D16: 0.016187822 | E16: 153.49 | F16: 154.49 | G16: 0.0064939282 | H16: 3 | I16: 94400 | J16: Sí | K16: -0.11959635 | L16: -0.16827261 | M16: -0.10742562 | N16: -0.038805372 | O16: 0.21637238 | P16: 0.068150895 | Q16: -0.20711613 | R16: 0.4850167 | S16: 0.27763487 | T16: -0.19968507 | U16: Menor movimiento | V16: 196.65744 | W16: 0.27226424 | X16: 9 | Y16: 2026-10-19 | Z16: Sí | AA16: 7.4741164e+09 | AB16: 458.19 | AC16: No | AD16: 0.091765839 | AE16: 0.20194262 | AF16: 0.8128897 | AG16: =Pronóstico!$B$5*P16*AE16 -> 0.00068812851 | AH16: =IF(ISNUMBER(G16),G16,1)+2*'Mi portafolio'!$C$5 -> 0.0088139282 | AI16: =AF16*Pronóstico!$B$8+AG16-AH16 -> -0.0016742942
A17: PFE * | B17: Exterior (SIC) | C17: 502.92886 | D17: -0.00023398528 | E17: 494.96 | F17: 500.99 | G17: 0.012109042 | H17: 21300 | I17: 7100 | J17: Sí | K17: 0.070814403 | L17: 0.19468765 | M17: 0.10899095 | N17: 0.19164434 | O17: 0.21676642 | P17: 0.068275005 | Q17: -0.17472441 | R17: 0.18026826 | S17: 0.21572645 | T17: -0.18000236 | U17: Menor movimiento | V17: 526.96071 | W17: 0.047783794 | X17: 26 | Y17: 2026-11-03 | Z17: Sí | AA17: 1.6128297e+10 | AB17: 3564129 | AC17: Sí | AD17: 0.11283929 | AE17: -0.85343294 | AF17: 0.55461103 | AG17: =Pronóstico!$B$5*P17*AE17 -> -0.0029134069 | AH17: =IF(ISNUMBER(G17),G17,1)+2*'Mi portafolio'!$C$5 -> 0.014429042 | AI17: =AF17*Pronóstico!$B$8+AG17-AH17 -> -0.012940774
... A19: COST * | B19: Exterior (SIC) | C19: 17202.327 | D19: 0.016083073 | E19: 17050.01 | F19: 17256.99 | G19: 0.012066342 | H19: 4820 | I19: 4520 | J19: Sí | K19: 0.12717176 | L19: 0.062796784 | M19: 0.015611839 | N19: 0.0027417381 | O19: 0.21774762 | P19: 0.068584053 | Q19: -0.19236377 | R19: 0.11593723 | S19: 0.23525626 | T19: -0.18956705 | U19: Menor movimiento | V19: 19204.837 | W19: 0.11640925 | X19: 35 | Y19: 2026-12-10 | Z19: No | AA19: 3.8258309e+10 | AB19: 77811800 | AC19: Sí | AD19: -0.11039136 | AE19: -1.190343 | AF19: 0.22688101 | AG19: =Pronóstico!$B$5*P19*AE19 -> -0.0040819275 | AH19: =IF(ISNUMBER(G19),G19,1)+2*'Mi portafolio'!$C$5 -> 0.014386342 | AI19: =AF19*Pronóstico!$B$8+AG19-AH19 -> -0.016667627
A20: ACTINVR B | B20: Mexicana | C20: 21.51 | D20: 0 | E20: 21.51 | F20: 21.55 | G20: 0.0018578727 | H20: 247 | I20: 5153 | J20: Sí | K20: 0.0027032912 | L20: 0.0027032912 | M20: 0.029508048 | N20: 0.15412448 | O20: 0.21962124 | P20: 0.069174188 | Q20: -0.073215979 | R20: 0.12603034 | S20: 0.13520399 | T20: -0.056122388 | U20: Menor movimiento | V20: 26 | X20: 1 | Z20: No | AA20: 347686.37 | AB20: 5322.85 | AC20: No | AD20: 0.15101295 | AE20: 0.55712041 | AF20: 0.096204868 | AG20: =Pronóstico!$B$5*P20*AE20 -> 0.0019269176 | AH20: =IF(ISNUMBER(G20),G20,1)+2*'Mi portafolio'!$C$5 -> 0.0041778727 | AI20: =AF20*Pronóstico!$B$8+AG20-AH20 -> -0.0014874244
A21: PEP * | B21: Exterior (SIC) | C21: 2290.0009 | D21: 0.029865438 | E21: 2270.01 | F21: 2275.34 | G21: 0.0023452539 | H21: 2906 | I21: 2 | J21: Sí | K21: -0.0093760759 | L21: -0.045162345 | M21: -0.12472754 | N21: -0.15899271 | O21: 0.21929056 | P21: 0.069070034 | Q21: -0.2322844 | R21: 0.10174295 | S21: 0.179695 | T21: -0.16973098 | U21: Menor movimiento | V21: 2698.1956 | W21: 0.17825089 | X21: 22 | Y21: 2026-10-08 | Z21: Sí | AA21: 2.2981961e+10 | AB21: 4548 | AC21: No | AD21: -0.15103273 | AE21: -1.005583 | AF21: 0.26474483 | AG21: =Pronóstico!$B$5*P21*AE21 -> -0.0034727824 | AH21: =IF(ISNUMBER(G21),G21,1)+2*'Mi portafolio'!$C$5 -> 0.0046652539 | AI21: =AF21*Pronóstico!$B$8+AG21-AH21 -> -0.0060368869
A22: CHDRAUI B | B22: Mexicana | C22: 86.54 | D22: 0.01204536 | E22: 86.61 | F22: 86.62 | G22: 0.0001154534 | H22: 112 | I22: 97 | J22: Sí | K22: -0.0072272257 | L22: -0.046391174 | M22: -0.14361098 | N22: -0.33565553 | O22: 0.2198246 | P22: 0.069238241 | Q22: -0.37763975 | R22: 0.52338023 | S22: 0.31205047 | T22: -0.17922149 | U22: Menor movimiento | V22: 122.5 | W22: 0.41553039 | X22: 14 | Y22: 2026-10-20 | Z22: Sí | AA22: 1.4192412e+08 | AB22: 8400.2 | AC22: Sí | AD22: -0.33081921 | AE22: -0.36923944 | AF22: 0.27817118 | AG22: =Pronóstico!$B$5*P22*AE22 -> -0.0012782745 | AH22: =IF(ISNUMBER(G22),G22,1)+2*'Mi portafolio'!$C$5 -> 0.0024354534 | AI22: =AF22*Pronóstico!$B$8+AG22-AH22 -> -0.0015060201
A23: BAC * | B23: Exterior (SIC) | C23: 959.11375 | D23: -0.0030782897 | E23: 950.01 | F23: 960.99 | G23: 0.011491366 | H23: 20000 | I23: 16300 | J23: Sí | K23: -0.095293865 | L23: -0.074560759 | M23: 0.033515406 | N23: 0.036061117 | O23: 0.21847827 | P23: 0.068814188 | Q23: -0.18944752 | R23: 0.27670563 | S23: 0.22980018 | T23: -0.26858456 | U23: Menor movimiento | V23: 1216.251 | W23: 0.2680988 | X23: 22 | Y23: 2026-10-14 | Z23: Sí | AA23: 3.9893822e+10 | AB23: 15550200 | AC23: Sí | AD23: 0.14519077 | AE23: 0.34370702 | AF23: 0.7009282 | AG23: =Pronóstico!$B$5*P23*AE23 -> 0.001182596 | AH23: =IF(ISNUMBER(G23),G23,1)+2*'Mi portafolio'!$C$5 -> 0.013811366 | AI23: =AF23*Pronóstico!$B$8+AG23-AH23 -> -0.0070658476
A24: GFINBUR O | B24: Mexicana | C24: 41.58 | D24: 0.0036206016 | E24: 41.58 | F24: 41.59 | G24: 0.0002404713 | H24: 716 | I24: 410 | J24: Sí | K24: -0.034146282 | L24: 0.0058055558 | M24: -0.055895088 | N24: -0.11301244 | O24: 0.2235518 | P24: 0.070412198 | Q24: -0.12223367 | R24: 0.81363975 | S24: 0.23621694 | T24: -0.17531056 | U24: Menor movimiento | V24: 44.71429 | W24: 0.07537975 | X24: 7 | Y24: 2025-07-21 | Z24: No | AA24: 1.4897571e+08 | AB24: 17051.9 | AC24: Sí | AD24: -0.081654349 | AE24: -1.3075298 | AF24: 0.57167421 | AG24: =Pronóstico!$B$5*P24*AE24 -> -0.0046033024 | AH24: =IF(ISNUMBER(G24),G24,1)+2*'Mi portafolio'!$C$5 -> 0.0025604713 | AI24: =AF24*Pronóstico!$B$8+AG24-AH24 -> -0.0026266768
A25: FUNO 11 | B25: Mexicana | C25: 30.37 | D25: 0.010302408 | E25: 30.37 | F25: 30.38 | G25: 0.0003292181 | H25: 6802 | I25: 5146 | J25: Sí | K25: 0.024603962 | L25: 0.031905553 | M25: 0.016941934 | N25: 0.22567808 | O25: 0.2260136 | P25: 0.071187593 | Q25: -0.12018598 | R25: 0.68982327 | S25: 0.19612239 | T25: -0.14241611 | U25: Menor movimiento | V25: 34.46154 | W25: 0.13472308 | X25: 13 | Y25: 2026-10-28 | Z25: Sí | AA25: 1.8404144e+08 | AB25: 156335.48 | AC25: Sí | AD25: 0.1962457 | AE25: -0.16611318 | AF25: 0.29624718 | AG25: =Pronóstico!$B$5*P25*AE25 -> -0.00059125988 | AH25: =IF(ISNUMBER(G25),G25,1)+2*'Mi portafolio'!$C$5 -> 0.0026492181 | AI25: =AF25*Pronóstico!$B$8+AG25-AH25 -> -0.00088930986
A26: FEMSA UBD | B26: Mexicana | C26: 216.08 | D26: 0.024415727 | E26: 215.82 | F26: 216.09 | G26: 0.0012502605 | H26: 291 | I26: 229 | J26: Sí | K26: 0.083107779 | L26: -0.027786485 | M26: 0.09945279 | N26: 0.28512061 | O26: 0.22800933 | P26: 0.071816188 | Q26: -0.13933176 | R26: 0.64848682 | S26: 0.17211638 | T26: -0.1659036 | U26: Menor movimiento | V26: 249.33333 | W26: 0.1538936 | X26: 12 | Y26: 2025-07-22 | Z26: No | AA26: 6.9343941e+08 | AB26: 49422.78 | AC26: Sí | AD26: 0.18651221 | AE26: -0.10012211 | AF26: 0.30660168 | AG26: =Pronóstico!$B$5*P26*AE26 -> -0.00035951943 | AH26: =IF(ISNUMBER(G26),G26,1)+2*'Mi portafolio'!$C$5 -> 0.0035702605 | AI26: =AF26*Pronóstico!$B$8+AG26-AH26 -> -0.0014964333
A27: JPM * | B27: Exterior (SIC) | C27: 5982.3211 | D27: 0.009520457 | E27: 5868.03 | F27: 5994.99 | G27: 0.02140433 | H27: 6702 | I27: 6502 | J27: Sí | K27: 0.0017373364 | L27: 0.026312755 | M27: 0.14342048 | N27: 0.11117476 | O27: 0.23090497 | P27: 0.072728229 | Q27: -0.16264195 | R27: 0.3508067 | S27: 0.23002535 | T27: -0.22107846 | U27: Menor movimiento | V27: 6765.293 | W27: 0.13088096 | X27: 22 | Y27: 2026-10-13 | Z27: Sí | AA27: 5.2304313e+10 | AB27: 38426820 | AC27: Sí | AD27: 0.10924763 | AE27: -0.44995285 | AF27: 0.77428161 | AG27: =Pronóstico!$B$5*P27*AE27 -> -0.0016362137 | AH27: =IF(ISNUMBER(G27),G27,1)+2*'Mi portafolio'!$C$5 -> 0.02372433 | AI27: =AF27*Pronóstico!$B$8+AG27-AH27 -> -0.019215452
A28: V * | B28: Exterior (SIC) | C28: 6859.6556 | D28: 0.025731419 | E28: 6803.63 | F28: 6848.94 | G28: 0.0066375781 | H28: 6600 | I28: 4200 | J28: Sí | K28: 0.10396687 | L28: 0.097481772 | M28: 0.26320587 | N28: 0.097141258 | O28: 0.23656975 | P28: 0.074512468 | Q28: -0.1801713 | R28: 0.093311155 | S28: 0.1912757 | T28: -0.15886462 | U28: Menor movimiento | V28: 7612.6716 | W28: 0.10977461 | X28: 37 | Y28: 2026-10-27 | Z28: Sí | AA28: 3.9731066e+10 | AB28: 28728000 | AC28: Sí | AD28: -0.0061828096 | AE28: -0.90639085 | AF28: 0.52346509 | AG28: =Pronóstico!$B$5*P28*AE28 -> -0.0033768709 | AH28: =IF(ISNUMBER(G28),G28,1)+2*'Mi portafolio'!$C$5 -> 0.0089575781 | AI28: =AF28*Pronóstico!$B$8+AG28-AH28 -> -0.0081799642
A29: KIMBER A | B29: Mexicana | C29: 37.71 | D29: 0.0090982115 | E29: 37.71 | F29: 37.73 | G29: 0.0005302227 | H29: 2983 | I29: 1629 | J29: Sí | K29: -0.009247703 | L29: 0.0011266593 | M29: -0.076516534 | N29: 0.1087984 | O29: 0.23592237 | P29: 0.074308561 | Q29: -0.17579968 | R29: 0.7363349 | S29: 0.15435276 | T29: -0.16163017 | U29: Menor movimiento | V29: 43.59091 | W29: 0.15595094 | X29: 11 | Y29: 2026-10-20 | Z29: Sí | AA29: 1.7979019e+08 | AB29: 61429.59 | AC29: Sí | AD29: 0.11914795 | AE29: -0.29480806 | AF29: 0.45097138 | AG29: =Pronóstico!$B$5*P29*AE29 -> -0.0010953381 | AH29: =IF(ISNUMBER(G29),G29,1)+2*'Mi portafolio'!$C$5 -> 0.0028502227 | AI29: =AF29*Pronóstico!$B$8+AG29-AH29 -> -0.00036642293
A30: KOF UBL | B30: Mexicana | C30: 198.33 | D30: 0.025862515 | E30: 198.69 | F30: 199.08 | G30: 0.0019609322 | H30: 587 | I30: 59 | J30: Sí | K30: 0.076009082 | L30: 0.094174158 | M30: 0.13707268 | N30: 0.2995855 | O30: 0.23309291 | P30: 0.073417366 | Q30: -0.15870433 | R30: 0.58596428 | S30: 0.21101562 | T30: -0.15020504 | U30: Menor movimiento | V30: 213.20769 | W30: 0.075014824 | X30: 13 | Y30: 2025-07-17 | Z30: No | AA30: 1.6318204e+08 | AB30: 11722.71 | AC30: Sí | AD30: 0.20778302 | AE30: -0.42877884 | AF30: 0.38495766 | AG30: =Pronóstico!$B$5*P30*AE30 -> -0.0015739907 | AH30: =IF(ISNUMBER(G30),G30,1)+2*'Mi portafolio'!$C$5 -> 0.0042809322 | AI30: =AF30*Pronóstico!$B$8+AG30-AH30 -> -0.0027997033
A31: MA * | B31: Exterior (SIC) | C31: 10498.243 | D31: 0.024964528 | E31: 10250.01 | F31: 10499.99 | G31: 0.024094458 | H31: 2215 | I31: 2000 | J31: Sí | K31: 0.094091367 | L31: 0.11575001 | M31: 0.17226446 | N31: 0.020495019 | O31: 0.23870872 | P31: 0.075186181 | Q31: -0.2265354 | R31: 0.0085650936 | S31: 0.19867292 | T31: -0.17198753 | U31: Menor movimiento | V31: 12102.856 | W31: 0.15284583 | X31: 37 | Y31: 2026-10-29 | Z31: Sí | AA31: 2.797862e+10 | AB31: 20819940 | AC31: Sí | AD31: -0.067267095 | AE31: -0.87743383 | AF31: 0.50542278 | AG31: =Pronóstico!$B$5*P31*AE31 -> -0.0032985449 | AH31: =IF(ISNUMBER(G31),G31,1)+2*'Mi portafolio'!$C$5 -> 0.026414458 | AI31: =AF31*Pronóstico!$B$8+AG31-AH31 -> -0.025701711
A32: FIBRAPL 14 | B32: Mexicana | C32: 75.98 | D32: 0.012661663 | E32: 75.84 | F32: 75.9 | G32: 0.0007908264 | H32: 863 | I32: 595 | J32: Sí | K32: 0.008494917 | L32: 0.003318486 | M32: -0.069242862 | N32: 0.091180513 | O32: 0.24024941 | P32: 0.07567145 | Q32: -0.15115795 | R32: 0.44505718 | S32: 0.35489541 | T32: -0.13730882 | U32: Menor movimiento | V32: 84.28815 | W32: 0.10934654 | X32: 13 | Y32: 2026-10-21 | Z32: Sí | AA32: 1.4631058e+08 | AB32: 45160.5 | AC32: Sí | AD32: 0.081989105 | AE32: -0.64027549 | AF32: 0.2429347 | AG32: =Pronóstico!$B$5*P32*AE32 -> -0.0024225288 | AH32: =IF(ISNUMBER(G32),G32,1)+2*'Mi portafolio'!$C$5 -> 0.0031108264 | AI32: =AF32*Pronóstico!$B$8+AG32-AH32 -> -0.003605302
... A60: MRK * | B60: Exterior (SIC) | C60: 2558.3023 | D60: -0.00094915838 | E60: 2480.51 | F60: 2603.49 | G60: 0.048379229 | H60: 800 | I60: 1000 | J60: Sí | K60: 0.033596608 | L60: 0.18793359 | M60: 0.27666869 | N60: 0.68851842 | O60: 0.30287054 | P60: 0.095395254 | Q60: -0.12374868 | R60: 0.30803108 | S60: 0.21206506 | T60: -0.19341873 | U60: Movimiento medio | V60: 2836.9508 | W60: 0.10891932 | X60: 25 | Y60: 2026-10-29 | Z60: Sí | AA60: 2.5388129e+10 | AB60: 2024800 | AC60: Sí | AD60: 0.63363386 | AE60: 1.0358925 | AF60: 0.63743921 | AG60: =Pronóstico!$B$5*P60*AE60 -> 0.0049409613 | AH60: =IF(ISNUMBER(G60),G60,1)+2*'Mi portafolio'!$C$5 -> 0.050699229 | AI60: =AF60*Pronóstico!$B$8+AG60-AH60 -> -0.040699226
A61: MEGA CPO | B61: Mexicana | C61: 52.41 | D61: 0.00019088051 | E61: 52.43 | F61: 52.47 | G61: 0.0007626311 | H61: 364 | I61: 59 | J61: Sí | K61: 0.015310096 | L61: -0.14535073 | M61: -0.085248263 | N61: 0.048496415 | O61: 0.30184271 | P61: 0.095071517 | Q61: -0.22542897 | R61: 0.76856516 | S61: 0.3158819 | T61: -0.17648936 | U61: Movimiento medio | V61: 69.62308 | W61: 0.32843122 | X61: 13 | Z61: No | AA61: 55956880 | AB61: 3095.73 | AC61: Sí | AD61: 0.032685895 | AE61: 0.30230636 | AF61: 0.65165283 | AG61: =Pronóstico!$B$5*P61*AE61 -> 0.0014370362 | AH61: =IF(ISNUMBER(G61),G61,1)+2*'Mi portafolio'!$C$5 -> 0.0030826311 | AI61: =AF61*Pronóstico!$B$8+AG61-AH61 -> 0.0035262529
A62: TMO * | B62: Exterior (SIC) | C62: 11704.691 | D62: -0.01569568 | E62: 11328.81 | F62: 11899.99 | G62: 0.049178606 | H62: 3626 | I62: 3726 | J62: Sí | K62: 0.14419268 | L62: 0.26702102 | M62: 0.27876649 | N62: 0.18310166 | O62: 0.30466837 | P62: 0.095961517 | Q62: -0.32460277 | R62: 0.14967227 | S62: 0.23917808 | T62: -0.21857484 | U62: Movimiento medio | V62: 12125.478 | W62: 0.035950247 | X62: 25 | Y62: 2026-10-21 | Z62: Sí | AA62: 2.8026537e+10 | AB62: 43003997 | AC62: Sí | AD62: 0.03400562 | AE62: -1.152287 | AF62: 0.86064042 | AG62: =Pronóstico!$B$5*P62*AE62 -> -0.0055287605 | AH62: =IF(ISNUMBER(G62),G62,1)+2*'Mi portafolio'!$C$5 -> 0.051498606 | AI62: =AF62*Pronóstico!$B$8+AG62-AH62 -> -0.050196887
A63: LAB B | B63: Mexicana | C63: 12.75 | D63: -0.0046764978 | E63: 12.74 | F63: 12.75 | G63: 0.0007846214 | H63: 835 | I63: 753 | J63: Sí | K63: 0.0046840883 | L63: -0.14273157 | M63: -0.27414272 | N63: -0.22112882 | O63: 0.30194093 | P63: 0.095102453 | Q63: -0.35305505 | R63: 0.73312063 | S63: 0.27313876 | T63: -0.22825232 | U63: Movimiento medio | V63: 21.66667 | W63: 0.69934667 | X63: 6 | Y63: 2026-10-21 | Z63: Sí | AA63: 46477058 | AB63: 9593.22 | AC63: Sí | AD63: -0.22476011 | AE63: 1.3688273 | AF63: 0.62552022 | AG63: =Pronóstico!$B$5*P63*AE63 -> 0.0065089417 | AH63: =IF(ISNUMBER(G63),G63,1)+2*'Mi portafolio'!$C$5 -> 0.0031046214 | AI63: =AF63*Pronóstico!$B$8+AG63-AH63 -> 0.0083687665
A64: CUERVO * | B64: Mexicana | C64: 13.91 | D64: 0.016093655 | E64: 13.89 | F64: 13.9 | G64: 0.0007196833 | H64: 300 | I64: 910 | J64: Sí | K64: -0.078301219 | L64: -0.042068942 | M64: -0.083282299 | N64: -0.33156005 | O64: 0.30157746 | P64: 0.09498797 | Q64: -0.43884505 | R64: 0.36704266 | S64: 0.34441944 | T64: -0.27718597 | U64: Movimiento medio | V64: 19.24545 | W64: 0.38356937 | X64: 11 | Y64: 2026-10-28 | Z64: Sí | AA64: 22109779 | AB64: 4167 | AC64: Sí | AD64: -0.27477397 | AE64: -0.35812021 | AF64: 0.39967892 | AG64: =Pronóstico!$B$5*P64*AE64 -> -0.0017008556 | AH64: =IF(ISNUMBER(G64),G64,1)+2*'Mi portafolio'!$C$5 -> 0.0030396833 | AI64: =AF64*Pronóstico!$B$8+AG64-AH64 -> -0.001568484
A65: SITES1 A-1 | B65: Mexicana | C65: 16.36 | D65: -0.0090853796 | E65: 16.36 | F65: 16.41 | G65: 0.0030515716 | H65: 21551 | I65: 100 | J65: Sí | K65: -0.02035929 | L65: -0.049941855 | M65: 0.037659305 | N65: 0.007870041 | O65: 0.30888654 | P65: 0.097290117 | Q65: -0.2230679 | R65: 0.26032041 | S65: 0.66834688 | T65: -0.27544425 | U65: Movimiento medio | V65: 21 | X65: 3 | Y65: 2025-05-12 | Z65: No | AA65: 700014.64 | AB65: 1641 | AC65: No | AD65: 0.028816004 | AE65: -0.1864123 | AF65: 0.034683437 | AG65: =Pronóstico!$B$5*P65*AE65 -> -0.0009068037 | AH65: =IF(ISNUMBER(G65),G65,1)+2*'Mi portafolio'!$C$5 -> 0.0053715716 | AI65: =AF65*Pronóstico!$B$8+AG65-AH65 -> -0.0060031099
A66: GAP B | B66: Mexicana | C66: 352.55 | D66: -0.026312851 | E66: 354.39 | F66: 354.82 | G66: 0.0012126169 | H66: 479 | I66: 666 | J66: Sí | K66: 0.0019055586 | L66: -0.13584851 | M66: -0.15923628 | N66: -0.13523332 | O66: 0.31773593 | P66: 0.10007741 | Q66: -0.32962039 | R66: 0.98806233 | S66: 0.42547331 | T66: -0.19522696 | U66: Movimiento medio | V66: 463.42307 | W66: 0.31448892 | X66: 13 | Y66: 2026-10-19 | Z66: Sí | AA66: 5.7796123e+08 | AB66: 169752.81 | AC66: Sí | AD66: -0.13687805 | AE66: -0.28309763 | AF66: 0.60445578 | AG66: =Pronóstico!$B$5*P66*AE66 -> -0.0014165839 | AH66: =IF(ISNUMBER(G66),G66,1)+2*'Mi portafolio'!$C$5 -> 0.0035326169 | AI66: =AF66*Pronóstico!$B$8+AG66-AH66 -> -0.0001519327
A67: TX * | B67: Exterior (SIC) | C67: 1024.7368 | D67: 0.010318698 | E67: 1000.41 | F67: 1049.19 | G67: 0.047599532 | H67: 1000 | I67: 1515 | J67: Sí | K67: 0.042206228 | L67: 0.30533889 | M67: 0.43153218 | N67: 0.61121898 | O67: 0.31725476 | P67: 0.099925855 | Q67: -0.18257028 | R67: 0.69662482 | S67: 0.27507941 | T67: -0.18330572 | U67: Movimiento medio | V67: 1072.4233 | W67: 0.046535341 | X67: 13 | Y67: 2026-11-03 | Z67: Sí | AA67: 4.1215303e+08 | AB67: 1009060 | AC67: Sí | AD67: 0.54596944 | AE67: 0.45807614 | AF67: 1.0638475 | AG67: =Pronóstico!$B$5*P67*AE67 -> 0.0022886825 | AH67: =IF(ISNUMBER(G67),G67,1)+2*'Mi portafolio'!$C$5 -> 0.049919532 | AI67: =AF67*Pronóstico!$B$8+AG67-AH67 -> -0.039187615
A68: TGT * | B68: Exterior (SIC) | C68: 2822.1561 | D68: 0.040886777 | E68: 2755.91 | F68: 2886.09 | G68: 0.046146756 | H68: 1000 | I68: 1200 | J68: Sí | K68: 0.059752923 | L68: 0.20602217 | M68: 0.35440265 | N68: 0.75431948 | O68: 0.32064442 | P68: 0.1009935 | Q68: -0.13812185 | R68: 0.14400546 | S68: 0.31531402 | T68: -0.24934219 | U68: Movimiento medio | V68: 2989.3719 | W68: 0.059251085 | X68: 34 | Y68: 2026-11-18 | Z68: No | AA68: 1.0283449e+10 | AB68: 2805000 | AC68: Sí | AD68: 0.65540424 | AE68: 0.85442917 | AF68: 0.74979241 | AG68: =Pronóstico!$B$5*P68*AE68 -> 0.0043145896 | AH68: =IF(ISNUMBER(G68),G68,1)+2*'Mi portafolio'!$C$5 -> 0.048466756 | AI68: =AF68*Pronóstico!$B$8+AG68-AH68 -> -0.038201434
A69: CVS * | B69: Exterior (SIC) | C69: 1605.0882 | D69: 0.014364247 | E69: 1562.11 | F69: 1638.29 | G69: 0.047606549 | H69: 2400 | I69: 1600 | J69: Sí | K69: -0.0060546374 | L69: -0.12965438 | M69: 0.25759503 | N69: 0.087519169 | O69: 0.31983121 | P69: 0.10073736 | Q69: -0.22468687 | R69: 0.17836607 | S69: 0.47033092 | T69: -0.28591928 | U69: Movimiento medio | V69: 2101.3913 | W69: 0.30920606 | X69: 25 | Y69: 2026-11-04 | Z69: Sí | AA69: 1.3955011e+10 | AB69: 2548800 | AC69: Sí | AD69: 0.094143813 | AE69: 0.39340686 | AF69: 0.35750459 | AG69: =Pronóstico!$B$5*P69*AE69 -> 0.0019815385 | AH69: =IF(ISNUMBER(G69),G69,1)+2*'Mi portafolio'!$C$5 -> 0.049926549 | AI69: =AF69*Pronóstico!$B$8+AG69-AH69 -> -0.045107673
A70: GOOGL * | B70: Exterior (SIC) | C70: 6330.7679 | D70: 0.0050324098 | E70: 6350 | F70: 6359.99 | G70: 0.0015719918 | H70: 7 | I70: 450 | J70: Sí | K70: 0.1321126 | L70: 0.026722893 | M70: 0.089583943 | N70: 0.35943049 | O70: 0.32670775 | P70: 0.10290327 | Q70: -0.20257148 | R70: 0.42259009 | S70: 0.37025331 | T70: -0.2102118 | U70: Movimiento medio | V70: 7796.2426 | W70: 0.23148449 | X70: 54 | Y70: 2026-10-28 | Z70: Sí | AA70: 1.6350069e+11 | AB70: 44450 | AC70: Sí | AD70: 0.20079088 | AE70: 0.33026595 | AF70: 1.0356739 | AG70: =Pronóstico!$B$5*P70*AE70 -> 0.0016992723 | AH70: =IF(ISNUMBER(G70),G70,1)+2*'Mi portafolio'!$C$5 -> 0.0038919918 | AI70: =AF70*Pronóstico!$B$8+AG70-AH70 -> 0.0060269147
A71: MSFT * | B71: Exterior (SIC) | C71: 9509.9936 | D71: -0.00016356657 | E71: 9643.37 | F71: 9661.05 | G71: 0.0018317049 | H71: 200 | I71: 950 | J71: Sí | K71: 0.14483302 | L71: 0.39359577 | M71: 0.34688041 | N71: 0.013805823 | O71: 0.33138521 | P71: 0.10437653 | Q71: -0.37298451 | R71: 0.089633169 | S71: 0.3101564 | T71: -0.2156225 | U71: Movimiento medio | V71: 10667.316 | W71: 0.12169543 | X71: 53 | Y71: 2026-10-28 | Z71: Sí | AA71: 1.9967086e+11 | AB71: 1928000 | AC71: Sí | AD71: -0.11445092 | AE71: -1.1763314 | AF71: 0.78798255 | AG71: =Pronóstico!$B$5*P71*AE71 -> -0.0061390696 | AH71: =IF(ISNUMBER(G71),G71,1)+2*'Mi portafolio'!$C$5 -> 0.0041517049 | AI71: =AF71*Pronóstico!$B$8+AG71-AH71 -> -0.0040369448
A72: CEMEX CPO | B72: Mexicana | C72: 17.32 | D72: -0.0011527641 | E72: 17.34 | F72: 17.35 | G72: 0.000576535 | H72: 23993 | I72: 2456 | J72: Sí | K72: -0.056875647 | L72: -0.20230467 | M72: -0.15337397 | N72: -0.01157844 | O72: 0.33105713 | P72: 0.10427319 | Q72: -0.27301917 | R72: 1.3373308 | S72: 0.33875602 | T72: -0.20726989 | U72: Movimiento medio | V72: 27.059717 | W72: 0.56233932 | X72: 7 | Y72: 2026-10-26 | Z72: Sí | AA72: 6.319027e+08 | AB72: 42611.6 | AC72: Sí | AD72: 0.048028881 | AE72: 1.5154895 | AF72: 0.95654766 | AG72: =Pronóstico!$B$5*P72*AE72 -> 0.0079012467 | AH72: =IF(ISNUMBER(G72),G72,1)+2*'Mi portafolio'!$C$5 -> 0.002896535 | AI72: =AF72*Pronóstico!$B$8+AG72-AH72 -> 0.01259636
A73: WYNN * | B73: Exterior (SIC) | C73: 1354.3953 | D73: 0.0056475438 | E73: 1356.75 | F73: 1393.19 | G73: 0.026502396 | H73: 5 | I73: 1200 | J73: Sí | K73: -0.11208295 | L73: -0.20105039 | M73: -0.26134878 | N73: -0.3702112 | O73: 0.326177 | P73: 0.1027361 | Q73: -0.44303617 | R73: 0.40568258 | S73: 0.38199967 | T73: -0.24216955 | U73: Movimiento medio | V73: 2384.4873 | W73: 0.76055489 | X73: 20 | Y73: 2026-11-05 | Z73: Sí | AA73: 3.497708e+09 | AB73: 6783.75 | AC73: No | AD73: -0.29071212 | AE73: 1.2298546 | AF73: 1.0984199 | AG73: =Pronóstico!$B$5*P73*AE73 -> 0.0063175232 | AH73: =IF(ISNUMBER(G73),G73,1)+2*'Mi portafolio'!$C$5 -> 0.028822396 | AI73: =AF73*Pronóstico!$B$8+AG73-AH73 -> -0.013787255
A74: FANG * | B74: Exterior (SIC) | C74: 3460.0525 | D74: 0.044610204 | H74: 0 | I74: 0 | J74: Sin contraparte | K74: 0.010076777 | L74: 0.037851648 | M74: 0.091100597 | N74: 0.38262733 | O74: 0.33620923 | P74: 0.10589595 | Q74: -0.18910245 | R74: -0.39499012 | S74: 0.2413524 | T74: -0.23848814 | U74: Movimiento medio | V74: 4259.6953 | W74: 0.23110711 | X74: 29 | Y74: 2026-11-02 | Z74: Sí | AA74: 1.1648395e+10 | AB74: 0 | AC74: No | AD74: 0.36883389 | AE74: 0.83963022 | AF74: -0.11802962 | AG74: =Pronóstico!$B$5*P74*AE74 -> 0.0044456722 | AH74: =IF(ISNUMBER(G74),G74,1)+2*'Mi portafolio'!$C$5 -> 1.00232 | AI74: =AF74*Pronóstico!$B$8+AG74-AH74 -> -0.99881107
A75: GE * | B75: Exterior (SIC) | C75: 5497.4545 | D75: 0.007367722 | E75: 5379.01 | F75: 5637.29 | G75: 0.046890517 | H75: 400 | I75: 300 | J75: Sí | K75: 0.00028574419 | L75: -0.11005189 | M75: 0.017478481 | N75: -0.0011042985 | O75: 0.33968516 | P75: 0.10699077 | Q75: -0.20576417 | R75: 0.71923084 | S75: 0.28026621 | T75: -0.2133133 | U75: Movimiento medio | V75: 7164.3838 | W75: 0.3032184 | X75: 21 | Y75: 2026-10-20 | Z75: Sí | AA75: 2.5498367e+10 | AB75: 1629354 | AC75: Sí | AD75: -0.0013896456 | AE75: 0.072899689 | AF75: 1.1778639 | AG75: =Pronóstico!$B$5*P75*AE75 -> 0.00038997969 | AH75: =IF(ISNUMBER(G75),G75,1)+2*'Mi portafolio'!$C$5 -> 0.049210517 | AI75: =AF75*Pronóstico!$B$8+AG75-AH75 -> -0.039472411
A76: GENTERA * | B76: Mexicana | C76: 36.32 | D76: -0.010890218 | E76: 36.35 | F76: 36.36 | G76: 0.0002750653 | H76: 599 | I76: 1466 | J76: Sí | K76: -0.080020251 | L76: -0.088559928 | M76: -0.2418321 | N76: -0.15806624 | O76: 0.33994902 | P76: 0.10707388 | Q76: -0.32905117 | R76: 0.8451182 | S76: 0.33486919 | T76: -0.23076924 | U76: Movimiento medio | V76: 54.73333 | W76: 0.50697494 | X76: 15 | Y76: 2026-10-21 | Z76: Sí | AA76: 1.675845e+08 | AB76: 21779.64 | AC76: Sí | AD76: -0.084834465 | AE76: 0.83516899 | AF76: 0.59290492 | AG76: =Pronóstico!$B$5*P76*AE76 -> 0.004471239 | AH76: =IF(ISNUMBER(G76),G76,1)+2*'Mi portafolio'!$C$5 -> 0.0025950653 | AI76: =AF76*Pronóstico!$B$8+AG76-AH76 -> 0.0065817684
A77: AMZN * | B77: Exterior (SIC) | C77: 4674.7605 | D77: 0.0015617685 | E77: 4691.84 | F77: 4710 | G77: 0.0038630736 | H77: 1400 | I77: 2 | J77: Sí | K77: 0.09601923 | L77: 0.080819895 | M77: 0.091012672 | N77: 0.19138584 | O77: 0.34815825 | P77: 0.10965954 | Q77: -0.27611967 | R77: 0.31304318 | S77: 0.31163527 | T77: -0.23020839 | U77: Movimiento medio | V77: 6018.264 | W77: 0.28739515 | X77: 58 | Y77: 2026-10-29 | Z77: Sí | AA77: 1.6188803e+11 | AB77: 9410 | AC77: No | AD77: 0.087011808 | AE77: 0.26293734 | AF77: 1.0743821 | AG77: =Pronóstico!$B$5*P77*AE77 -> 0.0014416794 | AH77: =IF(ISNUMBER(G77),G77,1)+2*'Mi portafolio'!$C$5 -> 0.0061830736 | AI77: =AF77*Pronóstico!$B$8+AG77-AH77 -> 0.0037854481
A78: LVS * | B78: Exterior (SIC) | C78: 645.33915 | D78: 0.0026122037 | E78: 637.01 | F78: 662.19 | G78: 0.038762315 | H78: 2400 | I78: 2400 | J78: Sí | K78: -0.11948112 | L78: -0.19171114 | M78: -0.32723965 | N78: -0.2632161 | O78: 0.33875167 | P78: 0.10669675 | Q78: -0.48468648 | R78: 0.35240776 | S78: 0.3855021 | T78: -0.32009707 | U78: Movimiento medio | V78: 1066.5365 | W78: 0.65267595 | X78: 19 | Y78: 2026-10-21 | Z78: Sí | AA78: 4.0035188e+09 | AB78: 1538376 | AC78: Sí | AD78: -0.16323895 | AE78: 1.3232486 | AF78: 0.94693487 | AG78: =Pronóstico!$B$5*P78*AE78 -> 0.0070593162 | AH78: =IF(ISNUMBER(G78),G78,1)+2*'Mi portafolio'!$C$5 -> 0.041082315 | AI78: =AF78*Pronóstico!$B$8+AG78-AH78 -> -0.026507643
A79: LLY * | B79: Exterior (SIC) | C79: 20879.762 | D79: -0.020746264 | E79: 20500.01 | F79: 21032.99 | G79: 0.025665375 | H79: 1200 | I79: 1200 | J79: Sí | K79: 0.10031598 | L79: 0.012755287 | M79: 0.34375274 | N79: 0.42258345 | O79: 0.35207708 | P79: 0.11089386 | Q79: -0.27788775 | R79: 0.031078698 | S79: 0.39732962 | T79: -0.21874002 | U79: Movimiento medio | V79: 24129.205 | W79: 0.15562645 | X79: 29 | Y79: 2026-10-29 | Z79: Sí | AA79: 4.6759624e+10 | AB79: 24780000 | AC79: Sí | AD79: 0.29288629 | AE79: 0.23214719 | AF79: 0.57512762 | AG79: =Pronóstico!$B$5*P79*AE79 -> 0.0012871848 | AH79: =IF(ISNUMBER(G79),G79,1)+2*'Mi portafolio'!$C$5 -> 0.027985375 | AI79: =AF79*Pronóstico!$B$8+AG79-AH79 -> -0.022133685
A80: GM * | B80: Exterior (SIC) | C80: 1478.5618 | D80: 0.01584227 | E80: 1435.01 | F80: 1504.99 | G80: 0.047605442 | H80: 1000 | I80: 1000 | J80: Sí | K80: 0.043784979 | L80: 0.10337674 | M80: 0.10628252 | N80: 0.38586346 | O80: 0.35912698 | P80: 0.11311437 | Q80: -0.17837584 | R80: 0.4475686 | S80: 0.34364355 | T80: -0.16112569 | U80: Movimiento medio | V80: 1897.3831 | W80: 0.28326262 | X80: 23 | Y80: 2026-10-20 | Z80: Sí | AA80: 1.1309276e+10 | AB80: 1460000 | AC80: Sí | AD80: 0.32772888 | AE80: 0.97467478 | AF80: 1.1714352 | AG80: =Pronóstico!$B$5*P80*AE80 -> 0.005512486 | AH80: =IF(ISNUMBER(G80),G80,1)+2*'Mi portafolio'!$C$5 -> 0.049925442 | AI80: =AF80*Pronóstico!$B$8+AG80-AH80 -> -0.035115851
A81: BA * | B81: Exterior (SIC) | C81: 3384.3545 | D81: -0.00033879465 | E81: 3323.01 | F81: 3422.72 | G81: 0.029562405 | H81: 1200 | I81: 1050 | J81: Sí | K81: -0.030857619 | L81: -0.10306818 | M81: -0.12446046 | N81: -0.13803792 | O81: 0.35227432 | P81: 0.11095598 | Q81: -0.25725335 | R81: 0.53358107 | S81: 0.41770114 | T81: -0.23791954 | U81: Movimiento medio | V81: 4933.4268 | W81: 0.45771572 | X81: 26 | Y81: 2026-10-27 | Z81: Sí | AA81: 3.101252e+10 | AB81: 3509488.5 | AC81: Sí | AD81: -0.11059293 | AE81: 0.51114588 | AF81: 1.222208 | AG81: =Pronóstico!$B$5*P81*AE81 -> 0.0028357346 | AH81: =IF(ISNUMBER(G81),G81,1)+2*'Mi portafolio'!$C$5 -> 0.031882405 | AI81: =AF81*Pronóstico!$B$8+AG81-AH81 -> -0.019346607
A82: GCARSO A1 | B82: Mexicana | C82: 145.93 | D82: 0.021060695 | E82: 144.01 | F82: 144.76 | G82: 0.0051944454 | H82: 130 | I82: 457 | J82: Sí | K82: 0.06053769 | L82: 0.16893621 | M82: -0.049346249 | N82: 0.19362889 | O82: 0.34366543 | P82: 0.10824443 | Q82: -0.18673599 | R82: 1.0510548 | S82: 0.45208652 | T82: -0.17963224 | U82: Movimiento medio | V82: 130 | X82: 1 | Y82: 2026-11-02 | Z82: Sí | AA82: 56331226 | AB82: 18824 | AC82: Sí | AD82: 0.12549408 | AE82: 0.40184552 | AF82: 0.54896964 | AG82: =Pronóstico!$B$5*P82*AE82 -> 0.002174877 | AH82: =IF(ISNUMBER(G82),G82,1)+2*'Mi portafolio'!$C$5 -> 0.0075144454 | AI82: =AF82*Pronóstico!$B$8+AG82-AH82 -> -0.00098266648
A83: ALPEK A | B83: Mexicana | C83: 14.68 | D83: -0.0081081003 | E83: 14.63 | F83: 14.64 | G83: 0.0006832935 | H83: 14760 | I83: 800 | J83: Sí | K83: 0.05157595 | L83: 0.17440002 | M83: 0.37711074 | N83: 0.4592445 | O83: 0.35088879 | P83: 0.11051958 | Q83: -0.20941406 | R83: -0.18217339 | S83: 0.3544153 | T83: -0.29697986 | U83: Movimiento medio | V83: 15.53333 | W83: 0.058128747 | X83: 12 | Y83: 2026-10-21 | Z83: Sí | AA83: 3.4290541e+08 | AB83: 11712 | AC83: Sí | AD83: 0.3876739 | AE83: 0.03430165 | AF83: -0.095492663 | AG83: =Pronóstico!$B$5*P83*AE83 -> 0.0001895502 | AH83: =IF(ISNUMBER(G83),G83,1)+2*'Mi portafolio'!$C$5 -> 0.0030032935 | AI83: =AF83*Pronóstico!$B$8+AG83-AH83 -> -0.0035716216
A84: UNH * | B84: Exterior (SIC) | C84: 6754.5497 | D84: 0.0010935333 | E84: 6600.21 | F84: 6799.99 | G84: 0.029817465 | H84: 1600 | I84: 1400 | J84: Sí | K84: 0.023850683 | L84: -0.093778085 | M84: 0.26304488 | N84: 0.056494186 | O84: 0.34251217 | P84: 0.10788119 | Q84: -0.30758206 | R84: 0.17496693 | S84: 0.44364077 | T84: -0.55883141 | U84: Movimiento medio | V84: 8744.6631 | W84: 0.29463302 | X84: 25 | Y84: 2026-10-13 | Z84: Sí | AA84: 3.246352e+10 | AB84: 9380000 | AC84: Sí | AD84: 0.03188307 | AE84: 0.1313116 | AF84: 0.5562651 | AG84: =Pronóstico!$B$5*P84*AE84 -> 0.00070830258 | AH84: =IF(ISNUMBER(G84),G84,1)+2*'Mi portafolio'!$C$5 -> 0.032137465 | AI84: =AF84*Pronóstico!$B$8+AG84-AH84 -> -0.02701436
A85: UBER * | B85: Exterior (SIC) | C85: 1250.7417 | D85: 0.017608457 | E85: 1247.03 | F85: 1257.49 | G85: 0.008352898 | H85: 5750 | I85: 4750 | J85: Sí | K85: 0.041350106 | L85: -0.036888147 | M85: -0.06130228 | N85: -0.26421905 | O85: 0.35771546 | P85: 0.11266978 | Q85: -0.37584381 | R85: 0.22040836 | S85: 0.33269605 | T85: -0.2224051 | U85: Movimiento medio | V85: 1830.8248 | W85: 0.46379129 | X85: 46 | Y85: 2026-11-04 | Z85: Sí | AA85: 2.1272735e+10 | AB85: 5937357.5 | AC85: Sí | AD85: -0.29343556 | AE85: -0.014827081 | AF85: 1.0459092 | AG85: =Pronóstico!$B$5*P85*AE85 -> -8.3528196e-05 | AH85: =IF(ISNUMBER(G85),G85,1)+2*'Mi portafolio'!$C$5 -> 0.010672898 | AI85: =AF85*Pronóstico!$B$8+AG85-AH85 -> -0.0024555598
A86: CSCO * | B86: Exterior (SIC) | C86: 2101.3913 | D86: -0.0041855244 | E86: 2061.81 | F86: 2163.19 | G86: 0.047990533 | H86: 16000 | I86: 15000 | J86: Sí | K86: 0.13957674 | L86: 0.010436587 | M86: 0.48947751 | N86: 0.65526855 | O86: 0.35845773 | P86: 0.11290357 | Q86: -0.19131725 | R86: 0.36331394 | S86: 0.4715961 | T86: -0.165589 | U86: Movimiento medio | V86: 2471.7125 | W86: 0.17622668 | X86: 25 | Y86: 2026-11-12 | Z86: Sí | AA86: 3.7708748e+10 | AB86: 31638000 | AC86: Sí | AD86: 0.45252925 | AE86: 0.8205713 | AF86: 0.82758809 | AG86: =Pronóstico!$B$5*P86*AE86 -> 0.0046322715 | AH86: =IF(ISNUMBER(G86),G86,1)+2*'Mi portafolio'!$C$5 -> 0.050310532 | AI86: =AF86*Pronóstico!$B$8+AG86-AH86 -> -0.039110102
A87: DVN * | B87: Exterior (SIC) | C87: 888.86164 | D87: 0.033227253 | E87: 865.21 | F87: 906.39 | G87: 0.046489049 | H87: 1400 | I87: 2800 | J87: Sí | K87: 0.080251529 | L87: 0.16910005 | M87: 0.15463258 | N87: 0.55836864 | O87: 0.35466177 | P87: 0.11170796 | Q87: -0.24139528 | R87: -0.43658384 | S87: 0.25839538 | T87: -0.22643218 | U87: Movimiento medio | V87: 1099.5532 | W87: 0.23703523 | X87: 28 | Y87: 2026-11-05 | Z87: Sí | AA87: 1.0600154e+10 | AB87: 1243200 | AC87: Sí | AD87: 0.44259795 | AE87: 1.0936102 | AF87: -0.17190433 | AG87: =Pronóstico!$B$5*P87*AE87 -> 0.0061082483 | AH87: =IF(ISNUMBER(G87),G87,1)+2*'Mi portafolio'!$C$5 -> 0.048809049 | AI87: =AF87*Pronóstico!$B$8+AG87-AH87 -> -0.044065121
A88: ABNB * | B88: Exterior (SIC) | C88: 2962.9326 | D88: 0.027335681 | E88: 2887.51 | F88: 2999.99 | G88: 0.038209766 | H88: 7800 | I88: 7400 | J88: Sí | K88: 0.033775951 | L88: 0.15793241 | M88: 0.2498086 | N88: 0.27783543 | O88: 0.37020959 | P88: 0.11660506 | Q88: -0.20523 | R88: 0.26892914 | S88: 0.30739087 | T88: -0.25370277 | U88: Movimiento medio | V88: 3332.2391 | W88: 0.1246422 | X88: 39 | Y88: 2026-11-05 | Z88: Sí | AA88: 1.341757e+10 | AB88: 21793000 | AC88: Sí | AD88: 0.23608546 | AE88: -0.095180083 | AF88: 1.245674 | AG88: =Pronóstico!$B$5*P88*AE88 -> -0.00055492397 | AH88: =IF(ISNUMBER(G88),G88,1)+2*'Mi portafolio'!$C$5 -> 0.040529767 | AI88: =AF88*Pronóstico!$B$8+AG88-AH88 -> -0.031198389
A89: GMEXICO B | B89: Mexicana | C89: 232.01 | D89: 0.0057663207 | E89: 231.58 | F89: 231.6 | G89: 8.63595e-05 | H89: 2926 | I89: 3477 | J89: Sí | K89: 0.015229741 | L89: 0.19523253 | M89: 0.13179162 | N89: 0.61347759 | O89: 0.36666794 | P89: 0.11548955 | Q89: -0.21068417 | R89: 1.7246527 | S89: 0.32409858 | T89: -0.16161262 | U89: Movimiento medio | V89: 234.76604 | W89: 0.011878971 | X89: 16 | Y89: 2026-10-20 | Z89: Sí | AA89: 1.33644e+09 | AB89: 677661.6 | AC89: Sí | AD89: 0.58927337 | AE89: 0.50097704 | AF89: 1.2348725 | AG89: =Pronóstico!$B$5*P89*AE89 -> 0.0028928806 | AH89: =IF(ISNUMBER(G89),G89,1)+2*'Mi portafolio'!$C$5 -> 0.0024063595 | AI89: =AF89*Pronóstico!$B$8+AG89-AH89 -> 0.010287097
A90: OXY1 * | B90: Exterior (SIC) | C90: 1086.094 | D90: 0.038517653 | E90: 1065 | F90: 1086 | G90: 0.019525802 | H90: 3600 | I90: 8 | J90: Sí | K90: 0.052759875 | L90: 0.13767305 | M90: 0.13807845 | N90: 0.46976153 | O90: 0.36633318 | P90: 0.11538411 | Q90: -0.29898633 | R90: -0.44244068 | S90: 0.38777881 | T90: -0.23907935 | U90: Movimiento medio | V90: 1240.9391 | W90: 0.14257062 | X90: 25 | Y90: 2026-11-09 | Z90: Sí | AA90: 9.8859064e+09 | AB90: 8720 | AC90: No | AD90: 0.39610329 | AE90: 0.48106013 | AF90: -0.18611438 | AG90: =Pronóstico!$B$5*P90*AE90 -> 0.0027753347 | AH90: =IF(ISNUMBER(G90),G90,1)+2*'Mi portafolio'!$C$5 -> 0.021845802 | AI90: =AF90*Pronóstico!$B$8+AG90-AH90 -> -0.020547566
A91: NFLX * | B91: Exterior (SIC) | C91: 1288.6815 | D91: 0.028998901 | E91: 1292 | F91: 1293 | G91: 0.0007736944 | H91: 2086 | I91: 6 | J91: Sí | K91: 0.002426967 | L91: -0.002547243 | M91: -0.30652569 | N91: -0.41696552 | O91: 0.37603991 | P91: 0.11844144 | Q91: -0.48085286 | R91: -0.044327861 | S91: 0.32979699 | T91: -0.20130573 | U91: Movimiento medio | V91: 1680.04 | W91: 0.30368911 | X91: 45 | Y91: 2026-10-20 | Z91: Sí | AA91: 4.6822031e+10 | AB91: 7758 | AC91: No | AD91: -0.4183771 | AE91: -1.1933762 | AF91: 0.64851123 | AG91: =Pronóstico!$B$5*P91*AE91 -> -0.0070672599 | AH91: =IF(ISNUMBER(G91),G91,1)+2*'Mi portafolio'!$C$5 -> 0.0030936944 | AI91: =AF91*Pronóstico!$B$8+AG91-AH91 -> -0.0050140398
A92: NKE * | B92: Exterior (SIC) | C92: 623.37583 | D92: 0.0094940575 | E92: 623 | F92: 623.11 | G92: 0.0001765494 | H92: 3 | I92: 23 | J92: Sí | K92: -0.013138068 | L92: -0.17749238 | M92: -0.18939571 | N92: -0.48146863 | O92: 0.36412009 | P92: 0.11468705 | Q92: -0.51001116 | R92: 0.18909431 | S92: 0.26765903 | T92: -0.31201405 | U92: Movimiento medio | V92: 692.58741 | W92: 0.11102705 | X92: 36 | Y92: 2026-12-17 | Z92: No | AA92: 2.9758193e+10 | AB92: 1869.33 | AC92: No | AD92: -0.47456543 | AE92: -2.213089 | AF92: 0.91654307 | AG92: =Pronóstico!$B$5*P92*AE92 -> -0.012690632 | AH92: =IF(ISNUMBER(G92),G92,1)+2*'Mi portafolio'!$C$5 -> 0.0024965494 | AI92: =AF92*Pronóstico!$B$8+AG92-AH92 -> -0.0079130302
A93: F * | B93: Exterior (SIC) | C93: 219.56053 | D93: 0.0079369359 | E93: 216.04 | F93: 220.29 | G93: 0.019480668 | H93: 16500 | I93: 49500 | J93: Sí | K93: -0.034830137 | L93: -0.08453448 | M93: 0.024583891 | N93: 0.045794332 | O93: 0.38407696 | P93: 0.12097287 | Q93: -0.27130074 | R93: 0.47783521 | S93: 0.41776528 | T93: -0.22650944 | U93: Movimiento medio | V93: 286.95863 | W93: 0.30696817 | X93: 18 | Y93: 2026-10-28 | Z93: Sí | AA93: 1.0423828e+10 | AB93: 3615150 | AC93: Sí | AD93: 0.083533968 | AE93: 0.34996754 | AF93: 1.130563 | AG93: =Pronóstico!$B$5*P93*AE93 -> 0.0021168289 | AH93: =IF(ISNUMBER(G93),G93,1)+2*'Mi portafolio'!$C$5 -> 0.021800668 | AI93: =AF93*Pronóstico!$B$8+AG93-AH93 -> -0.010711117
A94: NVDA * | B94: Exterior (SIC) | C94: 4215.2173 | D94: -0.011700919 | E94: 4271.01 | F94: 4289.99 | G94: 0.0044340614 | H94: 3600 | I94: 3200 | J94: Sí | K94: 0.11625947 | L94: 0.18531003 | M94: 0.23185091 | N94: 0.25187113 | O94: 0.37555146 | P94: 0.11828759 | Q94: -0.22420077 | R94: 0.46199155 | S94: 0.6378779 | T94: -0.26435795 | U94: Movimiento medio | V94: 5967.1988 | W94: 0.41563252 | X94: 59 | Y94: 2026-11-17 | Z94: No | AA94: 4.3453146e+11 | AB94: 13692800 | AC94: Sí | AD94: 0.12148758 | AE94: 1.0073472 | AF94: 1.0939895 | AG94: =Pronóstico!$B$5*P94*AE94 -> 0.0059578335 | AH94: =IF(ISNUMBER(G94),G94,1)+2*'Mi portafolio'!$C$5 -> 0.0067540614 | AI94: =AF94*Pronóstico!$B$8+AG94-AH94 -> 0.0078862285
A95: ORBIA * | B95: Mexicana | C95: 21.71 | D95: -0.023830966 | E95: 21.65 | F95: 21.66 | G95: 0.0004617871 | H95: 2373 | I95: 606 | J95: Sí | K95: 0.060576444 | L95: -0.044874636 | M95: 0.002771338 | N95: 0.19746277 | O95: 0.32364052 | P95: 0.10193718 | Q95: -0.23017486 | R95: 0.76349017 | S95: 0.36098989 | T95: -0.26395595 | U95: Movimiento medio | V95: 28.510628 | W95: 0.31324864 | X95: 13 | Y95: 2026-10-27 | Z95: Sí | AA95: 62585116 | AB95: 13125.96 | AC95: Sí | AD95: 0.12906786 | AE95: 0.51981858 | AF95: 0.43406755 | AG95: =Pronóstico!$B$5*P95*AE95 -> 0.002649442 | AH95: =IF(ISNUMBER(G95),G95,1)+2*'Mi portafolio'!$C$5 -> 0.0027817871 | AI95: =AF95*Pronóstico!$B$8+AG95-AH95 -> 0.0033126355
A96: TLEVISA CPO | B96: Mexicana | C96: 7.89 | D96: -0.0037830686 | E96: 7.88 | F96: 7.89 | G96: 0.0012682308 | H96: 13644 | I96: 3067 | J96: Sí | K96: -0.0050377785 | L96: -0.17536533 | M96: -0.26511627 | N96: -0.10430835 | O96: 0.39481398 | P96: 0.12435472 | Q96: -0.35527429 | R96: 0.57503038 | S96: 0.49240501 | T96: -0.23306775 | U96: Movimiento medio | V96: 14.125 | X96: 4 | Y96: 2026-10-28 | Z96: Sí | AA96: 1.1620966e+08 | AB96: 24198.63 | AC96: Sí | AD96: -0.099773205 | AE96: -0.96884003 | AF96: 0.6181997 | AG96: =Pronóstico!$B$5*P96*AE96 -> -0.0060239913 | AH96: =IF(ISNUMBER(G96),G96,1)+2*'Mi portafolio'!$C$5 -> 0.0035882308 | AI96: =AF96*Pronóstico!$B$8+AG96-AH96 -> -0.0047058753
A97: GME * | B97: Exterior (SIC) | C97: 464.17221 | D97: 0.051945244 | E97: 455.01 | F97: 471.99 | G97: 0.036634304 | H97: 4800 | I97: 4800 | J97: Sí | K97: 0.3814345 | L97: 0.20514151 | M97: 0.08626853 | N97: 0.092756854 | O97: 0.39869074 | P97: 0.12557578 | Q97: -0.34557331 | R97: 0.03302989 | S97: 3.5550546 | T97: -0.44087399 | U97: Movimiento medio | Y97: 2026-12-08 | Z97: No | AA97: 4.2865469e+09 | AB97: 2232000 | AC97: Sí | AD97: -0.20896948 | AE97: -1.6332674 | AF97: 0.8079015 | AG97: =Pronóstico!$B$5*P97*AE97 -> -0.010254941 | AH97: =IF(ISNUMBER(G97),G97,1)+2*'Mi portafolio'!$C$5 -> 0.038954304 | AI97: =AF97*Pronóstico!$B$8+AG97-AH97 -> -0.042797329
A98: DAL * | B98: Exterior (SIC) | C98: 1482.0109 | D98: -0.005782119 | E98: 1451.81 | F98: 1523.19 | G98: 0.047986555 | H98: 1600 | I98: 1600 | J98: Sí | K98: 0.11312044 | L98: -0.017294656 | M98: 0.19947421 | N98: 0.35913078 | O98: 0.40033129 | P98: 0.1260925 | Q98: -0.21834966 | R98: 0.65950273 | S98: 0.35913547 | T98: -0.39631818 | U98: Movimiento medio | V98: 1838.3694 | W98: 0.24045603 | X98: 24 | Y98: 2026-10-09 | Z98: Sí | AA98: 1.1457638e+10 | AB98: 2365984 | AC98: Sí | AD98: 0.22100963 | AE98: 0.43651977 | AF98: 1.7058497 | AG98: =Pronóstico!$B$5*P98*AE98 -> 0.0027520936 | AH98: =IF(ISNUMBER(G98),G98,1)+2*'Mi portafolio'!$C$5 -> 0.050306555 | AI98: =AF98*Pronóstico!$B$8+AG98-AH98 -> -0.034015972
A99: TSM N | B99: Exterior (SIC) | C99: 8290.3843 | D99: -0.02092066 | E99: 8427.01 | F99: 8479.99 | G99: 0.0062672266 | H99: 4400 | I99: 4600 | J99: Sí | K99: 0.13148541 | L99: 0.12902868 | M99: 0.29007491 | N99: 0.54373422 | O99: 0.39339458 | P99: 0.12390764 | Q99: -0.21704637 | R99: 0.78338339 | S99: 0.35167342 | T99: -0.21266006 | U99: Movimiento medio | V99: 10075.086 | W99: 0.21527365 | X99: 20 | Y99: 2026-10-15 | Z99: Sí | AA99: 7.8684641e+10 | AB99: 37311956 | AC99: Sí | AD99: 0.36434303 | AE99: 0.74700564 | AF99: 1.4706996 | AG99: =Pronóstico!$B$5*P99*AE99 -> 0.0046279855 | AH99: =IF(ISNUMBER(G99),G99,1)+2*'Mi portafolio'!$C$5 -> 0.0085872266 | AI99: =AF99*Pronóstico!$B$8+AG99-AH99 -> 0.0077129777
A100: CAT * | B100: Exterior (SIC) | C100: 14441.347 | D100: -0.010544529 | E100: 14590.01 | F100: 14988.79 | G100: 0.026963907 | H100: 500 | I100: 400 | J100: Sí | K100: 0.04921405 | L100: -0.11070967 | M100: 0.092982053 | N100: 0.50293918 | O100: 0.41212085 | P100: 0.12980587 | Q100: -0.28755657 | R100: 0.99959013 | S100: 0.26437619 | T100: -0.24085433 | U100: Mayor movimiento | V100: 17622.904 | W100: 0.22030892 | X100: 26 | Y100: 2026-10-29 | Z100: Sí | AA100: 3.4829634e+10 | AB100: 5860000 | AC100: Sí | AD100: 0.43244287 | AE100: 0.97930047 | AF100: 1.3950113 | AG100: =Pronóstico!$B$5*P100*AE100 -> 0.0063559473 | AH100: =IF(ISNUMBER(G100),G100,1)+2*'Mi portafolio'!$C$5 -> 0.029283907 | AI100: =AF100*Pronóstico!$B$8+AG100-AH100 -> -0.011856441
A101: ROKU * | B101: Exterior (SIC) | C101: 2787.9377 | D101: 0.015818559 | E101: 2728.01 | F101: 2849.99 | G101: 0.043736106 | H101: 1200 | I101: 1000 | J101: Sí | K101: 0.07822372 | L101: 0.1191206 | M101: 0.47783405 | N101: 0.60555583 | O101: 0.41382107 | P101: 0.13034139 | Q101: -0.30585141 | R101: 0.69867577 | S101: 0.76045645 | T101: -0.37047359 | U101: Mayor movimiento | V101: 2946.7129 | W101: 0.056950775 | X101: 20 | Y101: 2026-11-05 | Z101: Sí | AA101: 4.6815809e+09 | AB101: 2749000 | AC101: Sí | AD101: 0.48907485 | AE101: 0.33692465 | AF101: 1.3899975 | AG101: =Pronóstico!$B$5*P101*AE101 -> 0.0021957613 | AH101: =IF(ISNUMBER(G101),G101,1)+2*'Mi portafolio'!$C$5 -> 0.046056106 | AI101: =AF101*Pronóstico!$B$8+AG101-AH101 -> -0.032828618
A102: BABA N | B102: Exterior (SIC) | C102: 1910.6032 | D102: -0.0053019259 | E102: 1917.67 | F102: 1921.64 | G102: 0.0020680799 | H102: 3750 | I102: 3750 | J102: Sí | K102: 0.033826789 | L102: -0.027298628 | M102: -0.16069625 | N102: -0.37310469 | O102: 0.40501431 | P102: 0.12756752 | Q102: -0.4947639 | R102: 0.55492658 | S102: 0.64928615 | T102: -0.25811715 | U102: Movimiento medio | V102: 3371.1495 | W102: 0.76444247 | X102: 39 | Y102: 2026-11-24 | Z102: No | AA102: 1.6442413e+10 | AB102: 7191525 | AC102: Sí | AD102: -0.39361669 | AE102: 0.9167825 | AF102: 0.94932214 | AG102: =Pronóstico!$B$5*P102*AE102 -> 0.0058475834 | AH102: =IF(ISNUMBER(G102),G102,1)+2*'Mi portafolio'!$C$5 -> 0.0043880799 | AI102: =AF102*Pronóstico!$B$8+AG102-AH102 -> 0.0089938062
A103: META * | B103: Exterior (SIC) | C103: 12964.873 | D103: 0.0012166135 | E103: 13044.02 | F103: 13130.69 | G103: 0.0066224229 | H103: 1400 | I103: 1200 | J103: Sí | K103: 0.17492686 | L103: 0.13001267 | M103: 0.12185283 | N103: -0.014523872 | O103: 0.41706323 | P103: 0.13136257 | Q103: -0.33020801 | R103: 0.42157144 | S103: 0.47537463 | T103: -0.26338645 | U103: Mayor movimiento | V103: 14510.419 | W103: 0.11921031 | X103: 58 | Y103: 2026-10-28 | Z103: Sí | AA103: 2.8084725e+11 | AB103: 15720000 | AC103: Sí | AD103: -0.1612447 | AE103: -1.331088 | AF103: 1.011324 | AG103: =Pronóstico!$B$5*P103*AE103 -> -0.008742757 | AH103: =IF(ISNUMBER(G103),G103,1)+2*'Mi portafolio'!$C$5 -> 0.0089424229 | AI103: =AF103*Pronóstico!$B$8+AG103-AH103 -> -0.0096587993
A104: MELI N | B104: Exterior (SIC) | C104: 33497.912 | D104: -0.0035667638 | E104: 33001.51 | F104: 33759.96 | G104: 0.022721189 | H104: 485 | I104: 185 | J104: Sí | K104: 0.056856 | L104: 0.02612061 | M104: 0.038101985 | N104: -0.10151598 | O104: 0.41317044 | P104: 0.13013646 | Q104: -0.38861399 | R104: 0.53895164 | S104: 0.35933652 | T104: -0.25539795 | U104: Mayor movimiento | V104: 41312.198 | W104: 0.23327679 | X104: 26 | Y104: 2026-11-04 | Z104: Sí | AA104: 2.2451332e+10 | AB104: 6184918.2 | AC104: Sí | AD104: -0.149852 | AE104: -0.72757549 | AF104: 1.3175661 | AG104: =Pronóstico!$B$5*P104*AE104 -> -0.0047342048 | AH104: =IF(ISNUMBER(G104),G104,1)+2*'Mi portafolio'!$C$5 -> 0.025041189 | AI104: =AF104*Pronóstico!$B$8+AG104-AH104 -> -0.01931852
A105: NU N | B105: Exterior (SIC) | C105: 282.55144 | D105: 0.0084135837 | E105: 281.02 | F105: 282 | G105: 0.0034812262 | H105: 12800 | I105: 4 | J105: Sí | K105: 0.11302504 | L105: 0.1800901 | M105: 0.066644021 | N105: 0.021200446 | O105: 0.42415843 | P105: 0.13359735 | Q105: -0.37576469 | R105: 0.80681229 | S105: 0.33275108 | T105: -0.3482503 | U105: Mayor movimiento | V105: 340.78137 | W105: 0.20608609 | X105: 22 | Y105: 2026-11-12 | Z105: Sí | AA105: 2.0795286e+10 | AB105: 1127.12 | AC105: No | AD105: -0.082500025 | AE105: -0.65826754 | AF105: 1.5344249 | AG105: =Pronóstico!$B$5*P105*AE105 -> -0.0043971399 | AH105: =IF(ISNUMBER(G105),G105,1)+2*'Mi portafolio'!$C$5 -> 0.0058012262 | AI105: =AF105*Pronóstico!$B$8+AG105-AH105 -> 0.0019796096
A106: LUV * | B106: Exterior (SIC) | C106: 747.54053 | D106: -0.0039364198 | H106: 0 | I106: 0 | J106: Sin contraparte | K106: 0.1416552 | L106: -0.1054152 | M106: 0.047263069 | N106: 0.23028541 | O106: 0.44673897 | P106: 0.14070955 | Q106: -0.31971773 | R106: 0.72976858 | S106: 0.33568765 | T106: -0.26921004 | U106: Mayor movimiento | V106: 893.52224 | W106: 0.19528266 | X106: 23 | Y106: 2026-10-21 | Z106: Sí | AA106: 4.6141826e+09 | AB106: 0 | AC106: No | AD106: 0.077633075 | AE106: -0.22496292 | AF106: 1.5866362 | AG106: =Pronóstico!$B$5*P106*AE106 -> -0.0015827215 | AH106: =IF(ISNUMBER(G106),G106,1)+2*'Mi portafolio'!$C$5 -> 1.00232 | AI106: =AF106*Pronóstico!$B$8+AG106-AH106 -> -0.99131037
A107: ZM * | B107: Exterior (SIC) | C107: 1707.2896 | D107: 0.00063538099 | E107: 1672.81 | F107: 1745.77 | G107: 0.042684389 | H107: 800 | I107: 800 | J107: Sí | K107: 0.047736325 | L107: 0.059749672 | M107: 0.10930017 | N107: 0.15557611 | O107: 0.44884741 | P107: 0.14137365 | Q107: -0.24777604 | R107: 0.20379793 | S107: 0.33222947 | T107: -0.24056032 | U107: Mayor movimiento | V107: 2146.4107 | W107: 0.25720362 | X107: 25 | Y107: 2026-11-24 | Z107: No | AA107: 4.6635263e+09 | AB107: 1368000 | AC107: Sí | AD107: 0.10292645 | AE107: 0.16078952 | AF107: 1.0742954 | AG107: =Pronóstico!$B$5*P107*AE107 -> 0.00113657 | AH107: =IF(ISNUMBER(G107),G107,1)+2*'Mi portafolio'!$C$5 -> 0.045004389 | AI107: =AF107*Pronóstico!$B$8+AG107-AH107 -> -0.035341666
A108: PYPL * | B108: Exterior (SIC) | C108: 994.05827 | D108: 0.0060007051 | E108: 971.72 | F108: 998.99 | G108: 0.027675305 | H108: 5415 | I108: 8000 | J108: Sí | K108: 0.12599178 | L108: 0.19413106 | M108: 0.16811722 | N108: -0.19154821 | O108: 0.43535003 | P108: 0.13712237 | Q108: -0.49846428 | R108: -0.0036375749 | S108: 0.40483549 | T108: -0.35861984 | U108: Mayor movimiento | V108: 1033.2177 | W108: 0.039393535 | X108: 32 | Y108: 2026-10-27 | Z108: Sí | AA108: 1.1083237e+10 | AB108: 5360850 | AC108: Sí | AD108: -0.28200916 | AE108: -2.096544 | AF108: 1.0832423 | AG108: =Pronóstico!$B$5*P108*AE108 -> -0.014374154 | AH108: =IF(ISNUMBER(G108),G108,1)+2*'Mi portafolio'!$C$5 -> 0.029995305 | AI108: =AF108*Pronóstico!$B$8+AG108-AH108 -> -0.035772298
A109: TSLA * | B109: Exterior (SIC) | C109: 6723.6896 | D109: -0.0092636762 | E109: 6766.88 | F109: 6789.99 | G109: 0.0034093415 | H109: 400 | I109: 200 | J109: Sí | K109: 0.081429114 | L109: -0.026410401 | M109: -0.005420328 | N109: -0.16927637 | O109: 0.45565939 | P109: 0.14351922 | Q109: -0.4094749 | R109: 1.0052354 | S109: 0.64561261 | T109: -0.44586859 | U109: Mayor movimiento | V109: 7123.6392 | W109: 0.059483652 | X109: 37 | Y109: 2026-10-21 | Z109: Sí | AA109: 2.3127465e+11 | AB109: 1346642 | AC109: Sí | AD109: -0.23182794 | AE109: -1.8436852 | AF109: 1.697365 | AG109: =Pronóstico!$B$5*P109*AE109 -> -0.013230213 | AH109: =IF(ISNUMBER(G109),G109,1)+2*'Mi portafolio'!$C$5 -> 0.0057293415 | AI109: =AF109*Pronóstico!$B$8+AG109-AH109 -> -0.0054884038
A110: VOLAR A | B110: Mexicana | C110: 11.45 | D110: -0.0069324024 | E110: 11.48 | F110: 11.51 | G110: 0.0026098304 | H110: 419 | I110: 7505 | J110: Sí | K110: 0.0026246485 | L110: -0.16533136 | M110: -0.16715117 | N110: -0.10817123 | O110: 0.47023079 | P110: 0.14810878 | Q110: -0.41249997 | R110: 1.2019931 | S110: 0.49213677 | T110: -0.37620298 | U110: Mayor movimiento | V110: 16.91667 | W110: 0.47743843 | X110: 6 | Y110: 2026-10-26 | Z110: Sí | AA110: 30018551 | AB110: 4814.31 | AC110: Sí | AD110: -0.11050584 | AE110: 0.60976839 | AF110: 1.3346547 | AG110: =Pronóstico!$B$5*P110*AE110 -> 0.0045156025 | AH110: =IF(ISNUMBER(G110),G110,1)+2*'Mi portafolio'!$C$5 -> 0.0049298304 | AI110: =AF110*Pronóstico!$B$8+AG110-AH110 -> 0.01017827
A111: XYZ * | B111: Exterior (SIC) | C111: 1344.7742 | D111: -0.016397743 | E111: 1318.91 | F111: 1374.99 | G111: 0.041634805 | H111: 2000 | I111: 1500 | J111: Sí | K111: 0.0013882134 | L111: -0.02405491 | M111: 0.14644806 | N111: -0.029911794 | O111: 0.47125629 | P111: 0.14843178 | Q111: -0.42828214 | R111: 0.4919387 | S111: 0.59682881 | T111: -0.41919025 | U111: Mayor movimiento | V111: 1786.0261 | W111: 0.32812338 | X111: 42 | Y111: 2026-11-03 | Z111: Sí | AA111: 5.3687643e+09 | AB111: 2051370 | AC111: Sí | AD111: -0.031256617 | AE111: 0.10623543 | AF111: 1.8286103 | AG111: =Pronóstico!$B$5*P111*AE111 -> 0.00078843573 | AH111: =IF(ISNUMBER(G111),G111,1)+2*'Mi portafolio'!$C$5 -> 0.043954805 | AI111: =AF111*Pronóstico!$B$8+AG111-AH111 -> -0.028653589
A112: FCX * | B112: Exterior (SIC) | C112: 1282.3279 | D112: -0.0073437344 | E112: 1275.01 | F112: 1299.99 | G112: 0.019401942 | H112: 1200 | I112: 1200 | J112: Sí | K112: -0.0056249451 | L112: 0.22428473 | M112: 0.083979205 | N112: 0.70092345 | O112: 0.4661726 | P112: 0.14683057 | Q112: -0.21867512 | R112: 1.5114331 | S112: 0.32977523 | T112: -0.23052362 | U112: Mayor movimiento | V112: 1400.2563 | W112: 0.091964326 | X112: 22 | Y112: 2026-10-27 | Z112: Sí | AA112: 1.3683478e+10 | AB112: 1541880 | AC112: Sí | AD112: 0.71054517 | AE112: 1.1601652 | AF112: 1.7454956 | AG112: =Pronóstico!$B$5*P112*AE112 -> 0.0085173862 | AH112: =IF(ISNUMBER(G112),G112,1)+2*'Mi portafolio'!$C$5 -> 0.021721942 | AI112: =AF112*Pronóstico!$B$8+AG112-AH112 -> 0.00064858378
A113: CRM * | B113: Exterior (SIC) | C113: 4074.4408 | D113: 0.010319129 | E113: 3940.61 | F113: 4053.64 | G113: 0.028277825 | H113: 1050 | I113: 950 | J113: Sí | K113: -0.01083243 | L113: 0.36294202 | M113: 0.3361941 | N113: -0.082288966 | O113: 0.48223276 | P113: 0.15188904 | Q113: -0.45933613 | R113: -0.38326943 | S113: 0.5638655 | T113: -0.33573073 | U113: Mayor movimiento | V113: 5143.8477 | W113: 0.26246714 | X113: 54 | Y113: 2026-12-02 | Z113: No | AA113: 4.5946897e+10 | AB113: 3871250 | AC113: Sí | AD113: -0.072239061 | AE113: -0.34587663 | AF113: 0.7595221 | AG113: =Pronóstico!$B$5*P113*AE113 -> -0.0026267435 | AH113: =IF(ISNUMBER(G113),G113,1)+2*'Mi portafolio'!$C$5 -> 0.030597825 | AI113: =AF113*Pronóstico!$B$8+AG113-AH113 -> -0.027196615
A114: B N | B114: Exterior (SIC) | C114: 717.76962 | D114: 0.019640352 | E114: 705.01 | F114: 733.59 | G114: 0.039733074 | H114: 16400 | I114: 20500 | J114: Sí | K114: -0.047940632 | L114: 0.14572133 | M114: -0.026198913 | N114: 0.19306371 | O114: 0.46658955 | P114: 0.14696189 | Q114: -0.32601497 | R114: 1.3633783 | S114: 0.44216521 | T114: -0.19579214 | U114: Mayor movimiento | V114: 938.5896 | W114: 0.30764745 | X114: 16 | Y114: 2026-11-09 | Z114: Sí | AA114: 6.091178e+09 | AB114: 11644000 | AC114: Sí | AD114: 0.25314003 | AE114: 0.86935676 | AF114: 1.5893297 | AG114: =Pronóstico!$B$5*P114*AE114 -> 0.0063881158 | AH114: =IF(ISNUMBER(G114),G114,1)+2*'Mi portafolio'!$C$5 -> 0.042053074 | AI114: =AF114*Pronóstico!$B$8+AG114-AH114 -> -0.02305123
A115: AVGO * | B115: Exterior (SIC) | C115: 6613.5009 | D115: -0.021190741 | E115: 6768 | F115: 6780 | G115: 0.0017714792 | H115: 7 | I115: 100 | J115: Sí | K115: 0.076713693 | L115: -0.012915147 | M115: -0.02925276 | N115: 0.03622004 | O115: 0.46494793 | P115: 0.14644483 | Q115: -0.30381675 | R115: 0.65999028 | S115: 0.50507462 | T115: -0.28313541 | U115: Mayor movimiento | V115: 9644.9593 | W115: 0.45837423 | X115: 47 | Y115: 2026-12-09 | Z115: No | AA115: 1.5091377e+11 | AB115: 47459.93 | AC115: Sí | AD115: -0.037608561 | AE115: 0.73647417 | AF115: 1.391789 | AG115: =Pronóstico!$B$5*P115*AE115 -> 0.0053926419 | AH115: =IF(ISNUMBER(G115),G115,1)+2*'Mi portafolio'!$C$5 -> 0.0040914792 | AI115: =AF115*Pronóstico!$B$8+AG115-AH115 -> 0.012347107
A116: AAL * | B116: Exterior (SIC) | C116: 230.81539 | D116: -0.00078515129 | E116: 228.01 | F116: 237.59 | G116: 0.041151203 | H116: 47900 | I116: 78900 | J116: Sí | K116: 0.054430143 | L116: -0.19167573 | M116: 0.098778537 | N116: 0.055536996 | O116: 0.48373934 | P116: 0.15236357 | Q116: -0.37291849 | R116: 0.80803487 | S116: 0.35838794 | T116: -0.38669874 | U116: Mayor movimiento | V116: 289.10631 | W116: 0.25254345 | X116: 23 | Y116: 2026-10-22 | Z116: Sí | AA116: 1.646119e+10 | AB116: 11091724 | AC116: Sí | AD116: 0.0010497167 | AE116: -0.17239588 | AF116: 1.9083375 | AG116: =Pronóstico!$B$5*P116*AE116 -> -0.0013133426 | AH116: =IF(ISNUMBER(G116),G116,1)+2*'Mi portafolio'!$C$5 -> 0.043471203 | AI116: =AF116*Pronóstico!$B$8+AG116-AH116 -> -0.02963901
A117: RCL * | B117: Exterior (SIC) | C117: 5122.6295 | D117: 0.009155576 | E117: 4993.81 | F117: 5237.39 | G117: 0.047615138 | H117: 2400 | I117: 2800 | J117: Sí | K117: 0.17244011 | L117: 0.019621813 | M117: 0.062750546 | N117: -0.056521734 | O117: 0.49322022 | P117: 0.15534977 | Q117: -0.33564769 | R117: 0.60171563 | S117: 0.36507669 | T117: -0.29310932 | U117: Mayor movimiento | V117: 6359.6011 | W117: 0.24147199 | X117: 27 | Y117: 2026-10-27 | Z117: Sí | AA117: 1.5196151e+10 | AB117: 12249600 | AC117: Sí | AD117: -0.1952866 | AE117: -0.82493401 | AF117: 1.7258984 | AG117: =Pronóstico!$B$5*P117*AE117 -> -0.0064076654 | AH117: =IF(ISNUMBER(G117),G117,1)+2*'Mi portafolio'!$C$5 -> 0.049935138 | AI117: =AF117*Pronóstico!$B$8+AG117-AH117 -> -0.042645197
A118: UAL * | B118: Exterior (SIC) | C118: 1936.3787 | D118: -0.022231717 | E118: 1930.01 | F118: 1990.79 | G118: 0.031003877 | H118: 5500 | I118: 5500 | J118: Sí | K118: 0.068608852 | L118: -0.087111882 | M118: 0.19004813 | N118: 0.059367126 | O118: 0.48924666 | P118: 0.15409821 | Q118: -0.27138361 | R118: 0.91456118 | S118: 0.6116648 | T118: -0.40103477 | U118: Mayor movimiento | V118: 2774.2522 | W118: 0.43270126 | X118: 23 | Y118: 2026-10-20 | Z118: Sí | AA118: 8.5251111e+09 | AB118: 10625065 | AC118: Sí | AD118: -0.0086483711 | AE118: 0.69654968 | AF118: 2.1094176 | AG118: =Pronóstico!$B$5*P118*AE118 -> 0.0053668531 | AH118: =IF(ISNUMBER(G118),G118,1)+2*'Mi portafolio'!$C$5 -> 0.033323877 | AI118: =AF118*Pronóstico!$B$8+AG118-AH118 -> -0.011215614
... A124: FSLR * | B124: Exterior (SIC) | C124: 3194.2019 | D124: -0.012933309 | E124: 3225.01 | F124: 3315.19 | G124: 0.027577138 | H124: 100 | I124: 400 | J124: Sí | K124: -0.06972216 | L124: -0.17404026 | M124: -0.051381741 | N124: -0.25231002 | O124: 0.5470793 | P124: 0.17231378 | Q124: -0.45144087 | R124: 0.67323893 | S124: 0.73308866 | T124: -0.342395 | U124: Mayor movimiento | V124: 4982.4782 | W124: 0.55985076 | X124: 30 | Y124: 2026-10-29 | Z124: Sí | AA124: 7.7557156e+09 | AB124: 324000 | AC124: Sí | AD124: -0.19627239 | AE124: 0.75982814 | AF124: 1.5099526 | AG124: =Pronóstico!$B$5*P124*AE124 -> 0.0065464431 | AH124: =IF(ISNUMBER(G124),G124,1)+2*'Mi portafolio'!$C$5 -> 0.029897138 | AI124: =AF124*Pronóstico!$B$8+AG124-AH124 -> -0.011366944
A125: AA1 * | B125: Exterior (SIC) | C125: 770.23178 | D125: 0.0083266793 | E125: 758 | H125: 1 | I125: 0 | J125: Sin contraparte | K125: -0.10275518 | L125: -0.095522012 | M125: -0.36392014 | N125: 0.17019323 | O125: 0.55269454 | P125: 0.17408242 | Q125: -0.48577156 | R125: 0.96263451 | S125: 0.48837472 | T125: -0.41412971 | U125: Mayor movimiento | V125: 1129.5704 | W125: 0.46653311 | X125: 12 | Y125: 2026-10-15 | Z125: Sí | AA125: 3.0999157e+09 | AB125: 0 | AC125: No | AD125: 0.30420729 | AE125: 1.8170874 | AF125: 1.5984923 | AG125: =Pronóstico!$B$5*P125*AE125 -> 0.015816149 | AH125: =IF(ISNUMBER(G125),G125,1)+2*'Mi portafolio'!$C$5 -> 1.00232 | AI125: =AF125*Pronóstico!$B$8+AG125-AH125 -> -0.9738174
A126: PINS * | B126: Exterior (SIC) | C126: 367.59825 | D126: 0.0072447329 | E126: 359.61 | F126: 369.99 | G126: 0.028453947 | H126: 8200 | I126: 16400 | J126: Sí | K126: 0.18921058 | L126: -0.070575717 | M126: 0.051065757 | N126: -0.3842136 | O126: 0.53432529 | P126: 0.16829665 | Q126: -0.59230637 | R126: -0.2544207 | S126: 0.36832158 | T126: -0.46076984 | U126: Mayor movimiento | V126: 527.34991 | W126: 0.43458222 | X126: 35 | Y126: 2026-11-09 | Z126: Sí | AA126: 4.8755519e+09 | AB126: 3038100 | AC126: Sí | AD126: -0.48218893 | AE126: -0.59951289 | AF126: 0.9765321 | AG126: =Pronóstico!$B$5*P126*AE126 -> -0.0050448005 | AH126: =IF(ISNUMBER(G126),G126,1)+2*'Mi portafolio'!$C$5 -> 0.030773947 | AI126: =AF126*Pronóstico!$B$8+AG126-AH126 -> -0.028068493
A127: ORCL * | B127: Exterior (SIC) | C127: 2472.8016 | D127: -0.039944582 | E127: 2560.02 | F127: 2584.99 | G127: 0.0097064923 | H127: 3400 | I127: 1600 | J127: Sí | K127: -0.093854758 | L127: 0.075844427 | M127: -0.15177027 | N127: -0.53426445 | O127: 0.56027766 | P127: 0.17647087 | Q127: -0.60984629 | R127: 0.32945914 | S127: 0.47168875 | T127: -0.42010247 | U127: Mayor movimiento | V127: 4319.9447 | W127: 0.74698392 | X127: 41 | Y127: 2026-12-10 | Z127: No | AA127: 8.4208443e+10 | AB127: 4096000 | AC127: Sí | AD127: -0.4860255 | AE127: 0.78254935 | AF127: 1.5526873 | AG127: =Pronóstico!$B$5*P127*AE127 -> 0.0069048584 | AH127: =IF(ISNUMBER(G127),G127,1)+2*'Mi portafolio'!$C$5 -> 0.012026492 | AI127: =AF127*Pronóstico!$B$8+AG127-AH127 -> 0.007201281
A128: SOFI * | B128: Exterior (SIC) | C128: 277.4686 | D128: -0.014284734 | E128: 278.03 | F128: 284.99 | G128: 0.024723811 | H128: 13600 | I128: 27200 | J128: Sí | K128: -0.053469244 | L128: -0.12577545 | M128: -0.14443076 | N128: -0.43292772 | O128: 0.55914758 | P128: 0.17611493 | Q128: -0.55411579 | R128: 0.87907823 | S128: 0.78236621 | T128: -0.35561684 | U128: Mayor movimiento | V128: 369.08353 | W128: 0.33018122 | X128: 22 | Y128: 2026-10-27 | Z128: Sí | AA128: 1.3701115e+10 | AB128: 3780800 | AC128: Sí | AD128: -0.40089397 | AE128: -1.0080697 | AF128: 2.3754155 | AG128: =Pronóstico!$B$5*P128*AE128 -> -0.0088768061 | AH128: =IF(ISNUMBER(G128),G128,1)+2*'Mi portafolio'!$C$5 -> 0.027043811 | AI128: =AF128*Pronóstico!$B$8+AG128-AH128 -> -0.017068113
A129: PLTR * | B129: Exterior (SIC) | C129: 3588.6665 | D129: 0.028209475 | E129: 3590.01 | F129: 3618.98 | G129: 0.0080371869 | H129: 2550 | I129: 1950 | J129: Sí | K129: 0.25110964 | L129: 0.57598645 | M129: 0.4623245 | N129: 0.092350918 | O129: 0.60963764 | P129: 0.19201781 | Q129: -0.50828413 | R129: 0.38854805 | S129: 0.85976549 | T129: -0.301762 | U129: Mayor movimiento | V129: 3627.7681 | W129: 0.010895847 | X129: 25 | Y129: 2026-11-02 | Z129: Sí | AA129: 7.4999797e+10 | AB129: 7029126 | AC129: Sí | AD129: -0.12689433 | AE129: -1.6778585 | AF129: 1.7207824 | AG129: =Pronóstico!$B$5*P129*AE129 -> -0.016108935 | AH129: =IF(ISNUMBER(G129),G129,1)+2*'Mi portafolio'!$C$5 -> 0.010357187 | AI129: =AF129*Pronóstico!$B$8+AG129-AH129 -> -0.012809118
A130: SHOP N | B130: Exterior (SIC) | C130: 3015.1225 | D130: 0.010655103 | E130: 2963.61 | F130: 3049.99 | G130: 0.028728216 | H130: 800 | I130: 1200 | J130: Sí | K130: 0.40635379 | L130: 0.3812152 | M130: 0.37159135 | N130: 0.037023915 | O130: 0.59098487 | P130: 0.18614274 | Q130: -0.50168387 | R130: 0.34234214 | S130: 0.5312739 | T130: -0.37112531 | U130: Mayor movimiento | V130: 3141.9817 | W130: 0.042074295 | X130: 48 | Y130: 2026-11-03 | Z130: Sí | AA130: 2.4925445e+10 | AB130: 2424400 | AC130: Sí | AD130: -0.2626152 | AE130: -2.0241717 | AF130: 1.8253914 | AG130: =Pronóstico!$B$5*P130*AE130 -> -0.018839243 | AH130: =IF(ISNUMBER(G130),G130,1)+2*'Mi portafolio'!$C$5 -> 0.031048216 | AI130: =AF130*Pronóstico!$B$8+AG130-AH130 -> -0.035400226
A131: AMAT * | B131: Exterior (SIC) | C131: 9225.4453 | D131: -0.012453303 | E131: 9287.61 | F131: 9500 | G131: 0.022609581 | H131: 4328 | I131: 1 | J131: Sí | K131: 0.16535881 | L131: -0.081492064 | M131: 0.36132954 | N131: 1.2404327 | O131: 0.59807288 | P131: 0.18837525 | Q131: -0.43558081 | R131: 1.2919386 | S131: 0.63022151 | T131: -0.26389131 | U131: Mayor movimiento | V131: 11598.759 | W131: 0.25725733 | X131: 36 | Y131: 2026-11-12 | Z131: Sí | AA131: 5.2529278e+10 | AB131: 9200 | AC131: No | AD131: 0.92252605 | AE131: 1.9844847 | AF131: 1.8496455 | AG131: =Pronóstico!$B$5*P131*AE131 -> 0.018691391 | AH131: =IF(ISNUMBER(G131),G131,1)+2*'Mi portafolio'!$C$5 -> 0.024929581 | AI131: =AF131*Pronóstico!$B$8+AG131-AH131 -> 0.0084415351
A132: AFRM * | B132: Exterior (SIC) | C132: 1362.1103 | D132: 0.0066073256 | E132: 1339.21 | F132: 1403.99 | G132: 0.047229513 | H132: 1200 | I132: 800 | J132: Sí | K132: 0.18205288 | L132: -0.04994815 | M132: 0.32421799 | N132: 0.088526616 | O132: 0.59351726 | P132: 0.18694037 | Q132: -0.48987799 | R132: 0.52721499 | S132: 1.1407956 | T132: -0.45807022 | U132: Mayor movimiento | V132: 1790.9069 | W132: 0.31480309 | X132: 32 | Y132: 2026-11-05 | Z132: Sí | AA132: 4.8858452e+09 | AB132: 1083136 | AC132: Sí | AD132: -0.079121895 | AE132: -0.10581622 | AF132: 2.3663964 | AG132: =Pronóstico!$B$5*P132*AE132 -> -0.00098906615 | AH132: =IF(ISNUMBER(G132),G132,1)+2*'Mi portafolio'!$C$5 -> 0.049549513 | AI132: =AF132*Pronóstico!$B$8+AG132-AH132 -> -0.031757655
A133: TWLO * | B133: Exterior (SIC) | C133: 5027.4733 | D133: 0.025142037 | E133: 4951.81 | F133: 5187.59 | G133: 0.046507683 | H133: 500 | I133: 400 | J133: Sí | K133: 0.30902376 | L133: 0.3167092 | M133: 1.1739712 | N133: 1.5584795 | O133: 0.63610826 | P133: 0.20035527 | Q133: -0.28386094 | R133: 0.047360169 | S133: 0.67176473 | T133: -0.36879734 | U133: Mayor movimiento | V133: 4774.887 | W133: -0.050241199 | X133: 28 | Y133: 2026-10-29 | Z133: Sí | AA133: 2.3478874e+10 | AB133: 1969600 | AC133: Sí | AD133: 0.95449431 | AE133: 0.84476503 | AF133: 1.3006933 | AG133: =Pronóstico!$B$5*P133*AE133 -> 0.0084626562 | AH133: =IF(ISNUMBER(G133),G133,1)+2*'Mi portafolio'!$C$5 -> 0.048827683 | AI133: =AF133*Pronóstico!$B$8+AG133-AH133 -> -0.030042064
A134: NVAX * | B134: Exterior (SIC) | C134: 197.41387 | D134: -0.020383882 | E134: 196.01 | F134: 200.49 | G134: 0.02259773 | H134: 3500 | I134: 4500 | J134: Sí | K134: 0.18577584 | L134: 0.2666267 | M134: 0.31724865 | N134: 0.32300007 | O134: 0.66519956 | P134: 0.20951817 | Q134: -0.33871212 | R134: 1.0279268 | S134: 3.663693 | T134: -0.42794822 | U134: Mayor movimiento | V134: 254.1823 | W134: 0.28756046 | X134: 9 | Y134: 2026-11-05 | Z134: Sí | AA134: 1.4192768e+09 | AB134: 682500 | AC134: Sí | AD134: 0.11572527 | AE134: 0.35111824 | AF134: 1.8657186 | AG134: =Pronóstico!$B$5*P134*AE134 -> 0.0036782825 | AH134: =IF(ISNUMBER(G134),G134,1)+2*'Mi portafolio'!$C$5 -> 0.02491773 | AI134: =AF134*Pronóstico!$B$8+AG134-AH134 -> -0.0064321575
...

Sheet Correlaciones
A1: Correlaciones de rendimientos diarios (último año, en pesos)
A2: Cerca de 1 = se mueven casi igual (no se diversifican entre sí). Cerca de 0 = independientes.
B4: BRKB * | C4: SIGMAF A | D4: LIVEPOL C-1 | E4: GRUMA B | F4: KO * | G4: FIBRAMQ 12 | H4: VESTA * | I4: MCD * | J4: JNJ * | K4: PG * | L4: WALMEX * | M4: AGNC * | N4: PFE * | O4: AC * | P4: COST * | Q4: ACTINVR B | R4: PEP * | S4: CHDRAUI B | T4: BAC * | U4: GFINBUR O | V4: FUNO 11 | W4: FEMSA UBD | X4: JPM * | Y4: V * | Z4: KIMBER A | AA4: KOF UBL | AB4: MA * | AC4: FIBRAPL 14 | AD4: AMX B | AE4: ASUR B | AF4: PINFRA * | AG4: T * | AH4: VZ * | AI4: CVX * | AJ4: ALSEA * | AK4: GFNORTE O | AL4: AAPL * | AM4: BOLSA A | AN4: HD * | AO4: ABBV * | AP4: DIS * | AQ4: XOM * | AR4: WFC * | AS4: BBAJIO O | AT4: AXP * | AU4: WMT * | AV4: BIMBO A | AW4: GCC * | AX4: BMY * | AY4: SBUX * | AZ4: OMA B | BA4: FDX * | BB4: C * | BC4: Q * | BD4: R A | BE4: MRK * | BF4: MEGA CPO | BG4: TMO * | BH4: LAB B | BI4: CUERVO * | BJ4: SITES1 A-1 | BK4: GAP B | BL4: TX * | BM4: TGT * | BN4: CVS * | BO4: GOOGL * | BP4: MSFT * | BQ4: CEMEX CPO | BR4: WYNN * | BS4: FANG * | BT4: GE * | BU4: GENTERA * | BV4: AMZN * | BW4: LVS * | BX4: LLY * | BY4: GM * | BZ4: BA * | CA4: GCARSO A1 | CB4: ALPEK A | CC4: UNH * | CD4: UBER * | CE4: CSCO * | CF4: DVN * | CG4: ABNB * | CH4: GMEXICO B | CI4: OXY1 * | CJ4: NFLX * | CK4: NKE * | CL4: F * | CM4: NVDA * | CN4: ORBIA * | CO4: TLEVISA CPO | CP4: GME * | CQ4: DAL * | CR4: TSM N | CS4: CAT * | CT4: ROKU * | CU4: BABA N | CV4: META * | CW4: MELI N | CX4: NU N | CY4: LUV * | CZ4: ZM * | DA4: PYPL * | DB4: TSLA * | DC4: VOLAR A | DD4: XYZ * | DE4: FCX * | DF4: CRM * | DG4: B N | DH4: AVGO * | DI4: AAL * | DJ4: RCL * | DK4: UAL * | DL4: PE&OLES * | DM4: CCL1 N | DN4: ETSY * | DO4: QCOM * | DP4: NCLH N | DQ4: FSLR * | DR4: AA1 * | DS4: PINS * | DT4: ORCL * | DU4: SOFI * | DV4: PLTR * | DW4: SHOP N | DX4: AMAT * | DY4: AFRM * | DZ4: TWLO * | EA4: NVAX * | EB4: UPST * | EC4: MFRISCO A-1 | ED4: RIVN * | EE4: AMD * | EF4: CLF * | EG4: INTC * | EH4: FUBO * | EI4: MU * | EJ4: LCID * | EK4: MARA * | EL4: RIOT * | EM4: SPCE * | EN4: MRNA * | EO4: BYND *
A5: BRKB * | B5: 1 | C5: -0.03 | D5: -0.11 | E5: 0.07 | F5: 0.44 | G5: -0.1 | H5: -0.01 | I5: 0.47 | J5: 0.32 | K5: 0.44 | L5: 0.07 | M5: 0.26 | N5: 0.32 | O5: 0.15 | P5: 0.39 | Q5: 0.03 | R5: 0.38 | S5: 0.01 | T5: 0.25 | U5: 0.08 | V5: 0.04 | W5: 0.03 | X5: 0.33 | Y5: 0.45 | Z5: 0.05 | AA5: 0.06 | AB5: 0.49 | AC5: 0.04 | AD5: 0.07 | AE5: 0.01 | AF5: -0.12 | AG5: 0.27 | AH5: 0.31 | AI5: 0.18 | AJ5: 0.04 | AK5: -0.02 | AL5: 0.29 | AM5: 0.03 | AN5: 0.37 | AO5: 0.25 | AP5: 0.24 | AQ5: 0.13 | AR5: 0.24 | AS5: -0.12 | AT5: 0.29 | AU5: 0.31 | AV5: 0.08 | AW5: 0 | AX5: 0.34 | AY5: 0.26 | AZ5: 0.02 | BA5: 0.19 | BB5: 0.16 | BC5: 0.11 | BD5: 0.01 | BE5: 0.29 | BF5: 0.04 | BG5: 0.21 | BH5: 0.05 | BI5: 0.1 | BJ5: -0.02 | BK5: 0.02 | BL5: 0.09 | BM5: 0.18 | BN5: 0.28 | BO5: 0.15 | BP5: 0.12 | BQ5: -0.05 | BR5: 0.22 | BS5: 0.03 | BT5: 0.19 | BU5: -0.07 | BV5: 0.14 | BW5: 0.17 | BX5: 0.27 | BY5: 0.16 | BZ5: 0.22 | CA5: 0.05 | CB5: 0.04 | CC5: 0.22 | CD5: 0.18 | CE5: 0.07 | CF5: 0.08 | CG5: 0.24 | CH5: -0.07 | CI5: 0.1 | CJ5: 0.27 | CK5: 0.33 | CL5: 0.11 | CM5: -0.14 | CN5: -0.03 | CO5: 0.02 | CP5: 0.18 | CQ5: 0.27 | CR5: -0.05 | CS5: 0.01 | CT5: 0.1 | CU5: 0 | CV5: 0.07 | CW5: 0.11 | CX5: 0.07 | CY5: 0.22 | CZ5: 0.1 | DA5: 0.12 | DB5: 0 | DC5: -0.02 | DD5: 0.14 | DE5: -0.08 | DF5: 0.17 | DG5: 0.02 | DH5: -0.04 | DI5: 0.27 | DJ5: 0.22 | DK5: 0.23 | DL5: -0.11 | DM5: 0.27 | DN5: 0.2 | DO5: 0.07 | DP5: 0.26 | DQ5: 0.01 | DR5: -0.05 | DS5: 0.11 | DT5: -0.12 | DU5: -0.01 | DV5: 0 | DW5: 0.11 | DX5: -0.15 | DY5: 0.16 | DZ5: 0.02 | EA5: 0 | EB5: 0.05 | EC5: -0.11 | ED5: 0.05 | EE5: -0.08 | EF5: 0.06 | EG5: -0.07 | EH5: 0.07 | EI5: -0.19 | EJ5: 0.07 | EK5: -0.03 | EL5: -0.11 | EM5: -0.07 | EN5: 0 | EO5: -0.02
A6: SIGMAF A | B6: -0.03 | C6: 1 | D6: 0.08 | E6: 0.09 | F6: 0.02 | G6: 0.02 | H6: 0.14 | I6: 0.08 | J6: 0.04 | K6: -0.07 | L6: 0.31 | M6: 0.07 | N6: 0 | O6: 0.17 | P6: 0.08 | Q6: 0 | R6: 0.03 | S6: 0.07 | T6: 0 | U6: 0.12 | V6: 0.15 | W6: 0.14 | X6: 0.03 | Y6: 0.12 | Z6: 0.2 | AA6: 0.09 | AB6: 0.05 | AC6: 0.04 | AD6: 0.2 | AE6: 0.2 | AF6: 0.22 | AG6: -0.01 | AH6: 0 | AI6: -0.01 | AJ6: 0.1 | AK6: 0.21 | AL6: 0 | AM6: 0.08 | AN6: 0.02 | AO6: 0.04 | AP6: -0.05 | AQ6: 0.02 | AR6: 0 | AS6: 0.11 | AT6: 0.02 | AU6: 0.05 | AV6: 0.28 | AW6: 0.19 | AX6: 0 | AY6: 0.13 | AZ6: 0.09 | BA6: 0.06 | BB6: -0.07 | BC6: 0.02 | BD6: 0.16 | BE6: 0.07 | BF6: -0.01 | BG6: 0.02 | BH6: 0.05 | BI6: -0.01 | BJ6: 0.02 | BK6: 0.06 | BL6: 0 | BM6: 0.04 | BN6: 0.03 | BO6: -0.02 | BP6: -0.06 | BQ6: 0.19 | BR6: -0.06 | BS6: -0.03 | BT6: 0.04 | BU6: 0.06 | BV6: -0.02 | BW6: -0.04 | BX6: -0.07 | BY6: -0.02 | BZ6: 0.12 | CA6: 0.15 | CB6: 0.09 | CC6: -0.02 | CD6: -0.04 | CE6: -0.03 | CF6: -0.04 | CG6: -0.01 | CH6: 0.12 | CI6: -0.05 | CJ6: -0.01 | CK6: -0.06 | CL6: 0.01 | CM6: -0.07 | CN6: 0.17 | CO6: 0.07 | CP6: 0.01 | CQ6: -0.02 | CR6: -0.06 | CS6: 0.05 | CT6: 0.03 | CU6: 0.01 | CV6: -0.06 | CW6: 0.02 | CX6: 0.02 | CY6: 0 | CZ6: -0.13 | DA6: -0.01 | DB6: 0.05 | DC6: 0.04 | DD6: -0.04 | DE6: 0.07 | DF6: -0.08 | DG6: 0.05 | DH6: 0.06 | DI6: -0.03 | DJ6: -0.05 | DK6: 0.01 | DL6: 0.17 | DM6: -0.01 | DN6: 0.1 | DO6: 0.15 | DP6: -0.02 | DQ6: 0.02 | DR6: 0.05 | DS6: -0.07 | DT6: -0.04 | DU6: -0.05 | DV6: -0.05 | DW6: -0.11 | DX6: 0.04 | DY6: 0.01 | DZ6: -0.1 | EA6: 0.02 | EB6: -0.08 | EC6: 0.03 | ED6: 0.13 | EE6: 0.03 | EF6: 0.11 | EG6: 0.08 | EH6: -0.01 | EI6: 0.02 | EJ6: -0.02 | EK6: 0.04 | EL6: 0.02 | EM6: -0.06 | EN6: 0.01 | EO6: 0.04
A7: LIVEPOL C-1 | B7: -0.11 | C7: 0.08 | D7: 1 | E7: 0.12 | F7: -0.09 | G7: 0.12 | H7: 0.15 | I7: -0.02 | J7: -0.04 | K7: -0.05 | L7: 0.11 | M7: -0.07 | N7: 0.18 | O7: 0.03 | P7: 0 | Q7: 0.02 | R7: -0.16 | S7: 0.11 | T7: 0.06 | U7: 0.12 | V7: 0.03 | W7: -0.04 | X7: 0.01 | Y7: 0 | Z7: 0.09 | AA7: 0.09 | AB7: 0.03 | AC7: 0.08 | AD7: 0.02 | AE7: 0.19 | AF7: 0.17 | AG7: -0.02 | AH7: -0.03 | AI7: -0.1 | AJ7: 0.21 | AK7: 0.02 | AL7: 0.04 | AM7: 0.09 | AN7: -0.05 | AO7: 0.02 | AP7: 0.03 | AQ7: -0.09 | AR7: 0.06 | AS7: 0.12 | AT7: 0.02 | AU7: -0.04 | AV7: 0.1 | AW7: 0.04 | AX7: 0.09 | AY7: -0.03 | AZ7: 0.21 | BA7: -0.03 | BB7: 0.05 | BC7: 0.06 | BD7: 0.16 | BE7: -0.02 | BF7: 0.13 | BG7: 0.04 | BH7: 0.11 | BI7: 0.12 | BJ7: 0.07 | BK7: 0.22 | BL7: -0.05 | BM7: 0.05 | BN7: -0.11 | BO7: 0.08 | BP7: 0.08 | BQ7: 0.1 | BR7: 0.04 | BS7: -0.06 | BT7: 0.05 | BU7: 0.1 | BV7: 0.03 | BW7: 0.03 | BX7: 0.08 | BY7: -0.05 | BZ7: -0.01 | CA7: 0.15 | CB7: -0.06 | CC7: -0.01 | CD7: 0.04 | CE7: 0.04 | CF7: -0.04 | CG7: 0.1 | CH7: 0.04 | CI7: -0.07 | CJ7: 0.05 | CK7: 0.02 | CL7: 0 | CM7: 0.06 | CN7: 0.2 | CO7: 0 | CP7: 0.04 | CQ7: 0.04 | CR7: -0.01 | CS7: 0.03 | CT7: 0.07 | CU7: 0.08 | CV7: 0.02 | CW7: -0.01 | CX7: 0 | CY7: 0.02 | CZ7: 0.11 | DA7: 0.16 | DB7: 0.09 | DC7: 0.18 | DD7: 0.18 | DE7: 0.04 | DF7: 0.07 | DG7: 0.08 | DH7: 0.04 | DI7: 0.03 | DJ7: 0 | DK7: 0.02 | DL7: 0.2 | DM7: 0.02 | DN7: -0.06 | DO7: 0.07 | DP7: 0.02 | DQ7: -0.01 | DR7: -0.02 | DS7: 0.04 | DT7: 0.04 | DU7: 0.11 | DV7: 0.06 | DW7: 0.07 | DX7: 0.06 | DY7: 0.03 | DZ7: 0.12 | EA7: 0.04 | EB7: 0.05 | EC7: 0 | ED7: 0.1 | EE7: 0.04 | EF7: 0.08 | EG7: -0.01 | EH7: 0.06 | EI7: 0.06 | EJ7: 0.05 | EK7: 0.04 | EL7: 0.09 | EM7: 0.02 | EN7: -0.01 | EO7: -0.09
A8: GRUMA B | B8: 0.07 | C8: 0.09 | D8: 0.12 | E8: 1 | F8: 0.13 | G8: 0.05 | H8: 0.22 | I8: 0.16 | J8: 0.07 | K8: 0.09 | L8: 0.31 | M8: 0.19 | N8: 0.19 | O8: 0.36 | P8: 0.16 | Q8: 0.08 | R8: 0.09 | S8: 0.25 | T8: 0.14 | U8: 0.32 | V8: 0.32 | W8: 0.27 | X8: 0.14 | Y8: 0.05 | Z8: 0.18 | AA8: 0.2 | AB8: 0.06 | AC8: 0.31 | AD8: 0.24 | AE8: 0.19 | AF8: 0.34 | AG8: 0.08 | AH8: 0.09 | AI8: 0.07 | AJ8: 0.1 | AK8: 0.3 | AL8: 0.14 | AM8: 0.16 | AN8: 0.12 | AO8: 0.11 | AP8: 0.13 | AQ8: 0.11 | AR8: 0.08 | AS8: 0.18 | AT8: 0.13 | AU8: 0.09 | AV8: 0.45 | AW8: 0.17 | AX8: 0.13 | AY8: 0.11 | AZ8: 0.24 | BA8: 0.18 | BB8: 0.12 | BC8: 0.22 | BD8: 0.23 | BE8: 0.09 | BF8: 0.32 | BG8: -0.01 | BH8: 0.22 | BI8: 0.21 | BJ8: 0.06 | BK8: 0.18 | BL8: 0.11 | BM8: 0.22 | BN8: 0.08 | BO8: 0.08 | BP8: 0.08 | BQ8: 0.15 | BR8: 0.07 | BS8: 0.03 | BT8: 0.06 | BU8: 0.17 | BV8: -0.03 | BW8: 0.13 | BX8: 0.03 | BY8: 0.06 | BZ8: 0.13 | CA8: 0.26 | CB8: 0.02 | CC8: 0.07 | CD8: 0.05 | CE8: 0.01 | CF8: 0.03 | CG8: 0.03 | CH8: 0.19 | CI8: -0.05 | CJ8: 0.06 | CK8: 0.12 | CL8: 0 | CM8: -0.03 | CN8: 0.16 | CO8: 0.14 | CP8: 0.03 | CQ8: 0.17 | CR8: 0.08 | CS8: 0.08 | CT8: 0.15 | CU8: 0.01 | CV8: 0 | CW8: 0.1 | CX8: 0.07 | CY8: 0.19 | CZ8: 0.06 | DA8: -0.01 | DB8: 0.19 | DC8: 0.17 | DD8: 0.13 | DE8: 0.15 | DF8: 0.04 | DG8: 0.09 | DH8: 0.1 | DI8: 0.2 | DJ8: 0.08 | DK8: 0.13 | DL8: 0.11 | DM8: 0.12 | DN8: -0.02 | DO8: 0.14 | DP8: 0.06 | DQ8: 0.08 | DR8: 0.12 | DS8: -0.01 | DT8: 0.05 | DU8: 0.14 | DV8: 0.09 | DW8: 0.02 | DX8: 0.05 | DY8: 0.09 | DZ8: 0.03 | EA8: 0.05 | EB8: 0.12 | EC8: 0.09 | ED8: 0.19 | EE8: 0.08 | EF8: 0.01 | EG8: 0.06 | EH8: -0.02 | EI8: -0.02 | EJ8: 0.17 | EK8: 0.07 | EL8: 0.1 | EM8: 0.05 | EN8: 0.02 | EO8: 0.02
A9: KO * | B9: 0.44 | C9: 0.02 | D9: -0.09 | E9: 0.13 | F9: 1 | G9: -0.02 | H9: 0.08 | I9: 0.58 | J9: 0.46 | K9: 0.58 | L9: 0.16 | M9: 0.29 | N9: 0.3 | O9: 0.08 | P9: 0.48 | Q9: -0.1 | R9: 0.65 | S9: 0.11 | T9: 0.05 | U9: 0.07 | V9: 0.05 | W9: 0.13 | X9: 0.04 | Y9: 0.31 | Z9: 0.1 | AA9: 0.27 | AB9: 0.33 | AC9: -0.02 | AD9: 0.14 | AE9: -0.07 | AF9: -0.08 | AG9: 0.4 | AH9: 0.41 | AI9: 0.24 | AJ9: -0.02 | AK9: -0.03 | AL9: 0.27 | AM9: -0.01 | AN9: 0.4 | AO9: 0.39 | AP9: 0.29 | AQ9: 0.26 | AR9: 0.06 | AS9: 0.01 | AT9: 0.08 | AU9: 0.41 | AV9: 0.09 | AW9: -0.03 | AX9: 0.36 | AY9: 0.33 | AZ9: -0.03 | BA9: 0.21 | BB9: -0.07 | BC9: 0.08 | BD9: 0.01 | BE9: 0.41 | BF9: 0.03 | BG9: 0.1 | BH9: 0 | BI9: -0.07 | BJ9: -0.08 | BK9: -0.06 | BL9: 0.11 | BM9: 0.36 | BN9: 0.21 | BO9: 0.08 | BP9: -0.02 | BQ9: -0.04 | BR9: 0.14 | BS9: 0.15 | BT9: 0.08 | BU9: -0.06 | BV9: 0.02 | BW9: 0.16 | BX9: 0.22 | BY9: 0.25 | BZ9: 0.08 | CA9: 0.05 | CB9: 0.07 | CC9: 0.08 | CD9: 0.17 | CE9: -0.08 | CF9: 0.24 | CG9: 0.17 | CH9: -0.07 | CI9: 0.19 | CJ9: 0.3 | CK9: 0.26 | CL9: 0.14 | CM9: -0.19 | CN9: -0.09 | CO9: -0.01 | CP9: 0.12 | CQ9: 0.1 | CR9: -0.13 | CS9: -0.13 | CT9: -0.01 | CU9: 0 | CV9: -0.06 | CW9: 0.1 | CX9: 0.05 | CY9: 0.13 | CZ9: 0.02 | DA9: 0.07 | DB9: -0.08 | DC9: -0.09 | DD9: 0.03 | DE9: -0.11 | DF9: 0.08 | DG9: -0.06 | DH9: -0.16 | DI9: 0.11 | DJ9: 0.15 | DK9: 0.07 | DL9: -0.11 | DM9: 0.16 | DN9: 0.17 | DO9: -0.11 | DP9: 0.14 | DQ9: -0.1 | DR9: -0.08 | DS9: 0.04 | DT9: -0.26 | DU9: -0.12 | DV9: -0.08 | DW9: -0.04 | DX9: -0.19 | DY9: 0 | DZ9: -0.05 | EA9: 0.01 | EB9: -0.05 | EC9: -0.12 | ED9: -0.02 | EE9: -0.18 | EF9: -0.06 | EG9: -0.09 | EH9: 0.06 | EI9: -0.2 | EJ9: 0.03 | EK9: -0.05 | EL9: -0.16 | EM9: -0.09 | EN9: 0.09 | EO9: 0.11
A10: FIBRAMQ 12 | B10: -0.1 | C10: 0.02 | D10: 0.12 | E10: 0.05 | F10: -0.02 | G10: 1 | H10: 0.18 | I10: 0.02 | J10: -0.01 | K10: 0.01 | L10: -0.02 | M10: 0.06 | N10: 0.05 | O10: 0.11 | P10: -0.1 | Q10: 0.05 | R10: -0.02 | S10: -0.05 | T10: 0.02 | U10: 0.07 | V10: 0.14 | W10: 0.05 | X10: -0.03 | Y10: -0.04 | Z10: 0.21 | AA10: 0.08 | AB10: 0 | AC10: 0.16 | AD10: 0.03 | AE10: 0.22 | AF10: 0.18 | AG10: -0.08 | AH10: -0.08 | AI10: -0.06 | AJ10: 0.08 | AK10: 0.13 | AL10: -0.06 | AM10: 0.16 | AN10: -0.02 | AO10: 0.03 | AP10: 0.05 | AQ10: -0.01 | AR10: 0 | AS10: 0.15 | AT10: -0.02 | AU10: -0.02 | AV10: 0.05 | AW10: 0.11 | AX10: 0.05 | AY10: 0.03 | AZ10: 0.11 | BA10: 0.01 | BB10: 0.08 | BC10: 0.03 | BD10: 0.16 | BE10: -0.03 | BF10: 0.21 | BG10: -0.02 | BH10: 0.03 | BI10: 0.1 | BJ10: 0.05 | BK10: 0.16 | BL10: 0.08 | BM10: -0.07 | BN10: 0.02 | BO10: 0.07 | BP10: -0.03 | BQ10: 0.09 | BR10: 0 | BS10: 0 | BT10: 0.01 | BU10: -0.01 | BV10: 0.02 | BW10: 0.08 | BX10: -0.01 | BY10: 0.03 | BZ10: -0.09 | CA10: 0.12 | CB10: -0.02 | CC10: 0.04 | CD10: 0.02 | CE10: -0.01 | CF10: 0.02 | CG10: 0.06 | CH10: 0.17 | CI10: -0.02 | CJ10: 0.08 | CK10: -0.1 | CL10: 0.07 | CM10: -0.01 | CN10: 0.11 | CO10: -0.05 | CP10: 0.05 | CQ10: -0.05 | CR10: -0.01 | CS10: 0 | CT10: 0.14 | CU10: -0.03 | CV10: 0.01 | CW10: -0.03 | CX10: 0.08 | CY10: 0 | CZ10: -0.11 | DA10: -0.09 | DB10: 0.08 | DC10: 0.1 | DD10: 0.05 | DE10: 0.02 | DF10: 0.01 | DG10: 0.02 | DH10: -0.03 | DI10: 0 | DJ10: -0.04 | DK10: -0.05 | DL10: 0.16 | DM10: 0.04 | DN10: 0.02 | DO10: -0.03 | DP10: 0.01 | DQ10: -0.17 | DR10: 0.07 | DS10: -0.02 | DT10: -0.05 | DU10: 0.03 | DV10: 0.04 | DW10: -0.08 | DX10: 0.01 | DY10: -0.04 | DZ10: 0.04 | EA10: 0.04 | EB10: 0.01 | EC10: 0.15 | ED10: 0.07 | EE10: 0.03 | EF10: 0.07 | EG10: 0.05 | EH10: -0.07 | EI10: 0 | EJ10: 0.1 | EK10: 0.04 | EL10: 0.04 | EM10: -0.06 | EN10: 0 | EO10: 0.06
A11: VESTA * | B11: -0.01 | C11: 0.14 | D11: 0.15 | E11: 0.22 | F11: 0.08 | G11: 0.18 | H11: 1 | I11: 0.09 | J11: 0 | K11: 0.1 | L11: 0.2 | M11: 0.18 | N11: 0.11 | O11: 0.21 | P11: 0.02 | Q11: -0.02 | R11: 0.06 | S11: 0.25 | T11: 0.03 | U11: 0.3 | V11: 0.37 | W11: 0.15 | X11: 0.07 | Y11: -0.08 | Z11: 0.28 | AA11: 0.22 | AB11: -0.09 | AC11: 0.23 | AD11: 0.21 | AE11: 0.21 | AF11: 0.26 | AG11: -0.02 | AH11: 0.01 | AI11: -0.11 | AJ11: 0.27 | AK11: 0.26 | AL11: 0.01 | AM11: 0.17 | AN11: 0.14 | AO11: 0 | AP11: 0.03 | AQ11: -0.08 | AR11: -0.01 | AS11: 0.31 | AT11: 0 | AU11: 0.02 | AV11: 0.19 | AW11: 0.35 | AX11: 0.06 | AY11: 0.01 | AZ11: 0.28 | BA11: 0.08 | BB11: 0.03 | BC11: 0.16 | BD11: 0.24 | BE11: 0.09 | BF11: 0.23 | BG11: 0.04 | BH11: 0.3 | BI11: 0.14 | BJ11: -0.08 | BK11: 0.19 | BL11: 0.13 | BM11: 0.06 | BN11: -0.08 | BO11: 0.18 | BP11: 0.03 | BQ11: 0.27 | BR11: 0.12 | BS11: -0.09 | BT11: 0.18 | BU11: 0.19 | BV11: 0.07 | BW11: 0.1 | BX11: 0.06 | BY11: 0.13 | BZ11: 0.12 | CA11: 0.28 | CB11: -0.1 | CC11: -0.06 | CD11: 0.05 | CE11: 0.02 | CF11: -0.12 | CG11: 0.11 | CH11: 0.27 | CI11: -0.12 | CJ11: -0.01 | CK11: 0.02 | CL11: 0.22 | CM11: 0.04 | CN11: 0.23 | CO11: 0.13 | CP11: 0.05 | CQ11: 0.09 | CR11: 0.1 | CS11: 0.11 | CT11: 0.14 | CU11: 0.04 | CV11: 0.02 | CW11: 0.07 | CX11: 0.06 | CY11: 0.03 | CZ11: 0.11 | DA11: 0.06 | DB11: 0.12 | DC11: 0.16 | DD11: 0.06 | DE11: 0.11 | DF11: 0.03 | DG11: 0.11 | DH11: 0.09 | DI11: 0.11 | DJ11: 0.06 | DK11: 0.09 | DL11: 0.22 | DM11: 0.14 | DN11: 0.09 | DO11: 0.13 | DP11: 0.11 | DQ11: 0.13 | DR11: 0.04 | DS11: 0.02 | DT11: 0.01 | DU11: 0.05 | DV11: 0.02 | DW11: 0.03 | DX11: 0.1 | DY11: -0.05 | DZ11: 0.04 | EA11: 0.1 | EB11: 0 | EC11: 0.04 | ED11: 0.21 | EE11: 0.1 | EF11: 0 | EG11: 0.09 | EH11: -0.04 | EI11: 0.03 | EJ11: 0.1 | EK11: 0.05 | EL11: 0.09 | EM11: 0.02 | EN11: 0.01 | EO11: 0.03
A12: MCD * | B12: 0.47 | C12: 0.08 | D12: -0.02 | E12: 0.16 | F12: 0.58 | G12: 0.02 | H12: 0.09 | I12: 1 | J12: 0.43 | K12: 0.56 | L12: 0.14 | M12: 0.31 | N12: 0.37 | O12: 0.11 | P12: 0.49 | Q12: -0.03 | R12: 0.55 | S12: 0.11 | T12: 0.16 | U12: 0.07 | V12: 0.12 | W12: 0.19 | X12: 0.17 | Y12: 0.4 | Z12: 0.12 | AA12: 0.21 | AB12: 0.42 | AC12: 0.04 | AD12: 0.08 | AE12: 0.05 | AF12: 0 | AG12: 0.31 | AH12: 0.31 | AI12: 0.11 | AJ12: 0.05 | AK12: 0.05 | AL12: 0.3 | AM12: 0.04 | AN12: 0.48 | AO12: 0.36 | AP12: 0.3 | AQ12: 0.14 | AR12: 0.2 | AS12: -0.01 | AT12: 0.23 | AU12: 0.42 | AV12: 0.14 | AW12: 0.03 | AX12: 0.41 | AY12: 0.36 | AZ12: 0.07 | BA12: 0.22 | BB12: 0.09 | BC12: 0.12 | BD12: 0.04 | BE12: 0.35 | BF12: 0.09 | BG12: 0.15 | BH12: 0.03 | BI12: 0.03 | BJ12: 0.01 | BK12: 0 | BL12: 0.12 | BM12: 0.34 | BN12: 0.13 | BO12: 0.21 | BP12: 0.11 | BQ12: 0.02 | BR12: 0.24 | BS12: 0.02 | BT12: 0.18 | BU12: -0.06 | BV12: 0.14 | BW12: 0.2 | BX12: 0.33 | BY12: 0.23 | BZ12: 0.2 | CA12: 0.06 | CB12: 0.01 | CC12: 0.12 | CD12: 0.23 | CE12: -0.01 | CF12: 0.07 | CG12: 0.29 | CH12: 0.02 | CI12: 0.12 | CJ12: 0.25 | CK12: 0.33 | CL12: 0.1 | CM12: -0.15 | CN12: -0.05 | CO12: 0.11 | CP12: 0.19 | CQ12: 0.22 | CR12: -0.06 | CS12: -0.03 | CT12: 0.06 | CU12: 0.07 | CV12: 0.06 | CW12: 0.24 | CX12: 0.17 | CY12: 0.24 | CZ12: 0.09 | DA12: 0.12 | DB12: -0.03 | DC12: 0.03 | DD12: 0.17 | DE12: -0.01 | DF12: 0.12 | DG12: 0.08 | DH12: -0.06 | DI12: 0.23 | DJ12: 0.26 | DK12: 0.18 | DL12: -0.03 | DM12: 0.28 | DN12: 0.27 | DO12: 0.04 | DP12: 0.25 | DQ12: -0.03 | DR12: -0.04 | DS12: 0.07 | DT12: -0.12 | DU12: 0 | DV12: 0.08 | DW12: 0.18 | DX12: -0.16 | DY12: 0.13 | DZ12: -0.01 | EA12: 0.1 | EB12: 0.09 | EC12: -0.07 | ED12: 0.11 | EE12: -0.14 | EF12: 0 | EG12: -0.16 | EH12: 0.14 | EI12: -0.23 | EJ12: 0.04 | EK12: -0.01 | EL12: -0.1 | EM12: 0 | EN12: 0.07 | EO12: 0.01
A13: JNJ * | B13: 0.32 | C13: 0.04 | D13: -0.04 | E13: 0.07 | F13: 0.46 | G13: -0.01 | H13: 0 | I13: 0.43 | J13: 1 | K13: 0.46 | L13: 0.1 | M13: 0.2 | N13: 0.41 | O13: 0.11 | P13: 0.41 | Q13: 0.01 | R13: 0.49 | S13: 0.15 | T13: 0.12 | U13: 0.1 | V13: -0.02 | W13: 0.16 | X13: 0.16 | Y13: 0.26 | Z13: 0.07 | AA13: 0.18 | AB13: 0.23 | AC13: -0.14 | AD13: 0.12 | AE13: -0.08 | AF13: 0 | AG13: 0.3 | AH13: 0.28 | AI13: 0.21 | AJ13: 0.02 | AK13: 0.08 | AL13: 0.21 | AM13: 0.07 | AN13: 0.29 | AO13: 0.56 | AP13: 0.12 | AQ13: 0.21 | AR13: 0.09 | AS13: 0.06 | AT13: 0.03 | AU13: 0.43 | AV13: 0.04 | AW13: 0.03 | AX13: 0.52 | AY13: 0.19 | AZ13: -0.05 | BA13: 0.2 | BB13: 0.01 | BC13: 0 | BD13: 0.04 | BE13: 0.55 | BF13: 0.04 | BG13: 0.19 | BH13: -0.03 | BI13: -0.01 | BJ13: -0.03 | BK13: -0.06 | BL13: 0.17 | BM13: 0.2 | BN13: 0.21 | BO13: 0.14 | BP13: -0.15 | BQ13: -0.03 | BR13: 0.09 | BS13: 0.12 | BT13: 0.2 | BU13: 0.03 | BV13: -0.01 | BW13: 0.15 | BX13: 0.5 | BY13: 0.08 | BZ13: 0.1 | CA13: 0.02 | CB13: 0.11 | CC13: 0.11 | CD13: 0.09 | CE13: 0.01 | CF13: 0.17 | CG13: 0.1 | CH13: 0 | CI13: 0.15 | CJ13: 0.21 | CK13: 0.22 | CL13: 0.11 | CM13: -0.13 | CN13: 0.04 | CO13: -0.06 | CP13: 0.12 | CQ13: 0.09 | CR13: -0.11 | CS13: 0.04 | CT13: 0 | CU13: 0.01 | CV13: -0.08 | CW13: 0.07 | CX13: 0.06 | CY13: 0.07 | CZ13: 0.04 | DA13: 0 | DB13: -0.09 | DC13: -0.06 | DD13: 0.01 | DE13: -0.04 | DF13: -0.01 | DG13: 0.1 | DH13: -0.15 | DI13: 0.04 | DJ13: 0.13 | DK13: 0.06 | DL13: 0 | DM13: 0.12 | DN13: 0.08 | DO13: -0.07 | DP13: 0.15 | DQ13: -0.02 | DR13: 0.01 | DS13: 0.01 | DT13: -0.23 | DU13: -0.12 | DV13: -0.04 | DW13: -0.01 | DX13: -0.13 | DY13: -0.12 | DZ13: 0 | EA13: 0.01 | EB13: -0.06 | EC13: 0.03 | ED13: -0.05 | EE13: -0.15 | EF13: 0.05 | EG13: -0.1 | EH13: 0.01 | EI13: -0.18 | EJ13: -0.04 | EK13: -0.08 | EL13: -0.08 | EM13: -0.09 | EN13: 0.11 | EO13: -0.04
A14: PG * | B14: 0.44 | C14: -0.07 | D14: -0.05 | E14: 0.09 | F14: 0.58 | G14: 0.01 | H14: 0.1 | I14: 0.56 | J14: 0.46 | K14: 1 | L14: 0.09 | M14: 0.31 | N14: 0.35 | O14: 0.18 | P14: 0.42 | Q14: -0.04 | R14: 0.6 | S14: 0.18 | T14: 0.13 | U14: 0.11 | V14: 0.15 | W14: 0.19 | X14: 0.14 | Y14: 0.3 | Z14: 0.14 | AA14: 0.21 | AB14: 0.32 | AC14: 0.05 | AD14: 0.15 | AE14: 0.04 | AF14: -0.05 | AG14: 0.36 | AH14: 0.37 | AI14: 0.08 | AJ14: 0.05 | AK14: 0.03 | AL14: 0.28 | AM14: 0.02 | AN14: 0.52 | AO14: 0.32 | AP14: 0.32 | AQ14: 0.08 | AR14: 0.14 | AS14: 0.01 | AT14: 0.17 | AU14: 0.43 | AV14: 0.09 | AW14: 0.03 | AX14: 0.39 | AY14: 0.27 | AZ14: 0.04 | BA14: 0.3 | BB14: 0 | BC14: 0.03 | BD14: 0.1 | BE14: 0.4 | BF14: 0.1 | BG14: 0.14 | BH14: 0.03 | BI14: 0.04 | BJ14: -0.05 | BK14: 0.02 | BL14: 0.2 | BM14: 0.34 | BN14: 0.23 | BO14: 0.21 | BP14: -0.04 | BQ14: 0.1 | BR14: 0.14 | BS14: -0.05 | BT14: 0.18 | BU14: -0.04 | BV14: 0.14 | BW14: 0.11 | BX14: 0.25 | BY14: 0.21 | BZ14: 0.17 | CA14: 0.15 | CB14: -0.02 | CC14: 0.15 | CD14: 0.12 | CE14: -0.04 | CF14: 0.02 | CG14: 0.18 | CH14: 0.02 | CI14: 0.01 | CJ14: 0.18 | CK14: 0.35 | CL14: 0.16 | CM14: -0.14 | CN14: -0.02 | CO14: 0.06 | CP14: 0.18 | CQ14: 0.19 | CR14: -0.04 | CS14: 0.05 | CT14: 0.09 | CU14: 0.05 | CV14: 0.09 | CW14: 0.13 | CX14: 0.12 | CY14: 0.28 | CZ14: 0.01 | DA14: 0.14 | DB14: -0.02 | DC14: 0.13 | DD14: 0.12 | DE14: -0.01 | DF14: -0.03 | DG14: 0.05 | DH14: -0.15 | DI14: 0.23 | DJ14: 0.27 | DK14: 0.2 | DL14: 0.02 | DM14: 0.33 | DN14: 0.19 | DO14: 0.02 | DP14: 0.29 | DQ14: -0.01 | DR14: -0.11 | DS14: 0.07 | DT14: -0.22 | DU14: -0.06 | DV14: -0.03 | DW14: 0.01 | DX14: -0.17 | DY14: 0.02 | DZ14: -0.09 | EA14: 0.11 | EB14: 0 | EC14: -0.13 | ED14: -0.06 | EE14: -0.07 | EF14: 0.12 | EG14: -0.08 | EH14: -0.01 | EI14: -0.24 | EJ14: 0.01 | EK14: -0.07 | EL14: -0.1 | EM14: -0.09 | EN14: 0.08 | EO14: 0.01
A15: WALMEX * | B15: 0.07 | C15: 0.31 | D15: 0.11 | E15: 0.31 | F15: 0.16 | G15: -0.02 | H15: 0.2 | I15: 0.14 | J15: 0.1 | K15: 0.09 | L15: 1 | M15: 0.17 | N15: 0.15 | O15: 0.37 | P15: 0.14 | Q15: 0.09 | R15: 0.1 | S15: 0.35 | T15: 0.03 | U15: 0.32 | V15: 0.29 | W15: 0.19 | X15: 0.05 | Y15: 0.17 | Z15: 0.3 | AA15: 0.31 | AB15: 0.12 | AC15: 0.12 | AD15: 0.22 | AE15: 0.25 | AF15: 0.29 | AG15: -0.02 | AH15: 0.01 | AI15: -0.02 | AJ15: 0.23 | AK15: 0.27 | AL15: 0.11 | AM15: 0.16 | AN15: 0.14 | AO15: 0.06 | AP15: 0.09 | AQ15: 0 | AR15: -0.01 | AS15: 0.2 | AT15: 0.06 | AU15: 0.1 | AV15: 0.3 | AW15: 0.16 | AX15: 0.15 | AY15: 0.28 | AZ15: 0.27 | BA15: 0.24 | BB15: 0.05 | BC15: 0.11 | BD15: 0.22 | BE15: 0.11 | BF15: 0.17 | BG15: 0.01 | BH15: 0.26 | BI15: 0.18 | BJ15: 0.01 | BK15: 0.2 | BL15: 0.09 | BM15: 0.13 | BN15: 0.1 | BO15: 0.09 | BP15: 0.18 | BQ15: 0.23 | BR15: 0.1 | BS15: -0.06 | BT15: 0.14 | BU15: 0.08 | BV15: 0.12 | BW15: 0.14 | BX15: -0.04 | BY15: 0.05 | BZ15: 0.15 | CA15: 0.18 | CB15: -0.08 | CC15: 0.01 | CD15: 0.15 | CE15: 0.06 | CF15: 0 | CG15: 0.11 | CH15: 0.17 | CI15: -0.02 | CJ15: -0.02 | CK15: 0.04 | CL15: 0.05 | CM15: 0.05 | CN15: 0.16 | CO15: 0.08 | CP15: 0.04 | CQ15: 0.13 | CR15: 0.13 | CS15: 0.08 | CT15: 0.1 | CU15: 0.11 | CV15: 0 | CW15: 0.15 | CX15: 0.07 | CY15: 0.08 | CZ15: 0.14 | DA15: 0.12 | DB15: 0.12 | DC15: 0.15 | DD15: 0.06 | DE15: 0.09 | DF15: 0.06 | DG15: 0.12 | DH15: 0.08 | DI15: 0.14 | DJ15: 0.08 | DK15: 0.15 | DL15: 0.15 | DM15: 0.15 | DN15: 0.21 | DO15: 0.15 | DP15: 0.1 | DQ15: 0.1 | DR15: 0.04 | DS15: 0.04 | DT15: 0.03 | DU15: -0.01 | DV15: 0.07 | DW15: -0.01 | DX15: 0.12 | DY15: 0.07 | DZ15: 0.1 | EA15: 0.11 | EB15: 0.04 | EC15: 0.03 | ED15: 0.08 | EE15: 0.11 | EF15: 0.07 | EG15: 0.2 | EH15: 0 | EI15: 0.08 | EJ15: 0.14 | EK15: 0.12 | EL15: 0.15 | EM15: 0.01 | EN15: 0 | EO15: 0.03
A16: AGNC * | B16: 0.26 | C16: 0.07 | D16: -0.07 | E16: 0.19 | F16: 0.29 | G16: 0.06 | H16: 0.18 | I16: 0.31 | J16: 0.2 | K16: 0.31 | L16: 0.17 | M16: 1 | N16: 0.3 | O16: 0.22 | P16: 0.21 | Q16: 0 | R16: 0.31 | S16: 0.12 | T16: 0.36 | U16: 0.29 | V16: 0.29 | W16: 0.17 | X16: 0.34 | Y16: 0.23 | Z16: 0.29 | AA16: 0.21 | AB16: 0.24 | AC16: 0.11 | AD16: 0.17 | AE16: 0.23 | AF16: 0.13 | AG16: 0.04 | AH16: 0.05 | AI16: -0.06 | AJ16: 0.03 | AK16: 0.24 | AL16: 0.27 | AM16: 0.19 | AN16: 0.54 | AO16: 0.15 | AP16: 0.27 | AQ16: -0.11 | AR16: 0.25 | AS16: 0.24 | AT16: 0.38 | AU16: 0.24 | AV16: 0.19 | AW16: 0.24 | AX16: 0.27 | AY16: 0.36 | AZ16: 0.26 | BA16: 0.37 | BB16: 0.33 | BC16: 0.15 | BD16: 0.18 | BE16: 0.29 | BF16: 0.26 | BG16: 0.33 | BH16: 0.16 | BI16: 0.13 | BJ16: -0.11 | BK16: 0.17 | BL16: 0.37 | BM16: 0.32 | BN16: 0.03 | BO16: 0.32 | BP16: 0.16 | BQ16: 0.32 | BR16: 0.35 | BS16: -0.09 | BT16: 0.35 | BU16: 0.13 | BV16: 0.32 | BW16: 0.27 | BX16: 0.14 | BY16: 0.4 | BZ16: 0.41 | CA16: 0.23 | CB16: -0.04 | CC16: 0.08 | CD16: 0.28 | CE16: 0.09 | CF16: -0.08 | CG16: 0.35 | CH16: 0.34 | CI16: -0.11 | CJ16: 0.09 | CK16: 0.31 | CL16: 0.33 | CM16: 0.22 | CN16: 0.04 | CO16: 0.1 | CP16: 0.15 | CQ16: 0.43 | CR16: 0.31 | CS16: 0.28 | CT16: 0.26 | CU16: 0.15 | CV16: 0.27 | CW16: 0.31 | CX16: 0.35 | CY16: 0.41 | CZ16: 0.1 | DA16: 0.17 | DB16: 0.3 | DC16: 0.32 | DD16: 0.31 | DE16: 0.35 | DF16: 0.11 | DG16: 0.37 | DH16: 0.18 | DI16: 0.41 | DJ16: 0.36 | DK16: 0.43 | DL16: 0.19 | DM16: 0.45 | DN16: 0.33 | DO16: 0.26 | DP16: 0.4 | DQ16: 0.26 | DR16: 0.23 | DS16: 0.13 | DT16: 0.14 | DU16: 0.3 | DV16: 0.16 | DW16: 0.23 | DX16: 0.25 | DY16: 0.37 | DZ16: 0.1 | EA16: 0.21 | EB16: 0.37 | EC16: 0.04 | ED16: 0.29 | EE16: 0.22 | EF16: 0.25 | EG16: 0.23 | EH16: 0.14 | EI16: 0.19 | EJ16: 0.33 | EK16: 0.27 | EL16: 0.31 | EM16: 0.18 | EN16: 0.17 | EO16: 0.09
... A148: BYND * | B148: -0.02 | C148: 0.04 | D148: -0.09 | E148: 0.02 | F148: 0.11 | G148: 0.06 | H148: 0.03 | I148: 0.01 | J148: -0.04 | K148: 0.01 | L148: 0.03 | M148: 0.09 | N148: 0.03 | O148: 0.01 | P148: 0.01 | Q148: 0.01 | R148: 0.02 | S148: -0.07 | T148: 0.04 | U148: 0.04 | V148: -0.01 | W148: -0.04 | X148: 0.06 | Y148: 0.03 | Z148: 0.03 | AA148: -0.02 | AB148: 0.04 | AC148: 0 | AD148: -0.03 | AE148: 0.03 | AF148: -0.05 | AG148: -0.09 | AH148: -0.04 | AI148: -0.02 | AJ148: 0.01 | AK148: 0.07 | AL148: 0.12 | AM148: 0.05 | AN148: 0.1 | AO148: 0.02 | AP148: 0.17 | AQ148: -0.01 | AR148: 0.06 | AS148: 0.11 | AT148: 0.12 | AU148: -0.02 | AV148: 0.05 | AW148: 0.01 | AX148: 0.07 | AY148: 0.03 | AZ148: -0.06 | BA148: 0.1 | BB148: 0.09 | BC148: -0.06 | BD148: 0.12 | BE148: 0.07 | BF148: 0.1 | BG148: 0.14 | BH148: 0.05 | BI148: -0.07 | BJ148: -0.03 | BK148: -0.12 | BL148: 0.11 | BM148: 0.16 | BN148: 0.04 | BO148: 0.06 | BP148: 0.08 | BQ148: -0.04 | BR148: 0.11 | BS148: 0.01 | BT148: 0.11 | BU148: 0.05 | BV148: 0.15 | BW148: 0.12 | BX148: 0.02 | BY148: 0.32 | BZ148: 0.12 | CA148: -0.03 | CB148: -0.07 | CC148: 0.08 | CD148: 0.09 | CE148: 0.07 | CF148: -0.03 | CG148: 0.13 | CH148: 0.08 | CI148: -0.02 | CJ148: 0.14 | CK148: 0.12 | CL148: 0.14 | CM148: 0.07 | CN148: 0.03 | CO148: 0.02 | CP148: 0.06 | CQ148: 0.13 | CR148: 0.1 | CS148: 0.07 | CT148: 0.16 | CU148: 0.09 | CV148: 0.06 | CW148: 0.15 | CX148: 0.1 | CY148: 0.1 | CZ148: 0.08 | DA148: 0.11 | DB148: 0.12 | DC148: 0.06 | DD148: 0.17 | DE148: 0.12 | DF148: 0.15 | DG148: 0.02 | DH148: 0.04 | DI148: 0.1 | DJ148: 0.15 | DK148: 0.08 | DL148: 0.01 | DM148: 0.16 | DN148: 0.14 | DO148: 0.09 | DP148: 0.14 | DQ148: 0.02 | DR148: 0.06 | DS148: 0.13 | DT148: 0.11 | DU148: 0.21 | DV148: 0.11 | DW148: 0.08 | DX148: 0.08 | DY148: 0.23 | DZ148: 0.09 | EA148: 0.09 | EB148: 0.25 | EC148: 0.01 | ED148: 0.09 | EE148: 0.11 | EF148: 0.03 | EG148: 0.07 | EH148: 0.05 | EI148: 0.04 | EJ148: 0.06 | EK148: 0.15 | EL148: 0.11 | EM148: 0.04 | EN148: 0.08 | EO148: 1

Sheet Covarianza
A1: Hoja de apoyo (no tocar): varianza del portafolio = w' · Σ · w
A2: Varianza anual del portafolio | B2: =SUMPRODUCT(EP6:EP149,EQ6:EQ149) -> 0.4223723
B4: BRKB * | C4: SIGMAF A | D4: LIVEPOL C-1 | E4: GRUMA B | F4: KO * | G4: FIBRAMQ 12 | H4: VESTA * | I4: MCD * | J4: JNJ * | K4: PG * | L4: WALMEX * | M4: AGNC * | N4: PFE * | O4: AC * | P4: COST * | Q4: ACTINVR B | R4: PEP * | S4: CHDRAUI B | T4: BAC * | U4: GFINBUR O | V4: FUNO 11 | W4: FEMSA UBD | X4: JPM * | Y4: V * | Z4: KIMBER A | AA4: KOF UBL | AB4: MA * | AC4: FIBRAPL 14 | AD4: AMX B | AE4: ASUR B | AF4: PINFRA * | AG4: T * | AH4: VZ * | AI4: CVX * | AJ4: ALSEA * | AK4: GFNORTE O | AL4: AAPL * | AM4: BOLSA A | AN4: HD * | AO4: ABBV * | AP4: DIS * | AQ4: XOM * | AR4: WFC * | AS4: BBAJIO O | AT4: AXP * | AU4: WMT * | AV4: BIMBO A | AW4: GCC * | AX4: BMY * | AY4: SBUX * | AZ4: OMA B | BA4: FDX * | BB4: C * | BC4: Q * | BD4: R A | BE4: MRK * | BF4: MEGA CPO | BG4: TMO * | BH4: LAB B | BI4: CUERVO * | BJ4: SITES1 A-1 | BK4: GAP B | BL4: TX * | BM4: TGT * | BN4: CVS * | BO4: GOOGL * | BP4: MSFT * | BQ4: CEMEX CPO | BR4: WYNN * | BS4: FANG * | BT4: GE * | BU4: GENTERA * | BV4: AMZN * | BW4: LVS * | BX4: LLY * | BY4: GM * | BZ4: BA * | CA4: GCARSO A1 | CB4: ALPEK A | CC4: UNH * | CD4: UBER * | CE4: CSCO * | CF4: DVN * | CG4: ABNB * | CH4: GMEXICO B | CI4: OXY1 * | CJ4: NFLX * | CK4: NKE * | CL4: F * | CM4: NVDA * | CN4: ORBIA * | CO4: TLEVISA CPO | CP4: GME * | CQ4: DAL * | CR4: TSM N | CS4: CAT * | CT4: ROKU * | CU4: BABA N | CV4: META * | CW4: MELI N | CX4: NU N | CY4: LUV * | CZ4: ZM * | DA4: PYPL * | DB4: TSLA * | DC4: VOLAR A | DD4: XYZ * | DE4: FCX * | DF4: CRM * | DG4: B N | DH4: AVGO * | DI4: AAL * | DJ4: RCL * | DK4: UAL * | DL4: PE&OLES * | DM4: CCL1 N | DN4: ETSY * | DO4: QCOM * | DP4: NCLH N | DQ4: FSLR * | DR4: AA1 * | DS4: PINS * | DT4: ORCL * | DU4: SOFI * | DV4: PLTR * | DW4: SHOP N | DX4: AMAT * | DY4: AFRM * | DZ4: TWLO * | EA4: NVAX * | EB4: UPST * | EC4: MFRISCO A-1 | ED4: RIVN * | EE4: AMD * | EF4: CLF * | EG4: INTC * | EH4: FUBO * | EI4: MU * | EJ4: LCID * | EK4: MARA * | EL4: RIOT * | EM4: SPCE * | EN4: MRNA * | EO4: BYND * | EP4: Σw | EQ4: w
A5: w (peso) | B5: =SUMIF('Mi portafolio'!$A$8:$A$19,B$4,'Mi portafolio'!$B$8:$B$19) -> 0 | C5: =SUMIF('Mi portafolio'!$A$8:$A$19,C$4,'Mi portafolio'!$B$8:$B$19) -> 0 | D5: =SUMIF('Mi portafolio'!$A$8:$A$19,D$4,'Mi portafolio'!$B$8:$B$19) -> 0 | E5: =SUMIF('Mi portafolio'!$A$8:$A$19,E$4,'Mi portafolio'!$B$8:$B$19) -> 0 | F5: =SUMIF('Mi portafolio'!$A$8:$A$19,F$4,'Mi portafolio'!$B$8:$B$19) -> 0 | G5: =SUMIF('Mi portafolio'!$A$8:$A$19,G$4,'Mi portafolio'!$B$8:$B$19) -> 0 | H5: =SUMIF('Mi portafolio'!$A$8:$A$19,H$4,'Mi portafolio'!$B$8:$B$19) -> 0 | I5: =SUMIF('Mi portafolio'!$A$8:$A$19,I$4,'Mi portafolio'!$B$8:$B$19) -> 0 | ... EO5: =SUMIF('Mi portafolio'!$A$8:$A$19,EO$4,'Mi portafolio'!$B$8:$B$19) -> 0
A6: BRKB * | B6: 0.026774189 | C6: -0.00088367569 | D6: -0.0033180869 | E6: 0.0023116581 | F6: 0.014517632 | G6: -0.0034337772 | H6: -0.00040132723 | I6: 0.016157944 | J6: 0.010795809 | K6: 0.015017873 | L6: 0.0022871874 | M6: 0.0091731123 | N6: 0.011437839 | O6: 0.0052198676 | P6: 0.013803191 | Q6: 0.001053541 | R6: 0.013524598 | S6: 0.00037168562 | T6: 0.009064132 | U6: 0.0029754695 | V6: 0.0013361836 | W6: 0.0010387093 | X6: 0.01261985 | Y6: 0.017569797 | Z6: 0.002080449 | AA6: 0.0021923673 | AB6: 0.019271087 | AC6: 0.0017084426 | AD6: 0.0029656436 | AE6: 0.00023380525 | AF6: -0.0050386703 | AG6: 0.011468276 | AH6: 0.013482833 | AI6: 0.007707005 | AJ6: 0.0018252091 | AK6: -0.00089921668 | AL6: 0.012294531 | AM6: 0.001276842 | AN6: 0.016045157 | AO6: 0.011106823 | AP6: 0.010805379 | AQ6: 0.0058575335 | AR6: 0.010344642 | AS6: -0.0054787023 | AT6: 0.012599219 | AU6: 0.013843962 | AV6: 0.00381116 | AW6: 3.8698315e-05 | AX6: 0.016010993 | AY6: 0.011899668 | AZ6: 0.00078171782 | BA6: 0.0091305065 | BB6: 0.0077153487 | BC6: 0.0053842901 | BD6: 0.00041621772 | BE6: 0.014350757 | BF6: 0.0021442495 | BG6: 0.010253998 | BH6: 0.0025216197 | BI6: 0.0046883373 | BJ6: -0.0011281494 | BK6: 0.00078654663 | BL6: 0.0047766057 | BM6: 0.0092512754 | BN6: 0.014713886 | BO6: 0.0078230093 | BP6: 0.0066320879 | BQ6: -0.0025214978 | BR6: 0.011729742 | BS6: 0.0017739665 | BT6: 0.010472435 | BU6: -0.0039311534 | BV6: 0.0078437443 | BW6: 0.0094185362 | BX6: 0.015840685 | BY6: 0.0092361697 | BZ6: 0.012415574 | CA6: 0.0028859244 | CB6: 0.0024958822 | CC6: 0.012333823 | CD6: 0.010628101 | CE6: 0.0039629702 | CF6: 0.00492087 | CG6: 0.014819813 | CH6: -0.0042013941 | CI6: 0.0062203171 | CJ6: 0.016468235 | CK6: 0.019509724 | CL6: 0.0067246527 | CM6: -0.0085064575 | CN6: -0.0016354139 | CO6: 0.0011984239 | CP6: 0.012021871 | CQ6: 0.017603317 | CR6: -0.0035120836 | CS6: 0.00037904845 | CT6: 0.006966562 | CU6: -0.00027967446 | CV6: 0.0048031355 | CW6: 0.0074647387 | CX6: 0.004992432 | CY6: 0.015778419 | CZ6: 0.0073253784 | DA6: 0.0086086866 | DB6: 0.00025694833 | DC6: -0.0018623399 | DD6: 0.010909702 | DE6: -0.0063427544 | DF6: 0.013285689 | DG6: 0.0017722877 | DH6: -0.0031154763 | DI6: 0.021343965 | DJ6: 0.018031341 | DK6: 0.018504619 | DL6: -0.0088418254 | DM6: 0.02231716 | DN6: 0.016724028 | DO6: 0.0060433918 | DP6: 0.02376296 | DQ6: 0.0012164927 | DR6: -0.004367197 | DS6: 0.0099956626 | DT6: -0.011436909 | DU6: -0.00056299358 | DV6: -0.0002589484 | DW6: 0.010192974 | DX6: -0.014233653 | DY6: 0.015076085 | DZ6: 0.0019944029 | EA6: 0.00026379234 | EB6: 0.0058232922 | EC6: -0.011841417 | ED6: 0.0063362991 | EE6: -0.0093110749 | EF6: 0.0065326202 | EG6: -0.008367121 | EH6: 0.0088916082 | EI6: -0.025618726 | EJ6: 0.0093091877 | EK6: -0.0035550981 | EL6: -0.016033413 | EM6: -0.013082452 | EN6: 0.00074530973 | EO6: -0.0061273357 | EP6: =SUMPRODUCT(B6:EO6,$B$5:$EO$5) -> -0.016379714 | EQ6: =SUMIF('Mi portafolio'!$A$8:$A$19,$A6,'Mi portafolio'!$B$8:$B$19) -> 0
A7: SIGMAF A | B7: -0.00088367569 | C7: 0.029379065 | D7: 0.0026495912 | E7: 0.0030057902 | F7: 0.00067642078 | G7: 0.00053229927 | H7: 0.0049422947 | I7: 0.0028391596 | J7: 0.0015465994 | K7: -0.0024906799 | L7: 0.010736609 | M7: 0.0026619754 | N7: 3.5988682e-05 | O7: 0.0065253077 | P7: 0.00283096 | Q7: -4.0569949e-05 | R7: 0.0011651773 | S7: 0.0025134092 | T7: 0.00014275113 | U7: 0.0044800327 | V7: 0.0058116797 | W7: 0.005513412 | X7: 0.0013344188 | Y7: 0.0046954245 | Z7: 0.0080303186 | AA7: 0.0036920801 | AB7: 0.0018735179 | AC7: 0.0018209528 | AD7: 0.0081690384 | AE7: 0.0084371544 | AF7: 0.0095502318 | AG7: -0.00060832665 | AH7: 4.795149e-05 | AI7: -0.00047228163 | AJ7: 0.0044477396 | AK7: 0.0094701046 | AL7: -7.4630704e-05 | AM7: 0.0034747568 | AN7: 0.00098494409 | AO7: 0.0016575647 | AP7: -0.0023810421 | AQ7: 0.00091482191 | AR7: -0.00012161413 | AS7: 0.0053903592 | AT7: 0.0011376644 | AU7: 0.0025684448 | AV7: 0.013280283 | AW7: 0.0091843957 | AX7: -0.0002068908 | AY7: 0.0061870271 | AZ7: 0.0043594103 | BA7: 0.003102272 | BB7: -0.0032932671 | BC7: 0.00084174848 | BD7: 0.0080978459 | BE7: 0.0038045883 | BF7: -0.00031135308 | BG7: 0.00079628346 | BH7: 0.0026586431 | BI7: -0.00077349385 | BJ7: 0.00082630145 | BK7: 0.0030498035 | BL7: -4.9759799e-05 | BM7: 0.0021436366 | BN7: 0.0018080974 | BO7: -0.00087483395 | BP7: -0.0034330663 | BQ7: 0.010794307 | BR7: -0.0035318448 | BS7: -0.0014778437 | BT7: 0.0024040846 | BU7: 0.0035045606 | BV7: -0.0012456841 | BW7: -0.002264544 | BX7: -0.0041435657 | BY7: -0.0012217549 | BZ7: 0.0070418922 | CA7: 0.0087279893 | CB7: 0.005627292 | CC7: -0.0013601516 | CD7: -0.0023240797 | CE7: -0.0017994661 | CF7: -0.0025248731 | CG7: -0.00087955851 | CH7: 0.0076586727 | CI7: -0.0031599413 | CJ7: -0.00050085594 | CK7: -0.0040566013 | CL7: 0.00066650947 | CM7: -0.0042161291 | CN7: 0.0094137363 | CO7: 0.0044010719 | CP7: 0.00098513976 | CQ7: -0.0015221389 | CR7: -0.0038493933 | CS7: 0.0033407581 | CT7: 0.0020476721 | CU7: 0.00065628071 | CV7: -0.0044972026 | CW7: 0.0016385452 | CX7: 0.0014810125 | CY7: -6.5414213e-05 | CZ7: -0.009998605 | DA7: -0.00056283765 | DB7: 0.0041845304 | DC7: 0.0032360418 | DD7: -0.0028743487 | DE7: 0.0055435915 | DF7: -0.0069027783 | DG7: 0.0041394525 | DH7: 0.0045739089 | DI7: -0.0022601182 | DJ7: -0.0044545395 | DK7: 0.00050786269 | DL7: 0.014200741 | DM7: -0.00080264664 | DN7: 0.0083261668 | DO7: 0.01449213 | DP7: -0.001494176 | DQ7: 0.0017354027 | DR7: 0.0051033473 | DS7: -0.0062114529 | DT7: -0.0037595171 | DU7: -0.0051078068 | DV7: -0.0057341381 | DW7: -0.011004536 | DX7: 0.003706888 | DY7: 0.00086832062 | DZ7: -0.011325388 | EA7: 0.0019410306 | EB7: -0.0089498035 | EC7: 0.0037745488 | ED7: 0.015221717 | EE7: 0.0036159882 | EF7: 0.012700021 | EG7: 0.0099872812 | EH7: -0.00097757776 | EI7: 0.0032185705 | EJ7: -0.002894679 | EK7: 0.0056337094 | EL7: 0.0031516127 | EM7: -0.011041515 | EN7: 0.001770274 | EO7: 0.014401478 | EP7: =SUMPRODUCT(B7:EO7,$B$5:$EO$5) -> 0.0063789233 | EQ7: =SUMIF('Mi portafolio'!$A$8:$A$19,$A7,'Mi portafolio'!$B$8:$B$19) -> 0
A8: LIVEPOL C-1 | B8: -0.0033180869 | C8: 0.0026495912 | D8: 0.037011143 | E8: 0.0046646452 | F8: -0.0033320349 | G8: 0.0045931539 | H8: 0.005856973 | I8: -0.00077785347 | J8: -0.0014884529 | K8: -0.0021672209 | L8: 0.0041034117 | M8: -0.0028327669 | N8: 0.0073488987 | O8: 0.0013902188 | P8: -1.687043e-05 | Q8: 0.0008143803 | R8: -0.0067224398 | S8: 0.0046130504 | T8: 0.002466861 | U8: 0.0052226311 | V8: 0.001464739 | W8: -0.0015755966 | X8: 0.00056852267 | Y8: -4.9253717e-05 | Z8: 0.0040912515 | AA8: 0.0040998651 | AB8: 0.0014111228 | AC8: 0.0037490689 | AD8: 0.00084812138 | AE8: 0.0087644809 | AF8: 0.008129958 | AG8: -0.00093715438 | AH8: -0.0014310136 | AI8: -0.0051088771 | AJ8: 0.010220964 | AK8: 0.0011200068 | AL8: 0.0020954945 | AM8: 0.0044966094 | AN8: -0.0023641247 | AO8: 0.0010619007 | AP8: 0.0014576412 | AQ8: -0.0049420719 | AR8: 0.0031022175 | AS8: 0.0064330828 | AT8: 0.00094299123 | AU8: -0.0020425683 | AV8: 0.0050982041 | AW8: 0.0022730151 | AX8: 0.0051243089 | AY8: -0.0014955839 | AZ8: 0.011589075 | BA8: -0.0015306201 | BB8: 0.0026442308 | BC8: 0.0032293238 | BD8: 0.0090750124 | BE8: -0.0010971724 | BF8: 0.0077821939 | BG8: 0.0021033379 | BH8: 0.0063982501 | BI8: 0.0067578897 | BJ8: 0.004258253 | BK8: 0.01330508 | BL8: -0.0032796005 | BM8: 0.0029661152 | BN8: -0.0070730078 | BO8: 0.0049512207 | BP8: 0.004999316 | BQ8: 0.0064127962 | BR8: 0.0023746478 | BS8: -0.0038508675 | BT8: 0.0031810265 | BU8: 0.0065650349 | BV8: 0.0022521667 | BW8: 0.0017838833 | BX8: 0.005376591 | BY8: -0.0032192585 | BZ8: -0.00071547753 | CA8: 0.010086731 | CB8: -0.0042677359 | CC8: -0.0005965715 | CD8: 0.0029004361 | CE8: 0.0030661343 | CF8: -0.0027752035 | CG8: 0.0072689351 | CH8: 0.0027278457 | CI8: -0.0048598766 | CJ8: 0.0036664227 | CK8: 0.0014150649 | CL8: -0.00011820737 | CM8: 0.0039902725 | CN8: 0.012359786 | CO8: -3.1833351e-06 | CP8: 0.0034093256 | CQ8: 0.0033160668 | CR8: -0.00071333132 | CS8: 0.0019916339 | CT8: 0.0053002975 | CU8: 0.0060608667 | CV8: 0.0013052858 | CW8: -0.0008755021 | CX8: -0.00027167788 | CY8: 0.0015777879 | CZ8: 0.0096750456 | DA8: 0.013138157 | DB8: 0.0081496049 | DC8: 0.016411554 | DD8: 0.016458455 | DE8: 0.0035090606 | DF8: 0.0067070227 | DG8: 0.0068972139 | DH8: 0.0038800617 | DI8: 0.0025132463 | DJ8: 3.3622323e-06 | DK8: 0.002113121 | DL8: 0.018944368 | DM8: 0.0018781943 | DN8: -0.0059296283 | DO8: 0.007216107 | DP8: 0.001786024 | DQ8: -0.00079632882 | DR8: -0.001692386 | DS8: 0.0039364978 | DT8: 0.0038725825 | DU8: 0.011850069 | DV8: 0.0065982825 | DW8: 0.0080247809 | DX8: 0.0071761369 | DY8: 0.0034416174 | DZ8: 0.014380732 | EA8: 0.0051543284 | EB8: 0.0060738669 | EC8: -0.00033946066 | ED8: 0.013613297 | EE8: 0.0054005658 | EF8: 0.010966195 | EG8: -0.0012516327 | EH8: 0.0086147702 | EI8: 0.0088611822 | EJ8: 0.0087913406 | EK8: 0.0064051081 | EL8: 0.014815514 | EM8: 0.0051018385 | EN8: -0.0037271396 | EO8: -0.039246885 | EP8: =SUMPRODUCT(B8:EO8,$B$5:$EO$5) -> 0.0043298189 | EQ8: =SUMIF('Mi portafolio'!$A$8:$A$19,$A8,'Mi portafolio'!$B$8:$B$19) -> 0
A9: GRUMA B | B9: 0.0023116581 | C9: 0.0030057902 | D9: 0.0046646452 | E9: 0.037758853 | F9: 0.0052921937 | G9: 0.0017859385 | H9: 0.0088728153 | I9: 0.0063919888 | J9: 0.0026183734 | K9: 0.0035083972 | L9: 0.012115927 | M9: 0.0081499975 | N9: 0.0078314724 | O9: 0.015080374 | P9: 0.0067314507 | Q9: 0.0032941704 | R9: 0.0040374844 | S9: 0.010542794 | T9: 0.005908475 | U9: 0.01378181 | V9: 0.013864404 | W9: 0.012094159 | X9: 0.0064903645 | Y9: 0.0021818009 | Z9: 0.0082415926 | AA9: 0.0092749691 | AB9: 0.0027863392 | AC9: 0.014400627 | AD9: 0.011401122 | AE9: 0.0091004738 | AF9: 0.016316839 | AG9: 0.003958082 | AH9: 0.004442488 | AI9: 0.0032846366 | AJ9: 0.004945255 | AK9: 0.01514142 | AL9: 0.0072209112 | AM9: 0.0082509317 | AN9: 0.0064718405 | AO9: 0.0054729295 | AP9: 0.0070695065 | AQ9: 0.0056748938 | AR9: 0.0039912139 | AS9: 0.0098093781 | AT9: 0.0068608629 | AU9: 0.0048354081 | AV9: 0.024268539 | AW9: 0.0090855904 | AX9: 0.0074884623 | AY9: 0.0059553718 | AZ9: 0.013505413 | BA9: 0.010186182 | BB9: 0.007077388 | BC9: 0.012634827 | BD9: 0.012818978 | BE9: 0.0054055364 | BF9: 0.018906719 | BG9: -0.00038426135 | BH9: 0.01278855 | BI9: 0.012228643 | BJ9: 0.0034659125 | BK9: 0.011343903 | BL9: 0.0065424047 | BM9: 0.013807539 | BN9: 0.0051297722 | BO9: 0.0050428388 | BP9: 0.0050123713 | BQ9: 0.0093970513 | BR9: 0.004736269 | BS9: 0.0020711104 | BT9: 0.0037615739 | BU9: 0.011390334 | BV9: -0.0020030329 | BW9: 0.0083747452 | BX9: 0.0018646094 | BY9: 0.0038974032 | BZ9: 0.008784074 | CA9: 0.017642992 | CB9: 0.0010891463 | CC9: 0.004346252 | CD9: 0.0038098136 | CE9: 0.00088844941 | CF9: 0.0021986905 | CG9: 0.0024845305 | CH9: 0.013368792 | CI9: -0.0037202455 | CJ9: 0.0046096962 | CK9: 0.0087560849 | CL9: -0.00025831631 | CM9: -0.0019709363 | CN9: 0.0097784337 | CO9: 0.010450206 | CP9: 0.0025523874 | CQ9: 0.013356193 | CR9: 0.0060817892 | CS9: 0.0062996968 | CT9: 0.012251995 | CU9: 0.00087037124 | CV9: -0.00035136202 | CW9: 0.0080912914 | CX9: 0.0055933915 | CY9: 0.016389494 | CZ9: 0.0050992199 | DA9: -0.0011850905 | DB9: 0.016658799 | DC9: 0.015675213 | DD9: 0.011454664 | DE9: 0.013292084 | DF9: 0.0035046703 | DG9: 0.0080848871 | DH9: 0.0088590352 | DI9: 0.018657839 | DJ9: 0.0074657365 | DK9: 0.012774729 | DL9: 0.010214174 | DM9: 0.012197802 | DN9: -0.0016414979 | DO9: 0.015396883 | DP9: 0.0061829084 | DQ9: 0.0090215756 | DR9: 0.012716766 | DS9: -0.001071283 | DT9: 0.0050998068 | DU9: 0.014746921 | DV9: 0.010925916 | DW9: 0.002181295 | DX9: 0.0059984074 | DY9: 0.010667563 | DZ9: 0.0041139476 | EA9: 0.0060488952 | EB9: 0.014963522 | EC9: 0.011552637 | ED9: 0.02587023 | EE9: 0.010398793 | EF9: 0.0014695784 | EG9: 0.0090844726 | EH9: -0.0023803902 | EI9: -0.0025661857 | EJ9: 0.027439858 | EK9: 0.011076308 | EL9: 0.016396319 | EM9: 0.0097873905 | EN9: 0.0066822237 | EO9: 0.0070333762 | EP9: =SUMPRODUCT(B9:EO9,$B$5:$EO$5) -> 0.0036328166 | EQ9: =SUMIF('Mi portafolio'!$A$8:$A$19,$A9,'Mi portafolio'!$B$8:$B$19) -> 0
A10: KO * | B10: 0.014517632 | C10: 0.00067642078 | D10: -0.0033320349 | E10: 0.0052921937 | F10: 0.041489206 | G10: -0.00086579789 | H10: 0.0034948462 | I10: 0.024511115 | J10: 0.019396531 | K10: 0.024753308 | L10: 0.0064950374 | M10: 0.012967485 | N10: 0.01321516 | O10: 0.0036014576 | P10: 0.021369524 | Q10: -0.0045536746 | R10: 0.029039568 | S10: 0.0049564535 | T10: 0.0022963115 | U10: 0.0032784543 | V10: 0.0023225651 | W10: 0.0061299468 | X10: 0.0016593395 | Y10: 0.014842322 | Z10: 0.0049925445 | AA10: 0.012770809 | AB10: 0.015953149 | AC10: -0.00092939072 | AD10: 0.0068938967 | AE10: -0.003420734 | AF10: -0.003938033 | AG10: 0.020971139 | AH10: 0.022113923 | AI10: 0.01247388 | AJ10: -0.0010345811 | AK10: -0.0015874672 | AL10: 0.014081961 | AM10: -0.00040024931 | AN10: 0.021608282 | AO10: 0.02105414 | AP10: 0.016030004 | AQ10: 0.01418786 | AR10: 0.0033174935 | AS10: 0.00047320297 | AT10: 0.0042231842 | AU10: 0.022953404 | AV10: 0.0049941369 | AW10: -0.0017656756 | AX10: 0.020934587 | AY10: 0.018739119 | AZ10: -0.0019185666 | BA10: 0.012558872 | BB10: -0.0044744583 | BC10: 0.0046512905 | BD10: 0.00060489722 | BE10: 0.025000547 | BF10: 0.0020357657 | BG10: 0.0063875638 | BH10: -0.00013319863 | BI10: -0.0043413348 | BJ10: -0.005213968 | BK10: -0.003790069 | BL10: 0.0070662463 | BM10: 0.023643336 | BN10: 0.013573854 | BO10: 0.0051798107 | BP10: -0.0010279268 | BQ10: -0.0025835267 | BR10: 0.0095470167 | BS10: 0.010373044 | BT10: 0.0056576273 | BU10: -0.0041550581 | BV10: 0.0015573801 | BW10: 0.011372237 | BX10: 0.015460683 | BY10: 0.018424522 | BZ10: 0.0059991786 | CA10: 0.0035882702 | CB10: 0.0049700297 | CC10: 0.0054772881 | CD10: 0.012105342 | CE10: -0.005704693 | CF10: 0.017202103 | CG10: 0.012740222 | CH10: -0.0049476228 | CI10: 0.014396484 | CJ10: 0.022964982 | CK10: 0.019631702 | CL10: 0.010818787 | CM10: -0.014181022 | CN10: -0.0057434263 | CO10: -0.00066617085 | CP10: 0.010067104 | CQ10: 0.0084783266 | CR10: -0.010580406 | CS10: -0.01127649 | CT10: -0.00099552776 | CU10: -0.00020826631 | CV10: -0.0049896471 | CW10: 0.008041894 | CX10: 0.0046603655 | CY10: 0.012272968 | CZ10: 0.0014590124 | DA10: 0.0060807985 | DB10: -0.0073922379 | DC10: -0.0085589707 | DD10: 0.0027273832 | DE10: -0.010195632 | DF10: 0.0074352014 | DG10: -0.0053888647 | DH10: -0.0151725 | DI10: 0.010354578 | DJ10: 0.014716844 | DK10: 0.0067988696 | DL10: -0.010416428 | DM10: 0.016523854 | DN10: 0.01735277 | DO10: -0.012931235 | DP10: 0.015249367 | DQ10: -0.011597011 | DR10: -0.0092595301 | DS10: 0.0047379652 | DT10: -0.029515293 | DU10: -0.013865823 | DV10: -0.0096546454 | DW10: -0.0046043986 | DX10: -0.02318533 | DY10: 0.00055281822 | DZ10: -0.0064909182 | EA10: 0.0019174893 | EB10: -0.0067294659 | EC10: -0.016254337 | ED10: -0.0029857049 | EE10: -0.024418761 | EF10: -0.0086567295 | EG10: -0.014604808 | EH10: 0.0094584855 | EI10: -0.033485271 | EJ10: 0.0047200677 | EK10: -0.0081132292 | EL10: -0.029223499 | EM10: -0.020356716 | EN10: 0.035620633 | EO10: 0.049367655 | EP10: =SUMPRODUCT(B10:EO10,$B$5:$EO$5) -> -0.022908379 | EQ10: =SUMIF('Mi portafolio'!$A$8:$A$19,$A10,'Mi portafolio'!$B$8:$B$19) -> 0
A11: FIBRAMQ 12 | B11: -0.0034337772 | C11: 0.00053229927 | D11: 0.0045931539 | E11: 0.0017859385 | F11: -0.00086579789 | G11: 0.041613589 | H11: 0.0075106735 | I11: 0.00080636617 | J11: -0.00057981806 | K11: 0.00050478755 | L11: -0.0006514633 | M11: 0.00251802 | N11: 0.0022467319 | O11: 0.005006427 | P11: -0.0042957994 | Q11: 0.0021135367 | R11: -0.0009899849 | S11: -0.002083877 | T11: 0.00095387401 | U11: 0.0033759045 | V11: 0.0062501408 | W11: 0.0021202297 | X11: -0.0012445821 | Y11: -0.0020710555 | Z11: 0.010086151 | AA11: 0.0039628523 | AB11: -0.00019349075 | AC11: 0.0076531754 | AD11: 0.0016117733 | AE11: 0.010838518 | AF11: 0.0091764055 | AG11: -0.0042424565 | AH11: -0.004300452 | AI11: -0.0029368681 | AJ11: 0.0041697806 | AK11: 0.0067199325 | AL11: -0.0030923813 | AM11: 0.0087290259 | AN11: -0.0012089459 | AO11: 0.0015550435 | AP11: 0.0027276756 | AQ11: -0.00053406157 | AR11: -0.00010977844 | AS11: 0.0082666626 | AT11: -0.0010296067 | AU11: -0.00094675203 | AV11: 0.002842969 | AW11: 0.0061019201 | AX11: 0.0027585297 | AY11: 0.001960955 | AZ11: 0.0066079734 | BA11: 0.00069443499 | BB11: 0.0050479665 | BC11: 0.0015029633 | BD11: 0.0091739876 | BE11: -0.0016569435 | BF11: 0.013228196 | BG11: -0.0012086804 | BH11: 0.0018310593 | BI11: 0.0061156625 | BJ11: 0.0028745157 | BK11: 0.010439749 | BL11: 0.0051718806 | BM11: -0.0046675525 | BN11: 0.0014353991 | BO11: 0.0047580201 | BP11: -0.0017651865 | BQ11: 0.0059737724 | BR11: 0.00032797691 | BS11: 0.0001467598 | BT11: 0.00086995568 | BU11: -0.00072173387 | BV11: 0.0012244597 | BW11: 0.0056734616 | BX11: -0.00074480719 | BY11: 0.002469608 | BZ11: -0.0062121044 | CA11: 0.0083391039 | CB11: -0.0015155508 | CC11: 0.0028193526 | CD11: 0.0016437551 | CE11: -0.00066374015 | CF11: 0.0013822093 | CG11: 0.00480691 | CH11: 0.012530756 | CI11: -0.0012663674 | CJ11: 0.0061538198 | CK11: -0.0071247788 | CL11: 0.0054659141 | CM11: -0.00090677742 | CN11: 0.007201696 | CO11: -0.003784799 | CP11: 0.0043431141 | CQ11: -0.0041225804 | CR11: -0.00095317127 | CS11: -0.00010474495 | CT11: 0.012005892 | CU11: -0.0023072872 | CV11: 0.0011761464 | CW11: -0.0027457931 | CX11: 0.0068387574 | CY11: 0.00017129681 | CZ11: -0.0099086449 | DA11: -0.0078665332 | DB11: 0.0073986764 | DC11: 0.0092543986 | DD11: 0.0051641518 | DE11: 0.0022902489 | DF11: 0.00054563934 | DG11: 0.0019977313 | DH11: -0.0025251154 | DI11: -0.0003112289 | DJ11: -0.0039158872 | DK11: -0.005059253 | DL11: 0.015815638 | DM11: 0.0042139625 | DN11: 0.0024945901 | DO11: -0.003785088 | DP11: 0.00058890001 | DQ11: -0.019349428 | DR11: 0.0082031688 | DS11: -0.002361739 | DT11: -0.0053047648 | DU11: 0.0038593731 | DV11: 0.0047991056 | DW11: -0.0092673402 | DX11: 0.0013202641 | DY11: -0.0052727983 | DZ11: 0.0050070602 | EA11: 0.0048403562 | EB11: 0.0017586243 | EC11: 0.0209328 | ED11: 0.010043495 | EE11: 0.0039279147 | EF11: 0.0098401725 | EG11: 0.0080054278 | EH11: -0.010717269 | EI11: 0.00079755093 | EJ11: 0.017820871 | EK11: 0.0072519543 | EL11: 0.0078197495 | EM11: -0.012557253 | EN11: 0.0016852169 | EO11: 0.027965811 | EP11: =SUMPRODUCT(B11:EO11,$B$5:$EO$5) -> 0.0044197618 | EQ11: =SUMIF('Mi portafolio'!$A$8:$A$19,$A11,'Mi portafolio'!$B$8:$B$19) -> 0
A12: VESTA * | B12: -0.00040132723 | C12: 0.0049422947 | D12: 0.005856973 | E12: 0.0088728153 | F12: 0.0034948462 | G12: 0.0075106735 | H12: 0.042252515 | I12: 0.0038218753 | J12: 0.00013310041 | K12: 0.0043467895 | L12: 0.0084469145 | M12: 0.0079074984 | N12: 0.0048867827 | O12: 0.0095450548 | P12: 0.00089013739 | Q12: -0.0007792984 | R12: 0.0025881703 | S12: 0.011309769 | T12: 0.001545687 | U12: 0.01374608 | V12: 0.017048143 | W12: 0.0068214632 | X12: 0.0032934177 | Y12: -0.003710134 | Z12: 0.013619 | AA12: 0.010329738 | AB12: -0.0042141687 | AC12: 0.011422388 | AD12: 0.010603849 | AE12: 0.010563384 | AF12: 0.013371198 | AG12: -0.0012911751 | AH12: 0.00052048064 | AI12: -0.0058515388 | AJ12: 0.014147173 | AK12: 0.01385687 | AL12: 0.00072620259 | AM12: 0.0092742355 | AN12: 0.0077827649 | AO12: 0.00019787343 | AP12: 0.0014529687 | AQ12: -0.00427196 | AR12: -0.00064484069 | AS12: 0.017762423 | AT12: -1.4407435e-05 | AU12: 0.0013327767 | AV12: 0.010677746 | AW12: 0.020457766 | AX12: 0.0037042399 | AY12: 0.00049963901 | AZ12: 0.016601702 | BA12: 0.0047540699 | BB12: 0.0020529898 | BC12: 0.0095120355 | BD12: 0.014216921 | BE12: 0.0054608421 | BF12: 0.014525825 | BG12: 0.002288114 | BH12: 0.018705578 | BI12: 0.0088441799 | BJ12: -0.0052973676 | BK12: 0.012315476 | BL12: 0.0083581279 | BM12: 0.003628334 | BN12: -0.0051304745 | BO12: 0.012279139 | BP12: 0.0017393242 | BQ12: 0.018578805 | BR12: 0.0079151183 | BS12: -0.0062182654 | BT12: 0.012773036 | BU12: 0.012967618 | BV12: 0.0047304721 | BW12: 0.0067733941 | BX12: 0.0042240626 | BY12: 0.0093244475 | BZ12: 0.009044936 | CA12: 0.019880095 | CB12: -0.0070869642 | CC12: -0.0040199491 | CD12: 0.0039736589 | CE12: 0.0014032634 | CF12: -0.0085604721 | CG12: 0.0086570764 | CH12: 0.020067031 | CI12: -0.0087122184 | CJ12: -0.00092537773 | CK12: 0.0013703605 | CL12: 0.017720754 | CM12: 0.0028513043 | CN12: 0.015220547 | CO12: 0.01067629 | CP12: 0.0040188633 | CQ12: 0.0070643365 | CR12: 0.0082637214 | CS12: 0.0092400786 | CT12: 0.012121707 | CU12: 0.0034114599 | CV12: 0.0019620141 | CW12: 0.0061562119 | CX12: 0.0056558516 | CY12: 0.0029480028 | CZ12: 0.0098486701 | DA12: 0.00519217 | DB12: 0.011512136 | DC12: 0.015667842 | DD12: 0.0061496239 | DE12: 0.010227461 | DF12: 0.0030538581 | DG12: 0.010953186 | DH12: 0.0084384503 | DI12: 0.010804071 | DJ12: 0.0059578583 | DK12: 0.0088552107 | DL12: 0.022148457 | DM12: 0.014116685 | DN12: 0.009695484 | DO12: 0.015213248 | DP12: 0.012105771 | DQ12: 0.014507238 | DR12: 0.0040299842 | DS12: 0.0020911187 | DT12: 0.0016742041 | DU12: 0.0055168921 | DV12: 0.0021795847 | DW12: 0.0035686494 | DX12: 0.012318593 | DY12: -0.0060399822 | DZ12: 0.0054330633 | EA12: 0.013428424 | EB12: -0.00051236807 | EC12: 0.0052246031 | ED12: 0.031154494 | EE12: 0.013735284 | EF12: 0.00047843456 | EG12: 0.013616069 | EH12: -0.0063181582 | EI12: 0.0046326263 | EJ12: 0.017771429 | EK12: 0.0092774792 | EL12: 0.016391016 | EM12: 0.0055011004 | EN12: 0.0046005004 | EO12: 0.013528303 | EP12: =SUMPRODUCT(B12:EO12,$B$5:$EO$5) -> 0.0089939706 | EQ12: =SUMIF('Mi portafolio'!$A$8:$A$19,$A12,'Mi portafolio'!$B$8:$B$19) -> 0
A13: MCD * | B13: 0.016157944 | C13: 0.0028391596 | D13: -0.00077785347 | E13: 0.0063919888 | F13: 0.024511115 | G13: 0.00080636617 | H13: 0.0038218753 | I13: 0.043422766 | J13: 0.018505505 | K13: 0.024290823 | L13: 0.0058215211 | M13: 0.014022869 | N13: 0.01664538 | O13: 0.0049191917 | P13: 0.022065727 | Q13: -0.0013446975 | R13: 0.024931688 | S13: 0.0048652002 | T13: 0.0071565311 | U13: 0.003314349 | V13: 0.005543567 | W13: 0.0088222221 | X13: 0.0082167983 | Y13: 0.019908318 | Z13: 0.0058213737 | AA13: 0.010049148 | AB13: 0.020680666 | AC13: 0.0017745489 | AD13: 0.0039296111 | AE13: 0.0024040691 | AF13: 0.00012892197 | AG13: 0.016808822 | AH13: 0.016653564 | AI13: 0.0060829112 | AJ13: 0.0025961509 | AK13: 0.0026210713 | AL13: 0.016021378 | AM13: 0.0020501072 | AN13: 0.027016593 | AO13: 0.019798725 | AP13: 0.017165042 | AQ13: 0.0079584525 | AR13: 0.010810028 | AS13: -0.00044629768 | AT13: 0.012992444 | AU13: 0.023951941 | AV13: 0.0078521701 | AW13: 0.0020311782 | AX13: 0.024678395 | AY13: 0.021406638 | AZ13: 0.0043084981 | BA13: 0.013250421 | BB13: 0.0053736743 | BC13: 0.0074618794 | BD13: 0.0022154153 | BE13: 0.022071478 | BF13: 0.0057323438 | BG13: 0.0094524768 | BH13: 0.0021741272 | BI13: 0.0020855591 | BJ13: 0.00088692742 | BK13: -7.0915168e-05 | BL13: 0.0080769056 | BM13: 0.022837499 | BN13: 0.0089867193 | BO13: 0.014136414 | BP13: 0.0075658653 | BQ13: 0.0013930332 | BR13: 0.016397962 | BS13: 0.0015301398 | BT13: 0.013078876 | BU13: -0.0039911833 | BV13: 0.010285557 | BW13: 0.013956695 | BX13: 0.023891622 | BY13: 0.016934512 | BZ13: 0.014559901 | CA13: 0.0046061684 | CB13: 0.00082595154 | CC13: 0.0085877785 | CD13: 0.016785407 | CE13: -0.00050633684 | CF13: 0.0048046961 | CG13: 0.02201344 | CH13: 0.001470333 | CI13: 0.0094729015 | CJ13: 0.019630126 | CK13: 0.025271017 | CL13: 0.0079734369 | CM13: -0.012099355 | CN13: -0.0033393133 | CO13: 0.0091186602 | CP13: 0.015784855 | CQ13: 0.018603643 | CR13: -0.0048599297 | CS13: -0.0024952915 | CT13: 0.0055763515 | CU13: 0.006038038 | CV13: 0.0050668139 | CW13: 0.020705412 | CX13: 0.014956906 | CY13: 0.022193906 | CZ13: 0.0081318356 | DA13: 0.011046393 | DB13: -0.0027442943 | DC13: 0.0029549399 | DD13: 0.016325805 | DE13: -0.0006449584 | DF13: 0.011624114 | DG13: 0.0080800388 | DH13: -0.0060553902 | DI13: 0.023065765 | DJ13: 0.026532932 | DK13: 0.018459395 | DL13: -0.0034666394 | DM13: 0.029342769 | DN13: 0.028028876 | DO13: 0.0043375898 | DP13: 0.029052252 | DQ13: -0.0037950028 | DR13: -0.0050509672 | DS13: 0.0082192749 | DT13: -0.014471713 | DU13: 0.00029279453 | DV13: 0.0097114684 | DW13: 0.021751007 | DX13: -0.019942138 | DY13: 0.015609856 | DZ13: -0.001123101 | EA13: 0.014415749 | EB13: 0.012494999 | EC13: -0.010154205 | ED13: 0.015582835 | EE13: -0.019390013 | EF13: 0.00049225368 | EG13: -0.025498594 | EH13: 0.02224941 | EI13: -0.037918939 | EJ13: 0.0061358913 | EK13: -0.001345732 | EL13: -0.018365515 | EM13: 0.0007592742 | EN13: 0.028943737 | EO13: 0.0040883869 | EP13: =SUMPRODUCT(B13:EO13,$B$5:$EO$5) -> -0.02926989 | EQ13: =SUMIF('Mi portafolio'!$A$8:$A$19,$A13,'Mi portafolio'!$B$8:$B$19) -> 0
A14: JNJ * | B14: 0.010795809 | C14: 0.0015465994 | D14: -0.0014884529 | E14: 0.0026183734 | F14: 0.019396531 | G14: -0.00057981806 | H14: 0.00013310041 | I14: 0.018505505 | J14: 0.04247152 | K14: 0.019543568 | L14: 0.004150695 | M14: 0.0089403131 | N14: 0.01839134 | O14: 0.0050413435 | P14: 0.0186002 | Q14: 0.0004001665 | R14: 0.022181017 | S14: 0.0065740953 | T14: 0.005609116 | U14: 0.004785883 | V14: -0.0010819527 | W14: 0.0075375756 | X14: 0.0076387353 | Y14: 0.012769407 | Z14: 0.0032711246 | AA14: 0.0086039858 | AB14: 0.011232438 | AC14: -0.0067595507 | AD14: 0.0060789329 | AE14: -0.0041120868 | AF14: 0.00023632266 | AG14: 0.015845237 | AH14: 0.015270581 | AI14: 0.011366093 | AJ14: 0.00082614278 | AK14: 0.004507159 | AL14: 0.011030698 | AM14: 0.0039312392 | AN14: 0.015829257 | AO14: 0.030636435 | AP14: 0.0067723864 | AQ14: 0.011738982 | AR14: 0.0050126861 | AS14: 0.0033073999 | AT14: 0.0018685582 | AU14: 0.024264152 | AV14: 0.0021403501 | AW14: 0.0015306889 | AX14: 0.030494666 | AY14: 0.011015959 | AZ14: -0.0030361794 | BA14: 0.011776237 | BB14: 0.0008470433 | BC14: -8.7553645e-05 | BD14: 0.0025082478 | BE14: 0.034400153 | BF14: 0.0025930619 | BG14: 0.011840411 | BH14: -0.0018491171 | BI14: -0.00069444668 | BJ14: -0.0018780392 | BK14: -0.0041462363 | BL14: 0.01141353 | BM14: 0.013521168 | BN14: 0.013549432 | BO14: 0.0095748456 | BP14: -0.010039376 | BQ14: -0.0018174482 | BR14: 0.0060269789 | BS14: 0.0082043213 | BT14: 0.013904041 | BU14: 0.0018312688 | BV14: -0.0010391638 | BW14: 0.010311044 | BX14: 0.036009931 | BY14: 0.0057699747 | BZ14: 0.007529425 | CA14: 0.0014495763 | CB14: 0.0081883287 | CC14: 0.0078177133 | CD14: 0.006389393 | CE14: 0.0004821845 | CF14: 0.012063149 | CG14: 0.0072756977 | CH14: 0.00030907139 | CI14: 0.011584683 | CJ14: 0.016599846 | CK14: 0.016212411 | CL14: 0.0089517598 | CM14: -0.01041276 | CN14: 0.0026213794 | CO14: -0.0044765449 | CP14: 0.009858955 | CQ14: 0.0076982398 | CR14: -0.0092743533 | CS14: 0.0034832135 | CT14: 0.00023471432 | CU14: 0.00088023966 | CV14: -0.0070037273 | CW14: 0.0060713965 | CX14: 0.0048855981 | CY14: 0.006739339 | CZ14: 0.0033117156 | DA14: 0.00013339873 | DB14: -0.0080713304 | DC14: -0.0058654666 | DD14: 0.001125365 | DE14: -0.0033629208 | DF14: -0.00090281281 | DG14: 0.009848659 | DH14: -0.014154312 | DI14: 0.0036515541 | DJ14: 0.013618362 | DK14: 0.0064072419 | DL14: -8.6903597e-05 | DM14: 0.012338695 | DN14: 0.0078524432 | DO14: -0.0079649805 | DP14: 0.017603621 | DQ14: -0.0027599653 | DR14: 0.00060845434 | DS14: 0.00065118785 | DT14: -0.02620271 | DU14: -0.013293762 | DV14: -0.0048452185 | DW14: -0.0013862608 | DX14: -0.016004296 | DY14: -0.015205769 | DZ14: 0.00055975531 | EA14: 0.0019957886 | EB14: -0.0085784896 | EC14: 0.0038060013 | ED14: -0.0079730906 | EE14: -0.021559248 | EF14: 0.0076247935 | EG14: -0.016673841 | EH14: 0.0023419824 | EI14: -0.03020137 | EJ14: -0.0062394732 | EK14: -0.014733611 | EL14: -0.015233259 | EM14: -0.019957632 | EN14: 0.044496388 | EO14: -0.018642621 | EP14: =SUMPRODUCT(B14:EO14,$B$5:$EO$5) -> -0.021676718 | EQ14: =SUMIF('Mi portafolio'!$A$8:$A$19,$A14,'Mi portafolio'!$B$8:$B$19) -> 0
A15: PG * | B15: 0.015017873 | C15: -0.0024906799 | D15: -0.0021672209 | E15: 0.0035083972 | F15: 0.024753308 | G15: 0.00050478755 | H15: 0.0043467895 | I15: 0.024290823 | J15: 0.019543568 | K15: 0.043368338 | L15: 0.0039581817 | M15: 0.013931698 | N15: 0.015591275 | O15: 0.0081292234 | P15: 0.018913119 | Q15: -0.0019355843 | R15: 0.027257997 | S15: 0.0081090334 | T15: 0.0060462649 | U15: 0.0049629919 | V15: 0.007049923 | W15: 0.0092523663 | X15: 0.0066325957 | Y15: 0.014876052 | Z15: 0.0070092921 | AA15: 0.010238181 | AB15: 0.015723378 | AC15: 0.0023226651 | AD15: 0.0074676251 | AE15: 0.0022519852 | AF15: -0.0023554202 | AG15: 0.01926921 | AH15: 0.019906921 | AI15: 0.0042773058 | AJ15: 0.0025206562 | AK15: 0.0015838605 | AL15: 0.014998556 | AM15: 0.0010418887 | AN15: 0.02883818 | AO15: 0.017794264 | AP15: 0.017958184 | AQ15: 0.0044565197 | AR15: 0.0078393739 | AS15: 0.00042068518 | AT15: 0.0092184304 | AU15: 0.024702272 | AV15: 0.0051260626 | AW15: 0.0020454226 | AX15: 0.023560704 | AY15: 0.01557626 | AZ15: 0.0025192775 | BA15: 0.017750308 | BB15: 0.00022897795 | BC15: 0.0017953511 | BD15: 0.0060262869 | BE15: 0.025150047 | BF15: 0.0061071321 | BG15: 0.0086303945 | BH15: 0.0020515071 | BI15: 0.0026129511 | BJ15: -0.0029687305 | BK15: 0.0014508861 | BL15: 0.013391278 | BM15: 0.022524291 | BN15: 0.015457279 | BO15: 0.014124526 | BP15: -0.0029775816 | BQ15: 0.006866807 | BR15: 0.0096859179 | BS15: -0.0033824867 | BT15: 0.012650536 | BU15: -0.002785869 | BV15: 0.010439811 | BW15: 0.0079594655 | BX15: 0.018031608 | BY15: 0.01568609 | BZ15: 0.012611471 | CA15: 0.010390646 | CB15: -0.0014474406 | CC15: 0.01072718 | CD15: 0.0089094887 | CE15: -0.0031695823 | CF15: 0.0016346608 | CG15: 0.01371746 | CH15: 0.0012906142 | CI15: 0.0011011963 | CJ15: 0.014155585 | CK15: 0.02624501 | CL15: 0.012644744 | CM15: -0.011126381 | CN15: -0.0016492401 | CO15: 0.0051627819 | CP15: 0.015040334 | CQ15: 0.015886748 | CR15: -0.0031561125 | CS15: 0.0046439327 | CT15: 0.0076891297 | CU15: 0.0039934888 | CV15: 0.0073926944 | CW15: 0.011596661 | CX15: 0.010271037 | CY15: 0.02646739 | CZ15: 0.00050293089 | DA15: 0.012269692 | DB15: -0.0022022874 | DC15: 0.012544523 | DD15: 0.0113411 | DE15: -0.0010067944 | DF15: -0.0029788213 | DG15: 0.005040324 | DH15: -0.014513531 | DI15: 0.023167674 | DJ15: 0.028214623 | DK15: 0.020432391 | DL15: 0.0022836388 | DM15: 0.035289861 | DN15: 0.020550028 | DO15: 0.0021472912 | DP15: 0.033515448 | DQ15: -0.0011925028 | DR15: -0.012110477 | DS15: 0.0081743366 | DT15: -0.026233278 | DU15: -0.0071524177 | DV15: -0.0037545761 | DW15: 0.0014801475 | DX15: -0.020977145 | DY15: 0.0019585546 | DZ15: -0.01156889 | EA15: 0.015168396 | EB15: -5.9100468e-05 | EC15: -0.018367533 | ED15: -0.0095168759 | EE15: -0.010125549 | EF15: 0.017341695 | EG15: -0.012421337 | EH15: -0.00087889005 | EI15: -0.04038937 | EJ15: 0.0019531464 | EK15: -0.013013002 | EL15: -0.018456269 | EM15: -0.020478666 | EN15: 0.033436564 | EO15: 0.0033113607 | EP15: =SUMPRODUCT(B15:EO15,$B$5:$EO$5) -> -0.025279324 | EQ15: =SUMIF('Mi portafolio'!$A$8:$A$19,$A15,'Mi portafolio'!$B$8:$B$19) -> 0
A16: WALMEX * | B16: 0.0022871874 | C16: 0.010736609 | D16: 0.0041034117 | E16: 0.012115927 | F16: 0.0064950374 | G16: -0.0006514633 | H16: 0.0084469145 | I16: 0.0058215211 | J16: 0.004150695 | K16: 0.0039581817 | L16: 0.041120646 | M16: 0.0076543394 | N16: 0.006476313 | O16: 0.016351203 | P16: 0.0063890067 | Q16: 0.0041191207 | R16: 0.0044992698 | S16: 0.015791753 | T16: 0.001496576 | U16: 0.01443286 | V16: 0.013496556 | W16: 0.0087203347 | X16: 0.0024208741 | Y16: 0.0083165331 | Z16: 0.014309815 | AA16: 0.014577983 | AB16: 0.0059726509 | AC16: 0.0059114283 | AD16: 0.010885105 | AE16: 0.012474869 | AF16: 0.014519859 | AG16: -0.00093032174 | AH16: 0.00054747878 | AI16: -0.0010312004 | AJ16: 0.011852922 | AK16: 0.014134504 | AL16: 0.0057801399 | AM16: 0.0087112764 | AN16: 0.0074525168 | AO16: 0.0030317112 | AP16: 0.004816451 | AQ16: -0.00020183627 | AR16: -0.00049488113 | AS16: 0.011111141 | AT16: 0.0030045786 | AU16: 0.0057034772 | AV16: 0.016667057 | AW16: 0.0094007593 | AX16: 0.0088934576 | AY16: 0.015945678 | AZ16: 0.015741564 | BA16: 0.014279628 | BB16: 0.0030825446 | BC16: 0.0066115318 | BD16: 0.012808608 | BE16: 0.0070607629 | BF16: 0.010429062 | BG16: 0.00060210624 | BH16: 0.015918994 | BI16: 0.011154626 | BJ16: 0.00078726855 | BK16: 0.013191245 | BL16: 0.005671714 | BM16: 0.0086094507 | BN16: 0.0064942085 | BO16: 0.0059617612 | BP16: 0.01215012 | BQ16: 0.015451007 | BR16: 0.0067612483 | BS16: -0.0043839216 | BT16: 0.009323118 | BU16: 0.0054794564 | BV16: 0.0081748148 | BW16: 0.0096989347 | BX16: -0.0026079615 | BY16: 0.0039222143 | BZ16: 0.010359097 | CA16: 0.012701163 | CB16: -0.0056918053 | CC16: 0.00057884005 | CD16: 0.010905939 | CE16: 0.004234181 | CF16: -0.0001746591 | CG16: 0.0081181777 | CH16: 0.012683875 | CI16: -0.001147206 | CJ16: -0.001151895 | CK16: 0.00296067 | CL16: 0.0036437431 | CM16: 0.0037432546 | CN16: 0.010193348 | CO16: 0.0068010903 | CP16: 0.0035483287 | CQ16: 0.010470706 | CR16: 0.010125343 | CS16: 0.006457804 | CT16: 0.0079733309 | CU16: 0.009135327 | CV16: -3.450244e-05 | CW16: 0.012486317 | CX16: 0.0060656741 | CY16: 0.0075990691 | CZ16: 0.012649013 | DA16: 0.0105382 | DB16: 0.011545355 | DC16: 0.013895455 | DD16: 0.0056846375 | DE16: 0.0087188609 | DF16: 0.006031316 | DG16: 0.011006742 | DH16: 0.0076099731 | DI16: 0.013286944 | DJ16: 0.0081775241 | DK16: 0.014964315 | DL16: 0.015233759 | DM16: 0.015528025 | DN16: 0.021477095 | DO16: 0.016306036 | DP16: 0.011391958 | DQ16: 0.011480413 | DR16: 0.0046486466 | DS16: 0.0045820631 | DT16: 0.0029904768 | DU16: -0.0016269926 | DV16: 0.0084259673 | DW16: -0.00071395196 | DX16: 0.014520415 | DY16: 0.0079052461 | DZ16: 0.012946421 | EA16: 0.014725336 | EB16: 0.0047090275 | EC16: 0.0045645592 | ED16: 0.011658222 | EE16: 0.015713377 | EF16: 0.010118708 | EG16: 0.031389353 | EH16: 0.00027776842 | EI16: 0.013724209 | EJ16: 0.023735576 | EK16: 0.020421507 | EL16: 0.026831659 | EM16: 0.0030674026 | EN16: -0.0011994082 | EO16: 0.013182658 | EP16: =SUMPRODUCT(B16:EO16,$B$5:$EO$5) -> 0.020852708 | EQ16: =SUMIF('Mi portafolio'!$A$8:$A$19,$A16,'Mi portafolio'!$B$8:$B$19) -> 0
A17: AGNC * | B17: 0.0091731123 | C17: 0.0026619754 | D17: -0.0028327669 | E17: 0.0081499975 | F17: 0.012967485 | G17: 0.00251802 | H17: 0.0079074984 | I17: 0.014022869 | J17: 0.0089403131 | K17: 0.013931698 | L17: 0.0076543394 | M17: 0.046817009 | N17: 0.013847126 | O17: 0.010540316 | P17: 0.0098109018 | Q17: 0.00016246915 | R17: 0.014476934 | S17: 0.0058375739 | T17: 0.016950652 | U17: 0.014252928 | V17: 0.014069373 | W17: 0.0082193426 | X17: 0.017063909 | Y17: 0.011894699 | Z17: 0.014675358 | AA17: 0.010427827 | AB17: 0.012553136 | AC17: 0.0056753738 | AD17: 0.0089953657 | AE17: 0.012465615 | AF17: 0.0071050168 | AG17: 0.0019761181 | AH17: 0.0029287183 | AI17: -0.0033180096 | AJ17: 0.0014817826 | AK17: 0.013147255 | AL17: 0.01505675 | AM17: 0.01082597 | AN17: 0.031186851 | AO17: 0.0089137736 | AP17: 0.01568577 | AQ17: -0.006475689 | AR17: 0.014400885 | AS17: 0.014060321 | AT17: 0.021636457 | AU17: 0.014365027 | AV17: 0.011266334 | AW17: 0.014938061 | AX17: 0.016876624 | AY17: 0.022208106 | AZ17: 0.016238659 | BA17: 0.022927488 | BB17: 0.021197956 | BC17: 0.0093266823 | BD17: 0.010999316 | BE17: 0.018755625 | BF17: 0.017293867 | BG17: 0.021921542 | BH17: 0.010549113 | BI17: 0.0085959361 | BJ17: -0.007174091 | BK17: 0.011482595 | BL17: 0.025249253 | BM17: 0.022307683 | BN17: 0.002054475 | BO17: 0.022492558 | BP17: 0.011625869 | BQ17: 0.022941438 | BR17: 0.02469606 | BS17: -0.0062622123 | BT17: 0.026006098 | BU17: 0.0092167775 | BV17: 0.02431732 | BW17: 0.02006985 | BX17: 0.010727735 | BY17: 0.030881346 | BZ17: 0.031571364 | CA17: 0.017412026 | CB17: -0.0029304374 | CC17: 0.0060027031 | CD17: 0.02183949 | CE17: 0.0071846332 | CF17: -0.0061314737 | CG17: 0.028063656 | CH17: 0.026637521 | CI17: -0.0084919683 | CJ17: 0.0077118965 | CK17: 0.024713879 | CL17: 0.027430139 | CM17: 0.017893114 | CN17: 0.0025575003 | CO17: 0.0082550553 | CP17: 0.012758136 | CQ17: 0.037559373 | CR17: 0.026324065 | CS17: 0.024691301 | CT17: 0.023552057 | CU17: 0.012963875 | CV17: 0.024533546 | CW17: 0.02759382 | CX17: 0.032164932 | CY17: 0.039551841 | CZ17: 0.010160601 | DA17: 0.01632119 | DB17: 0.029815494 | DC17: 0.032366505 | DD17: 0.031657767 | DE17: 0.03505119 | DF17: 0.010967349 | DG17: 0.037033628 | DH17: 0.018171071 | DI17: 0.04289338 | DJ17: 0.038863 | DK17: 0.045883351 | DL17: 0.019793671 | DM17: 0.049086151 | DN17: 0.035876846 | DO17: 0.031057017 | DP17: 0.047508942 | DQ17: 0.031267157 | DR17: 0.027399864 | DS17: 0.014793942 | DT17: 0.017042964 | DU17: 0.036261947 | DV17: 0.021455955 | DW17: 0.029729041 | DX17: 0.031910165 | DY17: 0.046920786 | DZ17: 0.013864423 | EA17: 0.030289567 | EB17: 0.051786209 | EC17: 0.0058040072 | ED17: 0.043916585 | EE17: 0.032644505 | EF17: 0.037356183 | EG17: 0.038049663 | EH17: 0.02411372 | EI17: 0.032352633 | EJ17: 0.059910299 | EK17: 0.050506931 | EL17: 0.057900309 | EM17: 0.042123614 | EN17: 0.069879622 | EO17: 0.042190338 | EP17: =SUMPRODUCT(B17:EO17,$B$5:$EO$5) -> 0.032709025 | EQ17: =SUMIF('Mi portafolio'!$A$8:$A$19,$A17,'Mi portafolio'!$B$8:$B$19) -> 0
... A149: BYND * | B149: -0.0061273357 | C149: 0.014401478 | D149: -0.039246885 | E149: 0.0070333762 | F149: 0.049367655 | G149: 0.027965811 | H149: 0.013528303 | I149: 0.0040883869 | J149: -0.018642621 | K149: 0.0033113607 | L149: 0.013182658 | M149: 0.042190338 | N149: 0.015778877 | O149: 0.0051594426 | P149: 0.0039033462 | Q149: 0.0068800648 | R149: 0.0091765078 | S149: -0.03425242 | T149: 0.019207951 | U149: 0.021384735 | V149: -0.004605605 | W149: -0.022200163 | X149: 0.029185363 | Y149: 0.017183321 | Z149: 0.016157725 | AA149: -0.012670352 | AB149: 0.020278469 | AC149: 0.0012132359 | AD149: -0.015884428 | AE149: 0.014419785 | AF149: -0.028157154 | AG149: -0.049933719 | AH149: -0.02189711 | AI149: -0.0097860846 | AJ149: 0.0042962282 | AK149: 0.038844068 | AL149: 0.069456906 | AM149: 0.029901894 | AN149: 0.058818842 | AO149: 0.012598634 | AP149: 0.10475487 | AQ149: -0.0082609968 | AR149: 0.036377138 | AS149: 0.070977452 | AT149: 0.071413805 | AU149: -0.0095886319 | AV149: 0.031826676 | AW149: 0.0072705137 | AX149: 0.044546933 | AY149: 0.020927809 | AZ149: -0.039500499 | BA149: 0.064172345 | BB149: 0.059267115 | BC149: -0.039498885 | BD149: 0.07631358 | BE149: 0.044493391 | BF149: 0.066607571 | BG149: 0.098670827 | BH149: 0.031382195 | BI149: -0.051029522 | BJ149: -0.019761548 | BK149: -0.087169943 | BL149: 0.080000184 | BM149: 0.11677909 | BN149: 0.026270185 | BO149: 0.047323237 | BP149: 0.059983148 | BQ149: -0.029553471 | BR149: 0.080913761 | BS149: 0.0077745738 | BT149: 0.081738441 | BU149: 0.03676251 | BV149: 0.12070118 | BW149: 0.089757413 | BX149: 0.017895863 | BY149: 0.2599895 | BZ149: 0.098332644 | CA149: -0.023942334 | CB149: -0.054155434 | CC149: 0.060016653 | CD149: 0.068938325 | CE149: 0.059710046 | CF149: -0.020062904 | CG149: 0.10626547 | CH149: 0.066593952 | CI149: -0.020130206 | CJ149: 0.11631114 | CK149: 0.09519152 | CL149: 0.12068747 | CM149: 0.063413684 | CN149: 0.02548307 | CO149: 0.013712679 | CP149: 0.053423022 | CQ149: 0.11515482 | CR149: 0.088193382 | CS149: 0.068078617 | CT149: 0.14637494 | CU149: 0.082498613 | CV149: 0.058494361 | CW149: 0.13912703 | CX149: 0.098467657 | CY149: 0.10257773 | CZ149: 0.085221136 | DA149: 0.10748708 | DB149: 0.12256789 | DC149: 0.063539726 | DD149: 0.18411883 | DE149: 0.12160545 | DF149: 0.15858562 | DG149: 0.019067276 | DH149: 0.040379678 | DI149: 0.10714324 | DJ149: 0.16492187 | DK149: 0.0878386 | DL149: 0.0065310335 | DM149: 0.18653747 | DN149: 0.16061474 | DO149: 0.11288395 | DP149: 0.17428462 | DQ149: 0.028267092 | DR149: 0.07982788 | DS149: 0.15548653 | DT149: 0.13330711 | DU149: 0.26021155 | DV149: 0.14960413 | DW149: 0.11178301 | DX149: 0.10327935 | DY149: 0.30326751 | DZ149: 0.12471499 | EA149: 0.14097204 | EB149: 0.37335293 | EC149: 0.018721816 | ED149: 0.15164979 | EE149: 0.16814379 | EF149: 0.049967974 | EG149: 0.11890269 | EH149: 0.090277013 | EI149: 0.079421337 | EJ149: 0.12117079 | EK149: 0.29344891 | EL149: 0.22239305 | EM149: 0.098992777 | EN149: 0.35098485 | EO149: 5.0954544 | EP149: =SUMPRODUCT(B149:EO149,$B$5:$EO$5) -> 0.089678437 | EQ149: =SUMIF('Mi portafolio'!$A$8:$A$19,$A149,'Mi portafolio'!$B$8:$B$19) -> 0
