Workbook

Sheet Leeme
B2: Reto Actinver 2026: las 145 acciones de la plataforma, con datos y calculadora de portafolio
B3: Precios de mercado y cierres al 2026-10-08. Datos descriptivos del pasado: NO son una recomendación de inversión y no predicen lo que va a pasar.
B5: Qué hay en cada hoja
B6: • Acciones: las 145 de tu monitor (Reto Actinver > Monitores > Acciones), con el precio de compra y de venta que vio la plataforma, la diferencia entre ambos, el volumen disponible y los datos históricos en pesos.
B7: • Mi portafolio: eliges emisoras y porcentajes (celdas amarillas). Revisa las reglas del reto, los costos reales (comisión + diferencia compra-venta) y cuánto se ha movido un portafolio así.
B8: • Correlaciones / Covarianza: qué tanto se mueven juntas (apoyo de la calculadora).
B10: Lo que más cambia el resultado: la diferencia entre precio de compra y de venta
B11: • Si compras al precio de venta y vendes al precio de compra, pierdes esa diferencia cada vez que haces el viaje completo. En las mexicanas es de centésimas de punto porcentual; en muchas del exterior (SIC) es de 2% a 5%.
B12: • 'Sin contraparte' = hoy no hay quien compre o quien venda (precio $0.00): esa orden no se asigna. Son datos de un instante; cambian durante el día.
B13: • Estos precios son una foto del monitor al momento de copiarlo. Vuelve a revisarlo en la plataforma antes de operar.
B15: Cómo leer las columnas históricas
B16: • Todo está en pesos. En las acciones del exterior se usó el precio en dólares por el tipo de cambio del día (aproximación del precio SIC en pesos).
... B28: • El rango ±1σ supone que el futuro se parece al último año; los eventos extremos pasan más seguido de lo que sugiere.

Sheet Mi portafolio
A1: Mi portafolio del Reto Actinver 2026
A2: Elige emisoras en las celdas amarillas (lista desplegable) y su porcentaje. Todo lo demás se calcula solo.
A4: Capital del reto ($) | C4: 1000000 | E4: Sesiones que faltan (aprox.) | H4: 25
A5: Comisión por operación (0.10% + 16% IVA) | C5: =0.001*1.16 -> 0.00116
A7: Emisora | B7: Peso (%) | C7: Tipo | D7: Perfil por volatilidad | E7: Volatilidad anual | F7: Mov. típico ±1σ (25 ses.) | G7: Peor caída 1 año | H7: Diferencia compra-venta | I7: ¿Operable hoy? | J7: Importe a comprar ($) | K7: Costo estimado ida y vuelta ($) | L7: Peor ventana 25 ses. (3a) en $ | M7: Mejor ventana 25 ses. (3a) en $ | N7: Beta | O7: Peso × beta
C8: =IF($A8="","",INDEX(Acciones!$B$5:$B$148,MATCH($A8,Acciones!$A$5:$A$148,0))) | D8: =IF($A8="","",INDEX(Acciones!$U$5:$U$148,MATCH($A8,Acciones!$A$5:$A$148,0))) | E8: =IF($A8="","",INDEX(Acciones!$O$5:$O$148,MATCH($A8,Acciones!$A$5:$A$148,0))) | F8: =IF($A8="","",E8*SQRT($H$4/252)) | G8: =IF($A8="","",INDEX(Acciones!$Q$5:$Q$148,MATCH($A8,Acciones!$A$5:$A$148,0))) | H8: =IF($A8="","",IF(INDEX(Acciones!$G$5:$G$148,MATCH($A8,Acciones!$A$5:$A$148,0))="","n/d",INDEX(Acciones!$G$5:$G$148,MATCH($A8,Acciones!$A$5:$A$148,0)))) | I8: =IF($A8="","",INDEX(Acciones!$J$5:$J$148,MATCH($A8,Acciones!$A$5:$A$148,0))) | J8: =IF(OR($A8="",$B8=""),"",$B8*$C$4) | K8: =IF(J8="","",J8*(IF(ISNUMBER(H8),H8,0)+2*$C$5)) | L8: =IF(J8="","",J8*INDEX(Acciones!$T$5:$T$148,MATCH($A8,Acciones!$A$5:$A$148,0))) | M8: =IF(J8="","",J8*INDEX(Acciones!$S$5:$S$148,MATCH($A8,Acciones!$A$5:$A$148,0))) | N8: =IF($A8="","",INDEX(Acciones!$R$5:$R$148,MATCH($A8,Acciones!$A$5:$A$148,0))) | O8: =IF(OR($A8="",$B8=""),0,$B8*N8) -> 0
C9: =IF($A9="","",INDEX(Acciones!$B$5:$B$148,MATCH($A9,Acciones!$A$5:$A$148,0))) | D9: =IF($A9="","",INDEX(Acciones!$U$5:$U$148,MATCH($A9,Acciones!$A$5:$A$148,0))) | E9: =IF($A9="","",INDEX(Acciones!$O$5:$O$148,MATCH($A9,Acciones!$A$5:$A$148,0))) | F9: =IF($A9="","",E9*SQRT($H$4/252)) | G9: =IF($A9="","",INDEX(Acciones!$Q$5:$Q$148,MATCH($A9,Acciones!$A$5:$A$148,0))) | H9: =IF($A9="","",IF(INDEX(Acciones!$G$5:$G$148,MATCH($A9,Acciones!$A$5:$A$148,0))="","n/d",INDEX(Acciones!$G$5:$G$148,MATCH($A9,Acciones!$A$5:$A$148,0)))) | I9: =IF($A9="","",INDEX(Acciones!$J$5:$J$148,MATCH($A9,Acciones!$A$5:$A$148,0))) | J9: =IF(OR($A9="",$B9=""),"",$B9*$C$4) | K9: =IF(J9="","",J9*(IF(ISNUMBER(H9),H9,0)+2*$C$5)) | L9: =IF(J9="","",J9*INDEX(Acciones!$T$5:$T$148,MATCH($A9,Acciones!$A$5:$A$148,0))) | M9: =IF(J9="","",J9*INDEX(Acciones!$S$5:$S$148,MATCH($A9,Acciones!$A$5:$A$148,0))) | N9: =IF($A9="","",INDEX(Acciones!$R$5:$R$148,MATCH($A9,Acciones!$A$5:$A$148,0))) | O9: =IF(OR($A9="",$B9=""),0,$B9*N9) -> 0
C10: =IF($A10="","",INDEX(Acciones!$B$5:$B$148,MATCH($A10,Acciones!$A$5:$A$148,0))) | D10: =IF($A10="","",INDEX(Acciones!$U$5:$U$148,MATCH($A10,Acciones!$A$5:$A$148,0))) | E10: =IF($A10="","",INDEX(Acciones!$O$5:$O$148,MATCH($A10,Acciones!$A$5:$A$148,0))) | F10: =IF($A10="","",E10*SQRT($H$4/252)) | G10: =IF($A10="","",INDEX(Acciones!$Q$5:$Q$148,MATCH($A10,Acciones!$A$5:$A$148,0))) | H10: =IF($A10="","",IF(INDEX(Acciones!$G$5:$G$148,MATCH($A10,Acciones!$A$5:$A$148,0))="","n/d",INDEX(Acciones!$G$5:$G$148,MATCH($A10,Acciones!$A$5:$A$148,0)))) | I10: =IF($A10="","",INDEX(Acciones!$J$5:$J$148,MATCH($A10,Acciones!$A$5:$A$148,0))) | J10: =IF(OR($A10="",$B10=""),"",$B10*$C$4) | K10: =IF(J10="","",J10*(IF(ISNUMBER(H10),H10,0)+2*$C$5)) | L10: =IF(J10="","",J10*INDEX(Acciones!$T$5:$T$148,MATCH($A10,Acciones!$A$5:$A$148,0))) | M10: =IF(J10="","",J10*INDEX(Acciones!$S$5:$S$148,MATCH($A10,Acciones!$A$5:$A$148,0))) | N10: =IF($A10="","",INDEX(Acciones!$R$5:$R$148,MATCH($A10,Acciones!$A$5:$A$148,0))) | O10: =IF(OR($A10="",$B10=""),0,$B10*N10) -> 0
C11: =IF($A11="","",INDEX(Acciones!$B$5:$B$148,MATCH($A11,Acciones!$A$5:$A$148,0))) | D11: =IF($A11="","",INDEX(Acciones!$U$5:$U$148,MATCH($A11,Acciones!$A$5:$A$148,0))) | E11: =IF($A11="","",INDEX(Acciones!$O$5:$O$148,MATCH($A11,Acciones!$A$5:$A$148,0))) | F11: =IF($A11="","",E11*SQRT($H$4/252)) | G11: =IF($A11="","",INDEX(Acciones!$Q$5:$Q$148,MATCH($A11,Acciones!$A$5:$A$148,0))) | H11: =IF($A11="","",IF(INDEX(Acciones!$G$5:$G$148,MATCH($A11,Acciones!$A$5:$A$148,0))="","n/d",INDEX(Acciones!$G$5:$G$148,MATCH($A11,Acciones!$A$5:$A$148,0)))) | I11: =IF($A11="","",INDEX(Acciones!$J$5:$J$148,MATCH($A11,Acciones!$A$5:$A$148,0))) | J11: =IF(OR($A11="",$B11=""),"",$B11*$C$4) | K11: =IF(J11="","",J11*(IF(ISNUMBER(H11),H11,0)+2*$C$5)) | L11: =IF(J11="","",J11*INDEX(Acciones!$T$5:$T$148,MATCH($A11,Acciones!$A$5:$A$148,0))) | M11: =IF(J11="","",J11*INDEX(Acciones!$S$5:$S$148,MATCH($A11,Acciones!$A$5:$A$148,0))) | N11: =IF($A11="","",INDEX(Acciones!$R$5:$R$148,MATCH($A11,Acciones!$A$5:$A$148,0))) | O11: =IF(OR($A11="",$B11=""),0,$B11*N11) -> 0
C12: =IF($A12="","",INDEX(Acciones!$B$5:$B$148,MATCH($A12,Acciones!$A$5:$A$148,0))) | D12: =IF($A12="","",INDEX(Acciones!$U$5:$U$148,MATCH($A12,Acciones!$A$5:$A$148,0))) | E12: =IF($A12="","",INDEX(Acciones!$O$5:$O$148,MATCH($A12,Acciones!$A$5:$A$148,0))) | F12: =IF($A12="","",E12*SQRT($H$4/252)) | G12: =IF($A12="","",INDEX(Acciones!$Q$5:$Q$148,MATCH($A12,Acciones!$A$5:$A$148,0))) | H12: =IF($A12="","",IF(INDEX(Acciones!$G$5:$G$148,MATCH($A12,Acciones!$A$5:$A$148,0))="","n/d",INDEX(Acciones!$G$5:$G$148,MATCH($A12,Acciones!$A$5:$A$148,0)))) | I12: =IF($A12="","",INDEX(Acciones!$J$5:$J$148,MATCH($A12,Acciones!$A$5:$A$148,0))) | J12: =IF(OR($A12="",$B12=""),"",$B12*$C$4) | K12: =IF(J12="","",J12*(IF(ISNUMBER(H12),H12,0)+2*$C$5)) | L12: =IF(J12="","",J12*INDEX(Acciones!$T$5:$T$148,MATCH($A12,Acciones!$A$5:$A$148,0))) | M12: =IF(J12="","",J12*INDEX(Acciones!$S$5:$S$148,MATCH($A12,Acciones!$A$5:$A$148,0))) | N12: =IF($A12="","",INDEX(Acciones!$R$5:$R$148,MATCH($A12,Acciones!$A$5:$A$148,0))) | O12: =IF(OR($A12="",$B12=""),0,$B12*N12) -> 0
C13: =IF($A13="","",INDEX(Acciones!$B$5:$B$148,MATCH($A13,Acciones!$A$5:$A$148,0))) | D13: =IF($A13="","",INDEX(Acciones!$U$5:$U$148,MATCH($A13,Acciones!$A$5:$A$148,0))) | E13: =IF($A13="","",INDEX(Acciones!$O$5:$O$148,MATCH($A13,Acciones!$A$5:$A$148,0))) | F13: =IF($A13="","",E13*SQRT($H$4/252)) | G13: =IF($A13="","",INDEX(Acciones!$Q$5:$Q$148,MATCH($A13,Acciones!$A$5:$A$148,0))) | H13: =IF($A13="","",IF(INDEX(Acciones!$G$5:$G$148,MATCH($A13,Acciones!$A$5:$A$148,0))="","n/d",INDEX(Acciones!$G$5:$G$148,MATCH($A13,Acciones!$A$5:$A$148,0)))) | I13: =IF($A13="","",INDEX(Acciones!$J$5:$J$148,MATCH($A13,Acciones!$A$5:$A$148,0))) | J13: =IF(OR($A13="",$B13=""),"",$B13*$C$4) | K13: =IF(J13="","",J13*(IF(ISNUMBER(H13),H13,0)+2*$C$5)) | L13: =IF(J13="","",J13*INDEX(Acciones!$T$5:$T$148,MATCH($A13,Acciones!$A$5:$A$148,0))) | M13: =IF(J13="","",J13*INDEX(Acciones!$S$5:$S$148,MATCH($A13,Acciones!$A$5:$A$148,0))) | N13: =IF($A13="","",INDEX(Acciones!$R$5:$R$148,MATCH($A13,Acciones!$A$5:$A$148,0))) | O13: =IF(OR($A13="",$B13=""),0,$B13*N13) -> 0
C14: =IF($A14="","",INDEX(Acciones!$B$5:$B$148,MATCH($A14,Acciones!$A$5:$A$148,0))) | D14: =IF($A14="","",INDEX(Acciones!$U$5:$U$148,MATCH($A14,Acciones!$A$5:$A$148,0))) | E14: =IF($A14="","",INDEX(Acciones!$O$5:$O$148,MATCH($A14,Acciones!$A$5:$A$148,0))) | F14: =IF($A14="","",E14*SQRT($H$4/252)) | G14: =IF($A14="","",INDEX(Acciones!$Q$5:$Q$148,MATCH($A14,Acciones!$A$5:$A$148,0))) | H14: =IF($A14="","",IF(INDEX(Acciones!$G$5:$G$148,MATCH($A14,Acciones!$A$5:$A$148,0))="","n/d",INDEX(Acciones!$G$5:$G$148,MATCH($A14,Acciones!$A$5:$A$148,0)))) | I14: =IF($A14="","",INDEX(Acciones!$J$5:$J$148,MATCH($A14,Acciones!$A$5:$A$148,0))) | J14: =IF(OR($A14="",$B14=""),"",$B14*$C$4) | K14: =IF(J14="","",J14*(IF(ISNUMBER(H14),H14,0)+2*$C$5)) | L14: =IF(J14="","",J14*INDEX(Acciones!$T$5:$T$148,MATCH($A14,Acciones!$A$5:$A$148,0))) | M14: =IF(J14="","",J14*INDEX(Acciones!$S$5:$S$148,MATCH($A14,Acciones!$A$5:$A$148,0))) | N14: =IF($A14="","",INDEX(Acciones!$R$5:$R$148,MATCH($A14,Acciones!$A$5:$A$148,0))) | O14: =IF(OR($A14="",$B14=""),0,$B14*N14) -> 0
C15: =IF($A15="","",INDEX(Acciones!$B$5:$B$148,MATCH($A15,Acciones!$A$5:$A$148,0))) | D15: =IF($A15="","",INDEX(Acciones!$U$5:$U$148,MATCH($A15,Acciones!$A$5:$A$148,0))) | E15: =IF($A15="","",INDEX(Acciones!$O$5:$O$148,MATCH($A15,Acciones!$A$5:$A$148,0))) | F15: =IF($A15="","",E15*SQRT($H$4/252)) | G15: =IF($A15="","",INDEX(Acciones!$Q$5:$Q$148,MATCH($A15,Acciones!$A$5:$A$148,0))) | H15: =IF($A15="","",IF(INDEX(Acciones!$G$5:$G$148,MATCH($A15,Acciones!$A$5:$A$148,0))="","n/d",INDEX(Acciones!$G$5:$G$148,MATCH($A15,Acciones!$A$5:$A$148,0)))) | I15: =IF($A15="","",INDEX(Acciones!$J$5:$J$148,MATCH($A15,Acciones!$A$5:$A$148,0))) | J15: =IF(OR($A15="",$B15=""),"",$B15*$C$4) | K15: =IF(J15="","",J15*(IF(ISNUMBER(H15),H15,0)+2*$C$5)) | L15: =IF(J15="","",J15*INDEX(Acciones!$T$5:$T$148,MATCH($A15,Acciones!$A$5:$A$148,0))) | M15: =IF(J15="","",J15*INDEX(Acciones!$S$5:$S$148,MATCH($A15,Acciones!$A$5:$A$148,0))) | N15: =IF($A15="","",INDEX(Acciones!$R$5:$R$148,MATCH($A15,Acciones!$A$5:$A$148,0))) | O15: =IF(OR($A15="",$B15=""),0,$B15*N15) -> 0
C16: =IF($A16="","",INDEX(Acciones!$B$5:$B$148,MATCH($A16,Acciones!$A$5:$A$148,0))) | D16: =IF($A16="","",INDEX(Acciones!$U$5:$U$148,MATCH($A16,Acciones!$A$5:$A$148,0))) | E16: =IF($A16="","",INDEX(Acciones!$O$5:$O$148,MATCH($A16,Acciones!$A$5:$A$148,0))) | F16: =IF($A16="","",E16*SQRT($H$4/252)) | G16: =IF($A16="","",INDEX(Acciones!$Q$5:$Q$148,MATCH($A16,Acciones!$A$5:$A$148,0))) | H16: =IF($A16="","",IF(INDEX(Acciones!$G$5:$G$148,MATCH($A16,Acciones!$A$5:$A$148,0))="","n/d",INDEX(Acciones!$G$5:$G$148,MATCH($A16,Acciones!$A$5:$A$148,0)))) | I16: =IF($A16="","",INDEX(Acciones!$J$5:$J$148,MATCH($A16,Acciones!$A$5:$A$148,0))) | J16: =IF(OR($A16="",$B16=""),"",$B16*$C$4) | K16: =IF(J16="","",J16*(IF(ISNUMBER(H16),H16,0)+2*$C$5)) | L16: =IF(J16="","",J16*INDEX(Acciones!$T$5:$T$148,MATCH($A16,Acciones!$A$5:$A$148,0))) | M16: =IF(J16="","",J16*INDEX(Acciones!$S$5:$S$148,MATCH($A16,Acciones!$A$5:$A$148,0))) | N16: =IF($A16="","",INDEX(Acciones!$R$5:$R$148,MATCH($A16,Acciones!$A$5:$A$148,0))) | O16: =IF(OR($A16="",$B16=""),0,$B16*N16) -> 0
C17: =IF($A17="","",INDEX(Acciones!$B$5:$B$148,MATCH($A17,Acciones!$A$5:$A$148,0))) | D17: =IF($A17="","",INDEX(Acciones!$U$5:$U$148,MATCH($A17,Acciones!$A$5:$A$148,0))) | E17: =IF($A17="","",INDEX(Acciones!$O$5:$O$148,MATCH($A17,Acciones!$A$5:$A$148,0))) | F17: =IF($A17="","",E17*SQRT($H$4/252)) | G17: =IF($A17="","",INDEX(Acciones!$Q$5:$Q$148,MATCH($A17,Acciones!$A$5:$A$148,0))) | H17: =IF($A17="","",IF(INDEX(Acciones!$G$5:$G$148,MATCH($A17,Acciones!$A$5:$A$148,0))="","n/d",INDEX(Acciones!$G$5:$G$148,MATCH($A17,Acciones!$A$5:$A$148,0)))) | I17: =IF($A17="","",INDEX(Acciones!$J$5:$J$148,MATCH($A17,Acciones!$A$5:$A$148,0))) | J17: =IF(OR($A17="",$B17=""),"",$B17*$C$4) | K17: =IF(J17="","",J17*(IF(ISNUMBER(H17),H17,0)+2*$C$5)) | L17: =IF(J17="","",J17*INDEX(Acciones!$T$5:$T$148,MATCH($A17,Acciones!$A$5:$A$148,0))) | M17: =IF(J17="","",J17*INDEX(Acciones!$S$5:$S$148,MATCH($A17,Acciones!$A$5:$A$148,0))) | N17: =IF($A17="","",INDEX(Acciones!$R$5:$R$148,MATCH($A17,Acciones!$A$5:$A$148,0))) | O17: =IF(OR($A17="",$B17=""),0,$B17*N17) -> 0
C18: =IF($A18="","",INDEX(Acciones!$B$5:$B$148,MATCH($A18,Acciones!$A$5:$A$148,0))) | D18: =IF($A18="","",INDEX(Acciones!$U$5:$U$148,MATCH($A18,Acciones!$A$5:$A$148,0))) | E18: =IF($A18="","",INDEX(Acciones!$O$5:$O$148,MATCH($A18,Acciones!$A$5:$A$148,0))) | F18: =IF($A18="","",E18*SQRT($H$4/252)) | G18: =IF($A18="","",INDEX(Acciones!$Q$5:$Q$148,MATCH($A18,Acciones!$A$5:$A$148,0))) | H18: =IF($A18="","",IF(INDEX(Acciones!$G$5:$G$148,MATCH($A18,Acciones!$A$5:$A$148,0))="","n/d",INDEX(Acciones!$G$5:$G$148,MATCH($A18,Acciones!$A$5:$A$148,0)))) | I18: =IF($A18="","",INDEX(Acciones!$J$5:$J$148,MATCH($A18,Acciones!$A$5:$A$148,0))) | J18: =IF(OR($A18="",$B18=""),"",$B18*$C$4) | K18: =IF(J18="","",J18*(IF(ISNUMBER(H18),H18,0)+2*$C$5)) | L18: =IF(J18="","",J18*INDEX(Acciones!$T$5:$T$148,MATCH($A18,Acciones!$A$5:$A$148,0))) | M18: =IF(J18="","",J18*INDEX(Acciones!$S$5:$S$148,MATCH($A18,Acciones!$A$5:$A$148,0))) | N18: =IF($A18="","",INDEX(Acciones!$R$5:$R$148,MATCH($A18,Acciones!$A$5:$A$148,0))) | O18: =IF(OR($A18="",$B18=""),0,$B18*N18) -> 0
C19: =IF($A19="","",INDEX(Acciones!$B$5:$B$148,MATCH($A19,Acciones!$A$5:$A$148,0))) | D19: =IF($A19="","",INDEX(Acciones!$U$5:$U$148,MATCH($A19,Acciones!$A$5:$A$148,0))) | E19: =IF($A19="","",INDEX(Acciones!$O$5:$O$148,MATCH($A19,Acciones!$A$5:$A$148,0))) | F19: =IF($A19="","",E19*SQRT($H$4/252)) | G19: =IF($A19="","",INDEX(Acciones!$Q$5:$Q$148,MATCH($A19,Acciones!$A$5:$A$148,0))) | H19: =IF($A19="","",IF(INDEX(Acciones!$G$5:$G$148,MATCH($A19,Acciones!$A$5:$A$148,0))="","n/d",INDEX(Acciones!$G$5:$G$148,MATCH($A19,Acciones!$A$5:$A$148,0)))) | I19: =IF($A19="","",INDEX(Acciones!$J$5:$J$148,MATCH($A19,Acciones!$A$5:$A$148,0))) | J19: =IF(OR($A19="",$B19=""),"",$B19*$C$4) | K19: =IF(J19="","",J19*(IF(ISNUMBER(H19),H19,0)+2*$C$5)) | L19: =IF(J19="","",J19*INDEX(Acciones!$T$5:$T$148,MATCH($A19,Acciones!$A$5:$A$148,0))) | M19: =IF(J19="","",J19*INDEX(Acciones!$S$5:$S$148,MATCH($A19,Acciones!$A$5:$A$148,0))) | N19: =IF($A19="","",INDEX(Acciones!$R$5:$R$148,MATCH($A19,Acciones!$A$5:$A$148,0))) | O19: =IF(OR($A19="",$B19=""),0,$B19*N19) -> 0
A21: Resumen y revisión de reglas
A22: Suma de pesos | B22: =SUM($B$8:$B$19) -> 0 | C22: =IF(ABS(B22-1)<0.0005,"OK: 100%",IF(B22<1,"Te falta "&TEXT(1-B22,"0.0%")&" por asignar (queda en efectivo, que no rinde)","Pasas de 100% por "&TEXT(B22-1,"0.0%"))) -> Te falta 100.0% por asignar (queda en efectivo, que no rinde)
A23: Emisoras distintas (mín. 5) | B23: =SUMPRODUCT(($A$8:$A$19<>"")*($B$8:$B$19>0)/COUNTIF($A$8:$A$19,$A$8:$A$19&"")) -> 0 | C23: =IF(B23>=5,"OK","REVISAR: necesitas al menos 5") -> REVISAR: necesitas al menos 5
A24: Peso máximo en una emisora (máx. 50%) | B24: =MAX($B$8:$B$19) -> 0 | C24: =IF(B24<=0.5,"OK","REVISAR: ninguna puede pasar de 50%") -> OK
A25: Emisoras repetidas en la lista | B25: =SUMPRODUCT(($A$8:$A$19<>"")*(COUNTIF($A$8:$A$19,$A$8:$A$19)>1)) -> 0 | C25: =IF(B25=0,"OK","REVISAR: repetiste una emisora") -> OK
A26: Emisoras sin contraparte hoy | B26: =SUMPRODUCT(($A$8:$A$19<>"")*($I$8:$I$19<>"Sí")) -> 0 | C26: =IF(B26=0,"OK","REVISAR: hoy no hay quien compre o venda alguna de tus emisoras") -> OK
A27: Total a invertir ($) | B27: =SUM($J$8:$J$19) -> 0
A28: Comisión total de compra ($) | B28: =B27*$C$5 -> 0
A29: Costo estimado ida y vuelta ($) | B29: =SUM($K$8:$K$19) -> 0 | C29: ="Comisiones + diferencia compra-venta: "&TEXT(B29/$C$4,"0.00%")&" del capital" -> Comisiones + diferencia compra-venta: 0.00% del capital
A30: Volatilidad anual del portafolio | B30: =SQRT(Covarianza!$B$2) -> 0 | C30: Usa la correlación entre emisoras (hoja Covarianza).
A31: Mov. típico del portafolio (±1σ) en el lapso | B31: =B30*SQRT($H$4/252) -> 0 | C31: ~2 de cada 3 veces el resultado cae dentro de ± este porcentaje.
A32: Mov. típico en pesos (±1σ) | B32: =B31*SUM($J$8:$J$19) -> 0 | C32: Solo la parte invertida; descuenta costos.
A33: Beta del portafolio vs IPC (aprox.) | B33: =SUM($O$8:$O$19) -> 0 | C33: 1 = se mueve como el IPC; >1 más; <1 menos.
A35: Los rangos son históricos y orientativos; el precio real puede salirse de ellos. No es una recomendación de inversión.

Sheet Acciones
A1: Las 145 acciones del Reto: mercado y datos históricos (2026-10-08)
A2: Ordenadas de menor a mayor volatilidad (las que no tienen historial, al final). Usa los filtros. No es una recomendación de inversión.
A4: Emisora | B4: Tipo | C4: Último precio ($) | D4: Var. del día | E4: Precio de compra ($) | F4: Precio de venta ($) | G4: Diferencia compra-venta | H4: Volumen compra | I4: Volumen venta | J4: ¿Operable hoy? | K4: Rend. 1 mes | L4: Rend. 3 meses | M4: Rend. 6 meses | N4: Rend. 12 meses | O4: Volatilidad anual (1 año) | P4: Mov. típico ±1σ en 25 sesiones | Q4: Peor caída (1 año) | R4: Beta vs IPC | S4: Mejor ventana 25 ses. (3 años) | T4: Peor ventana 25 ses. (3 años) | U4: Perfil por volatilidad
A5: BRKB * | B5: Exterior (SIC) | C5: 9246 | D5: 0.016 | E5: 9095.02 | F5: 9383.91 | G5: 0.031266962 | H5: 4540 | I5: 4437 | J5: Sí | K5: 0.06339403 | L5: 0.052310202 | M5: 0.076401029 | N5: -0.010774469 | O5: 0.16522586 | P5: =IF(O5="","",O5*SQRT(25/252)) -> 0.052041255 | Q5: -0.14409367 | R5: -0.03031935 | S5: 0.17107127 | T5: -0.10955247 | U5: Menor movimiento
A6: SIGMAF A | B6: Mexicana | C6: 18.24 | D6: -0.0108 | E6: 18.24 | F6: 18.25 | G6: 0.0005480954 | H6: 915 | I6: 558 | J6: Sí | K6: 0.0029476092 | L6: 0.13149876 | M6: 0.16839548 | N6: 0.22391747 | O6: 0.1781865 | P6: =IF(O6="","",O6*SQRT(25/252)) -> 0.056123473 | Q6: -0.076276235 | R6: 0.28592376 | S6: 0.34418485 | T6: -0.28528061 | U6: Menor movimiento
A7: LIVEPOL C-1 | B7: Mexicana | C7: 102.53 | D7: -0.015 | E7: 102.32 | F7: 102.53 | G7: 0.0020502807 | H7: 90 | I7: 322 | J7: Sí | K7: 0.039438645 | L7: 0.031070299 | M7: -0.021714096 | N7: 0.1935138 | O7: 0.19530862 | P7: =IF(O7="","",O7*SQRT(25/252)) -> 0.061516434 | Q7: -0.093163267 | R7: 0.17673997 | S7: 0.24484943 | T7: -0.17019387 | U7: Menor movimiento
A8: GRUMA B | B8: Mexicana | C8: 236.65 | D8: -0.0035 | E8: 236.41 | F8: 236.52 | G8: 0.0004651851 | H8: 28 | I8: 126 | J8: Sí | K8: 0.0001089388 | L8: -0.15733426 | M8: -0.22275069 | N8: -0.26914345 | O8: 0.20001218 | P8: =IF(O8="","",O8*SQRT(25/252)) -> 0.062997915 | Q8: -0.34068714 | R8: 0.43938567 | S8: 0.18266487 | T8: -0.12940001 | U8: Menor movimiento
A9: KO * | B9: Exterior (SIC) | C9: 1576 | D9: 0.0194 | E9: 1557.06 | F9: 1593.98 | G9: 0.023433533 | H9: 10809 | I9: 7200 | J9: Sí | K9: 0.061359237 | L9: 0.07309343 | M9: 0.15944588 | N9: 0.3092241 | O9: 0.20181491 | P9: =IF(O9="","",O9*SQRT(25/252)) -> 0.063565723 | Q9: -0.089133503 | R9: 0.0007845787 | S9: 0.18931182 | T9: -0.088620188 | U9: Menor movimiento
A10: FIBRAMQ 12 | B10: Mexicana | C10: 44.5 | D10: -0.0069 | E10: 44.5 | F10: 44.64 | G10: 0.0031411263 | H10: 800 | I10: 704 | J10: Sí | K10: 0.048192228 | L10: 0.0041764689 | M10: 0.10305163 | N10: 0.51956362 | O10: 0.20551878 | P10: =IF(O10="","",O10*SQRT(25/252)) -> 0.064732332 | Q10: -0.097821091 | R10: 0.25525109 | S10: 0.23851976 | T10: -0.12474435 | U10: Menor movimiento
A11: VESTA * | B11: Mexicana | C11: 61.43 | D11: 0.0119 | E11: 61.42 | F11: 61.43 | G11: 0.0001628002 | H11: 2852 | I11: 259 | J11: Sí | K11: 0.062889764 | L11: 0.02284223 | M11: -0.0011032095 | N11: 0.25337045 | O11: 0.20612128 | P11: =IF(O11="","",O11*SQRT(25/252)) -> 0.0649221 | Q11: -0.10973071 | R11: 0.5030334 | S11: 0.23707152 | T11: -0.15537195 | U11: Menor movimiento
A12: MCD * | B12: Exterior (SIC) | C12: 4226.01 | D12: 0.0183 | E12: 4247.15 | F12: 4349.19 | G12: 0.023740336 | H12: 4000 | I12: 4100 | J12: Sí | K12: -0.017128832 | L12: -0.11901367 | M12: -0.20904158 | N12: -0.2047482 | O12: 0.2080527 | P12: =IF(O12="","",O12*SQRT(25/252)) -> 0.065530442 | Q12: -0.29821461 | R12: 0.10341778 | S12: 0.23320543 | T12: -0.14651694 | U12: Menor movimiento
A13: JNJ * | B13: Exterior (SIC) | C13: 4542 | D13: -0.0259 | E13: 4501.21 | F13: 4649.99 | G13: 0.032515954 | H13: 400 | I13: 400 | J13: Sí | K13: 0.0053354318 | L13: 0.012378853 | M13: 0.090025844 | N13: 0.3403495 | O13: 0.20827219 | P13: =IF(O13="","",O13*SQRT(25/252)) -> 0.065599575 | Q13: -0.14032686 | R13: 0.073692344 | S13: 0.19099588 | T13: -0.12170604 | U13: Menor movimiento
A14: PG * | B14: Exterior (SIC) | C14: 2710 | D14: 0.0175 | E14: 2696.01 | F14: 2749.99 | G14: 0.019823724 | H14: 1805 | I14: 1500 | J14: Sí | K14: 0.10846619 | L14: 0.044507864 | M14: 0.060651461 | N14: -0.016072204 | O14: 0.20833179 | P14: =IF(O14="","",O14*SQRT(25/252)) -> 0.065618347 | Q14: -0.15054703 | R14: 0.12862297 | S14: 0.16111311 | T14: -0.11340134 | U14: Menor movimiento
A15: WALMEX * | B15: Mexicana | C15: 46.73 | D15: 0.0009 | E15: 46.72 | F15: 46.74 | G15: 0.0004279906 | H15: 2268 | I15: 901 | J15: Sí | K15: 0.0092732438 | L15: -0.050902496 | M15: -0.19017134 | N15: -0.1188246 | O15: 0.21334459 | P15: =IF(O15="","",O15*SQRT(25/252)) -> 0.067197228 | Q15: -0.27139285 | R15: 0.54970317 | S15: 0.19822374 | T15: -0.1722792 | U15: Menor movimiento
A16: AGNC * | B16: Exterior (SIC) | C16: 152.73 | D16: -0.0018 | E16: 153.49 | F16: 154.49 | G16: 0.0064939282 | H16: 3 | I16: 94400 | J16: Sí | K16: -0.13259703 | L16: -0.19260039 | M16: -0.1087275 | N16: -0.048211461 | O16: 0.21835082 | P16: =IF(O16="","",O16*SQRT(25/252)) -> 0.068774043 | Q16: -0.20711619 | R16: 0.47788417 | S16: 0.26803547 | T16: -0.19968516 | U16: Menor movimiento
... A73: WYNN * | B73: Exterior (SIC) | C73: 1356.75 | D73: -0.0097 | E73: 1356.75 | F73: 1393.19 | G73: 0.026502396 | H73: 5 | I73: 1200 | J73: Sí | K73: -0.12036692 | L73: -0.23110346 | M73: -0.262856 | N73: -0.39895196 | O73: 0.33466679 | P73: =IF(O73="","",O73*SQRT(25/252)) -> 0.10541013 | Q73: -0.44511639 | R73: 0.36471549 | S73: 0.38199967 | T73: -0.24216955 | U73: Movimiento medio
A74: FANG * | B74: Exterior (SIC) | C74: 3314.78 | D74: 0 | H74: 0 | I74: 0 | J74: Sin contraparte | K74: -0.0016192089 | L74: 0.069455994 | M74: 0.064054055 | N74: 0.28294842 | O74: 0.34103963 | P74: =IF(O74="","",O74*SQRT(25/252)) -> 0.10741739 | Q74: -0.18870962 | R74: -0.38724844 | S74: 0.24560118 | T74: -0.23848814 | U74: Movimiento medio
A75: GE * | B75: Exterior (SIC) | C75: 5431.18 | D75: -0.0035 | E75: 5379.01 | F75: 5637.29 | G75: 0.046890517 | H75: 400 | I75: 300 | J75: Sí | K75: -0.0055228145 | L75: -0.1314965 | M75: 0.0033227431 | N75: -0.0071765881 | O75: 0.34233611 | P75: =IF(O75="","",O75*SQRT(25/252)) -> 0.10782574 | Q75: -0.20576417 | R75: 0.71061917 | S75: 0.32796904 | T75: -0.21331343 | U75: Movimiento medio
A76: GENTERA * | B76: Mexicana | C76: 36.36 | D76: -0.0101 | E76: 36.35 | F76: 36.36 | G76: 0.0002750653 | H76: 599 | I76: 1466 | J76: Sí | K76: -0.082049986 | L76: -0.10355031 | M76: -0.27466049 | N76: -0.17139032 | O76: 0.34779149 | P76: =IF(O76="","",O76*SQRT(25/252)) -> 0.10954402 | Q76: -0.32905117 | R76: 0.85521793 | S76: 0.33408645 | T76: -0.23076924 | U76: Movimiento medio
A77: AMZN * | B77: Exterior (SIC) | C77: 4705 | D77: 0.0053 | E77: 4691.84 | F77: 4710 | G77: 0.0038630736 | H77: 1400 | I77: 2 | J77: Sí | K77: 0.090689349 | L77: 0.081871027 | M77: 0.1419768 | N77: 0.14462771 | O77: 0.34793752 | P77: =IF(O77="","",O77*SQRT(25/252)) -> 0.10959002 | Q77: -0.27418393 | R77: 0.32492482 | S77: 0.32915281 | T77: -0.22748539 | U77: Movimiento medio
A78: LVS * | B78: Exterior (SIC) | C78: 640.99 | D78: -0.0078 | E78: 637.01 | F78: 662.19 | G78: 0.038762315 | H78: 2400 | I78: 2400 | J78: Sí | K78: -0.12729331 | L78: -0.21412939 | M78: -0.31901647 | N78: -0.31225104 | O78: 0.35329329 | P78: =IF(O78="","",O78*SQRT(25/252)) -> 0.11127693 | Q78: -0.48792437 | R78: 0.36046237 | S78: 0.38550207 | T78: -0.32009706 | U78: Movimiento medio
A79: LLY * | B79: Exterior (SIC) | C79: 20650 | D79: -0.0377 | E79: 20500.01 | F79: 21032.99 | G79: 0.025665375 | H79: 1200 | I79: 1200 | J79: Sí | K79: 0.078992788 | L79: -0.014599218 | M79: 0.23474619 | N79: 0.3342604 | O79: 0.35445138 | P79: =IF(O79="","",O79*SQRT(25/252)) -> 0.11164169 | Q79: -0.27788775 | R79: 0.037321917 | S79: 0.39732962 | T79: -0.2187399 | U79: Movimiento medio
A80: GM * | B80: Exterior (SIC) | C80: 1460 | D80: 0 | E80: 1435.01 | F80: 1504.99 | G80: 0.047605442 | H80: 1000 | I80: 1000 | J80: Sí | K80: 0.029917468 | L80: 0.070609546 | M80: 0.094319451 | N80: 0.40124721 | O80: 0.35574695 | P80: =IF(O80="","",O80*SQRT(25/252)) -> 0.11204976 | Q80: -0.17837577 | R80: 0.42261491 | S80: 0.318855 | T80: -0.16498799 | U80: Movimiento medio
A81: BA * | B81: Exterior (SIC) | C81: 3342.37 | D81: -0.0128 | E81: 3323.01 | F81: 3422.72 | G81: 0.029562405 | H81: 1200 | I81: 1050 | J81: Sí | K81: -0.041417209 | L81: -0.14170923 | M81: -0.12848887 | N81: -0.17742236 | O81: 0.35585076 | P81: =IF(O81="","",O81*SQRT(25/252)) -> 0.11208245 | Q81: -0.25725335 | R81: 0.53195213 | S81: 0.41770114 | T81: -0.23791954 | U81: Movimiento medio
A82: GCARSO A1 | B82: Mexicana | C82: 144.8 | D82: 0.0132 | E82: 144.01 | F82: 144.76 | G82: 0.0051944454 | H82: 130 | I82: 457 | J82: Sí | K82: 0.068254169 | L82: 0.14387525 | M82: -0.022775845 | N82: 0.11561488 | O82: 0.35663327 | P82: =IF(O82="","",O82*SQRT(25/252)) -> 0.11232892 | Q82: -0.18673599 | R82: 1.0594383 | S82: 0.44129665 | T82: -0.18538894 | U82: Movimiento medio
A83: ALPEK A | B83: Mexicana | C83: 14.64 | D83: -0.0108 | E83: 14.63 | F83: 14.64 | G83: 0.0006832935 | H83: 14760 | I83: 800 | J83: Sí | K83: 0.092936804 | L83: 0.1675933 | M83: 0.42441863 | N83: 0.39204538 | O83: 0.35754005 | P83: =IF(O83="","",O83*SQRT(25/252)) -> 0.11261453 | Q83: -0.21244022 | R83: -0.12979404 | S83: 0.35449101 | T83: -0.31269158 | U83: Movimiento medio
A84: UNH * | B84: Exterior (SIC) | C84: 6700 | D84: -0.0118 | E84: 6600.21 | F84: 6799.99 | G84: 0.029817465 | H84: 1600 | I84: 1400 | J84: Sí | K84: 0.0100834 | L84: -0.09849306 | M84: 0.26098834 | N84: 0.027220404 | O84: 0.35805667 | P84: =IF(O84="","",O84*SQRT(25/252)) -> 0.11277725 | Q84: -0.31144564 | R84: 0.18091627 | S84: 0.42932884 | T84: -0.55883137 | U84: Movimiento medio
A85: UBER * | B85: Exterior (SIC) | C85: 1249.97 | D85: 0.0154 | E85: 1247.03 | F85: 1257.49 | G85: 0.008352898 | H85: 5750 | I85: 4750 | J85: Sí | K85: 0.028862388 | L85: -0.05404874 | M85: -0.012919774 | N85: -0.31045586 | O85: 0.36181855 | P85: =IF(O85="","",O85*SQRT(25/252)) -> 0.11396213 | Q85: -0.37584381 | R85: 0.22315842 | S85: 0.34773605 | T85: -0.23521314 | U85: Movimiento medio
A86: CSCO * | B86: Exterior (SIC) | C86: 2109.2 | D86: -0.0037 | E86: 2061.81 | F86: 2163.19 | G86: 0.047990533 | H86: 16000 | I86: 15000 | J86: Sí | K86: 0.1322785 | L86: -0.015203509 | M86: 0.44936326 | N86: 0.68029697 | O86: 0.36212118 | P86: =IF(O86="","",O86*SQRT(25/252)) -> 0.11405745 | Q86: -0.19131725 | R86: 0.36249239 | S86: 0.44976637 | T86: -0.16558896 | U86: Movimiento medio
... A105: NU N | B105: Exterior (SIC) | C105: 281.78 | D105: 0.0064 | E105: 281.02 | F105: 282 | G105: 0.0034812262 | H105: 12800 | I105: 4 | J105: Sí | K105: 0.097362733 | L105: 0.15339073 | M105: 0.072909631 | N105: 0.0032259431 | O105: 0.42845294 | P105: =IF(O105="","",O105*SQRT(25/252)) -> 0.13494999 | Q105: -0.37576469 | R105: 0.79285032 | S105: 0.35129967 | T105: -0.34878485 | U105: Mayor movimiento
A106: LUV * | B106: Exterior (SIC) | C106: 750.04 | D106: 0 | H106: 0 | I106: 0 | J106: Sin contraparte | K106: 0.13298004 | L106: -0.12344917 | M106: 0.065930941 | N106: 0.26992027 | O106: 0.44368823 | P106: =IF(O106="","",O106*SQRT(25/252)) -> 0.13974866 | Q106: -0.31971773 | R106: 0.71268553 | S106: 0.4289608 | T106: -0.25737293 | U106: Mayor movimiento
A107: ZM * | B107: Exterior (SIC) | C107: 1710 | D107: 0.0106 | E107: 1672.81 | F107: 1745.77 | G107: 0.042684389 | H107: 800 | I107: 800 | J107: Sí | K107: 0.042651683 | L107: 0.077195675 | M107: 0.15670419 | N107: 0.16334293 | O107: 0.44965075 | P107: =IF(O107="","",O107*SQRT(25/252)) -> 0.14162668 | Q107: -0.24777604 | R107: 0.19300193 | S107: 0.33899085 | T107: -0.23302308 | U107: Mayor movimiento
A108: PYPL * | B108: Exterior (SIC) | C108: 990 | D108: 0 | E108: 971.72 | F108: 998.99 | G108: 0.027675305 | H108: 5415 | I108: 8000 | J108: Sí | K108: 0.11051668 | L108: 0.20893283 | M108: 0.22831641 | N108: -0.27596185 | O108: 0.45477051 | P108: =IF(O108="","",O108*SQRT(25/252)) -> 0.14323925 | Q108: -0.51893168 | R108: -0.04520028 | S108: 0.4051552 | T108: -0.36143537 | U108: Mayor movimiento
A109: TSLA * | B109: Exterior (SIC) | C109: 6733.21 | D109: -0.0078 | E109: 6766.88 | F109: 6789.99 | G109: 0.0034093415 | H109: 400 | I109: 200 | J109: Sí | K109: 0.078077455 | L109: -0.06238986 | M109: 0.11200637 | N109: -0.15571016 | O109: 0.46667549 | P109: =IF(O109="","",O109*SQRT(25/252)) -> 0.14698896 | Q109: -0.4094749 | R109: 1.0091089 | S109: 0.69497041 | T109: -0.46194067 | U109: Mayor movimiento
A110: VOLAR A | B110: Mexicana | C110: 11.49 | D110: -0.0043 | E110: 11.48 | F110: 11.51 | G110: 0.0026098304 | H110: 419 | I110: 7505 | J110: Sí | K110: -0.0069084563 | L110: -0.21286788 | M110: -0.14179102 | N110: -0.091627161 | O110: 0.47002226 | P110: =IF(O110="","",O110*SQRT(25/252)) -> 0.1480431 | Q110: -0.41249997 | R110: 1.2009045 | S110: 0.49213677 | T110: -0.36902655 | U110: Mayor movimiento
A111: XYZ * | B111: Exterior (SIC) | C111: 1367.58 | D111: 0 | E111: 1318.91 | F111: 1374.99 | G111: 0.041634805 | H111: 2000 | I111: 1500 | J111: Sí | K111: -0.0056062731 | L111: -0.015189188 | M111: 0.22071215 | N111: -0.078621447 | O111: 0.47649271 | P111: =IF(O111="","",O111*SQRT(25/252)) -> 0.1500811 | Q111: -0.43412076 | R111: 0.48566376 | S111: 0.62487038 | T111: -0.41071499 | U111: Mayor movimiento
A112: FCX * | B112: Exterior (SIC) | C112: 1284.9 | D112: -0.0054 | E112: 1275.01 | F112: 1299.99 | G112: 0.019401942 | H112: 1200 | I112: 1200 | J112: Sí | K112: -0.015832979 | L112: 0.17864955 | M112: 0.09936159 | N112: 0.71849032 | O112: 0.4782983 | P112: =IF(O112="","",O112*SQRT(25/252)) -> 0.1506498 | Q112: -0.21867512 | R112: 1.5251834 | S112: 0.32550847 | T112: -0.23052349 | U112: Mayor movimiento
A113: CRM * | B113: Exterior (SIC) | C113: 4075 | D113: 0.0037 | E113: 3940.61 | F113: 4053.64 | G113: 0.028277825 | H113: 1050 | I113: 950 | J113: Sí | K113: -0.029698945 | L113: 0.39860498 | M113: 0.34746706 | N113: -0.082636482 | O113: 0.47836442 | P113: =IF(O113="","",O113*SQRT(25/252)) -> 0.15067063 | Q113: -0.45933613 | R113: -0.33794718 | S113: 0.5638655 | T113: -0.33383347 | U113: Mayor movimiento
A114: B N | B114: Exterior (SIC) | C114: 710 | D114: 0 | E114: 705.01 | F114: 733.59 | G114: 0.039733074 | H114: 16400 | I114: 20500 | J114: Sí | K114: -0.063300291 | L114: 0.10212293 | M114: -0.038183019 | N114: 0.1836569 | O114: 0.47890473 | P114: =IF(O114="","",O114*SQRT(25/252)) -> 0.15084081 | Q114: -0.32601497 | R114: 1.434939 | S114: 0.44573442 | T114: -0.19579207 | U114: Mayor movimiento
A115: AVGO * | B115: Exterior (SIC) | C115: 6779.99 | D115: 0.0003 | E115: 6768 | F115: 6780 | G115: 0.0017714792 | H115: 7 | I115: 100 | J115: Sí | K115: 0.088892603 | L115: -0.043542732 | M115: 0.085277525 | N115: 0.093689253 | O115: 0.48392426 | P115: =IF(O115="","",O115*SQRT(25/252)) -> 0.15242182 | Q115: -0.30381671 | R115: 0.71553926 | S115: 0.50928658 | T115: -0.28313549 | U115: Mayor movimiento
A116: AAL * | B116: Exterior (SIC) | C116: 231.56 | D116: -0.0012 | E116: 228.01 | F116: 237.59 | G116: 0.041151203 | H116: 47900 | I116: 78900 | J116: Sí | K116: 0.044993519 | L116: -0.23081365 | M116: 0.15270995 | N116: 0.069413183 | O116: 0.48737426 | P116: =IF(O116="","",O116*SQRT(25/252)) -> 0.15350846 | Q116: -0.37291849 | R116: 0.77788075 | S116: 0.48623896 | T116: -0.38123894 | U116: Mayor movimiento
A117: RCL * | B117: Exterior (SIC) | C117: 5104 | D117: -0.0089 | E117: 4993.81 | F117: 5237.39 | G117: 0.047615138 | H117: 2400 | I117: 2800 | J117: Sí | K117: 0.15941625 | L117: 0.017552506 | M117: 0.063541196 | N117: -0.10530555 | O117: 0.48900898 | P117: =IF(O117="","",O117*SQRT(25/252)) -> 0.15402335 | Q117: -0.33564763 | R117: 0.54609814 | S117: 0.36507683 | T117: -0.29310943 | U117: Mayor movimiento
A118: UAL * | B118: Exterior (SIC) | C118: 1931.83 | D118: -0.0246 | E118: 1930.01 | F118: 1990.79 | G118: 0.031003877 | H118: 5500 | I118: 5500 | J118: Sí | K118: 0.063046348 | L118: -0.12862386 | M118: 0.1300411 | N118: 0.086468474 | O118: 0.49472446 | P118: =IF(O118="","",O118*SQRT(25/252)) -> 0.15582356 | Q118: -0.27138361 | R118: 0.86070956 | S118: 0.6116648 | T118: -0.40103477 | U118: Mayor movimiento
... A124: FSLR * | B124: Exterior (SIC) | C124: 3240 | D124: 0.0144 | E124: 3225.01 | F124: 3315.19 | G124: 0.027577138 | H124: 100 | I124: 400 | J124: Sí | K124: -0.069174505 | L124: -0.19994338 | M124: -0.071046797 | N124: -0.23502163 | O124: 0.55805826 | P124: =IF(O124="","",O124*SQRT(25/252)) -> 0.17577183 | Q124: -0.45144087 | R124: 0.7079592 | S124: 0.70000674 | T124: -0.30811157 | U124: Mayor movimiento
A125: AA1 * | B125: Exterior (SIC) | C125: 765 | D125: 0.0017 | E125: 758 | H125: 1 | I125: 0 | J125: Sin contraparte | K125: -0.11498239 | L125: -0.10903299 | M125: -0.40398162 | N125: 0.1744484 | O125: 0.55860727 | P125: =IF(O125="","",O125*SQRT(25/252)) -> 0.17594475 | Q125: -0.48577156 | R125: 1.0082441 | S125: 0.48837459 | T125: -0.4113405 | U125: Mayor movimiento
A126: PINS * | B126: Exterior (SIC) | C126: 370.5 | D126: 0 | E126: 359.61 | F126: 369.99 | G126: 0.028453947 | H126: 8200 | I126: 16400 | J126: Sí | K126: 0.17862243 | L126: -0.07756463 | M126: 0.16402176 | N126: -0.36706979 | O126: 0.55872097 | P126: =IF(O126="","",O126*SQRT(25/252)) -> 0.17598057 | Q126: -0.59121615 | R126: -0.25055122 | S126: 0.36865458 | T126: -0.45384876 | U126: Mayor movimiento
A127: ORCL * | B127: Exterior (SIC) | C127: 2560 | D127: -0.0093 | E127: 2560.02 | F127: 2584.99 | G127: 0.0097064923 | H127: 3400 | I127: 1600 | J127: Sí | K127: -0.066475232 | L127: 0.034409279 | M127: 0.064511806 | N127: -0.50491376 | O127: 0.56856345 | P127: =IF(O127="","",O127*SQRT(25/252)) -> 0.17908065 | Q127: -0.64800681 | R127: 0.40754426 | S127: 0.43775506 | T127: -0.43587674 | U127: Mayor movimiento
A128: SOFI * | B128: Exterior (SIC) | C128: 278 | D128: -0.0107 | E128: 278.03 | F128: 284.99 | G128: 0.024723811 | H128: 13600 | I128: 27200 | J128: Sí | K128: -0.059374261 | L128: -0.16310062 | M128: -0.028907732 | N128: -0.46582009 | O128: 0.57476779 | P128: =IF(O128="","",O128*SQRT(25/252)) -> 0.18103484 | Q128: -0.55411579 | R128: 0.86328678 | S128: 0.78236621 | T128: -0.35561684 | U128: Mayor movimiento
A129: PLTR * | B129: Exterior (SIC) | C129: 3604.68 | D129: 0.0329 | E129: 3590.01 | F129: 3618.98 | G129: 0.0080371869 | H129: 2550 | I129: 1950 | J129: Sí | K129: 0.24298594 | L129: 0.60243788 | M129: 0.56519398 | N129: 0.066675061 | O129: 0.5965703 | P129: =IF(O129="","",O129*SQRT(25/252)) -> 0.18790198 | Q129: -0.50828413 | R129: 0.38198402 | S129: 0.83940005 | T129: -0.32048286 | U129: Mayor movimiento
A130: SHOP N | B130: Exterior (SIC) | C130: 3030.5 | D130: 0.0135 | E130: 2963.61 | F130: 3049.99 | G130: 0.028728216 | H130: 800 | I130: 1200 | J130: Sí | K130: 0.39886046 | L130: 0.39551642 | M130: 0.52968858 | N130: 0.014086746 | O130: 0.59974382 | P130: =IF(O130="","",O130*SQRT(25/252)) -> 0.18890155 | Q130: -0.50168387 | R130: 0.36350225 | S130: 0.53520388 | T130: -0.36550059 | U130: Mayor movimiento
A131: AMAT * | B131: Exterior (SIC) | C131: 9200 | D131: -0.0139 | E131: 9287.61 | F131: 9500 | G131: 0.022609581 | H131: 4328 | I131: 1 | J131: Sí | K131: 0.18339742 | L131: -0.11115699 | M131: 0.35495605 | N131: 1.4317711 | O131: 0.60060569 | P131: =IF(O131="","",O131*SQRT(25/252)) -> 0.18917301 | Q131: -0.43558081 | R131: 1.3049871 | S131: 0.68984924 | T131: -0.27025623 | U131: Mayor movimiento
A132: AFRM * | B132: Exterior (SIC) | C132: 1353.92 | D132: 0 | E132: 1339.21 | F132: 1403.99 | G132: 0.047229513 | H132: 1200 | I132: 800 | J132: Sí | K132: 0.17491766 | L132: -0.074542329 | M132: 0.58351163 | N132: -0.036709329 | O132: 0.60252562 | P132: =IF(O132="","",O132*SQRT(25/252)) -> 0.18977773 | Q132: -0.48987799 | R132: 0.51500269 | S132: 1.1586307 | T132: -0.45702457 | U132: Mayor movimiento
A133: TWLO * | B133: Exterior (SIC) | C133: 4924 | D133: 0 | E133: 4951.81 | F133: 5187.59 | G133: 0.046507683 | H133: 500 | I133: 400 | J133: Sí | K133: 0.30180299 | L133: 0.32904339 | M133: 1.2964032 | N133: 1.5358308 | O133: 0.61765526 | P133: =IF(O133="","",O133*SQRT(25/252)) -> 0.19454312 | Q133: -0.28386094 | R133: 0.064660207 | S133: 0.67373792 | T133: -0.36553393 | U133: Mayor movimiento
A134: NVAX * | B134: Exterior (SIC) | C134: 195 | D134: -0.0351 | E134: 196.01 | F134: 200.49 | G134: 0.02259773 | H134: 3500 | I134: 4500 | J134: Sí | K134: 0.17107205 | L134: 0.19204227 | M134: 0.30916576 | N134: 0.15367943 | O134: 0.65675856 | P134: =IF(O134="","",O134*SQRT(25/252)) -> 0.2068595 | Q134: -0.33871212 | R134: 0.97861104 | S134: 4.0708047 | T134: -0.41055214 | U134: Mayor movimiento
A135: UPST * | B135: Exterior (SIC) | C135: 425 | D135: -0.0177 | E135: 420.01 | F135: 440.99 | G135: 0.04873403 | H135: 8000 | I135: 3200 | J135: Sí | K135: -0.030481055 | L135: -0.2607981 | M135: -0.11241092 | N135: -0.55324342 | O135: 0.66352189 | P135: =IF(O135="","",O135*SQRT(25/252)) -> 0.20898975 | Q135: -0.57921577 | R135: 0.54092231 | S135: 1.1253758 | T135: -0.49143134 | U135: Mayor movimiento
A136: MFRISCO A-1 | B136: Mexicana | C136: 18.97 | D136: 0.0037 | E136: 18.71 | F136: 18.94 | G136: 0.012217795 | H136: 150 | I136: 210 | J136: Sí | K136: -0.18097749 | L136: 0.34296028 | M136: 0.97872353 | N136: 1.2627737 | O136: 0.67003499 | P136: =IF(O136="","",O136*SQRT(25/252)) -> 0.21104118 | Q136: -0.41617744 | R136: 0.9076416 | S136: 1.7426272 | T136: -0.35530086 | U136: Mayor movimiento
A137: RIVN * | B137: Exterior (SIC) | C137: 256.5 | D137: -0.0037 | E137: 253.81 | F137: 257.66 | G137: 0.015054646 | H137: 33400 | I137: 22600 | J137: Sí | K137: -0.063168678 | L137: -0.17295513 | M137: -0.046403298 | N137: 0.042724903 | O137: 0.69455293 | P137: =IF(O137="","",O137*SQRT(25/252)) -> 0.21876361 | Q137: -0.44840748 | R137: 1.1641553 | S137: 0.59188563 | T137: -0.3710934 | U137: Mayor movimiento
... A148: BYND * | B148: Exterior (SIC) | C148: 139.39 | D148: 0.0174 | E148: 138 | F148: 139.99 | G148: 0.014317062 | H148: 2 | I148: 2000 | J148: Sí | K148: -0.25712022 | L148: -0.60328981 | M148: -0.56398126 | N148: -0.88582698 | O148: 1.8453512 | P148: =IF(O148="","",O148*SQRT(25/252)) -> 0.58123099 | Q148: -0.93147474 | R148: -0.073726642 | S148: 0.67962571 | T148: -0.801353 | U148: Mayor movimiento
A149: LASITE B-1 | B149: Mexicana | C149: 3.12 | D149: 0 | H149: 0 | I149: 0 | J149: Sin contraparte | P149: =IF(O149="","",O149*SQRT(25/252)) | U149: Sin historial

Sheet Correlaciones
A1: Correlaciones de rendimientos diarios (último año, en pesos)
A2: Cerca de 1 = se mueven casi igual (no se diversifican entre sí). Cerca de 0 = independientes.
B4: BRKB * | C4: SIGMAF A | D4: LIVEPOL C-1 | E4: GRUMA B | F4: KO * | G4: FIBRAMQ 12 | H4: VESTA * | I4: MCD * | J4: JNJ * | K4: PG * | L4: WALMEX * | M4: AGNC * | N4: PFE * | O4: AC * | P4: COST * | Q4: ACTINVR B | R4: PEP * | S4: CHDRAUI B | T4: BAC * | U4: GFINBUR O | V4: FUNO 11 | W4: FEMSA UBD | X4: JPM * | Y4: V * | Z4: KIMBER A | AA4: KOF UBL | AB4: MA * | AC4: FIBRAPL 14 | AD4: AMX B | AE4: ASUR B | AF4: PINFRA * | AG4: T * | AH4: VZ * | AI4: CVX * | AJ4: ALSEA * | AK4: GFNORTE O | AL4: AAPL * | AM4: BOLSA A | AN4: HD * | AO4: ABBV * | AP4: DIS * | AQ4: XOM * | AR4: WFC * | AS4: BBAJIO O | AT4: AXP * | AU4: WMT * | AV4: BIMBO A | AW4: GCC * | AX4: BMY * | AY4: SBUX * | AZ4: OMA B | BA4: FDX * | BB4: C * | BC4: Q * | BD4: R A | BE4: MRK * | BF4: MEGA CPO | BG4: TMO * | BH4: LAB B | BI4: CUERVO * | BJ4: SITES1 A-1 | BK4: GAP B | BL4: TX * | BM4: TGT * | BN4: CVS * | BO4: GOOGL * | BP4: MSFT * | BQ4: CEMEX CPO | BR4: WYNN * | BS4: FANG * | BT4: GE * | BU4: GENTERA * | BV4: AMZN * | BW4: LVS * | BX4: LLY * | BY4: GM * | BZ4: BA * | CA4: GCARSO A1 | CB4: ALPEK A | CC4: UNH * | CD4: UBER * | CE4: CSCO * | CF4: DVN * | CG4: ABNB * | CH4: GMEXICO B | CI4: OXY1 * | CJ4: NFLX * | CK4: NKE * | CL4: F * | CM4: NVDA * | CN4: ORBIA * | CO4: TLEVISA CPO | CP4: GME * | CQ4: DAL * | CR4: TSM N | CS4: CAT * | CT4: ROKU * | CU4: BABA N | CV4: META * | CW4: MELI N | CX4: NU N | CY4: LUV * | CZ4: ZM * | DA4: PYPL * | DB4: TSLA * | DC4: VOLAR A | DD4: XYZ * | DE4: FCX * | DF4: CRM * | DG4: B N | DH4: AVGO * | DI4: AAL * | DJ4: RCL * | DK4: UAL * | DL4: PE&OLES * | DM4: CCL1 N | DN4: ETSY * | DO4: QCOM * | DP4: NCLH N | DQ4: FSLR * | DR4: AA1 * | DS4: PINS * | DT4: ORCL * | DU4: SOFI * | DV4: PLTR * | DW4: SHOP N | DX4: AMAT * | DY4: AFRM * | DZ4: TWLO * | EA4: NVAX * | EB4: UPST * | EC4: MFRISCO A-1 | ED4: RIVN * | EE4: AMD * | EF4: CLF * | EG4: INTC * | EH4: FUBO * | EI4: MU * | EJ4: LCID * | EK4: MARA * | EL4: RIOT * | EM4: SPCE * | EN4: MRNA * | EO4: BYND *
A5: BRKB * | B5: 1 | C5: -0.04 | D5: -0.11 | E5: 0.06 | F5: 0.43 | G5: -0.11 | H5: -0.02 | I5: 0.46 | J5: 0.32 | K5: 0.44 | L5: 0.07 | M5: 0.25 | N5: 0.33 | O5: 0.14 | P5: 0.38 | Q5: 0.03 | R5: 0.37 | S5: 0 | T5: 0.25 | U5: 0.07 | V5: 0.03 | W5: 0.02 | X5: 0.33 | Y5: 0.45 | Z5: 0.04 | AA5: 0.06 | AB5: 0.49 | AC5: 0.04 | AD5: 0.06 | AE5: 0 | AF5: -0.14 | AG5: 0.26 | AH5: 0.31 | AI5: 0.17 | AJ5: 0.03 | AK5: -0.03 | AL5: 0.28 | AM5: 0.04 | AN5: 0.36 | AO5: 0.26 | AP5: 0.23 | AQ5: 0.12 | AR5: 0.23 | AS5: -0.13 | AT5: 0.29 | AU5: 0.3 | AV5: 0.07 | AW5: -0.01 | AX5: 0.34 | AY5: 0.27 | AZ5: 0.03 | BA5: 0.19 | BB5: 0.16 | BC5: 0.1 | BD5: 0.01 | BE5: 0.3 | BF5: 0.04 | BG5: 0.21 | BH5: 0.04 | BI5: 0.1 | BJ5: -0.03 | BK5: 0.02 | BL5: 0.08 | BM5: 0.17 | BN5: 0.28 | BO5: 0.14 | BP5: 0.12 | BQ5: -0.05 | BR5: 0.22 | BS5: 0.02 | BT5: 0.18 | BU5: -0.07 | BV5: 0.13 | BW5: 0.16 | BX5: 0.28 | BY5: 0.16 | BZ5: 0.21 | CA5: 0.04 | CB5: 0.05 | CC5: 0.22 | CD5: 0.18 | CE5: 0.07 | CF5: 0.08 | CG5: 0.24 | CH5: -0.08 | CI5: 0.09 | CJ5: 0.26 | CK5: 0.32 | CL5: 0.11 | CM5: -0.14 | CN5: -0.04 | CO5: 0.01 | CP5: 0.17 | CQ5: 0.27 | CR5: -0.06 | CS5: 0 | CT5: 0.1 | CU5: 0 | CV5: 0.07 | CW5: 0.11 | CX5: 0.07 | CY5: 0.22 | CZ5: 0.1 | DA5: 0.12 | DB5: 0 | DC5: -0.02 | DD5: 0.14 | DE5: -0.09 | DF5: 0.17 | DG5: 0.01 | DH5: -0.05 | DI5: 0.27 | DJ5: 0.22 | DK5: 0.23 | DL5: -0.12 | DM5: 0.27 | DN5: 0.19 | DO5: 0.06 | DP5: 0.25 | DQ5: 0.01 | DR5: -0.06 | DS5: 0.11 | DT5: -0.13 | DU5: -0.01 | DV5: -0.02 | DW5: 0.1 | DX5: -0.15 | DY5: 0.15 | DZ5: 0.02 | EA5: 0 | EB5: 0.05 | EC5: -0.12 | ED5: 0.05 | EE5: -0.09 | EF5: 0.05 | EG5: -0.06 | EH5: 0.07 | EI5: -0.2 | EJ5: 0.06 | EK5: -0.03 | EL5: -0.11 | EM5: -0.07 | EN5: 0.02 | EO5: 0
A6: SIGMAF A | B6: -0.04 | C6: 1 | D6: 0.08 | E6: 0.09 | F6: 0.01 | G6: 0.02 | H6: 0.14 | I6: 0.08 | J6: 0.04 | K6: -0.08 | L6: 0.31 | M6: 0.07 | N6: -0.01 | O6: 0.18 | P6: 0.07 | Q6: 0 | R6: 0.03 | S6: 0.06 | T6: -0.01 | U6: 0.13 | V6: 0.16 | W6: 0.14 | X6: 0.03 | Y6: 0.1 | Z6: 0.21 | AA6: 0.09 | AB6: 0.03 | AC6: 0.04 | AD6: 0.2 | AE6: 0.2 | AF6: 0.24 | AG6: -0.02 | AH6: 0 | AI6: -0.02 | AJ6: 0.11 | AK6: 0.22 | AL6: -0.01 | AM6: 0.08 | AN6: 0.01 | AO6: 0.03 | AP6: -0.06 | AQ6: 0.01 | AR6: 0 | AS6: 0.12 | AT6: 0 | AU6: 0.05 | AV6: 0.28 | AW6: 0.19 | AX6: -0.01 | AY6: 0.12 | AZ6: 0.08 | BA6: 0.06 | BB6: -0.07 | BC6: 0.03 | BD6: 0.17 | BE6: 0.07 | BF6: 0 | BG6: 0.01 | BH6: 0.05 | BI6: -0.01 | BJ6: 0.03 | BK6: 0.06 | BL6: -0.01 | BM6: 0.03 | BN6: 0.03 | BO6: -0.02 | BP6: -0.07 | BQ6: 0.19 | BR6: -0.07 | BS6: -0.03 | BT6: 0.04 | BU6: 0.06 | BV6: -0.02 | BW6: -0.04 | BX6: -0.07 | BY6: -0.03 | BZ6: 0.12 | CA6: 0.16 | CB6: 0.1 | CC6: -0.02 | CD6: -0.04 | CE6: -0.03 | CF6: -0.04 | CG6: -0.03 | CH6: 0.13 | CI6: -0.06 | CJ6: -0.01 | CK6: -0.07 | CL6: 0 | CM6: -0.07 | CN6: 0.19 | CO6: 0.07 | CP6: 0.02 | CQ6: -0.03 | CR6: -0.06 | CS6: 0.05 | CT6: 0.03 | CU6: 0 | CV6: -0.06 | CW6: 0.02 | CX6: 0.01 | CY6: -0.01 | CZ6: -0.14 | DA6: -0.01 | DB6: 0.05 | DC6: 0.04 | DD6: -0.04 | DE6: 0.07 | DF6: -0.09 | DG6: 0.06 | DH6: 0.06 | DI6: -0.03 | DJ6: -0.06 | DK6: 0 | DL6: 0.18 | DM6: -0.01 | DN6: 0.09 | DO6: 0.15 | DP6: -0.02 | DQ6: 0.02 | DR6: 0.06 | DS6: -0.07 | DT6: -0.03 | DU6: -0.06 | DV6: -0.06 | DW6: -0.12 | DX6: 0.03 | DY6: 0.01 | DZ6: -0.11 | EA6: 0.02 | EB6: -0.08 | EC6: 0.04 | ED6: 0.13 | EE6: 0.03 | EF6: 0.11 | EG6: 0.07 | EH6: 0 | EI6: 0.02 | EJ6: -0.02 | EK6: 0.04 | EL6: 0.02 | EM6: -0.06 | EN6: -0.01 | EO6: 0.04
A7: LIVEPOL C-1 | B7: -0.11 | C7: 0.08 | D7: 1 | E7: 0.13 | F7: -0.09 | G7: 0.12 | H7: 0.15 | I7: -0.02 | J7: -0.03 | K7: -0.05 | L7: 0.11 | M7: -0.07 | N7: 0.18 | O7: 0.03 | P7: 0 | Q7: 0.02 | R7: -0.16 | S7: 0.11 | T7: 0.06 | U7: 0.12 | V7: 0.04 | W7: -0.04 | X7: 0.02 | Y7: 0 | Z7: 0.09 | AA7: 0.09 | AB7: 0.03 | AC7: 0.08 | AD7: 0.02 | AE7: 0.19 | AF7: 0.17 | AG7: -0.02 | AH7: -0.03 | AI7: -0.11 | AJ7: 0.21 | AK7: 0.03 | AL7: 0.05 | AM7: 0.09 | AN7: -0.05 | AO7: 0.02 | AP7: 0.03 | AQ7: -0.1 | AR7: 0.07 | AS7: 0.12 | AT7: 0.01 | AU7: -0.04 | AV7: 0.1 | AW7: 0.04 | AX7: 0.1 | AY7: -0.03 | AZ7: 0.2 | BA7: -0.03 | BB7: 0.05 | BC7: 0.06 | BD7: 0.16 | BE7: -0.02 | BF7: 0.13 | BG7: 0.04 | BH7: 0.11 | BI7: 0.12 | BJ7: 0.07 | BK7: 0.22 | BL7: -0.05 | BM7: 0.05 | BN7: -0.12 | BO7: 0.08 | BP7: 0.08 | BQ7: 0.1 | BR7: 0.04 | BS7: -0.06 | BT7: 0.05 | BU7: 0.1 | BV7: 0.04 | BW7: 0.03 | BX7: 0.09 | BY7: -0.05 | BZ7: -0.01 | CA7: 0.15 | CB7: -0.06 | CC7: -0.01 | CD7: 0.04 | CE7: 0.05 | CF7: -0.04 | CG7: 0.11 | CH7: 0.04 | CI7: -0.07 | CJ7: 0.05 | CK7: 0.01 | CL7: 0 | CM7: 0.06 | CN7: 0.2 | CO7: 0 | CP7: 0.05 | CQ7: 0.05 | CR7: -0.01 | CS7: 0.03 | CT7: 0.07 | CU7: 0.08 | CV7: 0.02 | CW7: -0.01 | CX7: 0 | CY7: 0.02 | CZ7: 0.12 | DA7: 0.17 | DB7: 0.09 | DC7: 0.18 | DD7: 0.19 | DE7: 0.05 | DF7: 0.08 | DG7: 0.08 | DH7: 0.05 | DI7: 0.03 | DJ7: 0 | DK7: 0.02 | DL7: 0.2 | DM7: 0.02 | DN7: -0.06 | DO7: 0.07 | DP7: 0.02 | DQ7: -0.01 | DR7: -0.02 | DS7: 0.03 | DT7: 0.04 | DU7: 0.11 | DV7: 0.06 | DW7: 0.07 | DX7: 0.06 | DY7: 0.03 | DZ7: 0.14 | EA7: 0.05 | EB7: 0.05 | EC7: 0 | ED7: 0.1 | EE7: 0.04 | EF7: 0.09 | EG7: -0.01 | EH7: 0.07 | EI7: 0.06 | EJ7: 0.06 | EK7: 0.04 | EL7: 0.09 | EM7: 0.02 | EN7: 0.01 | EO7: -0.08
A8: GRUMA B | B8: 0.06 | C8: 0.09 | D8: 0.13 | E8: 1 | F8: 0.13 | G8: 0.05 | H8: 0.22 | I8: 0.16 | J8: 0.05 | K8: 0.08 | L8: 0.31 | M8: 0.19 | N8: 0.18 | O8: 0.36 | P8: 0.15 | Q8: 0.07 | R8: 0.09 | S8: 0.24 | T8: 0.13 | U8: 0.31 | V8: 0.31 | W8: 0.27 | X8: 0.14 | Y8: 0.04 | Z8: 0.18 | AA8: 0.21 | AB8: 0.05 | AC8: 0.31 | AD8: 0.24 | AE8: 0.19 | AF8: 0.34 | AG8: 0.08 | AH8: 0.08 | AI8: 0.06 | AJ8: 0.1 | AK8: 0.3 | AL8: 0.14 | AM8: 0.16 | AN8: 0.12 | AO8: 0.1 | AP8: 0.13 | AQ8: 0.1 | AR8: 0.08 | AS8: 0.19 | AT8: 0.12 | AU8: 0.08 | AV8: 0.45 | AW8: 0.16 | AX8: 0.13 | AY8: 0.1 | AZ8: 0.23 | BA8: 0.18 | BB8: 0.12 | BC8: 0.22 | BD8: 0.23 | BE8: 0.08 | BF8: 0.32 | BG8: -0.01 | BH8: 0.22 | BI8: 0.2 | BJ8: 0.06 | BK8: 0.18 | BL8: 0.1 | BM8: 0.22 | BN8: 0.08 | BO8: 0.08 | BP8: 0.07 | BQ8: 0.15 | BR8: 0.07 | BS8: 0.03 | BT8: 0.05 | BU8: 0.17 | BV8: -0.03 | BW8: 0.13 | BX8: 0.02 | BY8: 0.05 | BZ8: 0.13 | CA8: 0.26 | CB8: 0.02 | CC8: 0.06 | CD8: 0.05 | CE8: 0 | CF8: 0.03 | CG8: 0.03 | CH8: 0.18 | CI8: -0.05 | CJ8: 0.06 | CK8: 0.12 | CL8: 0 | CM8: -0.03 | CN8: 0.16 | CO8: 0.14 | CP8: 0.03 | CQ8: 0.18 | CR8: 0.08 | CS8: 0.07 | CT8: 0.15 | CU8: 0.01 | CV8: -0.01 | CW8: 0.1 | CX8: 0.06 | CY8: 0.19 | CZ8: 0.05 | DA8: -0.03 | DB8: 0.19 | DC8: 0.17 | DD8: 0.12 | DE8: 0.15 | DF8: 0.04 | DG8: 0.09 | DH8: 0.1 | DI8: 0.2 | DJ8: 0.08 | DK8: 0.14 | DL8: 0.11 | DM8: 0.13 | DN8: -0.02 | DO8: 0.14 | DP8: 0.05 | DQ8: 0.08 | DR8: 0.12 | DS8: -0.02 | DT8: 0.05 | DU8: 0.13 | DV8: 0.09 | DW8: 0.02 | DX8: 0.05 | DY8: 0.09 | DZ8: 0.03 | EA8: 0.05 | EB8: 0.12 | EC8: 0.09 | ED8: 0.19 | EE8: 0.07 | EF8: 0.01 | EG8: 0.05 | EH8: -0.02 | EI8: -0.02 | EJ8: 0.17 | EK8: 0.06 | EL8: 0.08 | EM8: 0.04 | EN8: 0.03 | EO8: 0.02
A9: KO * | B9: 0.43 | C9: 0.01 | D9: -0.09 | E9: 0.13 | F9: 1 | G9: -0.03 | H9: 0.08 | I9: 0.57 | J9: 0.46 | K9: 0.58 | L9: 0.16 | M9: 0.29 | N9: 0.3 | O9: 0.07 | P9: 0.48 | Q9: -0.11 | R9: 0.65 | S9: 0.1 | T9: 0.05 | U9: 0.06 | V9: 0.04 | W9: 0.13 | X9: 0.03 | Y9: 0.3 | Z9: 0.1 | AA9: 0.27 | AB9: 0.32 | AC9: -0.03 | AD9: 0.13 | AE9: -0.07 | AF9: -0.1 | AG9: 0.39 | AH9: 0.41 | AI9: 0.23 | AJ9: -0.03 | AK9: -0.04 | AL9: 0.26 | AM9: 0 | AN9: 0.39 | AO9: 0.39 | AP9: 0.28 | AQ9: 0.25 | AR9: 0.05 | AS9: 0 | AT9: 0.08 | AU9: 0.4 | AV9: 0.08 | AW9: -0.04 | AX9: 0.36 | AY9: 0.34 | AZ9: -0.02 | BA9: 0.21 | BB9: -0.08 | BC9: 0.07 | BD9: 0.01 | BE9: 0.41 | BF9: 0.03 | BG9: 0.1 | BH9: -0.01 | BI9: -0.08 | BJ9: -0.09 | BK9: -0.05 | BL9: 0.11 | BM9: 0.35 | BN9: 0.2 | BO9: 0.08 | BP9: -0.01 | BQ9: -0.04 | BR9: 0.14 | BS9: 0.14 | BT9: 0.08 | BU9: -0.06 | BV9: 0.02 | BW9: 0.16 | BX9: 0.22 | BY9: 0.24 | BZ9: 0.08 | CA9: 0.03 | CB9: 0.07 | CC9: 0.07 | CD9: 0.16 | CE9: -0.08 | CF9: 0.23 | CG9: 0.16 | CH9: -0.07 | CI9: 0.18 | CJ9: 0.29 | CK9: 0.26 | CL9: 0.14 | CM9: -0.18 | CN9: -0.09 | CO9: -0.02 | CP9: 0.11 | CQ9: 0.1 | CR9: -0.13 | CS9: -0.14 | CT9: -0.02 | CU9: 0 | CV9: -0.06 | CW9: 0.09 | CX9: 0.05 | CY9: 0.14 | CZ9: 0.02 | DA9: 0.06 | DB9: -0.08 | DC9: -0.09 | DD9: 0.03 | DE9: -0.11 | DF9: 0.07 | DG9: -0.07 | DH9: -0.16 | DI9: 0.1 | DJ9: 0.14 | DK9: 0.07 | DL9: -0.11 | DM9: 0.16 | DN9: 0.16 | DO9: -0.12 | DP9: 0.13 | DQ9: -0.11 | DR9: -0.09 | DS9: 0.04 | DT9: -0.26 | DU9: -0.12 | DV9: -0.09 | DW9: -0.04 | DX9: -0.19 | DY9: 0 | DZ9: -0.06 | EA9: 0.01 | EB9: -0.06 | EC9: -0.13 | ED9: -0.03 | EE9: -0.18 | EF9: -0.07 | EG9: -0.09 | EH9: 0.06 | EI9: -0.2 | EJ9: 0.02 | EK9: -0.05 | EL9: -0.16 | EM9: -0.08 | EN9: 0.08 | EO9: 0.09
A10: FIBRAMQ 12 | B10: -0.11 | C10: 0.02 | D10: 0.12 | E10: 0.05 | F10: -0.03 | G10: 1 | H10: 0.18 | I10: 0.01 | J10: -0.01 | K10: 0.01 | L10: -0.01 | M10: 0.05 | N10: 0.05 | O10: 0.12 | P10: -0.11 | Q10: 0.05 | R10: -0.03 | S10: -0.05 | T10: 0.01 | U10: 0.08 | V10: 0.14 | W10: 0.04 | X10: -0.03 | Y10: -0.05 | Z10: 0.22 | AA10: 0.08 | AB10: -0.01 | AC10: 0.16 | AD10: 0.04 | AE10: 0.22 | AF10: 0.19 | AG10: -0.08 | AH10: -0.09 | AI10: -0.06 | AJ10: 0.09 | AK10: 0.14 | AL10: -0.07 | AM10: 0.17 | AN10: -0.03 | AO10: 0.02 | AP10: 0.05 | AQ10: -0.02 | AR10: 0 | AS10: 0.16 | AT10: -0.05 | AU10: -0.02 | AV10: 0.05 | AW10: 0.11 | AX10: 0.05 | AY10: 0.03 | AZ10: 0.11 | BA10: 0.01 | BB10: 0.08 | BC10: 0.04 | BD10: 0.17 | BE10: -0.02 | BF10: 0.22 | BG10: -0.02 | BH10: 0.03 | BI10: 0.1 | BJ10: 0.06 | BK10: 0.17 | BL10: 0.08 | BM10: -0.08 | BN10: 0.01 | BO10: 0.07 | BP10: -0.03 | BQ10: 0.09 | BR10: 0 | BS10: 0 | BT10: 0.01 | BU10: -0.01 | BV10: 0.02 | BW10: 0.09 | BX10: 0 | BY10: 0.03 | BZ10: -0.09 | CA10: 0.13 | CB10: -0.01 | CC10: 0.03 | CD10: 0.02 | CE10: -0.02 | CF10: 0.02 | CG10: 0.05 | CH10: 0.17 | CI10: -0.02 | CJ10: 0.07 | CK10: -0.1 | CL10: 0.07 | CM10: -0.02 | CN10: 0.13 | CO10: -0.04 | CP10: 0.06 | CQ10: -0.05 | CR10: -0.01 | CS10: 0 | CT10: 0.15 | CU10: -0.03 | CV10: 0.01 | CW10: -0.02 | CX10: 0.08 | CY10: 0 | CZ10: -0.11 | DA10: -0.09 | DB10: 0.08 | DC10: 0.1 | DD10: 0.05 | DE10: 0.03 | DF10: 0.01 | DG10: 0.04 | DH10: -0.03 | DI10: 0 | DJ10: -0.04 | DK10: -0.06 | DL10: 0.17 | DM10: 0.04 | DN10: 0.03 | DO10: -0.04 | DP10: 0.01 | DQ10: -0.18 | DR10: 0.07 | DS10: -0.02 | DT10: -0.04 | DU10: 0.04 | DV10: 0.04 | DW10: -0.08 | DX10: 0.01 | DY10: -0.04 | DZ10: 0.04 | EA10: 0.04 | EB10: 0.02 | EC10: 0.15 | ED10: 0.07 | EE10: 0.03 | EF10: 0.08 | EG10: 0.05 | EH10: -0.07 | EI10: 0.01 | EJ10: 0.11 | EK10: 0.05 | EL10: 0.05 | EM10: -0.04 | EN10: 0.03 | EO10: 0.08
A11: VESTA * | B11: -0.02 | C11: 0.14 | D11: 0.15 | E11: 0.22 | F11: 0.08 | G11: 0.18 | H11: 1 | I11: 0.09 | J11: 0 | K11: 0.1 | L11: 0.21 | M11: 0.17 | N11: 0.11 | O11: 0.21 | P11: 0.01 | Q11: -0.02 | R11: 0.05 | S11: 0.25 | T11: 0.03 | U11: 0.3 | V11: 0.37 | W11: 0.15 | X11: 0.06 | Y11: -0.09 | Z11: 0.28 | AA11: 0.21 | AB11: -0.1 | AC11: 0.23 | AD11: 0.22 | AE11: 0.21 | AF11: 0.26 | AG11: -0.03 | AH11: 0 | AI11: -0.12 | AJ11: 0.27 | AK11: 0.26 | AL11: 0.01 | AM11: 0.17 | AN11: 0.14 | AO11: 0 | AP11: 0.02 | AQ11: -0.09 | AR11: -0.02 | AS11: 0.31 | AT11: 0 | AU11: 0.02 | AV11: 0.19 | AW11: 0.35 | AX11: 0.06 | AY11: 0 | AZ11: 0.28 | BA11: 0.08 | BB11: 0.03 | BC11: 0.16 | BD11: 0.24 | BE11: 0.09 | BF11: 0.24 | BG11: 0.03 | BH11: 0.3 | BI11: 0.14 | BJ11: -0.08 | BK11: 0.19 | BL11: 0.13 | BM11: 0.05 | BN11: -0.08 | BO11: 0.18 | BP11: 0.03 | BQ11: 0.27 | BR11: 0.12 | BS11: -0.1 | BT11: 0.19 | BU11: 0.18 | BV11: 0.06 | BW11: 0.1 | BX11: 0.05 | BY11: 0.12 | BZ11: 0.13 | CA11: 0.28 | CB11: -0.1 | CC11: -0.06 | CD11: 0.05 | CE11: 0.02 | CF11: -0.13 | CG11: 0.11 | CH11: 0.26 | CI11: -0.13 | CJ11: -0.01 | CK11: 0.01 | CL11: 0.22 | CM11: 0.03 | CN11: 0.22 | CO11: 0.13 | CP11: 0.05 | CQ11: 0.08 | CR11: 0.11 | CS11: 0.11 | CT11: 0.15 | CU11: 0.04 | CV11: 0.02 | CW11: 0.07 | CX11: 0.06 | CY11: 0.04 | CZ11: 0.11 | DA11: 0.05 | DB11: 0.12 | DC11: 0.16 | DD11: 0.06 | DE11: 0.1 | DF11: 0.03 | DG11: 0.11 | DH11: 0.1 | DI11: 0.11 | DJ11: 0.06 | DK11: 0.09 | DL11: 0.22 | DM11: 0.14 | DN11: 0.09 | DO11: 0.13 | DP11: 0.11 | DQ11: 0.13 | DR11: 0.03 | DS11: 0.01 | DT11: 0.02 | DU11: 0.05 | DV11: 0.02 | DW11: 0.03 | DX11: 0.1 | DY11: -0.05 | DZ11: 0.04 | EA11: 0.1 | EB11: -0.01 | EC11: 0.04 | ED11: 0.22 | EE11: 0.1 | EF11: 0 | EG11: 0.09 | EH11: -0.04 | EI11: 0.03 | EJ11: 0.1 | EK11: 0.06 | EL11: 0.09 | EM11: 0.02 | EN11: 0.03 | EO11: 0.02
A12: MCD * | B12: 0.46 | C12: 0.08 | D12: -0.02 | E12: 0.16 | F12: 0.57 | G12: 0.01 | H12: 0.09 | I12: 1 | J12: 0.42 | K12: 0.55 | L12: 0.14 | M12: 0.3 | N12: 0.37 | O12: 0.11 | P12: 0.48 | Q12: -0.03 | R12: 0.54 | S12: 0.1 | T12: 0.15 | U12: 0.06 | V12: 0.11 | W12: 0.18 | X12: 0.16 | Y12: 0.4 | Z12: 0.11 | AA12: 0.21 | AB12: 0.41 | AC12: 0.03 | AD12: 0.07 | AE12: 0.05 | AF12: -0.01 | AG12: 0.3 | AH12: 0.3 | AI12: 0.1 | AJ12: 0.04 | AK12: 0.05 | AL12: 0.29 | AM12: 0.04 | AN12: 0.48 | AO12: 0.36 | AP12: 0.29 | AQ12: 0.13 | AR12: 0.18 | AS12: -0.01 | AT12: 0.23 | AU12: 0.41 | AV12: 0.13 | AW12: 0.03 | AX12: 0.41 | AY12: 0.37 | AZ12: 0.08 | BA12: 0.22 | BB12: 0.08 | BC12: 0.11 | BD12: 0.03 | BE12: 0.35 | BF12: 0.09 | BG12: 0.15 | BH12: 0.03 | BI12: 0.03 | BJ12: 0.01 | BK12: 0.01 | BL12: 0.12 | BM12: 0.33 | BN12: 0.13 | BO12: 0.2 | BP12: 0.11 | BQ12: 0.02 | BR12: 0.24 | BS12: 0.01 | BT12: 0.18 | BU12: -0.06 | BV12: 0.14 | BW12: 0.19 | BX12: 0.33 | BY12: 0.23 | BZ12: 0.2 | CA12: 0.05 | CB12: 0.01 | CC12: 0.11 | CD12: 0.22 | CE12: -0.01 | CF12: 0.06 | CG12: 0.29 | CH12: 0.02 | CI12: 0.11 | CJ12: 0.24 | CK12: 0.33 | CL12: 0.1 | CM12: -0.15 | CN12: -0.06 | CO12: 0.12 | CP12: 0.18 | CQ12: 0.22 | CR12: -0.06 | CS12: -0.03 | CT12: 0.06 | CU12: 0.07 | CV12: 0.06 | CW12: 0.24 | CX12: 0.16 | CY12: 0.24 | CZ12: 0.09 | DA12: 0.12 | DB12: -0.03 | DC12: 0.03 | DD12: 0.17 | DE12: -0.01 | DF12: 0.12 | DG12: 0.07 | DH12: -0.07 | DI12: 0.23 | DJ12: 0.26 | DK12: 0.18 | DL12: -0.04 | DM12: 0.28 | DN12: 0.25 | DO12: 0.03 | DP12: 0.24 | DQ12: -0.04 | DR12: -0.05 | DS12: 0.06 | DT12: -0.12 | DU12: 0 | DV12: 0.07 | DW12: 0.17 | DX12: -0.16 | DY12: 0.12 | DZ12: 0 | EA12: 0.1 | EB12: 0.09 | EC12: -0.08 | ED12: 0.1 | EE12: -0.14 | EF12: -0.01 | EG12: -0.16 | EH12: 0.14 | EI12: -0.23 | EJ12: 0.03 | EK12: -0.01 | EL12: -0.09 | EM12: 0 | EN12: 0.09 | EO12: 0.03
A13: JNJ * | B13: 0.32 | C13: 0.04 | D13: -0.03 | E13: 0.05 | F13: 0.46 | G13: -0.01 | H13: 0 | I13: 0.42 | J13: 1 | K13: 0.45 | L13: 0.09 | M13: 0.2 | N13: 0.42 | O13: 0.1 | P13: 0.41 | Q13: 0.01 | R13: 0.49 | S13: 0.14 | T13: 0.13 | U13: 0.09 | V13: -0.03 | W13: 0.15 | X13: 0.16 | Y13: 0.26 | Z13: 0.06 | AA13: 0.17 | AB13: 0.22 | AC13: -0.15 | AD13: 0.11 | AE13: -0.09 | AF13: -0.01 | AG13: 0.3 | AH13: 0.29 | AI13: 0.21 | AJ13: 0 | AK13: 0.08 | AL13: 0.2 | AM13: 0.09 | AN13: 0.29 | AO13: 0.56 | AP13: 0.12 | AQ13: 0.21 | AR13: 0.09 | AS13: 0.06 | AT13: 0.04 | AU13: 0.42 | AV13: 0.02 | AW13: 0.02 | AX13: 0.52 | AY13: 0.21 | AZ13: -0.04 | BA13: 0.2 | BB13: 0.02 | BC13: -0.01 | BD13: 0.04 | BE13: 0.56 | BF13: 0.04 | BG13: 0.2 | BH13: -0.04 | BI13: -0.01 | BJ13: -0.03 | BK13: -0.06 | BL13: 0.17 | BM13: 0.2 | BN13: 0.21 | BO13: 0.14 | BP13: -0.14 | BQ13: -0.03 | BR13: 0.09 | BS13: 0.11 | BT13: 0.2 | BU13: 0.03 | BV13: -0.02 | BW13: 0.15 | BX13: 0.51 | BY13: 0.08 | BZ13: 0.11 | CA13: 0.01 | CB13: 0.12 | CC13: 0.11 | CD13: 0.09 | CE13: 0.01 | CF13: 0.16 | CG13: 0.09 | CH13: 0 | CI13: 0.15 | CJ13: 0.2 | CK13: 0.21 | CL13: 0.12 | CM13: -0.13 | CN13: 0.04 | CO13: -0.07 | CP13: 0.11 | CQ13: 0.1 | CR13: -0.11 | CS13: 0.04 | CT13: 0 | CU13: 0.01 | CV13: -0.08 | CW13: 0.07 | CX13: 0.06 | CY13: 0.08 | CZ13: 0.04 | DA13: 0.01 | DB13: -0.09 | DC13: -0.06 | DD13: 0.01 | DE13: -0.03 | DF13: 0 | DG13: 0.1 | DH13: -0.15 | DI13: 0.04 | DJ13: 0.14 | DK13: 0.07 | DL13: -0.01 | DM13: 0.12 | DN13: 0.07 | DO13: -0.07 | DP13: 0.15 | DQ13: -0.03 | DR13: 0 | DS13: 0 | DT13: -0.22 | DU13: -0.11 | DV13: -0.05 | DW13: -0.01 | DX13: -0.13 | DY13: -0.13 | DZ13: 0 | EA13: 0.02 | EB13: -0.07 | EC13: 0.03 | ED13: -0.06 | EE13: -0.15 | EF13: 0.05 | EG13: -0.1 | EH13: 0.01 | EI13: -0.18 | EJ13: -0.04 | EK13: -0.08 | EL13: -0.07 | EM13: -0.08 | EN13: 0.14 | EO13: -0.03
A14: PG * | B14: 0.44 | C14: -0.08 | D14: -0.05 | E14: 0.08 | F14: 0.58 | G14: 0.01 | H14: 0.1 | I14: 0.55 | J14: 0.45 | K14: 1 | L14: 0.09 | M14: 0.3 | N14: 0.35 | O14: 0.17 | P14: 0.41 | Q14: -0.04 | R14: 0.59 | S14: 0.18 | T14: 0.13 | U14: 0.1 | V14: 0.15 | W14: 0.19 | X14: 0.13 | Y14: 0.3 | Z14: 0.14 | AA14: 0.21 | AB14: 0.31 | AC14: 0.04 | AD14: 0.14 | AE14: 0.04 | AF14: -0.06 | AG14: 0.35 | AH14: 0.36 | AI14: 0.07 | AJ14: 0.04 | AK14: 0.02 | AL14: 0.28 | AM14: 0.02 | AN14: 0.51 | AO14: 0.33 | AP14: 0.31 | AQ14: 0.07 | AR14: 0.13 | AS14: 0 | AT14: 0.17 | AU14: 0.43 | AV14: 0.08 | AW14: 0.03 | AX14: 0.4 | AY14: 0.28 | AZ14: 0.05 | BA14: 0.3 | BB14: 0 | BC14: 0.02 | BD14: 0.1 | BE14: 0.41 | BF14: 0.1 | BG14: 0.14 | BH14: 0.03 | BI14: 0.04 | BJ14: -0.05 | BK14: 0.03 | BL14: 0.2 | BM14: 0.33 | BN14: 0.23 | BO14: 0.21 | BP14: -0.04 | BQ14: 0.1 | BR14: 0.14 | BS14: -0.06 | BT14: 0.17 | BU14: -0.04 | BV14: 0.14 | BW14: 0.1 | BX14: 0.25 | BY14: 0.21 | BZ14: 0.17 | CA14: 0.14 | CB14: -0.02 | CC14: 0.15 | CD14: 0.12 | CE14: -0.04 | CF14: 0.01 | CG14: 0.18 | CH14: 0.02 | CI14: 0 | CJ14: 0.17 | CK14: 0.34 | CL14: 0.16 | CM14: -0.14 | CN14: -0.03 | CO14: 0.06 | CP14: 0.17 | CQ14: 0.19 | CR14: -0.04 | CS14: 0.05 | CT14: 0.08 | CU14: 0.05 | CV14: 0.08 | CW14: 0.13 | CX14: 0.11 | CY14: 0.29 | CZ14: 0.01 | DA14: 0.13 | DB14: -0.02 | DC14: 0.13 | DD14: 0.11 | DE14: -0.02 | DF14: -0.03 | DG14: 0.04 | DH14: -0.15 | DI14: 0.23 | DJ14: 0.27 | DK14: 0.2 | DL14: 0.02 | DM14: 0.33 | DN14: 0.19 | DO14: 0.01 | DP14: 0.29 | DQ14: -0.01 | DR14: -0.11 | DS14: 0.07 | DT14: -0.23 | DU14: -0.06 | DV14: -0.04 | DW14: 0.01 | DX14: -0.17 | DY14: 0.01 | DZ14: -0.09 | EA14: 0.11 | EB14: -0.01 | EC14: -0.14 | ED14: -0.07 | EE14: -0.08 | EF14: 0.12 | EG14: -0.08 | EH14: 0 | EI14: -0.24 | EJ14: 0.01 | EK14: -0.07 | EL14: -0.1 | EM14: -0.09 | EN14: 0.1 | EO14: 0.02
A15: WALMEX * | B15: 0.07 | C15: 0.31 | D15: 0.11 | E15: 0.31 | F15: 0.16 | G15: -0.01 | H15: 0.21 | I15: 0.14 | J15: 0.09 | K15: 0.09 | L15: 1 | M15: 0.17 | N15: 0.14 | O15: 0.37 | P15: 0.15 | Q15: 0.09 | R15: 0.1 | S15: 0.35 | T15: 0.03 | U15: 0.32 | V15: 0.3 | W15: 0.19 | X15: 0.05 | Y15: 0.17 | Z15: 0.3 | AA15: 0.31 | AB15: 0.12 | AC15: 0.12 | AD15: 0.22 | AE15: 0.25 | AF15: 0.29 | AG15: -0.02 | AH15: 0.01 | AI15: -0.02 | AJ15: 0.23 | AK15: 0.27 | AL15: 0.11 | AM15: 0.16 | AN15: 0.14 | AO15: 0.05 | AP15: 0.09 | AQ15: -0.01 | AR15: -0.01 | AS15: 0.2 | AT15: 0.04 | AU15: 0.1 | AV15: 0.3 | AW15: 0.16 | AX15: 0.15 | AY15: 0.27 | AZ15: 0.26 | BA15: 0.25 | BB15: 0.05 | BC15: 0.12 | BD15: 0.22 | BE15: 0.11 | BF15: 0.17 | BG15: 0.01 | BH15: 0.26 | BI15: 0.18 | BJ15: 0.02 | BK15: 0.2 | BL15: 0.09 | BM15: 0.13 | BN15: 0.1 | BO15: 0.09 | BP15: 0.18 | BQ15: 0.23 | BR15: 0.1 | BS15: -0.07 | BT15: 0.13 | BU15: 0.08 | BV15: 0.12 | BW15: 0.15 | BX15: -0.04 | BY15: 0.05 | BZ15: 0.15 | CA15: 0.19 | CB15: -0.08 | CC15: 0 | CD15: 0.15 | CE15: 0.06 | CF15: 0 | CG15: 0.1 | CH15: 0.17 | CI15: -0.02 | CJ15: -0.02 | CK15: 0.03 | CL15: 0.05 | CM15: 0.05 | CN15: 0.16 | CO15: 0.09 | CP15: 0.05 | CQ15: 0.13 | CR15: 0.13 | CS15: 0.08 | CT15: 0.1 | CU15: 0.11 | CV15: 0 | CW15: 0.15 | CX15: 0.07 | CY15: 0.09 | CZ15: 0.14 | DA15: 0.11 | DB15: 0.13 | DC15: 0.15 | DD15: 0.06 | DE15: 0.09 | DF15: 0.07 | DG15: 0.12 | DH15: 0.09 | DI15: 0.14 | DJ15: 0.08 | DK15: 0.15 | DL15: 0.16 | DM15: 0.15 | DN15: 0.21 | DO15: 0.15 | DP15: 0.1 | DQ15: 0.11 | DR15: 0.04 | DS15: 0.04 | DT15: 0.03 | DU15: -0.02 | DV15: 0.07 | DW15: -0.01 | DX15: 0.12 | DY15: 0.07 | DZ15: 0.11 | EA15: 0.12 | EB15: 0.03 | EC15: 0.03 | ED15: 0.07 | EE15: 0.11 | EF15: 0.07 | EG15: 0.2 | EH15: 0 | EI15: 0.08 | EJ15: 0.15 | EK15: 0.11 | EL15: 0.14 | EM15: 0.02 | EN15: 0 | EO15: 0.04
A16: AGNC * | B16: 0.25 | C16: 0.07 | D16: -0.07 | E16: 0.19 | F16: 0.29 | G16: 0.05 | H16: 0.17 | I16: 0.3 | J16: 0.2 | K16: 0.3 | L16: 0.17 | M16: 1 | N16: 0.29 | O16: 0.22 | P16: 0.2 | Q16: 0 | R16: 0.3 | S16: 0.12 | T16: 0.36 | U16: 0.29 | V16: 0.29 | W16: 0.16 | X16: 0.34 | Y16: 0.23 | Z16: 0.29 | AA16: 0.21 | AB16: 0.24 | AC16: 0.1 | AD16: 0.16 | AE16: 0.24 | AF16: 0.12 | AG16: 0.03 | AH16: 0.05 | AI16: -0.07 | AJ16: 0.02 | AK16: 0.23 | AL16: 0.26 | AM16: 0.2 | AN16: 0.53 | AO16: 0.16 | AP16: 0.26 | AQ16: -0.12 | AR16: 0.24 | AS16: 0.23 | AT16: 0.37 | AU16: 0.24 | AV16: 0.18 | AW16: 0.24 | AX16: 0.27 | AY16: 0.37 | AZ16: 0.27 | BA16: 0.37 | BB16: 0.33 | BC16: 0.14 | BD16: 0.17 | BE16: 0.29 | BF16: 0.27 | BG16: 0.33 | BH16: 0.16 | BI16: 0.13 | BJ16: -0.11 | BK16: 0.18 | BL16: 0.37 | BM16: 0.32 | BN16: 0.03 | BO16: 0.32 | BP16: 0.16 | BQ16: 0.33 | BR16: 0.35 | BS16: -0.09 | BT16: 0.35 | BU16: 0.13 | BV16: 0.33 | BW16: 0.27 | BX16: 0.14 | BY16: 0.4 | BZ16: 0.41 | CA16: 0.23 | CB16: -0.04 | CC16: 0.07 | CD16: 0.28 | CE16: 0.1 | CF16: -0.09 | CG16: 0.35 | CH16: 0.34 | CI16: -0.12 | CJ16: 0.08 | CK16: 0.31 | CL16: 0.33 | CM16: 0.22 | CN16: 0.03 | CO16: 0.1 | CP16: 0.14 | CQ16: 0.43 | CR16: 0.31 | CS16: 0.28 | CT16: 0.26 | CU16: 0.15 | CV16: 0.27 | CW16: 0.3 | CX16: 0.35 | CY16: 0.42 | CZ16: 0.11 | DA16: 0.16 | DB16: 0.3 | DC16: 0.32 | DD16: 0.31 | DE16: 0.35 | DF16: 0.1 | DG16: 0.36 | DH16: 0.18 | DI16: 0.41 | DJ16: 0.37 | DK16: 0.44 | DL16: 0.19 | DM16: 0.45 | DN16: 0.32 | DO16: 0.26 | DP16: 0.39 | DQ16: 0.26 | DR16: 0.22 | DS16: 0.12 | DT16: 0.14 | DU16: 0.3 | DV16: 0.16 | DW16: 0.23 | DX16: 0.25 | DY16: 0.36 | DZ16: 0.1 | EA16: 0.21 | EB16: 0.36 | EC16: 0.05 | ED16: 0.29 | EE16: 0.22 | EF16: 0.25 | EG16: 0.23 | EH16: 0.14 | EI16: 0.18 | EJ16: 0.32 | EK16: 0.28 | EL16: 0.32 | EM16: 0.18 | EN16: 0.21 | EO16: 0.11
... A148: BYND * | B148: 0 | C148: 0.04 | D148: -0.08 | E148: 0.02 | F148: 0.09 | G148: 0.08 | H148: 0.02 | I148: 0.03 | J148: -0.03 | K148: 0.02 | L148: 0.04 | M148: 0.11 | N148: 0.03 | O148: 0.02 | P148: 0.02 | Q148: 0.02 | R148: 0.03 | S148: -0.06 | T148: 0.06 | U148: 0.08 | V148: 0 | W148: -0.01 | X148: 0.08 | Y148: 0.04 | Z148: 0.06 | AA148: -0.02 | AB148: 0.04 | AC148: 0.02 | AD148: -0.03 | AE148: 0.05 | AF148: -0.06 | AG148: -0.1 | AH148: -0.04 | AI148: -0.02 | AJ148: 0.02 | AK148: 0.07 | AL148: 0.12 | AM148: 0.05 | AN148: 0.14 | AO148: 0.03 | AP148: 0.19 | AQ148: -0.01 | AR148: 0.06 | AS148: 0.12 | AT148: 0.16 | AU148: 0 | AV148: 0.09 | AW148: 0.03 | AX148: 0.07 | AY148: 0.04 | AZ148: -0.04 | BA148: 0.11 | BB148: 0.11 | BC148: -0.07 | BD148: 0.13 | BE148: 0.07 | BF148: 0.14 | BG148: 0.16 | BH148: 0.06 | BI148: -0.06 | BJ148: -0.05 | BK148: -0.11 | BL148: 0.15 | BM148: 0.18 | BN148: 0.05 | BO148: 0.1 | BP148: 0.11 | BQ148: -0.01 | BR148: 0.12 | BS148: 0 | BT148: 0.12 | BU148: 0.06 | BV148: 0.17 | BW148: 0.11 | BX148: 0.03 | BY148: 0.3 | BZ148: 0.15 | CA148: -0.04 | CB148: -0.09 | CC148: 0.09 | CD148: 0.11 | CE148: 0.1 | CF148: -0.05 | CG148: 0.17 | CH148: 0.1 | CI148: -0.03 | CJ148: 0.16 | CK148: 0.14 | CL148: 0.15 | CM148: 0.11 | CN148: 0.03 | CO148: 0.02 | CP148: 0.09 | CQ148: 0.14 | CR148: 0.13 | CS148: 0.09 | CT148: 0.19 | CU148: 0.13 | CV148: 0.08 | CW148: 0.15 | CX148: 0.13 | CY148: 0.13 | CZ148: 0.08 | DA148: 0.12 | DB148: 0.17 | DC148: 0.1 | DD148: 0.21 | DE148: 0.16 | DF148: 0.15 | DG148: 0.04 | DH148: 0.07 | DI148: 0.11 | DJ148: 0.17 | DK148: 0.11 | DL148: 0.02 | DM148: 0.19 | DN148: 0.17 | DO148: 0.1 | DP148: 0.17 | DQ148: 0.03 | DR148: 0.06 | DS148: 0.14 | DT148: 0.15 | DU148: 0.23 | DV148: 0.14 | DW148: 0.1 | DX148: 0.1 | DY148: 0.25 | DZ148: 0.1 | EA148: 0.1 | EB148: 0.28 | EC148: 0.03 | ED148: 0.13 | EE148: 0.14 | EF148: 0.02 | EG148: 0.09 | EH148: 0.07 | EI148: 0.07 | EJ148: 0.08 | EK148: 0.19 | EL148: 0.14 | EM148: 0.06 | EN148: 0.11 | EO148: 1

Sheet Covarianza
A1: Hoja de apoyo (no tocar): varianza del portafolio = w' · Σ · w
A2: Varianza anual del portafolio | B2: =SUMPRODUCT(EP6:EP149,EQ6:EQ149) -> 0
B4: BRKB * | C4: SIGMAF A | D4: LIVEPOL C-1 | E4: GRUMA B | F4: KO * | G4: FIBRAMQ 12 | H4: VESTA * | I4: MCD * | J4: JNJ * | K4: PG * | L4: WALMEX * | M4: AGNC * | N4: PFE * | O4: AC * | P4: COST * | Q4: ACTINVR B | R4: PEP * | S4: CHDRAUI B | T4: BAC * | U4: GFINBUR O | V4: FUNO 11 | W4: FEMSA UBD | X4: JPM * | Y4: V * | Z4: KIMBER A | AA4: KOF UBL | AB4: MA * | AC4: FIBRAPL 14 | AD4: AMX B | AE4: ASUR B | AF4: PINFRA * | AG4: T * | AH4: VZ * | AI4: CVX * | AJ4: ALSEA * | AK4: GFNORTE O | AL4: AAPL * | AM4: BOLSA A | AN4: HD * | AO4: ABBV * | AP4: DIS * | AQ4: XOM * | AR4: WFC * | AS4: BBAJIO O | AT4: AXP * | AU4: WMT * | AV4: BIMBO A | AW4: GCC * | AX4: BMY * | AY4: SBUX * | AZ4: OMA B | BA4: FDX * | BB4: C * | BC4: Q * | BD4: R A | BE4: MRK * | BF4: MEGA CPO | BG4: TMO * | BH4: LAB B | BI4: CUERVO * | BJ4: SITES1 A-1 | BK4: GAP B | BL4: TX * | BM4: TGT * | BN4: CVS * | BO4: GOOGL * | BP4: MSFT * | BQ4: CEMEX CPO | BR4: WYNN * | BS4: FANG * | BT4: GE * | BU4: GENTERA * | BV4: AMZN * | BW4: LVS * | BX4: LLY * | BY4: GM * | BZ4: BA * | CA4: GCARSO A1 | CB4: ALPEK A | CC4: UNH * | CD4: UBER * | CE4: CSCO * | CF4: DVN * | CG4: ABNB * | CH4: GMEXICO B | CI4: OXY1 * | CJ4: NFLX * | CK4: NKE * | CL4: F * | CM4: NVDA * | CN4: ORBIA * | CO4: TLEVISA CPO | CP4: GME * | CQ4: DAL * | CR4: TSM N | CS4: CAT * | CT4: ROKU * | CU4: BABA N | CV4: META * | CW4: MELI N | CX4: NU N | CY4: LUV * | CZ4: ZM * | DA4: PYPL * | DB4: TSLA * | DC4: VOLAR A | DD4: XYZ * | DE4: FCX * | DF4: CRM * | DG4: B N | DH4: AVGO * | DI4: AAL * | DJ4: RCL * | DK4: UAL * | DL4: PE&OLES * | DM4: CCL1 N | DN4: ETSY * | DO4: QCOM * | DP4: NCLH N | DQ4: FSLR * | DR4: AA1 * | DS4: PINS * | DT4: ORCL * | DU4: SOFI * | DV4: PLTR * | DW4: SHOP N | DX4: AMAT * | DY4: AFRM * | DZ4: TWLO * | EA4: NVAX * | EB4: UPST * | EC4: MFRISCO A-1 | ED4: RIVN * | EE4: AMD * | EF4: CLF * | EG4: INTC * | EH4: FUBO * | EI4: MU * | EJ4: LCID * | EK4: MARA * | EL4: RIOT * | EM4: SPCE * | EN4: MRNA * | EO4: BYND * | EP4: Σw | EQ4: w
A5: w (peso) | B5: =SUMIF('Mi portafolio'!$A$8:$A$19,B$4,'Mi portafolio'!$B$8:$B$19) -> 0 | C5: =SUMIF('Mi portafolio'!$A$8:$A$19,C$4,'Mi portafolio'!$B$8:$B$19) -> 0 | D5: =SUMIF('Mi portafolio'!$A$8:$A$19,D$4,'Mi portafolio'!$B$8:$B$19) -> 0 | E5: =SUMIF('Mi portafolio'!$A$8:$A$19,E$4,'Mi portafolio'!$B$8:$B$19) -> 0 | F5: =SUMIF('Mi portafolio'!$A$8:$A$19,F$4,'Mi portafolio'!$B$8:$B$19) -> 0 | G5: =SUMIF('Mi portafolio'!$A$8:$A$19,G$4,'Mi portafolio'!$B$8:$B$19) -> 0 | H5: =SUMIF('Mi portafolio'!$A$8:$A$19,H$4,'Mi portafolio'!$B$8:$B$19) -> 0 | I5: =SUMIF('Mi portafolio'!$A$8:$A$19,I$4,'Mi portafolio'!$B$8:$B$19) -> 0 | ... EO5: =SUMIF('Mi portafolio'!$A$8:$A$19,EO$4,'Mi portafolio'!$B$8:$B$19) -> 0
A6: BRKB * | B6: 0.02727092 | C6: -0.00122523 | D6: -0.00345012 | E6: 0.00208389 | F6: 0.01435937 | G6: -0.00377712 | H6: -0.00065853 | I6: 0.01596738 | J6: 0.0111789 | K6: 0.01510253 | L6: 0.00222703 | M6: 0.00904954 | N6: 0.01187081 | O6: 0.00520829 | P6: 0.01394559 | Q6: 0.00104226 | R6: 0.01346009 | S6: -7.47e-05 | T6: 0.00931484 | U6: 0.00260089 | V6: 0.00104324 | W6: 0.00069693 | X6: 0.01272944 | Y6: 0.01775372 | Z6: 0.00161083 | AA6: 0.00213791 | AB6: 0.01952476 | AC6: 0.00140505 | AD6: 0.0025251 | AE6: 2.188e-05 | AF6: -0.00606462 | AG6: 0.01133127 | AH6: 0.01336448 | AI6: 0.00743067 | AJ6: 0.0013282 | AK6: -0.00121092 | AL6: 0.01229607 | AM6: 0.00161021 | AN6: 0.01604514 | AO6: 0.0116548 | AP6: 0.0105343 | AQ6: 0.00564818 | AR6: 0.01015298 | AS6: -0.00605007 | AT6: 0.01320923 | AU6: 0.01388286 | AV6: 0.00332249 | AW6: -0.00034858 | AX6: 0.0165345 | AY6: 0.01283902 | AZ6: 0.00131045 | BA6: 0.00930667 | BB6: 0.00772162 | BC6: 0.00514125 | BD6: 0.00029551 | BE6: 0.01498739 | BF6: 0.002049 | BG6: 0.01070841 | BH6: 0.00228696 | BI6: 0.00489387 | BJ6: -0.00133134 | BK6: 0.00129733 | BL6: 0.00442165 | BM6: 0.00890447 | BN6: 0.015467 | BO6: 0.00770444 | BP6: 0.00672687 | BQ6: -0.00263818 | BR6: 0.01200569 | BS6: 0.00113147 | BT6: 0.01042084 | BU6: -0.00421387 | BV6: 0.0077107 | BW6: 0.00929915 | BX6: 0.01652023 | BY6: 0.00945363 | BZ6: 0.01251631 | CA6: 0.00216271 | CB6: 0.00278956 | CC6: 0.01329651 | CD6: 0.01065297 | CE6: 0.00415145 | CF6: 0.00466572 | CG6: 0.01482064 | CH6: -0.00469597 | CI6: 0.00577993 | CJ6: 0.01629339 | CK6: 0.02021462 | CL6: 0.00676833 | CM6: -0.00864228 | CN6: -0.00195328 | CO6: 0.0008506 | CP6: 0.01115812 | CQ6: 0.0179563 | CR6: -0.00372367 | CS6: 0.00020566 | CT6: 0.00669597 | CU6: -0.00021047 | CV6: 0.00455955 | CW6: 0.00744613 | CX6: 0.00469308 | CY6: 0.01588571 | CZ6: 0.00759817 | DA6: 0.00864992 | DB6: -7.552e-05 | DC6: -0.0014991 | DD6: 0.0110526 | DE6: -0.00701858 | DF6: 0.01346945 | DG6: 0.00069811 | DH6: -0.00376747 | DI6: 0.02166132 | DJ6: 0.01805063 | DK6: 0.0190478 | DL6: -0.01004149 | DM6: 0.02245357 | DN6: 0.01629239 | DO6: 0.00568335 | DP6: 0.02336596 | DQ6: 0.00071706 | DR6: -0.00545215 | DS6: 0.00977369 | DT6: -0.01180086 | DU6: -0.00094387 | DV6: -0.00172778 | DW6: 0.01018744 | DX6: -0.01485884 | DY6: 0.01469509 | DZ6: 0.00209805 | EA6: 0.00019128 | EB6: 0.00553558 | EC6: -0.01282979 | ED6: 0.00603948 | EE6: -0.01042106 | EF6: 0.00635184 | EG6: -0.00826232 | EH6: 0.00854188 | EI6: -0.02635167 | EJ6: 0.00840899 | EK6: -0.0042044 | EL6: -0.01566089 | EM6: -0.01379308 | EN6: 0.00375763 | EO6: -0.00095233 | EP6: =SUMPRODUCT(B6:EO6,$B$5:$EO$5) -> 0 | EQ6: =SUMIF('Mi portafolio'!$A$8:$A$19,$A6,'Mi portafolio'!$B$8:$B$19) -> 0
A7: SIGMAF A | B7: -0.00122523 | C7: 0.03032129 | D7: 0.0028041 | E7: 0.00319255 | F7: 0.00040299 | G7: 0.00083876 | H7: 0.0051104 | I7: 0.00273161 | J7: 0.00151001 | K7: -0.00293126 | L7: 0.0111274 | M7: 0.00254736 | N7: -0.00029034 | O7: 0.00696736 | P7: 0.00258493 | Q7: -5.552e-05 | R7: 0.00099835 | S7: 0.0025064 | T7: -0.00033098 | U7: 0.00495596 | V7: 0.0062495 | W7: 0.0055248 | X7: 0.0013091 | Y7: 0.00422577 | Z7: 0.00861616 | AA7: 0.00365925 | AB7: 0.00138272 | AC7: 0.00186414 | AD7: 0.00840785 | AE7: 0.00869148 | AF7: 0.01049109 | AG7: -0.00079844 | AH7: -0.00011662 | AI7: -0.00085768 | AJ7: 0.00479885 | AK7: 0.01016849 | AL7: -0.00049695 | AM7: 0.00397934 | AN7: 0.00063756 | AO7: 0.00137315 | AP7: -0.00289754 | AQ7: 0.00054645 | AR7: -0.00018836 | AS7: 0.00603443 | AT7: -0.00017084 | AU7: 0.00235576 | AV7: 0.01377895 | AW7: 0.00953833 | AX7: -0.00038886 | AY7: 0.00597089 | AZ7: 0.00428279 | BA7: 0.00311471 | BB7: -0.00387509 | BC7: 0.0013779 | BD7: 0.0088567 | BE7: 0.00377277 | BF7: -0.00020252 | BG7: 0.00048506 | BH7: 0.0029318 | BI7: -0.000783 | BJ7: 0.0014544 | BK7: 0.00318421 | BL7: -0.00037767 | BM7: 0.00173707 | BN7: 0.00151278 | BO7: -0.00127893 | BP7: -0.00411902 | BQ7: 0.0111429 | BR7: -0.00431267 | BS7: -0.00175069 | BT7: 0.00217495 | BU7: 0.00375029 | BV7: -0.00137376 | BW7: -0.00238158 | BX7: -0.00411719 | BY7: -0.00184464 | BZ7: 0.00715094 | CA7: 0.00978303 | CB7: 0.00624498 | CC7: -0.00151424 | CD7: -0.00278 | CE7: -0.00217653 | CF7: -0.0027256 | CG7: -0.00169831 | CH7: 0.00817224 | CI7: -0.00359012 | CJ7: -0.00090146 | CK7: -0.00481241 | CL7: 0.00032232 | CM7: -0.00497712 | CN7: 0.0108791 | CO7: 0.00488416 | CP7: 0.0012104 | CQ7: -0.00179559 | CR7: -0.00416143 | CS7: 0.00344661 | CT7: 0.00209848 | CU7: 0.00021929 | CV7: -0.00477694 | CW7: 0.00157196 | CX7: 0.00105104 | CY7: -0.00052126 | CZ7: -0.01084357 | DA7: -0.00115133 | DB7: 0.0037139 | DC7: 0.00345748 | DD7: -0.00357027 | DE7: 0.00579657 | DF7: -0.00723146 | DG7: 0.00539804 | DH7: 0.0046066 | DI7: -0.00293393 | DJ7: -0.00517432 | DK7: -0.0001148 | DL7: 0.01540398 | DM7: -0.00118511 | DN7: 0.00845742 | DO7: 0.01505694 | DP7: -0.00192691 | DQ7: 0.00209114 | DR7: 0.00580278 | DS7: -0.00703607 | DT7: -0.00319304 | DU7: -0.0061412 | DV7: -0.00594828 | DW7: -0.01236489 | DX7: 0.0031151 | DY7: 0.00099009 | DZ7: -0.01166729 | EA7: 0.00248178 | EB7: -0.00901807 | EC7: 0.0040421 | ED7: 0.01577662 | EE7: 0.0037962 | EF7: 0.01376206 | EG7: 0.00987041 | EH7: -0.00029547 | EI7: 0.00271397 | EJ7: -0.00303432 | EK7: 0.00594633 | EL7: 0.00245528 | EM7: -0.0110707 | EN7: -0.00315498 | EO7: 0.01246263 | EP7: =SUMPRODUCT(B7:EO7,$B$5:$EO$5) -> 0 | EQ7: =SUMIF('Mi portafolio'!$A$8:$A$19,$A7,'Mi portafolio'!$B$8:$B$19) -> 0
A8: LIVEPOL C-1 | B8: -0.00345012 | C8: 0.0028041 | D8: 0.03818172 | E8: 0.00486979 | F8: -0.00344298 | G8: 0.00483089 | H8: 0.00590904 | I8: -0.0008363 | J8: -0.00138601 | K8: -0.00225645 | L8: 0.00424757 | M8: -0.00300205 | N8: 0.00791372 | O8: 0.00150504 | P8: 1.642e-05 | Q8: 0.0008388 | R8: -0.00710034 | S8: 0.00469729 | T8: 0.00260544 | U8: 0.00539696 | V8: 0.00163058 | W8: -0.00170753 | X8: 0.00076785 | Y8: 2.188e-05 | Z8: 0.00432243 | AA8: 0.00412536 | AB8: 0.00149827 | AC8: 0.00372571 | AD8: 0.00086387 | AE8: 0.00900713 | AF8: 0.00863475 | AG8: -0.00095644 | AH8: -0.00155692 | AI8: -0.00549058 | AJ8: 0.01052179 | AK8: 0.00130726 | AL8: 0.00236023 | AM8: 0.0046754 | AN8: -0.00256398 | AO8: 0.00113424 | AP8: 0.00154307 | AQ8: -0.00536562 | AR8: 0.00341161 | AS8: 0.00682551 | AT8: 0.00059434 | AU8: -0.0019981 | AV8: 0.00523993 | AW8: 0.00238212 | AX8: 0.0055289 | AY8: -0.00149166 | AZ8: 0.01181537 | BA8: -0.00155177 | BB8: 0.00285483 | BC8: 0.00351633 | BD8: 0.00951312 | BE8: -0.00097629 | BF8: 0.00801804 | BG8: 0.00260399 | BH8: 0.00654886 | BI8: 0.00687869 | BJ8: 0.00413724 | BK8: 0.0136883 | BL8: -0.00330593 | BM8: 0.00320417 | BN8: -0.00754291 | BO8: 0.0054213 | BP8: 0.00536654 | BQ8: 0.00652126 | BR8: 0.0023243 | BS8: -0.00416384 | BT8: 0.00342756 | BU8: 0.00679149 | BV8: 0.00265936 | BW8: 0.00217028 | BX8: 0.00615904 | BY8: -0.00333839 | BZ8: -0.00058199 | CA8: 0.01037798 | CB8: -0.00427998 | CC8: -0.00052022 | CD8: 0.00324413 | CE8: 0.00350955 | CF8: -0.00286491 | CG8: 0.00787098 | CH8: 0.00303513 | CI8: -0.00514366 | CJ8: 0.00357402 | CK8: 0.00080288 | CL8: -3.159e-05 | CM8: 0.00417129 | CN8: 0.01300302 | CO8: -2.057e-05 | CP8: 0.00397387 | CQ8: 0.00356368 | CR8: -0.00038902 | CS8: 0.00223139 | CT8: 0.00597897 | CU8: 0.00629838 | CV8: 0.0015 | CW8: -0.00078702 | CX8: -0.00033434 | CY8: 0.00184252 | CZ8: 0.01064417 | DA8: 0.01554343 | DB8: 0.00872036 | DC8: 0.01657596 | DD8: 0.01759043 | DE8: 0.0044292 | DF8: 0.00763947 | DG8: 0.00804325 | DH8: 0.00444537 | DI8: 0.00271137 | DJ8: 0.00019447 | DK8: 0.00207271 | DL8: 0.01968375 | DM8: 0.00214395 | DN8: -0.00624314 | DO8: 0.00800728 | DP8: 0.00189505 | DQ8: -0.00067901 | DR8: -0.00181712 | DS8: 0.00386071 | DT8: 0.00457224 | DU8: 0.01255917 | DV8: 0.00685318 | DW8: 0.00894236 | DX8: 0.007655 | DY8: 0.00415934 | DZ8: 0.0159911 | EA8: 0.00606714 | EB8: 0.00690536 | EC8: -0.00026084 | ED8: 0.01353387 | EE8: 0.00558363 | EF8: 0.0121654 | EG8: -0.00164508 | EH8: 0.0107868 | EI8: 0.00929717 | EJ8: 0.00944369 | EK8: 0.00667017 | EL8: 0.01516864 | EM8: 0.0047183 | EN8: 0.00249078 | EO8: -0.02773732 | EP8: =SUMPRODUCT(B8:EO8,$B$5:$EO$5) -> 0 | EQ8: =SUMIF('Mi portafolio'!$A$8:$A$19,$A8,'Mi portafolio'!$B$8:$B$19) -> 0
A9: GRUMA B | B9: 0.00208389 | C9: 0.00319255 | D9: 0.00486979 | E9: 0.03954808 | F9: 0.00525363 | G9: 0.00199572 | H9: 0.0091222 | I9: 0.00643985 | J9: 0.00220829 | K9: 0.00329236 | L9: 0.01255593 | M9: 0.00831472 | N9: 0.00785472 | O9: 0.01565921 | P9: 0.00675916 | Q9: 0.003285 | R9: 0.00382824 | S9: 0.01088201 | T9: 0.0057931 | U9: 0.01420965 | V9: 0.01434758 | W9: 0.01247923 | X9: 0.00655885 | Y9: 0.00187749 | Z9: 0.00859558 | AA9: 0.00969927 | AB9: 0.00257294 | AC9: 0.01484684 | AD9: 0.0117208 | AE9: 0.00932528 | AF9: 0.01705141 | AG9: 0.00394391 | AH9: 0.00430752 | AI9: 0.00332339 | AJ9: 0.00511019 | AK9: 0.0157621 | AL9: 0.00733595 | AM9: 0.00856475 | AN9: 0.00657424 | AO9: 0.00530805 | AP9: 0.00730996 | AQ9: 0.00580882 | AR9: 0.00403897 | AS9: 0.01044574 | AT9: 0.00662622 | AU9: 0.00464582 | AV9: 0.02495021 | AW9: 0.0093577 | AX9: 0.0073234 | AY9: 0.00564242 | AZ9: 0.01368433 | BA9: 0.01035729 | BB9: 0.00706098 | BC9: 0.01322894 | BD9: 0.01343117 | BE9: 0.00504326 | BF9: 0.01970007 | BG9: -0.00061454 | BH9: 0.01328334 | BI9: 0.01238584 | BJ9: 0.00390189 | BK9: 0.011569 | BL9: 0.00656173 | BM9: 0.01428878 | BN9: 0.00516102 | BO9: 0.0049761 | BP9: 0.00495531 | BQ9: 0.00963522 | BR9: 0.00457323 | BS9: 0.00210584 | BT9: 0.00360265 | BU9: 0.01184999 | BV9: -0.00216532 | BW9: 0.00869344 | BX9: 0.00120393 | BY9: 0.00386879 | BZ9: 0.00894561 | CA9: 0.01847556 | CB9: 0.00137994 | CC9: 0.00433987 | CD9: 0.00385731 | CE9: 0.00030032 | CF9: 0.00217398 | CG9: 0.00201842 | CH9: 0.01362353 | CI9: -0.00394937 | CJ9: 0.00455424 | CK9: 0.00920464 | CL9: -0.00037437 | CM9: -0.0026444 | CN9: 0.01041868 | CO9: 0.01117033 | CP9: 0.00203295 | CQ9: 0.01398693 | CR9: 0.0061675 | CS9: 0.00605735 | CT9: 0.01240931 | CU9: 0.00063741 | CV9: -0.00077305 | CW9: 0.00839736 | CX9: 0.00531726 | CY9: 0.0171903 | CZ9: 0.00467179 | DA9: -0.00262581 | DB9: 0.0178448 | DC9: 0.01641426 | DD9: 0.01177642 | DE9: 0.0139035 | DF9: 0.00376027 | DG9: 0.00855278 | DH9: 0.00922587 | DI9: 0.01974728 | DJ9: 0.00756526 | DK9: 0.01314835 | DL9: 0.01074302 | DM9: 0.01263659 | DN9: -0.00186445 | DO9: 0.01572688 | DP9: 0.00585715 | DQ9: 0.0092311 | DR9: 0.01312534 | DS9: -0.00177684 | DT9: 0.00549678 | DU9: 0.01558919 | DV9: 0.01137692 | DW9: 0.00228732 | DX9: 0.00565996 | DY9: 0.01132972 | DZ9: 0.00334653 | EA9: 0.00612084 | EB9: 0.01546898 | EC9: 0.01150355 | ED9: 0.02591968 | EE9: 0.01000647 | EF9: 0.00094322 | EG9: 0.00788364 | EH9: -0.00351256 | EI9: -0.0033923 | EJ9: 0.02925947 | EK9: 0.0098461 | EL9: 0.01479324 | EM9: 0.00872733 | EN9: 0.00805959 | EO9: 0.00835102 | EP9: =SUMPRODUCT(B9:EO9,$B$5:$EO$5) -> 0 | EQ9: =SUMIF('Mi portafolio'!$A$8:$A$19,$A9,'Mi portafolio'!$B$8:$B$19) -> 0
A10: KO * | B10: 0.01435937 | C10: 0.00040299 | D10: -0.00344298 | E10: 0.00525363 | F10: 0.04159741 | G10: -0.00112116 | H10: 0.00336541 | I10: 0.02422692 | J10: 0.01982494 | K10: 0.02480373 | L10: 0.00673445 | M10: 0.01274004 | N10: 0.01357076 | O10: 0.00341218 | P10: 0.0216253 | Q10: -0.00483679 | R10: 0.02910072 | S10: 0.00474202 | T10: 0.00234678 | U10: 0.00271308 | V10: 0.00196288 | W10: 0.00604588 | X10: 0.00127387 | Y10: 0.0147335 | Z10: 0.00471116 | AA10: 0.01314017 | AB10: 0.01587104 | AC10: -0.00141898 | AD10: 0.00671765 | AE10: -0.0036952 | AF10: -0.00508529 | AG10: 0.02087926 | AH10: 0.02189856 | AI10: 0.01207886 | AJ10: -0.00172554 | AK10: -0.00200963 | AL10: 0.01404468 | AM10: -0.00020037 | AN10: 0.02137466 | AO10: 0.02178134 | AP10: 0.01570783 | AQ10: 0.0139507 | AR10: 0.00272403 | AS10: 0.00013546 | AT10: 0.0047021 | AU10: 0.02305117 | AV10: 0.00454007 | AW10: -0.00221128 | AX10: 0.02136442 | AY10: 0.01982331 | AZ10: -0.00120245 | BA10: 0.01267519 | BB10: -0.00485133 | BC10: 0.00425659 | BD10: 0.00036671 | BE10: 0.02562431 | BF10: 0.00215993 | BG10: 0.00657499 | BH10: -0.0005096 | BI10: -0.00474962 | BJ10: -0.00560393 | BK10: -0.00322694 | BL10: 0.0068588 | BM10: 0.02335831 | BN10: 0.0137495 | BO10: 0.00504666 | BP10: -0.00094121 | BQ10: -0.00278453 | BR10: 0.00977853 | BS10: 0.00968033 | BT10: 0.00543176 | BU10: -0.00442593 | BV10: 0.00135227 | BW10: 0.01125965 | BX10: 0.01603075 | BY10: 0.01790619 | BZ10: 0.00603307 | CA10: 0.0022389 | CB10: 0.00516925 | CC10: 0.00544573 | CD10: 0.01211176 | CE10: -0.00573734 | CF10: 0.01694872 | CG10: 0.01242371 | CH10: -0.00544608 | CI10: 0.01387304 | CJ10: 0.02280624 | CK10: 0.02008286 | CL10: 0.01072329 | CM10: -0.01415489 | CN10: -0.00647769 | CO10: -0.00161627 | CP10: 0.00907223 | CQ10: 0.00842832 | CR10: -0.01076343 | CS10: -0.01162654 | CT10: -0.00150391 | CU10: -0.00012399 | CV10: -0.00533342 | CW10: 0.0080125 | CX10: 0.00443856 | CY10: 0.01241834 | CZ10: 0.00198541 | DA10: 0.00581329 | DB10: -0.00736626 | DC10: -0.00908898 | DD10: 0.00269837 | DE10: -0.0110377 | DF10: 0.00718114 | DG10: -0.00723015 | DH10: -0.01556222 | DI10: 0.01033509 | DJ10: 0.01446685 | DK10: 0.00713605 | DL10: -0.01184804 | DM10: 0.0162758 | DN10: 0.01658363 | DO10: -0.01391401 | DP10: 0.01433876 | DQ10: -0.01221845 | DR10: -0.01036639 | DS10: 0.00420063 | DT10: -0.0296932 | DU10: -0.01427731 | DV10: -0.0108048 | DW10: -0.00497464 | DX10: -0.02365387 | DY10: 3.656e-05 | DZ10: -0.00697185 | EA10: 0.00169816 | EB10: -0.00762956 | EC10: -0.01731597 | ED10: -0.00388905 | EE10: -0.02505806 | EF10: -0.00975874 | EG10: -0.01471092 | EH10: 0.00911485 | EI10: -0.03352807 | EJ10: 0.00351804 | EK10: -0.00839449 | EL10: -0.02838287 | EM10: -0.01905225 | EN10: 0.02124483 | EO10: 0.03186527 | EP10: =SUMPRODUCT(B10:EO10,$B$5:$EO$5) -> 0 | EQ10: =SUMIF('Mi portafolio'!$A$8:$A$19,$A10,'Mi portafolio'!$B$8:$B$19) -> 0
A11: FIBRAMQ 12 | B11: -0.00377712 | C11: 0.00083876 | D11: 0.00483089 | E11: 0.00199572 | F11: -0.00112116 | G11: 0.04238486 | H11: 0.00772304 | I11: 0.00053497 | J11: -0.00052102 | K11: 0.00035695 | L11: -0.00038852 | M11: 0.00252403 | N11: 0.00217289 | O11: 0.00544039 | P11: -0.00481995 | Q11: 0.00224291 | R11: -0.00120195 | S11: -0.00209972 | T11: 0.00063411 | U11: 0.00392877 | V11: 0.00684009 | W11: 0.00205237 | X11: -0.00129375 | Y11: -0.00259395 | Z11: 0.01080398 | AA11: 0.00405911 | AB11: -0.00067087 | AC11: 0.00784244 | AD11: 0.0019474 | AE11: 0.01111195 | AF11: 0.0101251 | AG11: -0.00458736 | AH11: -0.00467322 | AI11: -0.00349116 | AJ11: 0.00451253 | AK11: 0.00741403 | AL11: -0.00350662 | AM11: 0.00954598 | AN11: -0.00155489 | AO11: 0.00137482 | AP11: 0.00269024 | AQ11: -0.00108836 | AR11: -7.978e-05 | AS11: 0.00904246 | AT11: -0.00263419 | AU11: -0.00120312 | AV11: 0.00312411 | AW11: 0.00662541 | AX11: 0.0029562 | AY11: 0.0020027 | AZ11: 0.00672791 | BA11: 0.00067001 | BB11: 0.00501843 | BC11: 0.00237183 | BD11: 0.01013158 | BE11: -0.00153582 | BF11: 0.01407899 | BG11: -0.00109137 | BH11: 0.00213929 | BI11: 0.00609027 | BJ11: 0.00415905 | BK11: 0.01105173 | BL11: 0.00535743 | BM11: -0.00511926 | BN11: 0.00095609 | BO11: 0.00504008 | BP11: -0.00198397 | BQ11: 0.00643059 | BR11: -4.436e-05 | BS11: -0.00013294 | BT11: 0.00092061 | BU11: -0.00058941 | BV11: 0.00147494 | BW11: 0.0063329 | BX11: -8.027e-05 | BY11: 0.00213435 | BZ11: -0.00634488 | CA11: 0.00930746 | CB11: -0.00084262 | CC11: 0.00260176 | CD11: 0.00171329 | CE11: -0.00115136 | CF11: 0.00141923 | CG11: 0.00422488 | CH11: 0.01315572 | CI11: -0.0017067 | CJ11: 0.00537917 | CK11: -0.00793622 | CL11: 0.00567951 | CM11: -0.00135747 | CN11: 0.00900185 | CO11: -0.00334744 | CP11: 0.00471924 | CQ11: -0.00419865 | CR11: -0.00052388 | CS11: 0.00037315 | CT11: 0.01286769 | CU11: -0.00257065 | CV11: 0.00109918 | CW11: -0.00213631 | CX11: 0.00716268 | CY11: 0.00035742 | CZ11: -0.01040935 | DA11: -0.00908306 | DB11: 0.00749292 | DC11: 0.00962857 | DD11: 0.00502284 | DE11: 0.00294371 | DF11: 0.00070898 | DG11: 0.00368666 | DH11: -0.00248419 | DI11: -0.0003422 | DJ11: -0.00421225 | DK11: -0.00560207 | DL11: 0.0169968 | DM11: 0.00437931 | DN11: 0.00304927 | DO11: -0.00425352 | DP11: 0.00071968 | DQ11: -0.02074624 | DR11: 0.00869077 | DS11: -0.00276242 | DT11: -0.0043683 | DU11: 0.00425018 | DV11: 0.0053253 | DW11: -0.009535 | DX11: 0.00162204 | DY11: -0.00505002 | DZ11: 0.0053241 | EA11: 0.00511627 | EB11: 0.00251396 | EC11: 0.02025952 | ED11: 0.01004484 | EE11: 0.00448051 | EF11: 0.01125018 | EG11: 0.00865559 | EH11: -0.01110691 | EI11: 0.00148677 | EJ11: 0.01934711 | EK11: 0.00856928 | EL11: 0.00862281 | EM11: -0.00965449 | EN11: 0.00943361 | EO11: 0.02878523 | EP11: =SUMPRODUCT(B11:EO11,$B$5:$EO$5) -> 0 | EQ11: =SUMIF('Mi portafolio'!$A$8:$A$19,$A11,'Mi portafolio'!$B$8:$B$19) -> 0
A12: VESTA * | B12: -0.00065853 | C12: 0.0051104 | D12: 0.00590904 | E12: 0.0091222 | F12: 0.00336541 | G12: 0.00772304 | H12: 0.04327684 | I12: 0.00370453 | J12: -0.00014956 | K12: 0.00432872 | L12: 0.00881585 | M12: 0.00809796 | N12: 0.00491034 | O12: 0.00988057 | P12: 0.00067978 | Q12: -0.00074276 | R12: 0.00241434 | S12: 0.01171668 | T12: 0.00133321 | U12: 0.01403214 | V12: 0.0175549 | W12: 0.00700271 | X12: 0.00310612 | Y12: -0.00421346 | Z12: 0.01404121 | AA12: 0.0105219 | AB12: -0.0047864 | AC12: 0.01182163 | AD12: 0.01093609 | AE12: 0.0109847 | AF12: 0.01356655 | AG12: -0.00174375 | AH12: 0.00013361 | AI12: -0.00664142 | AJ12: 0.01464745 | AK12: 0.01435652 | AL12: 0.00054983 | AM12: 0.0094761 | AN12: 0.00788738 | AO12: -0.00025417 | AP12: 0.00112281 | AQ12: -0.00496954 | AR12: -0.00120766 | AS12: 0.01833238 | AT12: -0.00024454 | AU12: 0.00116207 | AV12: 0.01096084 | AW12: 0.02103142 | AX12: 0.00345848 | AY12: 9.942e-05 | AZ12: 0.01715755 | BA12: 0.0046022 | BB12: 0.00173462 | BC12: 0.0097085 | BD12: 0.01463981 | BE12: 0.00551454 | BF12: 0.01502121 | BG12: 0.00210478 | BH12: 0.01923574 | BI12: 0.00911047 | BJ12: -0.00530151 | BK12: 0.01279523 | BL12: 0.00851506 | BM12: 0.00332429 | BN12: -0.0057762 | BO12: 0.01263265 | BP12: 0.00204108 | BQ12: 0.01898963 | BR12: 0.00820067 | BS12: -0.0070304 | BT12: 0.01335619 | BU12: 0.01327164 | BV12: 0.00468989 | BW12: 0.0071703 | BX12: 0.00406663 | BY12: 0.00927031 | BZ12: 0.00944441 | CA12: 0.02031178 | CB12: -0.00747469 | CC12: -0.00439009 | CD12: 0.00393227 | CE12: 0.00134444 | CF12: -0.0094657 | CG12: 0.0084661 | CH12: 0.0205275 | CI12: -0.00977827 | CJ12: -0.0011613 | CK12: 0.00093981 | CL12: 0.0179428 | CM12: 0.00275339 | CN12: 0.01557705 | CO12: 0.01115813 | CP12: 0.00438073 | CQ12: 0.00695298 | CR12: 0.00869925 | CS12: 0.00929731 | CT12: 0.01253143 | CU12: 0.00345227 | CV12: 0.001979 | CW12: 0.00644528 | CX12: 0.00562384 | CY12: 0.0033188 | CZ12: 0.01009375 | DA12: 0.00486373 | DB12: 0.01201632 | DC12: 0.01618012 | DD12: 0.00629406 | DE12: 0.01035165 | DF12: 0.00271221 | DG12: 0.01121652 | DH12: 0.00913543 | DI12: 0.01094207 | DJ12: 0.00638194 | DK12: 0.00898867 | DL12: 0.02277917 | DM12: 0.0150002 | DN12: 0.0094924 | DO12: 0.01570752 | DP12: 0.01316528 | DQ12: 0.01519021 | DR12: 0.00385567 | DS12: 0.00103859 | DT12: 0.00187616 | DU12: 0.00566158 | DV12: 0.00223946 | DW12: 0.00358142 | DX12: 0.01280905 | DY12: -0.00640499 | DZ12: 0.00510969 | EA12: 0.0133476 | EB12: -0.00098844 | EC12: 0.00539968 | ED12: 0.032012 | EE12: 0.01395396 | EF12: -0.00060282 | EG12: 0.01447763 | EH12: -0.00704909 | EI12: 0.00507915 | EJ12: 0.01793195 | EK12: 0.009993 | EL12: 0.01731297 | EM12: 0.00540652 | EN12: 0.00747765 | EO12: 0.00828206 | EP12: =SUMPRODUCT(B12:EO12,$B$5:$EO$5) -> 0 | EQ12: =SUMIF('Mi portafolio'!$A$8:$A$19,$A12,'Mi portafolio'!$B$8:$B$19) -> 0
A13: MCD * | B13: 0.01596738 | C13: 0.00273161 | D13: -0.0008363 | E13: 0.00643985 | F13: 0.02422692 | G13: 0.00053497 | H13: 0.00370453 | I13: 0.04372578 | J13: 0.01872629 | K13: 0.02422535 | L13: 0.00603547 | M13: 0.01375139 | N13: 0.01693988 | O13: 0.00489844 | P13: 0.02216726 | Q13: -0.00149903 | R13: 0.02485324 | S13: 0.00474109 | T13: 0.00710635 | U13: 0.00297963 | V13: 0.00541199 | W13: 0.00882794 | X13: 0.00781761 | Y13: 0.01984507 | Z13: 0.00547979 | AA13: 0.0104038 | AB13: 0.02061142 | AC13: 0.00137444 | AD13: 0.00358947 | AE13: 0.00247061 | AF13: -0.00070628 | AG13: 0.01651206 | AH13: 0.01633895 | AI13: 0.00548696 | AJ13: 0.00214169 | AK13: 0.00257997 | AL13: 0.01591877 | AM13: 0.00237123 | AN13: 0.02684591 | AO13: 0.02029382 | AP13: 0.01671202 | AQ13: 0.0075377 | AR13: 0.01024946 | AS13: -0.00073387 | AT13: 0.01344628 | AU13: 0.02379349 | AV13: 0.00759153 | AW13: 0.00177252 | AX13: 0.0250038 | AY13: 0.02227183 | AZ13: 0.00516943 | BA13: 0.0132103 | BB13: 0.00501321 | BC13: 0.00718558 | BD13: 0.00215778 | BE13: 0.02252455 | BF13: 0.00578643 | BG13: 0.00962053 | BH13: 0.00195159 | BI13: 0.00194568 | BJ13: 0.00078433 | BK13: 0.00050874 | BL13: 0.00772175 | BM13: 0.02254832 | BN13: 0.00902005 | BO13: 0.01399695 | BP13: 0.00788444 | BQ13: 0.00143799 | BR13: 0.01657242 | BS13: 0.00057686 | BT13: 0.01296513 | BU13: -0.00428642 | BV13: 0.01023536 | BW13: 0.01377074 | BX13: 0.02433108 | BY13: 0.01690575 | BZ13: 0.01467013 | CA13: 0.00367942 | CB13: 0.00105348 | CC13: 0.00865101 | CD13: 0.01663835 | CE13: -0.00057481 | CF13: 0.0042472 | CG13: 0.02218093 | CH13: 0.00127206 | CI13: 0.00883662 | CJ13: 0.01906588 | CK13: 0.02591794 | CL13: 0.00776132 | CM13: -0.01209305 | CN13: -0.00385689 | CO13: 0.00918991 | CP13: 0.01502634 | CQ13: 0.01869162 | CR13: -0.0049393 | CS13: -0.00293093 | CT13: 0.00503134 | CU13: 0.00627539 | CV13: 0.00486215 | CW13: 0.02126213 | CX13: 0.01471329 | CY13: 0.0223299 | CZ13: 0.00851895 | DA13: 0.01116933 | DB13: -0.0030704 | DC13: 0.00314685 | DD13: 0.01650964 | DE13: -0.0012254 | DF13: 0.0118489 | DG13: 0.00678222 | DH13: -0.00647435 | DI13: 0.02310529 | DJ13: 0.02651733 | DK13: 0.01879838 | DL13: -0.00424537 | DM13: 0.02928171 | DN13: 0.0274625 | DO13: 0.00375134 | DP13: 0.02865083 | DQ13: -0.0044363 | DR13: -0.00636163 | DS13: 0.0071396 | DT13: -0.01437245 | DU13: 0.00031489 | DV13: 0.00843206 | DW13: 0.02176845 | DX13: -0.02026219 | DY13: 0.01551117 | DZ13: -0.00064487 | EA13: 0.01431021 | EB13: 0.01256741 | EC13: -0.01129311 | ED13: 0.01432567 | EE13: -0.02011413 | EF13: -0.00074043 | EG13: -0.02575104 | EH13: 0.02269546 | EI13: -0.0380175 | EJ13: 0.00513758 | EK13: -0.00176889 | EL13: -0.01720774 | EM13: -0.0002314 | EN13: 0.02481304 | EO13: 0.00899503 | EP13: =SUMPRODUCT(B13:EO13,$B$5:$EO$5) -> 0 | EQ13: =SUMIF('Mi portafolio'!$A$8:$A$19,$A13,'Mi portafolio'!$B$8:$B$19) -> 0
A14: JNJ * | B14: 0.0111789 | C14: 0.00151001 | D14: -0.00138601 | E14: 0.00220829 | F14: 0.01982494 | G14: -0.00052102 | H14: -0.00014956 | I14: 0.01872629 | J14: 0.04448445 | K14: 0.02011908 | L14: 0.00411102 | M14: 0.00925262 | N14: 0.01959258 | O14: 0.00485312 | P14: 0.0193031 | Q14: 0.00045245 | R14: 0.02281184 | S14: 0.00633133 | T14: 0.00630623 | U14: 0.00442855 | V14: -0.00147531 | W14: 0.00742013 | X14: 0.00806466 | Y14: 0.01299216 | Z14: 0.00295666 | AA14: 0.00846556 | AB14: 0.01142703 | AC14: -0.00764499 | AD14: 0.00594008 | AE14: -0.0046543 | AF14: -0.00045646 | AG14: 0.01637675 | AH14: 0.0157523 | AI14: 0.01146589 | AJ14: 0.00026272 | AK14: 0.00448598 | AL14: 0.01118178 | AM14: 0.00489484 | AN14: 0.01623677 | AO14: 0.0323775 | AP14: 0.0068249 | AQ14: 0.0119821 | AR14: 0.0051887 | AS14: 0.00344497 | AT14: 0.00221519 | AU14: 0.02500074 | AV14: 0.00144456 | AW14: 0.00139491 | AX14: 0.03194463 | AY14: 0.01292355 | AZ14: -0.00258227 | BA14: 0.01249254 | BB14: 0.00113025 | BC14: -0.00066968 | BD14: 0.00248974 | BE14: 0.03616812 | BF14: 0.00253802 | BG14: 0.0129524 | BH14: -0.00237982 | BI14: -0.00085692 | BJ14: -0.00192021 | BK14: -0.00394757 | BL14: 0.0117177 | BM14: 0.01350627 | BN14: 0.01430579 | BO14: 0.00964694 | BP14: -0.01004072 | BQ14: -0.00185642 | BR14: 0.00641354 | BS14: 0.00795787 | BT14: 0.0143336 | BU14: 0.00211086 | BV14: -0.00113191 | BW14: 0.01078559 | BX14: 0.03809078 | BY14: 0.00614769 | BZ14: 0.00802027 | CA14: 0.00071745 | CB14: 0.00877396 | CC14: 0.00845185 | CD14: 0.00673066 | CE14: 0.00088535 | CF14: 0.0123356 | CG14: 0.00720601 | CH14: 0.0003153 | CI14: 0.01164142 | CJ14: 0.01625079 | CK14: 0.0170351 | CL14: 0.00938823 | CM14: -0.01028048 | CN14: 0.00271802 | CO14: -0.00539319 | CP14: 0.00922072 | CQ14: 0.008111 | CR14: -0.00929549 | CS14: 0.00345334 | CT14: 0.00013404 | CU14: 0.00110497 | CV14: -0.00719367 | CW14: 0.00652324 | CX14: 0.00524567 | CY14: 0.00722125 | CZ14: 0.00406127 | DA14: 0.00055547 | DB14: -0.00840364 | DC14: -0.00621576 | DD14: 0.00111405 | DE14: -0.00333527 | DF14: -0.00013672 | DG14: 0.0097027 | DH14: -0.01499759 | DI14: 0.0037941 | DJ14: 0.01424279 | DK14: 0.00699819 | DL14: -0.00054627 | DM14: 0.01280253 | DN14: 0.00736784 | DO14: -0.00866548 | DP14: 0.01778092 | DQ14: -0.00299466 | DR14: 0.00038698 | DS14: 0.00049745 | DT14: -0.02692577 | DU14: -0.01344458 | DV14: -0.00607965 | DW14: -0.00151006 | DX14: -0.01666051 | DY14: -0.01595066 | DZ14: 0.00044909 | EA14: 0.00287835 | EB14: -0.00911566 | EC14: 0.00401406 | ED14: -0.00904521 | EE14: -0.02169005 | EF14: 0.00753609 | EG14: -0.01629556 | EH14: 0.0023186 | EI14: -0.03056313 | EJ14: -0.00661737 | EK14: -0.01469069 | EL14: -0.0136148 | EM14: -0.01899272 | EN14: 0.03818362 | EO14: -0.0105521 | EP14: =SUMPRODUCT(B14:EO14,$B$5:$EO$5) -> 0 | EQ14: =SUMIF('Mi portafolio'!$A$8:$A$19,$A14,'Mi portafolio'!$B$8:$B$19) -> 0
A15: PG * | B15: 0.01510253 | C15: -0.00293126 | D15: -0.00225645 | E15: 0.00329236 | F15: 0.02480373 | G15: 0.00035695 | H15: 0.00432872 | I15: 0.02422535 | J15: 0.02011908 | K15: 0.04417693 | L15: 0.00404204 | M15: 0.0139636 | N15: 0.01610438 | O15: 0.00817321 | P15: 0.01925167 | Q15: -0.00205262 | R15: 0.02757052 | S15: 0.00818469 | T15: 0.00624162 | U15: 0.00469265 | V15: 0.00712647 | W15: 0.00948235 | X15: 0.00643635 | Y15: 0.0149697 | Z15: 0.00679438 | AA15: 0.01058127 | AB15: 0.01578851 | AC15: 0.00202663 | AD15: 0.00740029 | AE15: 0.0021812 | AF15: -0.00338277 | AG15: 0.01937033 | AH15: 0.01989525 | AI15: 0.00381277 | AJ15: 0.00193212 | AK15: 0.00133686 | AL15: 0.0151128 | AM15: 0.00131558 | AN15: 0.02909479 | AO15: 0.01866313 | AP15: 0.01789072 | AQ15: 0.0040785 | AR15: 0.00740378 | AS15: 0.00012693 | AT15: 0.00988645 | AU15: 0.02507528 | AV15: 0.00473789 | AW15: 0.00186835 | AX15: 0.02428333 | AY15: 0.01673025 | AZ15: 0.00331329 | BA15: 0.01820126 | BB15: -2.569e-05 | BC15: 0.00097063 | BD15: 0.00617009 | BE15: 0.02597812 | BF15: 0.00633642 | BG15: 0.00898177 | BH15: 0.00180077 | BI15: 0.00261884 | BJ15: -0.00318908 | BK15: 0.00199857 | BL15: 0.01352556 | BM15: 0.02262687 | BN15: 0.01607794 | BO15: 0.01432747 | BP15: -0.00294611 | BQ15: 0.00721394 | BR15: 0.00989478 | BS15: -0.00433789 | BT15: 0.01263532 | BU15: -0.0030179 | BV15: 0.01036089 | BW15: 0.0076121 | BX15: 0.01873184 | BY15: 0.01599443 | BZ15: 0.01287191 | CA15: 0.00994713 | CB15: -0.00164803 | CC15: 0.01138202 | CD15: 0.00893133 | CE15: -0.00329396 | CF15: 0.00103909 | CG15: 0.01381842 | CH15: 0.00121988 | CI15: 0.000236 | CJ15: 0.0137169 | CK15: 0.02716775 | CL15: 0.01297621 | CM15: -0.01116343 | CN15: -0.00224728 | CO15: 0.00478032 | CP15: 0.01438519 | CQ15: 0.01599381 | CR15: -0.00338302 | CS15: 0.00468282 | CT15: 0.00727064 | CU15: 0.00426388 | CV15: 0.00720907 | CW15: 0.01171417 | CX15: 0.01017057 | CY15: 0.02672956 | CZ15: 0.00086876 | DA15: 0.01220086 | DB15: -0.00208334 | DC15: 0.01309189 | DD15: 0.01136603 | DE15: -0.00161098 | DF15: -0.00311765 | DG15: 0.00394762 | DH15: -0.01533487 | DI15: 0.02343126 | DJ15: 0.02826861 | DK15: 0.02082379 | DL15: 0.00167786 | DM15: 0.03571413 | DN15: 0.0201165 | DO15: 0.00124912 | DP15: 0.03362238 | DQ15: -0.00171426 | DR15: -0.01342982 | DS15: 0.00823774 | DT15: -0.02696275 | DU15: -0.00708227 | DV15: -0.00552601 | DW15: 0.00132954 | DX15: -0.02137134 | DY15: 0.00112357 | DZ15: -0.01206948 | EA15: 0.0151927 | EB15: -0.00071521 | EC15: -0.01928214 | ED15: -0.0103679 | EE15: -0.01125572 | EF15: 0.0172945 | EG15: -0.01339493 | EH15: -0.00069278 | EI15: -0.04083101 | EJ15: 0.00137945 | EK15: -0.01315408 | EL15: -0.01756233 | EM15: -0.02091744 | EN15: 0.02734232 | EO15: 0.0074068 | EP15: =SUMPRODUCT(B15:EO15,$B$5:$EO$5) -> 0 | EQ15: =SUMIF('Mi portafolio'!$A$8:$A$19,$A15,'Mi portafolio'!$B$8:$B$19) -> 0
A16: WALMEX * | B16: 0.00222703 | C16: 0.0111274 | D16: 0.00424757 | E16: 0.01255593 | F16: 0.00673445 | G16: -0.00038852 | H16: 0.00881585 | I16: 0.00603547 | J16: 0.00411102 | K16: 0.00404204 | L16: 0.04260152 | M16: 0.00800707 | N16: 0.00658767 | O16: 0.01708847 | P16: 0.00659166 | Q16: 0.00421604 | R16: 0.00460498 | S16: 0.01629616 | T16: 0.00118901 | U16: 0.01498826 | V16: 0.01412436 | W16: 0.00898561 | X16: 0.00237946 | Y16: 0.00832832 | Z16: 0.01499674 | AA16: 0.01509801 | AB16: 0.00600511 | AC16: 0.00610116 | AD16: 0.01112977 | AE16: 0.01276506 | AF16: 0.0153432 | AG16: -0.0011417 | AH16: 0.00050456 | AI16: -0.00120752 | AJ16: 0.01233162 | AK16: 0.01476316 | AL16: 0.00578587 | AM16: 0.00913972 | AN16: 0.00772693 | AO16: 0.00303348 | AP16: 0.00502899 | AQ16: -0.0004051 | AR16: -0.0005809 | AS16: 0.01186637 | AT16: 0.00253206 | AU16: 0.00570988 | AV16: 0.01719625 | AW16: 0.00973612 | AX16: 0.00927435 | AY16: 0.01625588 | AZ16: 0.01590209 | BA16: 0.01503869 | BB16: 0.00287525 | BC16: 0.0072046 | BD16: 0.01349416 | BE16: 0.00710341 | BF16: 0.0107585 | BG16: 0.00068612 | BH16: 0.01654455 | BI16: 0.01144558 | BJ16: 0.00125893 | BK16: 0.01350454 | BL16: 0.00586817 | BM16: 0.00886946 | BN16: 0.0065925 | BO16: 0.00632306 | BP16: 0.01284106 | BQ16: 0.01580461 | BR16: 0.00696023 | BS16: -0.00465218 | BT16: 0.00954885 | BU16: 0.00568427 | BV16: 0.00852307 | BW16: 0.0109441 | BX16: -0.00296204 | BY16: 0.00387745 | BZ16: 0.01076094 | CA16: 0.01350769 | CB16: -0.00550608 | CC16: 0.00018168 | CD16: 0.0113889 | CE16: 0.00436369 | CF16: -0.00017761 | CG16: 0.00797957 | CH16: 0.01305188 | CI16: -0.00122345 | CJ16: -0.00141625 | CK16: 0.00273565 | CL16: 0.00370376 | CM16: 0.00368501 | CN16: 0.01095375 | CO16: 0.00735241 | CP16: 0.00370393 | CQ16: 0.0107617 | CR16: 0.0105665 | CS16: 0.00684604 | CT16: 0.00820153 | CU16: 0.00961282 | CV16: 0.00018304 | CW16: 0.01314022 | CX16: 0.00598863 | CY16: 0.00821652 | CZ16: 0.01328026 | DA16: 0.01035284 | DB16: 0.01244333 | DC16: 0.01438898 | DD16: 0.00574722 | DE16: 0.00929143 | DF16: 0.00658502 | DG16: 0.01219659 | DH16: 0.00812649 | DI16: 0.01379848 | DJ16: 0.00852083 | DK16: 0.01514883 | DL16: 0.01598397 | DM16: 0.01597591 | DN16: 0.02256145 | DO16: 0.01731109 | DP16: 0.01142615 | DQ16: 0.01283838 | DR16: 0.00505835 | DS16: 0.00439381 | DT16: 0.00333709 | DU16: -0.0024631 | DV16: 0.00871781 | DW16: -0.00085732 | DX16: 0.01486524 | DY16: 0.00854534 | DZ16: 0.01302081 | EA16: 0.01601374 | EB16: 0.00476632 | EC16: 0.00457626 | ED16: 0.01080112 | EE16: 0.01620792 | EF16: 0.01063272 | EG16: 0.03199725 | EH16: -1.235e-05 | EI16: 0.01346183 | EJ16: 0.02548051 | EK16: 0.01985655 | EL16: 0.02565909 | EM16: 0.00391131 | EN16: 0.00038957 | EO16: 0.01418798 | EP16: =SUMPRODUCT(B16:EO16,$B$5:$EO$5) -> 0 | EQ16: =SUMIF('Mi portafolio'!$A$8:$A$19,$A16,'Mi portafolio'!$B$8:$B$19) -> 0
A17: AGNC * | B17: 0.00904954 | C17: 0.00254736 | D17: -0.00300205 | E17: 0.00831472 | F17: 0.01274004 | G17: 0.00252403 | H17: 0.00809796 | I17: 0.01375139 | J17: 0.00925262 | K17: 0.0139636 | L17: 0.00800707 | M17: 0.04788925 | N17: 0.01423832 | O17: 0.01091463 | P17: 0.00985537 | Q17: 0.00012863 | R17: 0.01445608 | S17: 0.00583393 | T17: 0.0173936 | U17: 0.0145359 | V17: 0.014704 | W17: 0.00834589 | X17: 0.01724701 | Y17: 0.01200583 | Z17: 0.01510871 | AA17: 0.01088669 | AB17: 0.01263046 | AC17: 0.00545008 | AD17: 0.00886763 | AE17: 0.01306234 | AF17: 0.00682845 | AG17: 0.00156908 | AH17: 0.00269521 | AI17: -0.00396349 | AJ17: 0.00092219 | AK17: 0.01375459 | AL17: 0.01513362 | AM17: 0.01170799 | AN17: 0.03151653 | AO17: 0.00929572 | AP17: 0.01559957 | AQ17: -0.00712329 | AR17: 0.01426059 | AS17: 0.01470829 | AT17: 0.02248026 | AU17: 0.01456864 | AV17: 0.01124704 | AW17: 0.01550294 | AX17: 0.01741065 | AY17: 0.02344326 | AZ17: 0.01775875 | BA17: 0.02346163 | BB17: 0.02144789 | BC17: 0.00909247 | BD17: 0.01147123 | BE17: 0.01924293 | BF17: 0.01817222 | BG17: 0.02262153 | BH17: 0.01095756 | BI17: 0.00899272 | BJ17: -0.00742092 | BK17: 0.01274334 | BL17: 0.02551765 | BM17: 0.02242369 | BN17: 0.00184246 | BO17: 0.02268732 | BP17: 0.01188479 | BQ17: 0.02447954 | BR17: 0.02531713 | BS17: -0.00708717 | BT17: 0.02631856 | BU17: 0.00969861 | BV17: 0.02470715 | BW17: 0.02052352 | BX17: 0.01102078 | BY17: 0.03136347 | BZ17: 0.03222832 | CA17: 0.01763904 | CB17: -0.00299739 | CC17: 0.00566985 | CD17: 0.0221284 | CE17: 0.00759494 | CF17: -0.0067143 | CG17: 0.02802523 | CH17: 0.02819871 | CI17: -0.00939215 | CJ17: 0.00703909 | CK17: 0.02533465 | CL17: 0.02803263 | CM17: 0.01864061 | CN17: 0.00255536 | CO17: 0.00804702 | CP17: 0.01242985 | CQ17: 0.03828738 | CR17: 0.0271101 | CS17: 0.02522405 | CT17: 0.02385789 | CU17: 0.01342694 | CV17: 0.02505149 | CW17: 0.02793492 | CX17: 0.03289541 | CY17: 0.04057679 | CZ17: 0.0106513 | DA17: 0.01589625 | DB17: 0.03058433 | DC17: 0.03417738 | DD17: 0.03245177 | DE17: 0.03595385 | DF17: 0.01079915 | DG17: 0.03766362 | DH17: 0.01820335 | DI17: 0.04349325 | DJ17: 0.03957391 | DK17: 0.04689587 | DL17: 0.0208865 | DM17: 0.04976982 | DN17: 0.03591859 | DO17: 0.03116209 | DP17: 0.04788833 | DQ17: 0.03172236 | DR17: 0.02747959 | DS17: 0.0143415 | DT17: 0.01787569 | DU17: 0.03737027 | DV17: 0.02081125 | DW17: 0.03049897 | DX17: 0.03253574 | DY17: 0.047629 | DZ17: 0.0132137 | EA17: 0.0309905 | EB17: 0.052568 | EC17: 0.00674971 | ED17: 0.04443664 | EE17: 0.03315695 | EF17: 0.03823844 | EG17: 0.03877139 | EH17: 0.0239783 | EI17: 0.0325448 | EJ17: 0.05934779 | EK17: 0.05277512 | EL17: 0.06097023 | EM17: 0.04306573 | EN17: 0.05827071 | EO17: 0.04263591 | EP17: =SUMPRODUCT(B17:EO17,$B$5:$EO$5) -> 0 | EQ17: =SUMIF('Mi portafolio'!$A$8:$A$19,$A17,'Mi portafolio'!$B$8:$B$19) -> 0
... A149: BYND * | B149: -0.00095233 | C149: 0.01246263 | D149: -0.02773732 | E149: 0.00835102 | F149: 0.03186527 | G149: 0.02878523 | H149: 0.00828206 | I149: 0.00899503 | J149: -0.0105521 | K149: 0.0074068 | L149: 0.01418798 | M149: 0.04263591 | N149: 0.01273964 | O149: 0.00826922 | P149: 0.00605119 | Q149: 0.00844686 | R149: 0.01226688 | S149: -0.02238558 | T149: 0.02216444 | U149: 0.03031846 | V149: 0.00137488 | W149: -0.00394154 | X149: 0.03084343 | Y149: 0.01646911 | Z149: 0.02345912 | AA149: -0.00816772 | AB149: 0.01788787 | AC149: 0.00909789 | AD149: -0.01401747 | AE149: 0.0214593 | AF149: -0.02617925 | AG149: -0.04368124 | AH149: -0.01559984 | AI149: -0.00733392 | AJ149: 0.01015752 | AK149: 0.03199953 | AL149: 0.05546246 | AM149: 0.02523232 | AN149: 0.06208187 | AO149: 0.01459787 | AP149: 0.08992734 | AQ149: -0.00567913 | AR149: 0.02772947 | AS149: 0.05970901 | AT149: 0.0764706 | AU149: -0.00135406 | AV149: 0.04234089 | AW149: 0.0137155 | AX149: 0.03611411 | AY149: 0.02071962 | AZ149: -0.022107 | BA149: 0.05582834 | BB149: 0.05773216 | BC149: -0.03628279 | BD149: 0.06399614 | BE149: 0.03591437 | BF149: 0.07171989 | BG149: 0.08478683 | BH149: 0.03351025 | BI149: -0.03388411 | BJ149: -0.02861693 | BK149: -0.06315033 | BL149: 0.0809431 | BM149: 0.10063336 | BN149: 0.0287582 | BO149: 0.0581522 | BP149: 0.06057084 | BQ149: -0.00512247 | BR149: 0.06830689 | BS149: -0.00211134 | BT149: 0.07179737 | BU149: 0.03531798 | BV149: 0.10100662 | BW149: 0.06368599 | BX149: 0.01651861 | BY149: 0.18064494 | BZ149: 0.0902137 | CA149: -0.02443359 | CB149: -0.05255942 | CC149: 0.05216797 | CD149: 0.06518068 | CE149: 0.06316414 | CF149: -0.02832569 | CG149: 0.10435831 | CH149: 0.06669534 | CI149: -0.02130952 | CJ149: 0.10208963 | CK149: 0.09178876 | CL149: 0.09688202 | CM149: 0.07219829 | CN149: 0.01665664 | CO149: 0.01183776 | CP149: 0.06316772 | CQ149: 0.09346749 | CR149: 0.09055776 | CS149: 0.06520255 | CT149: 0.13035943 | CU149: 0.08830628 | CV149: 0.05632954 | CW149: 0.11097897 | CX149: 0.09872961 | CY149: 0.09553566 | CZ149: 0.06431621 | DA149: 0.09386507 | DB149: 0.1309467 | DC149: 0.07980495 | DD149: 0.17129331 | DE149: 0.127928 | DF149: 0.11935447 | DG149: 0.03318928 | DH149: 0.05242728 | DI149: 0.08762817 | DJ149: 0.14113543 | DK149: 0.08874317 | DL149: 0.02033983 | DM149: 0.1615072 | DN149: 0.15169106 | DO149: 0.09546413 | DP149: 0.1588429 | DQ149: 0.03244559 | DR149: 0.05683016 | DS149: 0.13140492 | DT149: 0.14504348 | DU149: 0.2247597 | DV149: 0.14568571 | DW149: 0.10718013 | DX149: 0.10561542 | DY149: 0.25775533 | DZ149: 0.10940615 | EA149: 0.1102971 | EB149: 0.31284175 | EC149: 0.03348251 | ED149: 0.15473523 | EE149: 0.16350676 | EF149: 0.02275245 | EG149: 0.1190278 | EH149: 0.08999932 | EI149: 0.09202973 | EJ149: 0.11656583 | EK149: 0.27755521 | EL149: 0.21183942 | EM149: 0.11181263 | EN149: 0.25289767 | EO149: 2.8941735 | EP149: =SUMPRODUCT(B149:EO149,$B$5:$EO$5) -> 0 | EQ149: =SUMIF('Mi portafolio'!$A$8:$A$19,$A149,'Mi portafolio'!$B$8:$B$19) -> 0
